Workbook

Sheet HuongDan
A1: NGƯỠNG SME MAY FOB – UC01 (TRỤC W, 3 MỨC) VÀ UC02 (MILLER–ORR)
A2: Cách xây: chuẩn ngành FOB (20 DN may FOB, FiinTrade 2023–2025) → kiểm định biến điều tiết quy mô → áp cho từng DN; ngưỡng tiền UC02 theo Miller–Orr.
A4: KẾT QUẢ CHÍNH – NGƯỠNG CHO SME FOB (nhóm Nhỏ–vừa)
A5: Ngưỡng | B5: FOB nhỏ–vừa | C5: Đơn vị | D5: Mức UC01 / UC02
A6: Phải thu – tham chiếu (DSO, P50) | B6: =B3_NguongKhoanMuc!D4 -> 43.247052 | C6: ngày | D6: Trung vị ngành FOB
A7: Phải thu – CÓ NGUY CƠ (P75) | B7: =B3_NguongKhoanMuc!E4 -> 58.207139 | C7: ngày | D7: Vượt → Có nguy cơ
A8: Phải thu – TRẦM TRỌNG (P90) | B8: =B3_NguongKhoanMuc!F4 -> 66.263266 | C8: ngày | D8: Vượt → Thiếu trầm trọng
A9: Tồn kho – tham chiếu (DIO, P50) | B9: =B3_NguongKhoanMuc!G4 -> 69.751755 | C9: ngày | D9: Trung vị ngành FOB
A10: Tồn kho – CÓ NGUY CƠ (P75) | B10: =B3_NguongKhoanMuc!H4 -> 86.118055 | C10: ngày | D10: Vượt → Có nguy cơ
A11: Tồn kho – TRẦM TRỌNG (P90) | B11: =B3_NguongKhoanMuc!I4 -> 137.96515 | C11: ngày | D11: Vượt → Thiếu trầm trọng
A12: Phải trả – DPO THẤP (P10, kèm tiền mỏng) | B12: =B3_NguongKhoanMuc!L4 -> 14.892653 | C12: ngày | D12: Kèm tiền mỏng → Có nguy cơ
A13: Đệm tiền mỏng (P25) | B13: =B3_NguongKhoanMuc!M4 -> 0.083007995 | C13: % DT | D13: Điều kiện kèm R-AP-1
A14: Mức trọng yếu (vốn vượt ngưỡng / TSNH) | B14: =ThamSo!$C$9 -> 0.05 | C14: tỷ lệ | D14: Vượt → Thiếu trầm trọng
A15: UC02 – ℓ: L = ℓ × doanh thu năm | B15: =B6_MillerOrr!C17 -> 0.041798621 | C15: % DT | D15: Tiền < L → THIẾU
A16: UC02 – σ ngày dự phòng = tỷ lệ × doanh thu năm | B16: =B6_MillerOrr!C20 -> 0.0025058914 | C16: % DT / ngày | D16: Dùng khi DN < 90 ngày dữ liệu
A17: UC02 – ví dụ DT 300 tỷ: L / Z / H | B17: =TEXT(B6_MillerOrr!B30,"0.0")&" / "&TEXT(B6_MillerOrr!E30,"0.0")&" / "&TEXT(B6_MillerOrr!F30,"0.0") -> 12.5 / 14.0 / 17.0 | C17: tỷ đồng | D17: Tiền > H → THỪA
A18: Tỷ lệ khó khăn năm sau: W0 / W1 / W2 | B18: =TEXT(B5_KiemDinh!D5,"0%")&" / "&TEXT(B5_KiemDinh!D6,"0%")&" / "&TEXT(B5_KiemDinh!D7,"0%") -> 0% / 29% / 0% | D18: Kiểm định chiều hướng
A21: ĐỌC THEO THỨ TỰ
A22: MaTran_6O | B22: Ma trận 6 ô: W0 / W1 / W2 × Thiếu / Thừa; thứ tự ưu tiên giải pháp UC03 cho từng ô.
A23: ThamSo | B23: Mọi con số có thể chỉnh (phân vị, cửa sổ năm, mức trọng yếu, tham số Miller–Orr…), kèm cơ sở.
A24: HoSoDN | B24: 28 DN may, mô hình gia công / FOB, DN thuộc mẫu FOB, DN bị loại và lý do.
A25: DuLieu | B25: Số liệu FiinTrade 2023–2025 nguyên văn + cột tính toán; cột “– FOB” là mẫu tính ngưỡng.
A26: B1_ChuanNganh | B26: Bước 1: phân vị P10 / P25 / P50 / P75 / P90 của ngành FOB; đối chiếu số “Toàn ngành” FiinTrade.
A27: B2_BienDieuTiet | B27: Bước 2: hệ số quy mô, mùa vụ; chỉ áp dụng khi có ý nghĩa thống kê.
A28: B2a_KiemDinhMannWhitney | B28: Bước 2 (chi tiết): p-value bằng công thức Excel – xếp hạng, U, z, p.
A29: B3_NguongKhoanMuc | B29: Bước 3: ngưỡng từng khoản mục cho DN FOB; 7 quy tắc có mã.
A30: B4_PhanLopW | B30: Bước 4: áp cho từng năm–DN FOB → W0 An toàn / W1 Có nguy cơ / W2 Thiếu trầm trọng.
A31: B5_KiemDinh | B31: Bước 5: ba mức có phân biệt DN gặp khó năm sau không; độ nhạy.
A32: B6_MillerOrr | B32: Bước 6: ngưỡng tiền UC02 – L, Z, H theo Miller–Orr.
A33: TongHop2025 | B33: Ảnh chụp năm 2025: mức UC01, L / Z / H, trạng thái tiền, ô ma trận, ưu tiên giải pháp.
... A36: Nguong_SRS | B36: Khóa cấu hình đưa vào SRS.
A38: QUY ƯỚC MÀU
A39: Chữ xanh dương | B39: Số liệu nhập hoặc lựa chọn nhập tay.
A40: Chữ đen | B40: Công thức.
A41: Chữ xanh lá | B41: Liên kết sang sheet khác.
A42: Nền vàng | B42: Tham số được phép chỉnh.
A43: Nền xanh nhạt | B43: Ngưỡng / kết quả.
A45: GIỚI HẠN
A46: Mẫu | B46: DN may FOB đại chúng (20 DN, 60 năm–DN); rất ít năm–DN đạt chuẩn SME theo NĐ80; quy mô được kiểm định và không khác biệt có ý nghĩa.
A47: Cửa sổ 3 năm | B47: Ít quan sát hơn: P90 dựa trên ~6 năm–DN cao nhất; kiểm định biến cố chỉ có 40 năm–DN (2023, 2024).
A48: Tần suất | B48: Số liệu năm, chốt 31/12; hệ số mùa vụ chưa hiệu chỉnh; σ ngành của Miller–Orr suy từ biến động tiền năm.
A49: Miller–Orr | B49: F và r là tham số demo; L do chủ DN có thể nâng; σ nên dùng dữ liệu dòng tiền ngày của chính DN.
A50: Cấp hóa đơn / lô | B50: Quá hạn hóa đơn (ρ) và tuổi lô hàng không hiệu chỉnh được từ BCTC → giữ giá trị demo.

Sheet MaTran_6O
A1: MA TRẬN 6 TRƯỜNG HỢP: 3 mức UC01 (trục W) × 2 trạng thái tiền UC02 (Miller–Orr)
A2: UC01 xác định HÀNG (W0 An toàn / W1 Có nguy cơ / W2 Thiếu trầm trọng). UC02 xác định CỘT: Tiền < L → Thiếu; Tiền > H → Thừa. Ô M1–M6 = 2 × chỉ số W + chỉ số tiền + 1.
A4: Hàng W | B4: Mức UC01 | C4: Điều kiện (tất định, có mã quy tắc) | D4: UC01 bàn giao cho UC02 | E4: Cột THIẾU (Tiền < L) | F4: Cột THỪA (Tiền > H) | G4: Số năm–DN FOB trong dữ liệu | H4: Tỷ lệ khó khăn năm sau
A5: W0 | B5: An toàn | C5: DSO ≤ ngưỡng có nguy cơ, DIO ≤ ngưỡng có nguy cơ, không có “DPO thấp + tiền mỏng”. | D5: Không có finding vượt ngưỡng; vẫn giao DSO, DIO, DPO và ngưỡng để UC02 dùng. | E5: M1 – Thiếu, vốn lưu động an toàn | F5: M2 – Thừa, vốn lưu động an toàn | G5: =COUNTIF(B4_PhanLopW!$AD$5:$AD$64,A5) -> 32 | H5: =IF("",IFERROR(INDEX(B5_KiemDinh!$D$5:$D$7,MATCH(A5,B5_KiemDinh!$A$5:$A$7,0)),"")) -> 0
A6: W1 | B6: Có nguy cơ | C6: Có ít nhất 1 tín hiệu R-AR-1, R-INV-1 hoặc R-AP-1, nhưng không có tín hiệu trầm trọng và vốn vượt ngưỡng < m. | D6: Finding theo khoản mục: số ngày, ngưỡng, mức “Có nguy cơ”, vốn vượt ngưỡng (đồng), mã quy tắc. | E6: M3 – Thiếu, có nguy cơ | F6: M4 – Thừa, có nguy cơ | G6: =COUNTIF(B4_PhanLopW!$AD$5:$AD$64,A6) -> 9 | H6: =IF("",IFERROR(INDEX(B5_KiemDinh!$D$5:$D$7,MATCH(A6,B5_KiemDinh!$A$5:$A$7,0)),"")) -> 0.28571429
A7: W2 | B7: Thiếu trầm trọng | C7: Có R-AR-2 hoặc R-INV-2; HOẶC có tín hiệu có nguy cơ và vốn vượt ngưỡng / TSNH ≥ mức trọng yếu (R-MAT). | D7: Finding trọng yếu: khoản mục là điểm nghẽn chính, money_at_risk (đồng), tỷ lệ / TSNH, mã quy tắc. | E7: M5 – Thiếu, nghẽn trầm trọng | F7: M6 – Thừa, nghẽn trầm trọng | G7: =COUNTIF(B4_PhanLopW!$AD$5:$AD$64,A7) -> 19 | H7: =IF("",IFERROR(INDEX(B5_KiemDinh!$D$5:$D$7,MATCH(A7,B5_KiemDinh!$A$5:$A$7,0)),"")) -> 0
G8: 0
A10: Tiền nằm giữa L và H: trong vùng kiểm soát, không gán cột THIẾU / THỪA và không đề xuất hành động (theo dõi tiếp).
A12: THỨ TỰ ƯU TIÊN GIẢI PHÁP CHO UC03 THEO TỪNG Ô
A13: Ô | B13: Mức UC01 | C13: Tiền UC02 | D13: Thứ tự ưu tiên nguồn / cách dùng tiền | E13: Lý do
A14: M1 | B14: An toàn | C14: Thiếu | D14: 1. Vay ngắn hạn (short-term financing) | E14: Vốn lưu động lành mạnh, thiếu là tạm thời; vay ngắn hạn nhanh, chi phí thấp, không ảnh hưởng quan hệ khách hàng và NCC.
A15: M2 | B15: An toàn | C15: Thừa | D15: 1. Đầu tư ngắn hạn phần (Tiền − Z) | E15: Thừa ít và không có điểm nghẽn: tiền nhàn rỗi nên sinh lời; giữ lại tối thiểu Z.
A16: M3 | B16: Có nguy cơ | C16: Thiếu | D16: 1. Thu hồi phải thu (AR) → 2. Giãn trả NCC (AP) | E16: Xử lý đúng điểm đang giữ vốn trước khi đi vay.
A17: M4 | B17: Có nguy cơ | C17: Thừa | D17: 1. Giữ làm dự trữ | E17: Có dấu hiệu nghẽn: tiền dư là đệm cho rủi ro, chưa nên đầu tư.
A18: M5 | B18: Thiếu trầm trọng | C18: Thiếu | D18: 1. AR → 2. Hàng tồn kho → 3. AP → 4. Vay (chỉ khi 3 nguồn trên chưa đủ) | E18: Vốn bị giữ trọng yếu, đi vay khó: giải phóng vốn nội bộ trước.
A19: M6 | B19: Thiếu trầm trọng | C19: Thừa | D19: 1. Giữ làm dự trữ | E19: Tồn đọng nhiều tiền nhưng vốn lưu động nghẽn trầm trọng: giữ dự trữ, xử lý điểm nghẽn.
A21: Ví dụ cách đọc: một SME FOB có DSO 70 ngày (> ngưỡng trầm trọng 66,3) → R-AR-2 → W2. Nếu UC02 dự báo tiền xuống dưới L → ô M5: ưu tiên thu hồi phải thu, rồi giảm tồn kho, rồi giãn trả NCC, cuối cùng mới vay.

Sheet ThamSo
A1: THAM SỐ (ô vàng, chữ xanh: được phép chỉnh – toàn bộ file tự tính lại)
A3: Mã | B3: Tham số | C3: Giá trị | D3: Đơn vị | E3: Cơ sở
A4: P1 | B4: Phân vị mức THAM CHIẾU (bình thường) | C4: 0.5 | D4: phân vị | E4: Trung vị ngành FOB: một nửa năm–DN FOB có số ngày thấp hơn.
A5: P2 | B5: Phân vị ngưỡng CÓ NGUY CƠ (theo dõi) | C5: 0.75 | D5: phân vị | E5: Cao hơn 75% năm–DN FOB → UC01 mức “Có nguy cơ”.
A6: P3 | B6: Phân vị ngưỡng TRẦM TRỌNG | C6: 0.9 | D6: phân vị | E6: Thập phân vị cao nhất ngành FOB → UC01 mức “Thiếu trầm trọng”.
A7: P4 | B7: Phân vị DPO THẤP (NCC gần như không cho nợ) | C7: 0.1 | D7: phân vị | E7: Chỉ là tín hiệu khi đi kèm tiền mỏng (P5) – quy tắc có điều kiện.
A8: P5 | B8: Phân vị ĐỆM TIỀN mỏng ((Tiền + ĐTNH) / Doanh thu) | C8: 0.25 | D8: phân vị | E8: Đệm tiền thấp hơn 75% năm–DN FOB.
A9: P6 | B9: Mức TRỌNG YẾU: vốn vượt ngưỡng có nguy cơ / Tài sản ngắn hạn | C9: 0.05 | D9: tỷ lệ | E9: Chính sách chủ DN duyệt (materiality_share). Độ nhạy ở B5_KiemDinh.
A10: P7 | B10: Vượt ngưỡng TRẦM TRỌNG thì xếp W2 dù chưa đạt trọng yếu (1 = có) | C10: 1 | D10: cờ | E10: Một khoản ở thập phân vị cao nhất ngành đã là điểm nghẽn.
A11: P8 | B11: Doanh thu tối thiểu để coi là đang hoạt động | C11: 50000000000 | D11: đồng | E11: Loại năm gần như ngừng hoạt động (G20, MPT, GMC, VTI trong 2023–2025): số ngày khi đó vô nghĩa.
A12: P9 | B12: Ranh giới nhóm quy mô Nhỏ–vừa / Lớn (doanh thu) | C12: 1500000000000 | D12: đồng | E12: Chia nhóm để kiểm định biến điều tiết quy mô.
A13: P10 | B13: SME theo NĐ 80/2021: doanh thu tối đa (công nghiệp) | C13: 200000000000 | D13: đồng | E13: Nghị định 80/2021/NĐ-CP, Điều 5.
A14: P11 | B14: SME theo NĐ 80/2021: tổng nguồn vốn tối đa | C14: 100000000000 | D14: đồng | E14: Như trên (chưa kiểm được tiêu chí lao động – FiinTrade không có).
A15: P12 | B15: DIO trung vị dưới mức này → mô hình GIA CÔNG (CMT), loại khỏi mẫu FOB | C15: 20 | D15: ngày | E15: Gia công dùng nguyên liệu của khách nên gần như không có tồn kho: PTG 4, THM 5, DCG 9 ngày (2023–2025); DN FOB tiếp theo ≥ 23 ngày.
... A29: P26 | B29: Miller–Orr: số ngày dữ liệu tối thiểu để dùng σ riêng của DN | C29: 90 | D29: ngày | E29: Đủ ≥ 90 ngày dòng tiền ròng (trong 3 năm gần nhất) thì dùng σ ngày của chính DN; thiếu thì dùng σ ngành × doanh thu.

Sheet HoSoDN
A1: HỒ SƠ DOANH NGHIỆP, MÔ HÌNH KINH DOANH VÀ MẪU FOB
A2: Mô hình xếp theo DIO trung vị các năm hoạt động 2023–2025 (< P12 = 20 ngày → gia công CMT). Mẫu tính ngưỡng chỉ gồm DN FOB đang hoạt động, không bị loại.
A4: Mã | B4: Tên doanh nghiệp | C4: Nhóm thu thập | D4: Doanh thu trung vị (tỷ đồng) | E4: Tổng nguồn vốn trung vị (tỷ đồng) | F4: Số năm đạt chuẩn SME (NĐ80) | G4: DIO trung vị (ngày) | H4: Mô hình | I4: DN bị loại? | J4: Lý do loại | K4: Số năm trong mẫu FOB | L4: Nhóm quy mô chủ đạo (nhiều năm hơn; hòa → Nhỏ–vừa) | M4: DSO trung vị | N4: DIO trung vị (mẫu) | O4: DPO trung vị | P4: Đệm tiền trung vị | Q4: Thuộc mẫu FOB?
A5: AG1 | B5: CTCP 28.1 | C5: Nhóm 1 – nhỏ | D5: =IFERROR(MEDIAN(DuLieu!D5:D7)/1000000000,"") -> 337.51237 | E5: =IFERROR(MEDIAN(DuLieu!F5:F7)/1000000000,"") -> 151.53955 | F5: =COUNTIF(DuLieu!W5:W7,"Có") -> 0 | G5: =IFERROR(MEDIAN(DuLieu!X5:X7),"") -> 105.53788 | H5: =IF(I5="Có","Loại",IF(G5="","Chưa rõ",IF(G5<ThamSo!$C$15,"CMT","FOB"))) -> FOB | I5: Không | K5: =SUM(DuLieu!U5:U7) -> 3 | L5: =IF(K5=0,"",IF(COUNTIFS(DuLieu!U5:U7,1,DuLieu!V5:V7,"Nhỏ–vừa")>=COUNTIFS(DuLieu!U5:U7,1,DuLieu!V5:V7,"Lớn"),"Nhỏ–vừa","Lớn")) -> Nhỏ–vừa | M5: =IFERROR(MEDIAN(DuLieu!AB5:AB7),"") -> 25.857809 | N5: =IFERROR(MEDIAN(DuLieu!AE5:AE7),"") -> 105.53788 | O5: =IFERROR(MEDIAN(DuLieu!AH5:AH7),"") -> 84.012707 | P5: =IFERROR(MEDIAN(DuLieu!Y5:Y7),"") -> 0.04477945 | Q5: =IF(AND(H5="FOB",K5>0),"Có","Không") -> Có
A6: BDG | B6: May mặc Bình Dương | C6: Nhóm 2 – lớn | D6: =IFERROR(MEDIAN(DuLieu!D8:D10)/1000000000,"") -> 1765.7867 | E6: =IFERROR(MEDIAN(DuLieu!F8:F10)/1000000000,"") -> 1132.6229 | F6: =COUNTIF(DuLieu!W8:W10,"Có") -> 0 | G6: =IFERROR(MEDIAN(DuLieu!X8:X10),"") -> 59.720353 | H6: =IF(I6="Có","Loại",IF(G6="","Chưa rõ",IF(G6<ThamSo!$C$15,"CMT","FOB"))) -> FOB | I6: Không | K6: =SUM(DuLieu!U8:U10) -> 3 | L6: =IF(K6=0,"",IF(COUNTIFS(DuLieu!U8:U10,1,DuLieu!V8:V10,"Nhỏ–vừa")>=COUNTIFS(DuLieu!U8:U10,1,DuLieu!V8:V10,"Lớn"),"Nhỏ–vừa","Lớn")) -> Lớn | M6: =IFERROR(MEDIAN(DuLieu!AB8:AB10),"") -> 47.799581 | N6: =IFERROR(MEDIAN(DuLieu!AE8:AE10),"") -> 59.720353 | O6: =IFERROR(MEDIAN(DuLieu!AH8:AH10),"") -> 32.642841 | P6: =IFERROR(MEDIAN(DuLieu!Y8:Y10),"") -> 0.15094065 | Q6: =IF(AND(H6="FOB",K6>0),"Có","Không") -> Có
A7: BMG | B7: May Bình Minh | C7: Nhóm 1 – nhỏ | D7: =IFERROR(MEDIAN(DuLieu!D11:D13)/1000000000,"") -> 295.7249 | E7: =IFERROR(MEDIAN(DuLieu!F11:F13)/1000000000,"") -> 178.46685 | F7: =COUNTIF(DuLieu!W11:W13,"Có") -> 0 | G7: =IFERROR(MEDIAN(DuLieu!X11:X13),"") -> 64.140082 | H7: =IF(I7="Có","Loại",IF(G7="","Chưa rõ",IF(G7<ThamSo!$C$15,"CMT","FOB"))) -> FOB | I7: Không | K7: =SUM(DuLieu!U11:U13) -> 3 | L7: =IF(K7=0,"",IF(COUNTIFS(DuLieu!U11:U13,1,DuLieu!V11:V13,"Nhỏ–vừa")>=COUNTIFS(DuLieu!U11:U13,1,DuLieu!V11:V13,"Lớn"),"Nhỏ–vừa","Lớn")) -> Nhỏ–vừa | M7: =IFERROR(MEDIAN(DuLieu!AB11:AB13),"") -> 31.714545 | N7: =IFERROR(MEDIAN(DuLieu!AE11:AE13),"") -> 64.140082 | O7: =IFERROR(MEDIAN(DuLieu!AH11:AH13),"") -> 34.06861 | P7: =IFERROR(MEDIAN(DuLieu!Y11:Y13),"") -> 0.11842199 | Q7: =IF(AND(H7="FOB",K7>0),"Có","Không") -> Có
A8: DCG | B8: May Đáp Cầu | C8: Nhóm 1 – nhỏ | D8: =IFERROR(MEDIAN(DuLieu!D14:D16)/1000000000,"") -> 554.87991 | E8: =IFERROR(MEDIAN(DuLieu!F14:F16)/1000000000,"") -> 421.38798 | F8: =COUNTIF(DuLieu!W14:W16,"Có") -> 0 | G8: =IFERROR(MEDIAN(DuLieu!X14:X16),"") -> 9.2933175 | H8: =IF(I8="Có","Loại",IF(G8="","Chưa rõ",IF(G8<ThamSo!$C$15,"CMT","FOB"))) -> CMT | I8: Không | K8: =SUM(DuLieu!U14:U16) -> 0 | L8: =IF(K8=0,"",IF(COUNTIFS(DuLieu!U14:U16,1,DuLieu!V14:V16,"Nhỏ–vừa")>=COUNTIFS(DuLieu!U14:U16,1,DuLieu!V14:V16,"Lớn"),"Nhỏ–vừa","Lớn")) | M8: =IFERROR(MEDIAN(DuLieu!AB14:AB16),"") | N8: =IFERROR(MEDIAN(DuLieu!AE14:AE16),"") | O8: =IFERROR(MEDIAN(DuLieu!AH14:AH16),"") | P8: =IFERROR(MEDIAN(DuLieu!Y14:Y16),"") | Q8: =IF(AND(H8="FOB",K8>0),"Có","Không") -> Không
A9: DM7 | B9: Dệt may 7 | C9: Nhóm 1 – nhỏ | D9: =IFERROR(MEDIAN(DuLieu!D17:D19)/1000000000,"") -> 741.07097 | E9: =IFERROR(MEDIAN(DuLieu!F17:F19)/1000000000,"") -> 540.04457 | F9: =COUNTIF(DuLieu!W17:W19,"Có") -> 0 | G9: =IFERROR(MEDIAN(DuLieu!X17:X19),"") -> 55.712532 | H9: =IF(I9="Có","Loại",IF(G9="","Chưa rõ",IF(G9<ThamSo!$C$15,"CMT","FOB"))) -> FOB | I9: Không | K9: =SUM(DuLieu!U17:U19) -> 3 | L9: =IF(K9=0,"",IF(COUNTIFS(DuLieu!U17:U19,1,DuLieu!V17:V19,"Nhỏ–vừa")>=COUNTIFS(DuLieu!U17:U19,1,DuLieu!V17:V19,"Lớn"),"Nhỏ–vừa","Lớn")) -> Nhỏ–vừa | M9: =IFERROR(MEDIAN(DuLieu!AB17:AB19),"") -> 83.307468 | N9: =IFERROR(MEDIAN(DuLieu!AE17:AE19),"") -> 55.712532 | O9: =IFERROR(MEDIAN(DuLieu!AH17:AH19),"") -> 46.200039 | P9: =IFERROR(MEDIAN(DuLieu!Y17:Y19),"") -> 0.07036637 | Q9: =IF(AND(H9="FOB",K9>0),"Có","Không") -> Có
A10: G20 | B10: Đầu tư Dệt may Vĩnh Phúc | C10: Nhóm 1 – nhỏ | D10: =IFERROR(MEDIAN(DuLieu!D20:D22)/1000000000,"") -> 0 | E10: =IFERROR(MEDIAN(DuLieu!F20:F22)/1000000000,"") -> 94.998554 | F10: =COUNTIF(DuLieu!W20:W22,"Có") -> 1 | G10: =IFERROR(MEDIAN(DuLieu!X20:X22),"") | H10: =IF(I10="Có","Loại",IF(G10="","Chưa rõ",IF(G10<ThamSo!$C$15,"CMT","FOB"))) -> Chưa rõ | I10: Không | K10: =SUM(DuLieu!U20:U22) -> 0 | L10: =IF(K10=0,"",IF(COUNTIFS(DuLieu!U20:U22,1,DuLieu!V20:V22,"Nhỏ–vừa")>=COUNTIFS(DuLieu!U20:U22,1,DuLieu!V20:V22,"Lớn"),"Nhỏ–vừa","Lớn")) | M10: =IFERROR(MEDIAN(DuLieu!AB20:AB22),"") | N10: =IFERROR(MEDIAN(DuLieu!AE20:AE22),"") | O10: =IFERROR(MEDIAN(DuLieu!AH20:AH22),"") | P10: =IFERROR(MEDIAN(DuLieu!Y20:Y22),"") | Q10: =IF(AND(H10="FOB",K10>0),"Có","Không") -> Không
A11: GIL | B11: SXKD XNK Bình Thạnh | C11: Nhóm 2 – lớn | D11: =IFERROR(MEDIAN(DuLieu!D23:D25)/1000000000,"") -> 713.62099 | E11: =IFERROR(MEDIAN(DuLieu!F23:F25)/1000000000,"") -> 3357.159 | F11: =COUNTIF(DuLieu!W23:W25,"Có") -> 0 | G11: =IFERROR(MEDIAN(DuLieu!X23:X25),"") | H11: =IF(I11="Có","Loại",IF(G11="","Chưa rõ",IF(G11<ThamSo!$C$15,"CMT","FOB"))) -> Loại | I11: Có | J11: DIO 546–1.180 ngày trong 2023–2025 (2020–2021: 68–75 ngày): tồn kho không phản ánh hoạt động may FOB; giữ trong DuLieu để đối chiếu. | K11: =SUM(DuLieu!U23:U25) -> 0 | L11: =IF(K11=0,"",IF(COUNTIFS(DuLieu!U23:U25,1,DuLieu!V23:V25,"Nhỏ–vừa")>=COUNTIFS(DuLieu!U23:U25,1,DuLieu!V23:V25,"Lớn"),"Nhỏ–vừa","Lớn")) | M11: =IFERROR(MEDIAN(DuLieu!AB23:AB25),"") | N11: =IFERROR(MEDIAN(DuLieu!AE23:AE25),"") | O11: =IFERROR(MEDIAN(DuLieu!AH23:AH25),"") | P11: =IFERROR(MEDIAN(DuLieu!Y23:Y25),"") | Q11: =IF(AND(H11="FOB",K11>0),"Có","Không") -> Không
A12: GMC | B12: Garmex Sài Gòn | C12: Nhóm 1 – nhỏ | D12: =IFERROR(MEDIAN(DuLieu!D26:D28)/1000000000,"") -> 2.1279437 | E12: =IFERROR(MEDIAN(DuLieu!F26:F28)/1000000000,"") -> 375.94725 | F12: =COUNTIF(DuLieu!W26:W28,"Có") -> 3 | G12: =IFERROR(MEDIAN(DuLieu!X26:X28),"") | H12: =IF(I12="Có","Loại",IF(G12="","Chưa rõ",IF(G12<ThamSo!$C$15,"CMT","FOB"))) -> Chưa rõ | I12: Không | K12: =SUM(DuLieu!U26:U28) -> 0 | L12: =IF(K12=0,"",IF(COUNTIFS(DuLieu!U26:U28,1,DuLieu!V26:V28,"Nhỏ–vừa")>=COUNTIFS(DuLieu!U26:U28,1,DuLieu!V26:V28,"Lớn"),"Nhỏ–vừa","Lớn")) | M12: =IFERROR(MEDIAN(DuLieu!AB26:AB28),"") | N12: =IFERROR(MEDIAN(DuLieu!AE26:AE28),"") | O12: =IFERROR(MEDIAN(DuLieu!AH26:AH28),"") | P12: =IFERROR(MEDIAN(DuLieu!Y26:Y28),"") | Q12: =IF(AND(H12="FOB",K12>0),"Có","Không") -> Không
A13: HLT | B13: Dệt may Hoàng Thị Loan | C13: Nhóm 1 – nhỏ | D13: =IFERROR(MEDIAN(DuLieu!D29:D31)/1000000000,"") -> 780.8241 | E13: =IFERROR(MEDIAN(DuLieu!F29:F31)/1000000000,"") -> 288.50867 | F13: =COUNTIF(DuLieu!W29:W31,"Có") -> 0 | G13: =IFERROR(MEDIAN(DuLieu!X29:X31),"") -> 87.245942 | H13: =IF(I13="Có","Loại",IF(G13="","Chưa rõ",IF(G13<ThamSo!$C$15,"CMT","FOB"))) -> FOB | I13: Không | K13: =SUM(DuLieu!U29:U31) -> 3 | L13: =IF(K13=0,"",IF(COUNTIFS(DuLieu!U29:U31,1,DuLieu!V29:V31,"Nhỏ–vừa")>=COUNTIFS(DuLieu!U29:U31,1,DuLieu!V29:V31,"Lớn"),"Nhỏ–vừa","Lớn")) -> Nhỏ–vừa | M13: =IFERROR(MEDIAN(DuLieu!AB29:AB31),"") -> 21.528217 | N13: =IFERROR(MEDIAN(DuLieu!AE29:AE31),"") -> 87.245942 | O13: =IFERROR(MEDIAN(DuLieu!AH29:AH31),"") -> 8.1371547 | P13: =IFERROR(MEDIAN(DuLieu!Y29:Y31),"") -> 0.094380675 | Q13: =IF(AND(H13="FOB",K13>0),"Có","Không") -> Có
A14: HNI | B14: May Hữu Nghị | C14: Nhóm 1 – nhỏ | D14: =IFERROR(MEDIAN(DuLieu!D32:D34)/1000000000,"") -> 980.29229 | E14: =IFERROR(MEDIAN(DuLieu!F32:F34)/1000000000,"") -> 758.72573 | F14: =COUNTIF(DuLieu!W32:W34,"Có") -> 0 | G14: =IFERROR(MEDIAN(DuLieu!X32:X34),"") -> 26.977831 | H14: =IF(I14="Có","Loại",IF(G14="","Chưa rõ",IF(G14<ThamSo!$C$15,"CMT","FOB"))) -> FOB | I14: Không | K14: =SUM(DuLieu!U32:U34) -> 3 | L14: =IF(K14=0,"",IF(COUNTIFS(DuLieu!U32:U34,1,DuLieu!V32:V34,"Nhỏ–vừa")>=COUNTIFS(DuLieu!U32:U34,1,DuLieu!V32:V34,"Lớn"),"Nhỏ–vừa","Lớn")) -> Nhỏ–vừa | M14: =IFERROR(MEDIAN(DuLieu!AB32:AB34),"") -> 41.237603 | N14: =IFERROR(MEDIAN(DuLieu!AE32:AE34),"") -> 26.977831 | O14: =IFERROR(MEDIAN(DuLieu!AH32:AH34),"") -> 12.94332 | P14: =IFERROR(MEDIAN(DuLieu!Y32:Y34),"") -> 0.29666826 | Q14: =IF(AND(H14="FOB",K14>0),"Có","Không") -> Có
A15: HTG | B15: Dệt may Hòa Thọ | C15: Nhóm 2 – lớn | D15: =IFERROR(MEDIAN(DuLieu!D35:D37)/1000000000,"") -> 5111.1533 | E15: =IFERROR(MEDIAN(DuLieu!F35:F37)/1000000000,"") -> 2922.2156 | F15: =COUNTIF(DuLieu!W35:W37,"Có") -> 0 | G15: =IFERROR(MEDIAN(DuLieu!X35:X37),"") -> 64.557923 | H15: =IF(I15="Có","Loại",IF(G15="","Chưa rõ",IF(G15<ThamSo!$C$15,"CMT","FOB"))) -> FOB | I15: Không | K15: =SUM(DuLieu!U35:U37) -> 3 | L15: =IF(K15=0,"",IF(COUNTIFS(DuLieu!U35:U37,1,DuLieu!V35:V37,"Nhỏ–vừa")>=COUNTIFS(DuLieu!U35:U37,1,DuLieu!V35:V37,"Lớn"),"Nhỏ–vừa","Lớn")) -> Lớn | M15: =IFERROR(MEDIAN(DuLieu!AB35:AB37),"") -> 38.70394 | N15: =IFERROR(MEDIAN(DuLieu!AE35:AE37),"") -> 64.557923 | O15: =IFERROR(MEDIAN(DuLieu!AH35:AH37),"") -> 20.486733 | P15: =IFERROR(MEDIAN(DuLieu!Y35:Y37),"") -> 0.14111784 | Q15: =IF(AND(H15="FOB",K15>0),"Có","Không") -> Có
A16: HUG | B16: May Hưng Yên | C16: Nhóm 2 – lớn | D16: =IFERROR(MEDIAN(DuLieu!D38:D40)/1000000000,"") -> 690.5257 | E16: =IFERROR(MEDIAN(DuLieu!F38:F40)/1000000000,"") -> 607.90763 | F16: =COUNTIF(DuLieu!W38:W40,"Có") -> 0 | G16: =IFERROR(MEDIAN(DuLieu!X38:X40),"") -> 38.479621 | H16: =IF(I16="Có","Loại",IF(G16="","Chưa rõ",IF(G16<ThamSo!$C$15,"CMT","FOB"))) -> FOB | I16: Không | K16: =SUM(DuLieu!U38:U40) -> 3 | L16: =IF(K16=0,"",IF(COUNTIFS(DuLieu!U38:U40,1,DuLieu!V38:V40,"Nhỏ–vừa")>=COUNTIFS(DuLieu!U38:U40,1,DuLieu!V38:V40,"Lớn"),"Nhỏ–vừa","Lớn")) -> Nhỏ–vừa | M16: =IFERROR(MEDIAN(DuLieu!AB38:AB40),"") -> 33.706796 | N16: =IFERROR(MEDIAN(DuLieu!AE38:AE40),"") -> 38.479621 | O16: =IFERROR(MEDIAN(DuLieu!AH38:AH40),"") -> 18.735776 | P16: =IFERROR(MEDIAN(DuLieu!Y38:Y40),"") -> 0.337957 | Q16: =IF(AND(H16="FOB",K16>0),"Có","Không") -> Có
A17: M10 | B17: Tổng Công ty May 10 | C17: Nhóm 2 – lớn | D17: =IFERROR(MEDIAN(DuLieu!D41:D43)/1000000000,"") -> 4660.1994 | E17: =IFERROR(MEDIAN(DuLieu!F41:F43)/1000000000,"") -> 2615.8332 | F17: =COUNTIF(DuLieu!W41:W43,"Có") -> 0 | G17: =IFERROR(MEDIAN(DuLieu!X41:X43),"") -> 69.538398 | H17: =IF(I17="Có","Loại",IF(G17="","Chưa rõ",IF(G17<ThamSo!$C$15,"CMT","FOB"))) -> FOB | I17: Không | K17: =SUM(DuLieu!U41:U43) -> 3 | L17: =IF(K17=0,"",IF(COUNTIFS(DuLieu!U41:U43,1,DuLieu!V41:V43,"Nhỏ–vừa")>=COUNTIFS(DuLieu!U41:U43,1,DuLieu!V41:V43,"Lớn"),"Nhỏ–vừa","Lớn")) -> Lớn | M17: =IFERROR(MEDIAN(DuLieu!AB41:AB43),"") -> 43.565853 | N17: =IFERROR(MEDIAN(DuLieu!AE41:AE43),"") -> 69.538398 | O17: =IFERROR(MEDIAN(DuLieu!AH41:AH43),"") -> 61.424684 | P17: =IFERROR(MEDIAN(DuLieu!Y41:Y43),"") -> 0.10972324 | Q17: =IF(AND(H17="FOB",K17>0),"Có","Không") -> Có
A18: MGG | B18: May Đức Giang | C18: Nhóm 2 – lớn | D18: =IFERROR(MEDIAN(DuLieu!D44:D46)/1000000000,"") -> 1660.7887 | E18: =IFERROR(MEDIAN(DuLieu!F44:F46)/1000000000,"") -> 921.92385 | F18: =COUNTIF(DuLieu!W44:W46,"Có") -> 0 | G18: =IFERROR(MEDIAN(DuLieu!X44:X46),"") -> 23.284912 | H18: =IF(I18="Có","Loại",IF(G18="","Chưa rõ",IF(G18<ThamSo!$C$15,"CMT","FOB"))) -> FOB | I18: Không | K18: =SUM(DuLieu!U44:U46) -> 3 | L18: =IF(K18=0,"",IF(COUNTIFS(DuLieu!U44:U46,1,DuLieu!V44:V46,"Nhỏ–vừa")>=COUNTIFS(DuLieu!U44:U46,1,DuLieu!V44:V46,"Lớn"),"Nhỏ–vừa","Lớn")) -> Lớn | M18: =IFERROR(MEDIAN(DuLieu!AB44:AB46),"") -> 54.737569 | N18: =IFERROR(MEDIAN(DuLieu!AE44:AE46),"") -> 23.284912 | O18: =IFERROR(MEDIAN(DuLieu!AH44:AH46),"") -> 100.84166 | P18: =IFERROR(MEDIAN(DuLieu!Y44:Y46),"") -> 0.16247451 | Q18: =IF(AND(H18="FOB",K18>0),"Có","Không") -> Có
A19: MNB | B19: May Nhà Bè | C19: Nhóm 2 – lớn | D19: =IFERROR(MEDIAN(DuLieu!D47:D49)/1000000000,"") -> 4637.3728 | E19: =IFERROR(MEDIAN(DuLieu!F47:F49)/1000000000,"") -> 3096.388 | F19: =COUNTIF(DuLieu!W47:W49,"Có") -> 0 | G19: =IFERROR(MEDIAN(DuLieu!X47:X49),"") -> 67.294538 | H19: =IF(I19="Có","Loại",IF(G19="","Chưa rõ",IF(G19<ThamSo!$C$15,"CMT","FOB"))) -> FOB | I19: Không | K19: =SUM(DuLieu!U47:U49) -> 3 | L19: =IF(K19=0,"",IF(COUNTIFS(DuLieu!U47:U49,1,DuLieu!V47:V49,"Nhỏ–vừa")>=COUNTIFS(DuLieu!U47:U49,1,DuLieu!V47:V49,"Lớn"),"Nhỏ–vừa","Lớn")) -> Lớn | M19: =IFERROR(MEDIAN(DuLieu!AB47:AB49),"") -> 61.378637 | N19: =IFERROR(MEDIAN(DuLieu!AE47:AE49),"") -> 67.294538 | O19: =IFERROR(MEDIAN(DuLieu!AH47:AH49),"") -> 24.57389 | P19: =IFERROR(MEDIAN(DuLieu!Y47:Y49),"") -> 0.10649043 | Q19: =IF(AND(H19="FOB",K19>0),"Có","Không") -> Có
A20: MPT | B20: Tập đoàn MPT | C20: Nhóm 1 – nhỏ | D20: =IFERROR(MEDIAN(DuLieu!D50:D52)/1000000000,"") -> 0 | E20: =IFERROR(MEDIAN(DuLieu!F50:F52)/1000000000,"") -> 177.58481 | F20: =COUNTIF(DuLieu!W50:W52,"Có") -> 3 | G20: =IFERROR(MEDIAN(DuLieu!X50:X52),"") | H20: =IF(I20="Có","Loại",IF(G20="","Chưa rõ",IF(G20<ThamSo!$C$15,"CMT","FOB"))) -> Chưa rõ | I20: Không | K20: =SUM(DuLieu!U50:U52) -> 0 | L20: =IF(K20=0,"",IF(COUNTIFS(DuLieu!U50:U52,1,DuLieu!V50:V52,"Nhỏ–vừa")>=COUNTIFS(DuLieu!U50:U52,1,DuLieu!V50:V52,"Lớn"),"Nhỏ–vừa","Lớn")) | M20: =IFERROR(MEDIAN(DuLieu!AB50:AB52),"") | N20: =IFERROR(MEDIAN(DuLieu!AE50:AE52),"") | O20: =IFERROR(MEDIAN(DuLieu!AH50:AH52),"") | P20: =IFERROR(MEDIAN(DuLieu!Y50:Y52),"") | Q20: =IF(AND(H20="FOB",K20>0),"Có","Không") -> Không
A21: MSH | B21: May Sông Hồng | C21: Nhóm 2 – lớn | D21: =IFERROR(MEDIAN(DuLieu!D53:D55)/1000000000,"") -> 5280.4032 | E21: =IFERROR(MEDIAN(DuLieu!F53:F55)/1000000000,"") -> 4523.1889 | F21: =COUNTIF(DuLieu!W53:W55,"Có") -> 0 | G21: =IFERROR(MEDIAN(DuLieu!X53:X55),"") -> 50.400766 | H21: =IF(I21="Có","Loại",IF(G21="","Chưa rõ",IF(G21<ThamSo!$C$15,"CMT","FOB"))) -> FOB | I21: Không | K21: =SUM(DuLieu!U53:U55) -> 3 | L21: =IF(K21=0,"",IF(COUNTIFS(DuLieu!U53:U55,1,DuLieu!V53:V55,"Nhỏ–vừa")>=COUNTIFS(DuLieu!U53:U55,1,DuLieu!V53:V55,"Lớn"),"Nhỏ–vừa","Lớn")) -> Lớn | M21: =IFERROR(MEDIAN(DuLieu!AB53:AB55),"") -> 54.083058 | N21: =IFERROR(MEDIAN(DuLieu!AE53:AE55),"") -> 50.400766 | O21: =IFERROR(MEDIAN(DuLieu!AH53:AH55),"") -> 15.363061 | P21: =IFERROR(MEDIAN(DuLieu!Y53:Y55),"") -> 0.29248052 | Q21: =IF(AND(H21="FOB",K21>0),"Có","Không") -> Có
A22: NJC | B22: May Nam Định | C22: Nhóm 1 – nhỏ | D22: =IFERROR(MEDIAN(DuLieu!D56:D58)/1000000000,"") -> 661.50828 | E22: =IFERROR(MEDIAN(DuLieu!F56:F58)/1000000000,"") -> 409.33085 | F22: =COUNTIF(DuLieu!W56:W58,"Có") -> 0 | G22: =IFERROR(MEDIAN(DuLieu!X56:X58),"") -> 86.7301 | H22: =IF(I22="Có","Loại",IF(G22="","Chưa rõ",IF(G22<ThamSo!$C$15,"CMT","FOB"))) -> FOB | I22: Không | K22: =SUM(DuLieu!U56:U58) -> 3 | L22: =IF(K22=0,"",IF(COUNTIFS(DuLieu!U56:U58,1,DuLieu!V56:V58,"Nhỏ–vừa")>=COUNTIFS(DuLieu!U56:U58,1,DuLieu!V56:V58,"Lớn"),"Nhỏ–vừa","Lớn")) -> Nhỏ–vừa | M22: =IFERROR(MEDIAN(DuLieu!AB56:AB58),"") -> 61.065652 | N22: =IFERROR(MEDIAN(DuLieu!AE56:AE58),"") -> 86.7301 | O22: =IFERROR(MEDIAN(DuLieu!AH56:AH58),"") -> 17.897413 | P22: =IFERROR(MEDIAN(DuLieu!Y56:Y58),"") -> 0.061517656 | Q22: =IF(AND(H22="FOB",K22>0),"Có","Không") -> Có
A23: NTT | B23: Dệt may Nha Trang | C23: Nhóm 1 – nhỏ | D23: =IFERROR(MEDIAN(DuLieu!D59:D61)/1000000000,"") -> 1233.6482 | E23: =IFERROR(MEDIAN(DuLieu!F59:F61)/1000000000,"") -> 1123.848 | F23: =COUNTIF(DuLieu!W59:W61,"Có") -> 0 | G23: =IFERROR(MEDIAN(DuLieu!X59:X61),"") -> 104.63331 | H23: =IF(I23="Có","Loại",IF(G23="","Chưa rõ",IF(G23<ThamSo!$C$15,"CMT","FOB"))) -> FOB | I23: Không | K23: =SUM(DuLieu!U59:U61) -> 3 | L23: =IF(K23=0,"",IF(COUNTIFS(DuLieu!U59:U61,1,DuLieu!V59:V61,"Nhỏ–vừa")>=COUNTIFS(DuLieu!U59:U61,1,DuLieu!V59:V61,"Lớn"),"Nhỏ–vừa","Lớn")) -> Nhỏ–vừa | M23: =IFERROR(MEDIAN(DuLieu!AB59:AB61),"") -> 51.667854 | N23: =IFERROR(MEDIAN(DuLieu!AE59:AE61),"") -> 104.63331 | O23: =IFERROR(MEDIAN(DuLieu!AH59:AH61),"") -> 73.679788 | P23: =IFERROR(MEDIAN(DuLieu!Y59:Y61),"") -> 0.082408586 | Q23: =IF(AND(H23="FOB",K23>0),"Có","Không") -> Có
A24: PTG | B24: May Xuất khẩu Phan Thiết | C24: Nhóm 1 – nhỏ | D24: =IFERROR(MEDIAN(DuLieu!D62:D64)/1000000000,"") -> 488.1488 | E24: =IFERROR(MEDIAN(DuLieu!F62:F64)/1000000000,"") -> 363.67921 | F24: =COUNTIF(DuLieu!W62:W64,"Có") -> 0 | G24: =IFERROR(MEDIAN(DuLieu!X62:X64),"") -> 4.3673682 | H24: =IF(I24="Có","Loại",IF(G24="","Chưa rõ",IF(G24<ThamSo!$C$15,"CMT","FOB"))) -> CMT | I24: Không | K24: =SUM(DuLieu!U62:U64) -> 0 | L24: =IF(K24=0,"",IF(COUNTIFS(DuLieu!U62:U64,1,DuLieu!V62:V64,"Nhỏ–vừa")>=COUNTIFS(DuLieu!U62:U64,1,DuLieu!V62:V64,"Lớn"),"Nhỏ–vừa","Lớn")) | M24: =IFERROR(MEDIAN(DuLieu!AB62:AB64),"") | N24: =IFERROR(MEDIAN(DuLieu!AE62:AE64),"") | O24: =IFERROR(MEDIAN(DuLieu!AH62:AH64),"") | P24: =IFERROR(MEDIAN(DuLieu!Y62:Y64),"") | Q24: =IF(AND(H24="FOB",K24>0),"Có","Không") -> Không
A25: TCM | B25: Dệt may Thành Công | C25: Nhóm 2 – lớn | D25: =IFERROR(MEDIAN(DuLieu!D65:D67)/1000000000,"") -> 3645.2522 | E25: =IFERROR(MEDIAN(DuLieu!F65:F67)/1000000000,"") -> 3895.5344 | F25: =COUNTIF(DuLieu!W65:W67,"Có") -> 0 | G25: =IFERROR(MEDIAN(DuLieu!X65:X67),"") -> 121.89984 | H25: =IF(I25="Có","Loại",IF(G25="","Chưa rõ",IF(G25<ThamSo!$C$15,"CMT","FOB"))) -> FOB | I25: Không | K25: =SUM(DuLieu!U65:U67) -> 3 | L25: =IF(K25=0,"",IF(COUNTIFS(DuLieu!U65:U67,1,DuLieu!V65:V67,"Nhỏ–vừa")>=COUNTIFS(DuLieu!U65:U67,1,DuLieu!V65:V67,"Lớn"),"Nhỏ–vừa","Lớn")) -> Lớn | M25: =IFERROR(MEDIAN(DuLieu!AB65:AB67),"") -> 44.374219 | N25: =IFERROR(MEDIAN(DuLieu!AE65:AE67),"") -> 121.89984 | O25: =IFERROR(MEDIAN(DuLieu!AH65:AH67),"") -> 42.505649 | P25: =IFERROR(MEDIAN(DuLieu!Y65:Y67),"") -> 0.28770637 | Q25: =IF(AND(H25="FOB",K25>0),"Có","Không") -> Có
A26: TDT | B26: Đầu tư Phát triển TDT | C26: Nhóm 1 – nhỏ | D26: =IFERROR(MEDIAN(DuLieu!D68:D70)/1000000000,"") -> 563.12964 | E26: =IFERROR(MEDIAN(DuLieu!F68:F70)/1000000000,"") -> 615.18187 | F26: =COUNTIF(DuLieu!W68:W70,"Có") -> 0 | G26: =IFERROR(MEDIAN(DuLieu!X68:X70),"") -> 255.11526 | H26: =IF(I26="Có","Loại",IF(G26="","Chưa rõ",IF(G26<ThamSo!$C$15,"CMT","FOB"))) -> FOB | I26: Không | K26: =SUM(DuLieu!U68:U70) -> 3 | L26: =IF(K26=0,"",IF(COUNTIFS(DuLieu!U68:U70,1,DuLieu!V68:V70,"Nhỏ–vừa")>=COUNTIFS(DuLieu!U68:U70,1,DuLieu!V68:V70,"Lớn"),"Nhỏ–vừa","Lớn")) -> Nhỏ–vừa | M26: =IFERROR(MEDIAN(DuLieu!AB68:AB70),"") -> 34.643 | N26: =IFERROR(MEDIAN(DuLieu!AE68:AE70),"") -> 255.11526 | O26: =IFERROR(MEDIAN(DuLieu!AH68:AH70),"") -> 16.787181 | P26: =IFERROR(MEDIAN(DuLieu!Y68:Y70),"") -> 0.109882 | Q26: =IF(AND(H26="FOB",K26>0),"Có","Không") -> Có
A27: THM | B27: Tứ Hải Hà Nam | C27: Nhóm 1 – nhỏ | D27: =IFERROR(MEDIAN(DuLieu!D71:D73)/1000000000,"") -> 118.42341 | E27: =IFERROR(MEDIAN(DuLieu!F71:F73)/1000000000,"") -> 174.68358 | F27: =COUNTIF(DuLieu!W71:W73,"Có") -> 3 | G27: =IFERROR(MEDIAN(DuLieu!X71:X73),"") -> 4.9003357 | H27: =IF(I27="Có","Loại",IF(G27="","Chưa rõ",IF(G27<ThamSo!$C$15,"CMT","FOB"))) -> CMT | I27: Không | K27: =SUM(DuLieu!U71:U73) -> 0 | L27: =IF(K27=0,"",IF(COUNTIFS(DuLieu!U71:U73,1,DuLieu!V71:V73,"Nhỏ–vừa")>=COUNTIFS(DuLieu!U71:U73,1,DuLieu!V71:V73,"Lớn"),"Nhỏ–vừa","Lớn")) | M27: =IFERROR(MEDIAN(DuLieu!AB71:AB73),"") | N27: =IFERROR(MEDIAN(DuLieu!AE71:AE73),"") | O27: =IFERROR(MEDIAN(DuLieu!AH71:AH73),"") | P27: =IFERROR(MEDIAN(DuLieu!Y71:Y73),"") | Q27: =IF(AND(H27="FOB",K27>0),"Có","Không") -> Không
A28: TNG | B28: Đầu tư và Thương mại TNG | C28: Nhóm 2 – lớn | D28: =IFERROR(MEDIAN(DuLieu!D74:D76)/1000000000,"") -> 7655.7528 | E28: =IFERROR(MEDIAN(DuLieu!F74:F76)/1000000000,"") -> 5816.8752 | F28: =COUNTIF(DuLieu!W74:W76,"Có") -> 0 | G28: =IFERROR(MEDIAN(DuLieu!X74:X76),"") -> 70.3822 | H28: =IF(I28="Có","Loại",IF(G28="","Chưa rõ",IF(G28<ThamSo!$C$15,"CMT","FOB"))) -> FOB | I28: Không | K28: =SUM(DuLieu!U74:U76) -> 3 | L28: =IF(K28=0,"",IF(COUNTIFS(DuLieu!U74:U76,1,DuLieu!V74:V76,"Nhỏ–vừa")>=COUNTIFS(DuLieu!U74:U76,1,DuLieu!V74:V76,"Lớn"),"Nhỏ–vừa","Lớn")) -> Lớn | M28: =IFERROR(MEDIAN(DuLieu!AB74:AB76),"") -> 33.076023 | N28: =IFERROR(MEDIAN(DuLieu!AE74:AE76),"") -> 70.3822 | O28: =IFERROR(MEDIAN(DuLieu!AH74:AH76),"") -> 35.332391 | P28: =IFERROR(MEDIAN(DuLieu!Y74:Y76),"") -> 0.090705407 | Q28: =IF(AND(H28="FOB",K28>0),"Có","Không") -> Có
A29: VGG | B29: May Việt Tiến | C29: Nhóm 2 – lớn | D29: =IFERROR(MEDIAN(DuLieu!D77:D79)/1000000000,"") -> 9756.3632 | E29: =IFERROR(MEDIAN(DuLieu!F77:F79)/1000000000,"") -> 5292.0502 | F29: =COUNTIF(DuLieu!W77:W79,"Có") -> 0 | G29: =IFERROR(MEDIAN(DuLieu!X77:X79),"") -> 57.606144 | H29: =IF(I29="Có","Loại",IF(G29="","Chưa rõ",IF(G29<ThamSo!$C$15,"CMT","FOB"))) -> FOB | I29: Không | K29: =SUM(DuLieu!U77:U79) -> 3 | L29: =IF(K29=0,"",IF(COUNTIFS(DuLieu!U77:U79,1,DuLieu!V77:V79,"Nhỏ–vừa")>=COUNTIFS(DuLieu!U77:U79,1,DuLieu!V77:V79,"Lớn"),"Nhỏ–vừa","Lớn")) -> Lớn | M29: =IFERROR(MEDIAN(DuLieu!AB77:AB79),"") -> 58.483211 | N29: =IFERROR(MEDIAN(DuLieu!AE77:AE79),"") -> 57.606144 | O29: =IFERROR(MEDIAN(DuLieu!AH77:AH79),"") -> 76.865913 | P29: =IFERROR(MEDIAN(DuLieu!Y77:Y79),"") -> 0.083207798 | Q29: =IF(AND(H29="FOB",K29>0),"Có","Không") -> Có
A30: VTI | B30: SX - XNK Dệt may | C30: Nhóm 1 – nhỏ | D30: =IFERROR(MEDIAN(DuLieu!D80:D82)/1000000000,"") -> 4.8710692 | E30: =IFERROR(MEDIAN(DuLieu!F80:F82)/1000000000,"") -> 3.4733646 | F30: =COUNTIF(DuLieu!W80:W82,"Có") -> 3 | G30: =IFERROR(MEDIAN(DuLieu!X80:X82),"") | H30: =IF(I30="Có","Loại",IF(G30="","Chưa rõ",IF(G30<ThamSo!$C$15,"CMT","FOB"))) -> Loại | I30: Có | J30: Doanh thu 5–9 tỷ, DSO hàng nghìn ngày: không còn hoạt động may thực chất. | K30: =SUM(DuLieu!U80:U82) -> 0 | L30: =IF(K30=0,"",IF(COUNTIFS(DuLieu!U80:U82,1,DuLieu!V80:V82,"Nhỏ–vừa")>=COUNTIFS(DuLieu!U80:U82,1,DuLieu!V80:V82,"Lớn"),"Nhỏ–vừa","Lớn")) | M30: =IFERROR(MEDIAN(DuLieu!AB80:AB82),"") | N30: =IFERROR(MEDIAN(DuLieu!AE80:AE82),"") | O30: =IFERROR(MEDIAN(DuLieu!AH80:AH82),"") | P30: =IFERROR(MEDIAN(DuLieu!Y80:Y82),"") | Q30: =IF(AND(H30="FOB",K30>0),"Có","Không") -> Không
A31: X20 | B31: CTCP X20 | C31: Nhóm 1 – nhỏ | D31: =IFERROR(MEDIAN(DuLieu!D83:D85)/1000000000,"") -> 1115.5455 | E31: =IFERROR(MEDIAN(DuLieu!F83:F85)/1000000000,"") -> 599.21298 | F31: =COUNTIF(DuLieu!W83:W85,"Có") -> 0 | G31: =IFERROR(MEDIAN(DuLieu!X83:X85),"") -> 69.965112 | H31: =IF(I31="Có","Loại",IF(G31="","Chưa rõ",IF(G31<ThamSo!$C$15,"CMT","FOB"))) -> FOB | I31: Không | K31: =SUM(DuLieu!U83:U85) -> 3 | L31: =IF(K31=0,"",IF(COUNTIFS(DuLieu!U83:U85,1,DuLieu!V83:V85,"Nhỏ–vừa")>=COUNTIFS(DuLieu!U83:U85,1,DuLieu!V83:V85,"Lớn"),"Nhỏ–vừa","Lớn")) -> Nhỏ–vừa | M31: =IFERROR(MEDIAN(DuLieu!AB83:AB85),"") -> 24.972029 | N31: =IFERROR(MEDIAN(DuLieu!AE83:AE85),"") -> 69.965112 | O31: =IFERROR(MEDIAN(DuLieu!AH83:AH85),"") -> 72.420394 | P31: =IFERROR(MEDIAN(DuLieu!Y83:Y85),"") -> 0.14221504 | Q31: =IF(AND(H31="FOB",K31>0),"Có","Không") -> Có
A32: X26 | B32: CTCP 26 | C32: Nhóm 1 – nhỏ | D32: =IFERROR(MEDIAN(DuLieu!D86:D88)/1000000000,"") -> 1073.0118 | E32: =IFERROR(MEDIAN(DuLieu!F86:F88)/1000000000,"") -> 711.8833 | F32: =COUNTIF(DuLieu!W86:W88,"Có") -> 0 | G32: =IFERROR(MEDIAN(DuLieu!X86:X88),"") -> 73.87967 | H32: =IF(I32="Có","Loại",IF(G32="","Chưa rõ",IF(G32<ThamSo!$C$15,"CMT","FOB"))) -> FOB | I32: Không | K32: =SUM(DuLieu!U86:U88) -> 3 | L32: =IF(K32=0,"",IF(COUNTIFS(DuLieu!U86:U88,1,DuLieu!V86:V88,"Nhỏ–vừa")>=COUNTIFS(DuLieu!U86:U88,1,DuLieu!V86:V88,"Lớn"),"Nhỏ–vừa","Lớn")) -> Nhỏ–vừa | M32: =IFERROR(MEDIAN(DuLieu!AB86:AB88),"") -> 48.098369 | N32: =IFERROR(MEDIAN(DuLieu!AE86:AE88),"") -> 73.87967 | O32: =IFERROR(MEDIAN(DuLieu!AH86:AH88),"") -> 74.86254 | P32: =IFERROR(MEDIAN(DuLieu!Y86:Y88),"") -> 0.1541313 | Q32: =IF(AND(H32="FOB",K32>0),"Có","Không") -> Có
A34: Tổng | F34: =SUM(F5:F32) -> 13 | K34: =SUM(K5:K32) -> 60 | Q34: =COUNTIF(Q5:Q32,"Có") -> 20
A36: Kết quả lọc: 20 DN FOB × 3 năm = 60 năm–DN. Không thuộc mẫu: 3 DN gia công (DCG, PTG, THM); 3 DN không còn doanh thu ≥ 50 tỷ trong 2023–2025 (G20, GMC, MPT); 2 DN bị loại (VTI, GIL).

Sheet DuLieu
A1: DỮ LIỆU NGÀNH MAY: 28 DOANH NGHIỆP × 2023–2025 (FiinTrade) – mẫu tính ngưỡng chỉ gồm DN FOB
A2: Chữ xanh: số liệu FiinTrade nhập nguyên văn (5 file “Chỉ số tài chính” xuất 18/10/2026; DSO/DIO/DPO do FiinTrade tính trên số dư bình quân, 365 ngày). Chữ đen: công thức. Cột “– FOB” chỉ lấy năm–DN thuộc mẫu FOB đang hoạt động (cột U = 1).
A4: Mã | B4: Năm | C4: File FiinTrade | D4: Doanh thu thuần (đồng) | E4: Biên LN gộp | F4: Tổng nguồn vốn (đồng) | G4: Tài sản ngắn hạn (đồng) | H4: Tiền và tương đương tiền (đồng) | I4: Đầu tư tài chính ngắn hạn (đồng) | J4: Hàng tồn kho ròng (đồng) | K4: LNST cổ đông mẹ (đồng) | L4: DSO – FiinTrade (ngày) | M4: DIO – FiinTrade (ngày) | N4: DPO – FiinTrade (ngày) | O4: Giá vốn = DT × (1 − biên gộp) (đồng) | P4: Đệm tiền = (Tiền + ĐTNH) / DT | Q4: Tiền / DT | R4: Biến động tiền = (Tiền − Tiền năm trước) / DT | S4: Mô hình | T4: DN bị loại? | U4: Thuộc mẫu FOB & đang hoạt động (1/0) | V4: Nhóm quy mô | W4: SME theo NĐ80? | X4: DIO nếu hoạt động (mọi mô hình) | Y4: Đệm tiền – FOB | Z4: Đệm tiền – FOB Nhỏ–vừa | AA4: Đệm tiền – FOB Lớn | AB4: DSO – FOB | AC4: DSO – FOB Nhỏ–vừa | AD4: DSO – FOB Lớn | AE4: DIO – FOB | AF4: DIO – FOB Nhỏ–vừa | AG4: DIO – FOB Lớn | AH4: DPO – FOB | AI4: DPO – FOB Nhỏ–vừa | AJ4: DPO – FOB Lớn | AK4: Tiền / DT – FOB | AL4: Biến động tiền / DT – FOB | AM4: Khóa Mã-Năm
A5: AG1 | B5: 2023 | C5: FiinTrade_..._AG1_20261018.xlsx | D5: 269017127126 | E5: 0.14625449 | F5: 144115422092 | G5: 128660408494 | H5: 6804199578 | I5: 0 | J5: 93402244974 | K5: 10796262054 | L5: 25.857809 | M5: 145.84777 | N5: 107.20841 | O5: =IF(OR(D5="",E5=""),"",D5*(1-E5)) -> 2.2967216e+11 | P5: =IF(OR(H5="",D5=""),"",IF(D5<=0,"",(H5+N(I5))/D5)) -> 0.025292812 | Q5: =IF(OR(H5="",D5=""),"",IF(D5<=0,"",H5/D5)) -> 0.025292812 | R5: ="" | S5: =INDEX(HoSoDN!$H$5:$H$32,MATCH(A5,HoSoDN!$A$5:$A$32,0)) -> FOB | T5: =INDEX(HoSoDN!$I$5:$I$32,MATCH(A5,HoSoDN!$A$5:$A$32,0)) -> Không | U5: =IF(AND(S5="FOB",T5<>"Có",B5>=ThamSo!$C$22,B5<=ThamSo!$C$23,D5<>"",E5<>"",G5<>"",P5<>"",L5<>"",M5<>"",N5<>""),IF(D5>=ThamSo!$C$11,1,0),0) -> 1 | V5: =IF(D5="","",IF(D5<=ThamSo!$C$12,"Nhỏ–vừa","Lớn")) -> Nhỏ–vừa | W5: =IF(D5="","",IF(OR(D5<=ThamSo!$C$13,F5<=ThamSo!$C$14),"Có","Không")) -> Không | X5: =IF(AND(T5<>"Có",M5<>"",D5<>""),IF(D5>=ThamSo!$C$11,M5,""),"") -> 145.84777 | Y5: =IF(U5=1,P5,"") -> 0.025292812 | Z5: =IF(AND(U5=1,V5="Nhỏ–vừa"),P5,"") -> 0.025292812 | AA5: =IF(AND(U5=1,V5="Lớn"),P5,"") | AB5: =IF(U5=1,L5,"") -> 25.857809 | AC5: =IF(AND(U5=1,V5="Nhỏ–vừa"),L5,"") -> 25.857809 | AD5: =IF(AND(U5=1,V5="Lớn"),L5,"") | AE5: =IF(U5=1,M5,"") -> 145.84777 | AF5: =IF(AND(U5=1,V5="Nhỏ–vừa"),M5,"") -> 145.84777 | AG5: =IF(AND(U5=1,V5="Lớn"),M5,"") | AH5: =IF(U5=1,N5,"") -> 107.20841 | AI5: =IF(AND(U5=1,V5="Nhỏ–vừa"),N5,"") -> 107.20841 | AJ5: =IF(AND(U5=1,V5="Lớn"),N5,"") | AK5: =IF(U5=1,Q5,"") -> 0.025292812 | AL5: =IF(AND(U5=1,R5<>""),R5,"") | AM5: =A5&"-"&B5 -> AG1-2023
A6: AG1 | B6: 2024 | C6: FiinTrade_..._AG1_20261018.xlsx | D6: 337512371714 | E6: 0.11758799 | F6: 151539551502 | G6: 135967622195 | H6: 40157015524 | I6: 0 | J6: 78826891496 | K6: 8630835708 | L6: 20.640644 | M6: 105.53788 | N6: 84.012707 | O6: =IF(OR(D6="",E6=""),"",D6*(1-E6)) -> 2.9782497e+11 | P6: =IF(OR(H6="",D6=""),"",IF(D6<=0,"",(H6+N(I6))/D6)) -> 0.11897939 | Q6: =IF(OR(H6="",D6=""),"",IF(D6<=0,"",H6/D6)) -> 0.11897939 | R6: =IF(OR(A5<>A6,B6<=ThamSo!$C$22,H6="",H5="",D6=""),"",IF(D6<=0,"",(H6-H5)/D6)) -> 0.098819536 | S6: =INDEX(HoSoDN!$H$5:$H$32,MATCH(A6,HoSoDN!$A$5:$A$32,0)) -> FOB | T6: =INDEX(HoSoDN!$I$5:$I$32,MATCH(A6,HoSoDN!$A$5:$A$32,0)) -> Không | U6: =IF(AND(S6="FOB",T6<>"Có",B6>=ThamSo!$C$22,B6<=ThamSo!$C$23,D6<>"",E6<>"",G6<>"",P6<>"",L6<>"",M6<>"",N6<>""),IF(D6>=ThamSo!$C$11,1,0),0) -> 1 | V6: =IF(D6="","",IF(D6<=ThamSo!$C$12,"Nhỏ–vừa","Lớn")) -> Nhỏ–vừa | W6: =IF(D6="","",IF(OR(D6<=ThamSo!$C$13,F6<=ThamSo!$C$14),"Có","Không")) -> Không | X6: =IF(AND(T6<>"Có",M6<>"",D6<>""),IF(D6>=ThamSo!$C$11,M6,""),"") -> 105.53788 | Y6: =IF(U6=1,P6,"") -> 0.11897939 | Z6: =IF(AND(U6=1,V6="Nhỏ–vừa"),P6,"") -> 0.11897939 | AA6: =IF(AND(U6=1,V6="Lớn"),P6,"") | AB6: =IF(U6=1,L6,"") -> 20.640644 | AC6: =IF(AND(U6=1,V6="Nhỏ–vừa"),L6,"") -> 20.640644 | AD6: =IF(AND(U6=1,V6="Lớn"),L6,"") | AE6: =IF(U6=1,M6,"") -> 105.53788 | AF6: =IF(AND(U6=1,V6="Nhỏ–vừa"),M6,"") -> 105.53788 | AG6: =IF(AND(U6=1,V6="Lớn"),M6,"") | AH6: =IF(U6=1,N6,"") -> 84.012707 | AI6: =IF(AND(U6=1,V6="Nhỏ–vừa"),N6,"") -> 84.012707 | AJ6: =IF(AND(U6=1,V6="Lớn"),N6,"") | AK6: =IF(U6=1,Q6,"") -> 0.11897939 | AL6: =IF(AND(U6=1,R6<>""),R6,"") -> 0.098819536 | AM6: =A6&"-"&B6 -> AG1-2024
A7: AG1 | B7: 2025 | C7: FiinTrade_..._AG1_20261018.xlsx | D7: 384757383278 | E7: 0.11571369 | F7: 160263788547 | G7: 145047321035 | H7: 17229224009 | I7: 0 | J7: 77056556959 | K7: 11160450510 | L7: 26.756938 | M7: 83.614772 | N7: 69.834385 | O7: =IF(OR(D7="",E7=""),"",D7*(1-E7)) -> 3.4023569e+11 | P7: =IF(OR(H7="",D7=""),"",IF(D7<=0,"",(H7+N(I7))/D7)) -> 0.04477945 | Q7: =IF(OR(H7="",D7=""),"",IF(D7<=0,"",H7/D7)) -> 0.04477945 | R7: =IF(OR(A6<>A7,B7<=ThamSo!$C$22,H7="",H6="",D7=""),"",IF(D7<=0,"",(H7-H6)/D7)) -> -0.059590257 | S7: =INDEX(HoSoDN!$H$5:$H$32,MATCH(A7,HoSoDN!$A$5:$A$32,0)) -> FOB | T7: =INDEX(HoSoDN!$I$5:$I$32,MATCH(A7,HoSoDN!$A$5:$A$32,0)) -> Không | U7: =IF(AND(S7="FOB",T7<>"Có",B7>=ThamSo!$C$22,B7<=ThamSo!$C$23,D7<>"",E7<>"",G7<>"",P7<>"",L7<>"",M7<>"",N7<>""),IF(D7>=ThamSo!$C$11,1,0),0) -> 1 | V7: =IF(D7="","",IF(D7<=ThamSo!$C$12,"Nhỏ–vừa","Lớn")) -> Nhỏ–vừa | W7: =IF(D7="","",IF(OR(D7<=ThamSo!$C$13,F7<=ThamSo!$C$14),"Có","Không")) -> Không | X7: =IF(AND(T7<>"Có",M7<>"",D7<>""),IF(D7>=ThamSo!$C$11,M7,""),"") -> 83.614772 | Y7: =IF(U7=1,P7,"") -> 0.04477945 | Z7: =IF(AND(U7=1,V7="Nhỏ–vừa"),P7,"") -> 0.04477945 | AA7: =IF(AND(U7=1,V7="Lớn"),P7,"") | AB7: =IF(U7=1,L7,"") -> 26.756938 | AC7: =IF(AND(U7=1,V7="Nhỏ–vừa"),L7,"") -> 26.756938 | AD7: =IF(AND(U7=1,V7="Lớn"),L7,"") | AE7: =IF(U7=1,M7,"") -> 83.614772 | AF7: =IF(AND(U7=1,V7="Nhỏ–vừa"),M7,"") -> 83.614772 | AG7: =IF(AND(U7=1,V7="Lớn"),M7,"") | AH7: =IF(U7=1,N7,"") -> 69.834385 | AI7: =IF(AND(U7=1,V7="Nhỏ–vừa"),N7,"") -> 69.834385 | AJ7: =IF(AND(U7=1,V7="Lớn"),N7,"") | AK7: =IF(U7=1,Q7,"") -> 0.04477945 | AL7: =IF(AND(U7=1,R7<>""),R7,"") -> -0.059590257 | AM7: =A7&"-"&B7 -> AG1-2025
A8: BDG | B8: 2023 | C8: FiinTrade_..._HUG_20261018.xlsx | D8: 1565802348007 | E8: 0.17063204 | F8: 1011708486937 | G8: 762014891824 | H8: 69598955414 | I8: 166744272248 | J8: 257014934641 | K8: 123382071529 | L8: 46.399479 | M8: 75.031069 | N8: 38.543819 | O8: =IF(OR(D8="",E8=""),"",D8*(1-E8)) -> 1.2986263e+12 | P8: =IF(OR(H8="",D8=""),"",IF(D8<=0,"",(H8+N(I8))/D8)) -> 0.15094065 | Q8: =IF(OR(H8="",D8=""),"",IF(D8<=0,"",H8/D8)) -> 0.044449388 | R8: =IF(OR(A7<>A8,B8<=ThamSo!$C$22,H8="",H7="",D8=""),"",IF(D8<=0,"",(H8-H7)/D8)) | S8: =INDEX(HoSoDN!$H$5:$H$32,MATCH(A8,HoSoDN!$A$5:$A$32,0)) -> FOB | T8: =INDEX(HoSoDN!$I$5:$I$32,MATCH(A8,HoSoDN!$A$5:$A$32,0)) -> Không | U8: =IF(AND(S8="FOB",T8<>"Có",B8>=ThamSo!$C$22,B8<=ThamSo!$C$23,D8<>"",E8<>"",G8<>"",P8<>"",L8<>"",M8<>"",N8<>""),IF(D8>=ThamSo!$C$11,1,0),0) -> 1 | V8: =IF(D8="","",IF(D8<=ThamSo!$C$12,"Nhỏ–vừa","Lớn")) -> Lớn | W8: =IF(D8="","",IF(OR(D8<=ThamSo!$C$13,F8<=ThamSo!$C$14),"Có","Không")) -> Không | X8: =IF(AND(T8<>"Có",M8<>"",D8<>""),IF(D8>=ThamSo!$C$11,M8,""),"") -> 75.031069 | Y8: =IF(U8=1,P8,"") -> 0.15094065 | Z8: =IF(AND(U8=1,V8="Nhỏ–vừa"),P8,"") | AA8: =IF(AND(U8=1,V8="Lớn"),P8,"") -> 0.15094065 | AB8: =IF(U8=1,L8,"") -> 46.399479 | AC8: =IF(AND(U8=1,V8="Nhỏ–vừa"),L8,"") | AD8: =IF(AND(U8=1,V8="Lớn"),L8,"") -> 46.399479 | AE8: =IF(U8=1,M8,"") -> 75.031069 | AF8: =IF(AND(U8=1,V8="Nhỏ–vừa"),M8,"") | AG8: =IF(AND(U8=1,V8="Lớn"),M8,"") -> 75.031069 | AH8: =IF(U8=1,N8,"") -> 38.543819 | AI8: =IF(AND(U8=1,V8="Nhỏ–vừa"),N8,"") | AJ8: =IF(AND(U8=1,V8="Lớn"),N8,"") -> 38.543819 | AK8: =IF(U8=1,Q8,"") -> 0.044449388 | AL8: =IF(AND(U8=1,R8<>""),R8,"") | AM8: =A8&"-"&B8 -> BDG-2023
A9: BDG | B9: 2024 | C9: FiinTrade_..._HUG_20261018.xlsx | D9: 1821385866875 | E9: 0.17196293 | F9: 1132622851960 | G9: 892610103449 | H9: 48862200008 | I9: 265402054405 | J9: 235196575141 | K9: 164275444455 | L9: 47.799581 | M9: 59.720353 | N9: 31.093713 | O9: =IF(OR(D9="",E9=""),"",D9*(1-E9)) -> 1.508175e+12 | P9: =IF(OR(H9="",D9=""),"",IF(D9<=0,"",(H9+N(I9))/D9)) -> 0.17254128 | Q9: =IF(OR(H9="",D9=""),"",IF(D9<=0,"",H9/D9)) -> 0.026826935 | R9: =IF(OR(A8<>A9,B9<=ThamSo!$C$22,H9="",H8="",D9=""),"",IF(D9<=0,"",(H9-H8)/D9)) -> -0.011385152 | S9: =INDEX(HoSoDN!$H$5:$H$32,MATCH(A9,HoSoDN!$A$5:$A$32,0)) -> FOB | T9: =INDEX(HoSoDN!$I$5:$I$32,MATCH(A9,HoSoDN!$A$5:$A$32,0)) -> Không | U9: =IF(AND(S9="FOB",T9<>"Có",B9>=ThamSo!$C$22,B9<=ThamSo!$C$23,D9<>"",E9<>"",G9<>"",P9<>"",L9<>"",M9<>"",N9<>""),IF(D9>=ThamSo!$C$11,1,0),0) -> 1 | V9: =IF(D9="","",IF(D9<=ThamSo!$C$12,"Nhỏ–vừa","Lớn")) -> Lớn | W9: =IF(D9="","",IF(OR(D9<=ThamSo!$C$13,F9<=ThamSo!$C$14),"Có","Không")) -> Không | X9: =IF(AND(T9<>"Có",M9<>"",D9<>""),IF(D9>=ThamSo!$C$11,M9,""),"") -> 59.720353 | Y9: =IF(U9=1,P9,"") -> 0.17254128 | Z9: =IF(AND(U9=1,V9="Nhỏ–vừa"),P9,"") | AA9: =IF(AND(U9=1,V9="Lớn"),P9,"") -> 0.17254128 | AB9: =IF(U9=1,L9,"") -> 47.799581 | AC9: =IF(AND(U9=1,V9="Nhỏ–vừa"),L9,"") | AD9: =IF(AND(U9=1,V9="Lớn"),L9,"") -> 47.799581 | AE9: =IF(U9=1,M9,"") -> 59.720353 | AF9: =IF(AND(U9=1,V9="Nhỏ–vừa"),M9,"") | AG9: =IF(AND(U9=1,V9="Lớn"),M9,"") -> 59.720353 | AH9: =IF(U9=1,N9,"") -> 31.093713 | AI9: =IF(AND(U9=1,V9="Nhỏ–vừa"),N9,"") | AJ9: =IF(AND(U9=1,V9="Lớn"),N9,"") -> 31.093713 | AK9: =IF(U9=1,Q9,"") -> 0.026826935 | AL9: =IF(AND(U9=1,R9<>""),R9,"") -> -0.011385152 | AM9: =A9&"-"&B9 -> BDG-2024
A10: BDG | B10: 2025 | C10: FiinTrade_..._HUG_20261018.xlsx | D10: 1765786732419 | E10: 0.16278391 | F10: 1162581117483 | G10: 836089871106 | H10: 40096734073 | I10: 186523398636 | J10: 236366999548 | K10: 125019390165 | L10: 58.115114 | M10: 58.325885 | N10: 32.642841 | O10: =IF(OR(D10="",E10=""),"",D10*(1-E10)) -> 1.4783451e+12 | P10: =IF(OR(H10="",D10=""),"",IF(D10<=0,"",(H10+N(I10))/D10)) -> 0.12833947 | Q10: =IF(OR(H10="",D10=""),"",IF(D10<=0,"",H10/D10)) -> 0.022707575 | R10: =IF(OR(A9<>A10,B10<=ThamSo!$C$22,H10="",H9="",D10=""),"",IF(D10<=0,"",(H10-H9)/D10)) -> -0.004964057 | S10: =INDEX(HoSoDN!$H$5:$H$32,MATCH(A10,HoSoDN!$A$5:$A$32,0)) -> FOB | T10: =INDEX(HoSoDN!$I$5:$I$32,MATCH(A10,HoSoDN!$A$5:$A$32,0)) -> Không | U10: =IF(AND(S10="FOB",T10<>"Có",B10>=ThamSo!$C$22,B10<=ThamSo!$C$23,D10<>"",E10<>"",G10<>"",P10<>"",L10<>"",M10<>"",N10<>""),IF(D10>=ThamSo!$C$11,1,0),0) -> 1 | V10: =IF(D10="","",IF(D10<=ThamSo!$C$12,"Nhỏ–vừa","Lớn")) -> Lớn | W10: =IF(D10="","",IF(OR(D10<=ThamSo!$C$13,F10<=ThamSo!$C$14),"Có","Không")) -> Không | X10: =IF(AND(T10<>"Có",M10<>"",D10<>""),IF(D10>=ThamSo!$C$11,M10,""),"") -> 58.325885 | Y10: =IF(U10=1,P10,"") -> 0.12833947 | Z10: =IF(AND(U10=1,V10="Nhỏ–vừa"),P10,"") | AA10: =IF(AND(U10=1,V10="Lớn"),P10,"") -> 0.12833947 | AB10: =IF(U10=1,L10,"") -> 58.115114 | AC10: =IF(AND(U10=1,V10="Nhỏ–vừa"),L10,"") | AD10: =IF(AND(U10=1,V10="Lớn"),L10,"") -> 58.115114 | AE10: =IF(U10=1,M10,"") -> 58.325885 | AF10: =IF(AND(U10=1,V10="Nhỏ–vừa"),M10,"") | AG10: =IF(AND(U10=1,V10="Lớn"),M10,"") -> 58.325885 | AH10: =IF(U10=1,N10,"") -> 32.642841 | AI10: =IF(AND(U10=1,V10="Nhỏ–vừa"),N10,"") | AJ10: =IF(AND(U10=1,V10="Lớn"),N10,"") -> 32.642841 | AK10: =IF(U10=1,Q10,"") -> 0.022707575 | AL10: =IF(AND(U10=1,R10<>""),R10,"") -> -0.004964057 | AM10: =A10&"-"&B10 -> BDG-2025
A11: BMG | B11: 2023 | C11: FiinTrade_..._BMG_20261018.xlsx | D11: 295724897278 | E11: 0.16773156 | F11: 170519841613 | G11: 99960557124 | H11: 12093331210 | I11: 22927000000 | J11: 34200655246 | K11: 12757476122 | L11: 35.013296 | M11: 61.04222 | N11: 24.979894 | O11: =IF(OR(D11="",E11=""),"",D11*(1-E11)) -> 2.461225e+11 | P11: =IF(OR(H11="",D11=""),"",IF(D11<=0,"",(H11+N(I11))/D11)) -> 0.11842199 | Q11: =IF(OR(H11="",D11=""),"",IF(D11<=0,"",H11/D11)) -> 0.040893855 | R11: =IF(OR(A10<>A11,B11<=ThamSo!$C$22,H11="",H10="",D11=""),"",IF(D11<=0,"",(H11-H10)/D11)) | S11: =INDEX(HoSoDN!$H$5:$H$32,MATCH(A11,HoSoDN!$A$5:$A$32,0)) -> FOB | T11: =INDEX(HoSoDN!$I$5:$I$32,MATCH(A11,HoSoDN!$A$5:$A$32,0)) -> Không | U11: =IF(AND(S11="FOB",T11<>"Có",B11>=ThamSo!$C$22,B11<=ThamSo!$C$23,D11<>"",E11<>"",G11<>"",P11<>"",L11<>"",M11<>"",N11<>""),IF(D11>=ThamSo!$C$11,1,0),0) -> 1 | V11: =IF(D11="","",IF(D11<=ThamSo!$C$12,"Nhỏ–vừa","Lớn")) -> Nhỏ–vừa | W11: =IF(D11="","",IF(OR(D11<=ThamSo!$C$13,F11<=ThamSo!$C$14),"Có","Không")) -> Không | X11: =IF(AND(T11<>"Có",M11<>"",D11<>""),IF(D11>=ThamSo!$C$11,M11,""),"") -> 61.04222 | Y11: =IF(U11=1,P11,"") -> 0.11842199 | Z11: =IF(AND(U11=1,V11="Nhỏ–vừa"),P11,"") -> 0.11842199 | AA11: =IF(AND(U11=1,V11="Lớn"),P11,"") | AB11: =IF(U11=1,L11,"") -> 35.013296 | AC11: =IF(AND(U11=1,V11="Nhỏ–vừa"),L11,"") -> 35.013296 | AD11: =IF(AND(U11=1,V11="Lớn"),L11,"") | AE11: =IF(U11=1,M11,"") -> 61.04222 | AF11: =IF(AND(U11=1,V11="Nhỏ–vừa"),M11,"") -> 61.04222 | AG11: =IF(AND(U11=1,V11="Lớn"),M11,"") | AH11: =IF(U11=1,N11,"") -> 24.979894 | AI11: =IF(AND(U11=1,V11="Nhỏ–vừa"),N11,"") -> 24.979894 | AJ11: =IF(AND(U11=1,V11="Lớn"),N11,"") | AK11: =IF(U11=1,Q11,"") -> 0.040893855 | AL11: =IF(AND(U11=1,R11<>""),R11,"") | AM11: =A11&"-"&B11 -> BMG-2023
A12: BMG | B12: 2024 | C12: FiinTrade_..._BMG_20261018.xlsx | D12: 275980198004 | E12: 0.17963174 | F12: 178466849746 | G12: 110968220994 | H12: 19154911891 | I12: 20020000000 | J12: 45156721479 | K12: 13133441065 | L12: 31.714545 | M12: 64.140082 | N12: 34.455964 | O12: =IF(OR(D12="",E12=""),"",D12*(1-E12)) -> 2.2640539e+11 | P12: =IF(OR(H12="",D12=""),"",IF(D12<=0,"",(H12+N(I12))/D12)) -> 0.14194827 | Q12: =IF(OR(H12="",D12=""),"",IF(D12<=0,"",H12/D12)) -> 0.069406834 | R12: =IF(OR(A11<>A12,B12<=ThamSo!$C$22,H12="",H11="",D12=""),"",IF(D12<=0,"",(H12-H11)/D12)) -> 0.025587273 | S12: =INDEX(HoSoDN!$H$5:$H$32,MATCH(A12,HoSoDN!$A$5:$A$32,0)) -> FOB | T12: =INDEX(HoSoDN!$I$5:$I$32,MATCH(A12,HoSoDN!$A$5:$A$32,0)) -> Không | U12: =IF(AND(S12="FOB",T12<>"Có",B12>=ThamSo!$C$22,B12<=ThamSo!$C$23,D12<>"",E12<>"",G12<>"",P12<>"",L12<>"",M12<>"",N12<>""),IF(D12>=ThamSo!$C$11,1,0),0) -> 1 | V12: =IF(D12="","",IF(D12<=ThamSo!$C$12,"Nhỏ–vừa","Lớn")) -> Nhỏ–vừa | W12: =IF(D12="","",IF(OR(D12<=ThamSo!$C$13,F12<=ThamSo!$C$14),"Có","Không")) -> Không | X12: =IF(AND(T12<>"Có",M12<>"",D12<>""),IF(D12>=ThamSo!$C$11,M12,""),"") -> 64.140082 | Y12: =IF(U12=1,P12,"") -> 0.14194827 | Z12: =IF(AND(U12=1,V12="Nhỏ–vừa"),P12,"") -> 0.14194827 | AA12: =IF(AND(U12=1,V12="Lớn"),P12,"") | AB12: =IF(U12=1,L12,"") -> 31.714545 | AC12: =IF(AND(U12=1,V12="Nhỏ–vừa"),L12,"") -> 31.714545 | AD12: =IF(AND(U12=1,V12="Lớn"),L12,"") | AE12: =IF(U12=1,M12,"") -> 64.140082 | AF12: =IF(AND(U12=1,V12="Nhỏ–vừa"),M12,"") -> 64.140082 | AG12: =IF(AND(U12=1,V12="Lớn"),M12,"") | AH12: =IF(U12=1,N12,"") -> 34.455964 | AI12: =IF(AND(U12=1,V12="Nhỏ–vừa"),N12,"") -> 34.455964 | AJ12: =IF(AND(U12=1,V12="Lớn"),N12,"") | AK12: =IF(U12=1,Q12,"") -> 0.069406834 | AL12: =IF(AND(U12=1,R12<>""),R12,"") -> 0.025587273 | AM12: =A12&"-"&B12 -> BMG-2024
A13: BMG | B13: 2025 | C13: FiinTrade_..._BMG_20261018.xlsx | D13: 295940834048 | E13: 0.18565914 | F13: 190253004726 | G13: 113467882537 | H13: 11934241483 | I13: 335000000 | J13: 52315467227 | K13: 15332652459 | L13: 22.351583 | M13: 73.812934 | N13: 34.06861 | O13: =IF(OR(D13="",E13=""),"",D13*(1-E13)) -> 2.4099671e+11 | P13: =IF(OR(H13="",D13=""),"",IF(D13<=0,"",(H13+N(I13))/D13)) -> 0.041458427 | Q13: =IF(OR(H13="",D13=""),"",IF(D13<=0,"",H13/D13)) -> 0.040326444 | R13: =IF(OR(A12<>A13,B13<=ThamSo!$C$22,H13="",H12="",D13=""),"",IF(D13<=0,"",(H13-H12)/D13)) -> -0.024399034 | S13: =INDEX(HoSoDN!$H$5:$H$32,MATCH(A13,HoSoDN!$A$5:$A$32,0)) -> FOB | T13: =INDEX(HoSoDN!$I$5:$I$32,MATCH(A13,HoSoDN!$A$5:$A$32,0)) -> Không | U13: =IF(AND(S13="FOB",T13<>"Có",B13>=ThamSo!$C$22,B13<=ThamSo!$C$23,D13<>"",E13<>"",G13<>"",P13<>"",L13<>"",M13<>"",N13<>""),IF(D13>=ThamSo!$C$11,1,0),0) -> 1 | V13: =IF(D13="","",IF(D13<=ThamSo!$C$12,"Nhỏ–vừa","Lớn")) -> Nhỏ–vừa | W13: =IF(D13="","",IF(OR(D13<=ThamSo!$C$13,F13<=ThamSo!$C$14),"Có","Không")) -> Không | X13: =IF(AND(T13<>"Có",M13<>"",D13<>""),IF(D13>=ThamSo!$C$11,M13,""),"") -> 73.812934 | Y13: =IF(U13=1,P13,"") -> 0.041458427 | Z13: =IF(AND(U13=1,V13="Nhỏ–vừa"),P13,"") -> 0.041458427 | AA13: =IF(AND(U13=1,V13="Lớn"),P13,"") | AB13: =IF(U13=1,L13,"") -> 22.351583 | AC13: =IF(AND(U13=1,V13="Nhỏ–vừa"),L13,"") -> 22.351583 | AD13: =IF(AND(U13=1,V13="Lớn"),L13,"") | AE13: =IF(U13=1,M13,"") -> 73.812934 | AF13: =IF(AND(U13=1,V13="Nhỏ–vừa"),M13,"") -> 73.812934 | AG13: =IF(AND(U13=1,V13="Lớn"),M13,"") | AH13: =IF(U13=1,N13,"") -> 34.06861 | AI13: =IF(AND(U13=1,V13="Nhỏ–vừa"),N13,"") -> 34.06861 | AJ13: =IF(AND(U13=1,V13="Lớn"),N13,"") | AK13: =IF(U13=1,Q13,"") -> 0.040326444 | AL13: =IF(AND(U13=1,R13<>""),R13,"") -> -0.024399034 | AM13: =A13&"-"&B13 -> BMG-2025
A14: DCG | B14: 2023 | C14: FiinTrade_..._DM7_20261018.xlsx | D14: 554879911020 | E14: 0.22336446 | F14: 421387983406 | G14: 284808203569 | H14: 51053532229 | I14: 173667154043 | J14: 13826248956 | K14: 12336232260 | L14: 20.317411 | M14: 9.2933175 | N14: 8.3803209 | O14: =IF(OR(D14="",E14=""),"",D14*(1-E14)) -> 4.3093946e+11 | P14: =IF(OR(H14="",D14=""),"",IF(D14<=0,"",(H14+N(I14))/D14)) -> 0.40498977 | Q14: =IF(OR(H14="",D14=""),"",IF(D14<=0,"",H14/D14)) -> 0.092008255 | R14: =IF(OR(A13<>A14,B14<=ThamSo!$C$22,H14="",H13="",D14=""),"",IF(D14<=0,"",(H14-H13)/D14)) | S14: =INDEX(HoSoDN!$H$5:$H$32,MATCH(A14,HoSoDN!$A$5:$A$32,0)) -> CMT | T14: =INDEX(HoSoDN!$I$5:$I$32,MATCH(A14,HoSoDN!$A$5:$A$32,0)) -> Không | U14: =IF(AND(S14="FOB",T14<>"Có",B14>=ThamSo!$C$22,B14<=ThamSo!$C$23,D14<>"",E14<>"",G14<>"",P14<>"",L14<>"",M14<>"",N14<>""),IF(D14>=ThamSo!$C$11,1,0),0) -> 0 | V14: =IF(D14="","",IF(D14<=ThamSo!$C$12,"Nhỏ–vừa","Lớn")) -> Nhỏ–vừa | W14: =IF(D14="","",IF(OR(D14<=ThamSo!$C$13,F14<=ThamSo!$C$14),"Có","Không")) -> Không | X14: =IF(AND(T14<>"Có",M14<>"",D14<>""),IF(D14>=ThamSo!$C$11,M14,""),"") -> 9.2933175 | Y14: =IF(U14=1,P14,"") | Z14: =IF(AND(U14=1,V14="Nhỏ–vừa"),P14,"") | AA14: =IF(AND(U14=1,V14="Lớn"),P14,"") | AB14: =IF(U14=1,L14,"") | AC14: =IF(AND(U14=1,V14="Nhỏ–vừa"),L14,"") | AD14: =IF(AND(U14=1,V14="Lớn"),L14,"") | AE14: =IF(U14=1,M14,"") | AF14: =IF(AND(U14=1,V14="Nhỏ–vừa"),M14,"") | AG14: =IF(AND(U14=1,V14="Lớn"),M14,"") | AH14: =IF(U14=1,N14,"") | AI14: =IF(AND(U14=1,V14="Nhỏ–vừa"),N14,"") | AJ14: =IF(AND(U14=1,V14="Lớn"),N14,"") | AK14: =IF(U14=1,Q14,"") | AL14: =IF(AND(U14=1,R14<>""),R14,"") | AM14: =A14&"-"&B14 -> DCG-2023
A15: DCG | B15: 2024 | C15: FiinTrade_..._DM7_20261018.xlsx | D15: 731875404267 | E15: 0.24068147 | F15: 478123596170 | G15: 336718216466 | H15: 75596173316 | I15: 180256349726 | J15: 11600264321 | K15: 20228202016 | L15: 23.054359 | M15: 8.3500394 | N15: 7.7308265 | O15: =IF(OR(D15="",E15=""),"",D15*(1-E15)) -> 5.5572656e+11 | P15: =IF(OR(H15="",D15=""),"",IF(D15<=0,"",(H15+N(I15))/D15)) -> 0.34958481 | Q15: =IF(OR(H15="",D15=""),"",IF(D15<=0,"",H15/D15)) -> 0.10329104 | R15: =IF(OR(A14<>A15,B15<=ThamSo!$C$22,H15="",H14="",D15=""),"",IF(D15<=0,"",(H15-H14)/D15)) -> 0.033533906 | S15: =INDEX(HoSoDN!$H$5:$H$32,MATCH(A15,HoSoDN!$A$5:$A$32,0)) -> CMT | T15: =INDEX(HoSoDN!$I$5:$I$32,MATCH(A15,HoSoDN!$A$5:$A$32,0)) -> Không | U15: =IF(AND(S15="FOB",T15<>"Có",B15>=ThamSo!$C$22,B15<=ThamSo!$C$23,D15<>"",E15<>"",G15<>"",P15<>"",L15<>"",M15<>"",N15<>""),IF(D15>=ThamSo!$C$11,1,0),0) -> 0 | V15: =IF(D15="","",IF(D15<=ThamSo!$C$12,"Nhỏ–vừa","Lớn")) -> Nhỏ–vừa | W15: =IF(D15="","",IF(OR(D15<=ThamSo!$C$13,F15<=ThamSo!$C$14),"Có","Không")) -> Không | X15: =IF(AND(T15<>"Có",M15<>"",D15<>""),IF(D15>=ThamSo!$C$11,M15,""),"") -> 8.3500394 | Y15: =IF(U15=1,P15,"") | Z15: =IF(AND(U15=1,V15="Nhỏ–vừa"),P15,"") | AA15: =IF(AND(U15=1,V15="Lớn"),P15,"") | AB15: =IF(U15=1,L15,"") | AC15: =IF(AND(U15=1,V15="Nhỏ–vừa"),L15,"") | AD15: =IF(AND(U15=1,V15="Lớn"),L15,"") | AE15: =IF(U15=1,M15,"") | AF15: =IF(AND(U15=1,V15="Nhỏ–vừa"),M15,"") | AG15: =IF(AND(U15=1,V15="Lớn"),M15,"") | AH15: =IF(U15=1,N15,"") | AI15: =IF(AND(U15=1,V15="Nhỏ–vừa"),N15,"") | AJ15: =IF(AND(U15=1,V15="Lớn"),N15,"") | AK15: =IF(U15=1,Q15,"") | AL15: =IF(AND(U15=1,R15<>""),R15,"") | AM15: =A15&"-"&B15 -> DCG-2024
A16: DCG | B16: 2025 | C16: FiinTrade_..._DM7_20261018.xlsx | D16: 515338334088 | E16: 0.24777757 | F16: 360209847551 | G16: 245782632955 | H16: 3204618644 | I16: 152926174724 | J16: 10124390976 | K16: 18592465292 | L16: 38.724489 | M16: 10.227678 | N16: 14.651696 | O16: =IF(OR(D16="",E16=""),"",D16*(1-E16)) -> 3.8764905e+11 | P16: =IF(OR(H16="",D16=""),"",IF(D16<=0,"",(H16+N(I16))/D16)) -> 0.30296755 | Q16: =IF(OR(H16="",D16=""),"",IF(D16<=0,"",H16/D16)) -> 0.0062184752 | R16: =IF(OR(A15<>A16,B16<=ThamSo!$C$22,H16="",H15="",D16=""),"",IF(D16<=0,"",(H16-H15)/D16)) -> -0.14047384 | S16: =INDEX(HoSoDN!$H$5:$H$32,MATCH(A16,HoSoDN!$A$5:$A$32,0)) -> CMT | T16: =INDEX(HoSoDN!$I$5:$I$32,MATCH(A16,HoSoDN!$A$5:$A$32,0)) -> Không | U16: =IF(AND(S16="FOB",T16<>"Có",B16>=ThamSo!$C$22,B16<=ThamSo!$C$23,D16<>"",E16<>"",G16<>"",P16<>"",L16<>"",M16<>"",N16<>""),IF(D16>=ThamSo!$C$11,1,0),0) -> 0 | V16: =IF(D16="","",IF(D16<=ThamSo!$C$12,"Nhỏ–vừa","Lớn")) -> Nhỏ–vừa | W16: =IF(D16="","",IF(OR(D16<=ThamSo!$C$13,F16<=ThamSo!$C$14),"Có","Không")) -> Không | X16: =IF(AND(T16<>"Có",M16<>"",D16<>""),IF(D16>=ThamSo!$C$11,M16,""),"") -> 10.227678 | Y16: =IF(U16=1,P16,"") | Z16: =IF(AND(U16=1,V16="Nhỏ–vừa"),P16,"") | AA16: =IF(AND(U16=1,V16="Lớn"),P16,"") | AB16: =IF(U16=1,L16,"") | AC16: =IF(AND(U16=1,V16="Nhỏ–vừa"),L16,"") | AD16: =IF(AND(U16=1,V16="Lớn"),L16,"") | AE16: =IF(U16=1,M16,"") | AF16: =IF(AND(U16=1,V16="Nhỏ–vừa"),M16,"") | AG16: =IF(AND(U16=1,V16="Lớn"),M16,"") | AH16: =IF(U16=1,N16,"") | AI16: =IF(AND(U16=1,V16="Nhỏ–vừa"),N16,"") | AJ16: =IF(AND(U16=1,V16="Lớn"),N16,"") | AK16: =IF(U16=1,Q16,"") | AL16: =IF(AND(U16=1,R16<>""),R16,"") | AM16: =A16&"-"&B16 -> DCG-2025
A17: DM7 | B17: 2023 | C17: FiinTrade_..._DM7_20261018.xlsx | D17: 620231260463 | E17: 0.13704986 | F17: 496837922532 | G17: 333140259403 | H17: 15299677570 | I17: 0 | J17: 108189581639 | K17: 39614513924 | L17: 83.307468 | M17: 81.818822 | N17: 53.507638 | O17: =IF(OR(D17="",E17=""),"",D17*(1-E17)) -> 5.3522865e+11 | P17: =IF(OR(H17="",D17=""),"",IF(D17<=0,"",(H17+N(I17))/D17)) -> 0.024667698 | Q17: =IF(OR(H17="",D17=""),"",IF(D17<=0,"",H17/D17)) -> 0.024667698 | R17: =IF(OR(A16<>A17,B17<=ThamSo!$C$22,H17="",H16="",D17=""),"",IF(D17<=0,"",(H17-H16)/D17)) | S17: =INDEX(HoSoDN!$H$5:$H$32,MATCH(A17,HoSoDN!$A$5:$A$32,0)) -> FOB | T17: =INDEX(HoSoDN!$I$5:$I$32,MATCH(A17,HoSoDN!$A$5:$A$32,0)) -> Không | U17: =IF(AND(S17="FOB",T17<>"Có",B17>=ThamSo!$C$22,B17<=ThamSo!$C$23,D17<>"",E17<>"",G17<>"",P17<>"",L17<>"",M17<>"",N17<>""),IF(D17>=ThamSo!$C$11,1,0),0) -> 1 | V17: =IF(D17="","",IF(D17<=ThamSo!$C$12,"Nhỏ–vừa","Lớn")) -> Nhỏ–vừa | W17: =IF(D17="","",IF(OR(D17<=ThamSo!$C$13,F17<=ThamSo!$C$14),"Có","Không")) -> Không | X17: =IF(AND(T17<>"Có",M17<>"",D17<>""),IF(D17>=ThamSo!$C$11,M17,""),"") -> 81.818822 | Y17: =IF(U17=1,P17,"") -> 0.024667698 | Z17: =IF(AND(U17=1,V17="Nhỏ–vừa"),P17,"") -> 0.024667698 | AA17: =IF(AND(U17=1,V17="Lớn"),P17,"") | AB17: =IF(U17=1,L17,"") -> 83.307468 | AC17: =IF(AND(U17=1,V17="Nhỏ–vừa"),L17,"") -> 83.307468 | AD17: =IF(AND(U17=1,V17="Lớn"),L17,"") | AE17: =IF(U17=1,M17,"") -> 81.818822 | AF17: =IF(AND(U17=1,V17="Nhỏ–vừa"),M17,"") -> 81.818822 | AG17: =IF(AND(U17=1,V17="Lớn"),M17,"") | AH17: =IF(U17=1,N17,"") -> 53.507638 | AI17: =IF(AND(U17=1,V17="Nhỏ–vừa"),N17,"") -> 53.507638 | AJ17: =IF(AND(U17=1,V17="Lớn"),N17,"") | AK17: =IF(U17=1,Q17,"") -> 0.024667698 | AL17: =IF(AND(U17=1,R17<>""),R17,"") | AM17: =A17&"-"&B17 -> DM7-2023
... A19: DM7 | B19: 2025 | C19: FiinTrade_..._DM7_20261018.xlsx | D19: 741070971989 | E19: 0.16244957 | F19: 546179376122 | G19: 406303984542 | H19: 52146473943 | I19: 0 | J19: 87627616096 | K19: 54978209164 | L19: 112.89637 | M19: 55.712532 | N19: 36.144411 | O19: =IF(OR(D19="",E19=""),"",D19*(1-E19)) -> 6.2068431e+11 | P19: =IF(OR(H19="",D19=""),"",IF(D19<=0,"",(H19+N(I19))/D19)) -> 0.07036637 | Q19: =IF(OR(H19="",D19=""),"",IF(D19<=0,"",H19/D19)) -> 0.07036637 | R19: =IF(OR(A18<>A19,B19<=ThamSo!$C$22,H19="",H18="",D19=""),"",IF(D19<=0,"",(H19-H18)/D19)) -> -0.054495349 | S19: =INDEX(HoSoDN!$H$5:$H$32,MATCH(A19,HoSoDN!$A$5:$A$32,0)) -> FOB | T19: =INDEX(HoSoDN!$I$5:$I$32,MATCH(A19,HoSoDN!$A$5:$A$32,0)) -> Không | U19: =IF(AND(S19="FOB",T19<>"Có",B19>=ThamSo!$C$22,B19<=ThamSo!$C$23,D19<>"",E19<>"",G19<>"",P19<>"",L19<>"",M19<>"",N19<>""),IF(D19>=ThamSo!$C$11,1,0),0) -> 1 | V19: =IF(D19="","",IF(D19<=ThamSo!$C$12,"Nhỏ–vừa","Lớn")) -> Nhỏ–vừa | W19: =IF(D19="","",IF(OR(D19<=ThamSo!$C$13,F19<=ThamSo!$C$14),"Có","Không")) -> Không | X19: =IF(AND(T19<>"Có",M19<>"",D19<>""),IF(D19>=ThamSo!$C$11,M19,""),"") -> 55.712532 | Y19: =IF(U19=1,P19,"") -> 0.07036637 | Z19: =IF(AND(U19=1,V19="Nhỏ–vừa"),P19,"") -> 0.07036637 | AA19: =IF(AND(U19=1,V19="Lớn"),P19,"") | AB19: =IF(U19=1,L19,"") -> 112.89637 | AC19: =IF(AND(U19=1,V19="Nhỏ–vừa"),L19,"") -> 112.89637 | AD19: =IF(AND(U19=1,V19="Lớn"),L19,"") | AE19: =IF(U19=1,M19,"") -> 55.712532 | AF19: =IF(AND(U19=1,V19="Nhỏ–vừa"),M19,"") -> 55.712532 | AG19: =IF(AND(U19=1,V19="Lớn"),M19,"") | AH19: =IF(U19=1,N19,"") -> 36.144411 | AI19: =IF(AND(U19=1,V19="Nhỏ–vừa"),N19,"") -> 36.144411 | AJ19: =IF(AND(U19=1,V19="Lớn"),N19,"") | AK19: =IF(U19=1,Q19,"") -> 0.07036637 | AL19: =IF(AND(U19=1,R19<>""),R19,"") -> -0.054495349 | AM19: =A19&"-"&B19 -> DM7-2025
A20: G20 | B20: 2023 | C20: FiinTrade_..._BMG_20261018.xlsx | D20: 0 | F20: 94998553951 | G20: 93021232184 | H20: 12859718 | I20: 100000 | J20: 69793655896 | K20: -13207324290 | O20: =IF(OR(D20="",E20=""),"",D20*(1-E20)) | P20: =IF(OR(H20="",D20=""),"",IF(D20<=0,"",(H20+N(I20))/D20)) | Q20: =IF(OR(H20="",D20=""),"",IF(D20<=0,"",H20/D20)) | R20: =IF(OR(A19<>A20,B20<=ThamSo!$C$22,H20="",H19="",D20=""),"",IF(D20<=0,"",(H20-H19)/D20)) | S20: =INDEX(HoSoDN!$H$5:$H$32,MATCH(A20,HoSoDN!$A$5:$A$32,0)) -> Chưa rõ | T20: =INDEX(HoSoDN!$I$5:$I$32,MATCH(A20,HoSoDN!$A$5:$A$32,0)) -> Không | U20: =IF(AND(S20="FOB",T20<>"Có",B20>=ThamSo!$C$22,B20<=ThamSo!$C$23,D20<>"",E20<>"",G20<>"",P20<>"",L20<>"",M20<>"",N20<>""),IF(D20>=ThamSo!$C$11,1,0),0) -> 0 | V20: =IF(D20="","",IF(D20<=ThamSo!$C$12,"Nhỏ–vừa","Lớn")) -> Nhỏ–vừa | W20: =IF(D20="","",IF(OR(D20<=ThamSo!$C$13,F20<=ThamSo!$C$14),"Có","Không")) -> Có | X20: =IF(AND(T20<>"Có",M20<>"",D20<>""),IF(D20>=ThamSo!$C$11,M20,""),"") | Y20: =IF(U20=1,P20,"") | Z20: =IF(AND(U20=1,V20="Nhỏ–vừa"),P20,"") | AA20: =IF(AND(U20=1,V20="Lớn"),P20,"") | AB20: =IF(U20=1,L20,"") | AC20: =IF(AND(U20=1,V20="Nhỏ–vừa"),L20,"") | AD20: =IF(AND(U20=1,V20="Lớn"),L20,"") | AE20: =IF(U20=1,M20,"") | AF20: =IF(AND(U20=1,V20="Nhỏ–vừa"),M20,"") | AG20: =IF(AND(U20=1,V20="Lớn"),M20,"") | AH20: =IF(U20=1,N20,"") | AI20: =IF(AND(U20=1,V20="Nhỏ–vừa"),N20,"") | AJ20: =IF(AND(U20=1,V20="Lớn"),N20,"") | AK20: =IF(U20=1,Q20,"") | AL20: =IF(AND(U20=1,R20<>""),R20,"") | AM20: =A20&"-"&B20 -> G20-2023
A21: G20 | B21: 2024 | C21: FiinTrade_..._BMG_20261018.xlsx | O21: =IF(OR(D21="",E21=""),"",D21*(1-E21)) | P21: =IF(OR(H21="",D21=""),"",IF(D21<=0,"",(H21+N(I21))/D21)) | Q21: =IF(OR(H21="",D21=""),"",IF(D21<=0,"",H21/D21)) | R21: =IF(OR(A20<>A21,B21<=ThamSo!$C$22,H21="",H20="",D21=""),"",IF(D21<=0,"",(H21-H20)/D21)) | S21: =INDEX(HoSoDN!$H$5:$H$32,MATCH(A21,HoSoDN!$A$5:$A$32,0)) -> Chưa rõ | T21: =INDEX(HoSoDN!$I$5:$I$32,MATCH(A21,HoSoDN!$A$5:$A$32,0)) -> Không | U21: =IF(AND(S21="FOB",T21<>"Có",B21>=ThamSo!$C$22,B21<=ThamSo!$C$23,D21<>"",E21<>"",G21<>"",P21<>"",L21<>"",M21<>"",N21<>""),IF(D21>=ThamSo!$C$11,1,0),0) -> 0 | V21: =IF(D21="","",IF(D21<=ThamSo!$C$12,"Nhỏ–vừa","Lớn")) | W21: =IF(D21="","",IF(OR(D21<=ThamSo!$C$13,F21<=ThamSo!$C$14),"Có","Không")) | X21: =IF(AND(T21<>"Có",M21<>"",D21<>""),IF(D21>=ThamSo!$C$11,M21,""),"") | Y21: =IF(U21=1,P21,"") | Z21: =IF(AND(U21=1,V21="Nhỏ–vừa"),P21,"") | AA21: =IF(AND(U21=1,V21="Lớn"),P21,"") | AB21: =IF(U21=1,L21,"") | AC21: =IF(AND(U21=1,V21="Nhỏ–vừa"),L21,"") | AD21: =IF(AND(U21=1,V21="Lớn"),L21,"") | AE21: =IF(U21=1,M21,"") | AF21: =IF(AND(U21=1,V21="Nhỏ–vừa"),M21,"") | AG21: =IF(AND(U21=1,V21="Lớn"),M21,"") | AH21: =IF(U21=1,N21,"") | AI21: =IF(AND(U21=1,V21="Nhỏ–vừa"),N21,"") | AJ21: =IF(AND(U21=1,V21="Lớn"),N21,"") | AK21: =IF(U21=1,Q21,"") | AL21: =IF(AND(U21=1,R21<>""),R21,"") | AM21: =A21&"-"&B21 -> G20-2024
A22: G20 | B22: 2025 | C22: FiinTrade_..._BMG_20261018.xlsx | O22: =IF(OR(D22="",E22=""),"",D22*(1-E22)) | P22: =IF(OR(H22="",D22=""),"",IF(D22<=0,"",(H22+N(I22))/D22)) | Q22: =IF(OR(H22="",D22=""),"",IF(D22<=0,"",H22/D22)) | R22: =IF(OR(A21<>A22,B22<=ThamSo!$C$22,H22="",H21="",D22=""),"",IF(D22<=0,"",(H22-H21)/D22)) | S22: =INDEX(HoSoDN!$H$5:$H$32,MATCH(A22,HoSoDN!$A$5:$A$32,0)) -> Chưa rõ | T22: =INDEX(HoSoDN!$I$5:$I$32,MATCH(A22,HoSoDN!$A$5:$A$32,0)) -> Không | U22: =IF(AND(S22="FOB",T22<>"Có",B22>=ThamSo!$C$22,B22<=ThamSo!$C$23,D22<>"",E22<>"",G22<>"",P22<>"",L22<>"",M22<>"",N22<>""),IF(D22>=ThamSo!$C$11,1,0),0) -> 0 | V22: =IF(D22="","",IF(D22<=ThamSo!$C$12,"Nhỏ–vừa","Lớn")) | W22: =IF(D22="","",IF(OR(D22<=ThamSo!$C$13,F22<=ThamSo!$C$14),"Có","Không")) | X22: =IF(AND(T22<>"Có",M22<>"",D22<>""),IF(D22>=ThamSo!$C$11,M22,""),"") | Y22: =IF(U22=1,P22,"") | Z22: =IF(AND(U22=1,V22="Nhỏ–vừa"),P22,"") | AA22: =IF(AND(U22=1,V22="Lớn"),P22,"") | AB22: =IF(U22=1,L22,"") | AC22: =IF(AND(U22=1,V22="Nhỏ–vừa"),L22,"") | AD22: =IF(AND(U22=1,V22="Lớn"),L22,"") | AE22: =IF(U22=1,M22,"") | AF22: =IF(AND(U22=1,V22="Nhỏ–vừa"),M22,"") | AG22: =IF(AND(U22=1,V22="Lớn"),M22,"") | AH22: =IF(U22=1,N22,"") | AI22: =IF(AND(U22=1,V22="Nhỏ–vừa"),N22,"") | AJ22: =IF(AND(U22=1,V22="Lớn"),N22,"") | AK22: =IF(U22=1,Q22,"") | AL22: =IF(AND(U22=1,R22<>""),R22,"") | AM22: =A22&"-"&B22 -> G20-2025
A23: GIL | B23: 2023 | C23: FiinTrade_..._HUG_20261018.xlsx | D23: 936395864836 | E23: 0.06523291 | F23: 3357159038688 | G23: 2873181555790 | H23: 674805198823 | I23: 222264100878 | J23: 1364067752069 | K23: 28454692631 | L23: 49.754393 | M23: 545.84396 | N23: 184.97028 | O23: =IF(OR(D23="",E23=""),"",D23*(1-E23)) -> 8.7531204e+11 | P23: =IF(OR(H23="",D23=""),"",IF(D23<=0,"",(H23+N(I23))/D23)) -> 0.9580022 | Q23: =IF(OR(H23="",D23=""),"",IF(D23<=0,"",H23/D23)) -> 0.72064094 | R23: =IF(OR(A22<>A23,B23<=ThamSo!$C$22,H23="",H22="",D23=""),"",IF(D23<=0,"",(H23-H22)/D23)) | S23: =INDEX(HoSoDN!$H$5:$H$32,MATCH(A23,HoSoDN!$A$5:$A$32,0)) -> Loại | T23: =INDEX(HoSoDN!$I$5:$I$32,MATCH(A23,HoSoDN!$A$5:$A$32,0)) -> Có | U23: =IF(AND(S23="FOB",T23<>"Có",B23>=ThamSo!$C$22,B23<=ThamSo!$C$23,D23<>"",E23<>"",G23<>"",P23<>"",L23<>"",M23<>"",N23<>""),IF(D23>=ThamSo!$C$11,1,0),0) -> 0 | V23: =IF(D23="","",IF(D23<=ThamSo!$C$12,"Nhỏ–vừa","Lớn")) -> Nhỏ–vừa | W23: =IF(D23="","",IF(OR(D23<=ThamSo!$C$13,F23<=ThamSo!$C$14),"Có","Không")) -> Không | X23: =IF(AND(T23<>"Có",M23<>"",D23<>""),IF(D23>=ThamSo!$C$11,M23,""),"") | Y23: =IF(U23=1,P23,"") | Z23: =IF(AND(U23=1,V23="Nhỏ–vừa"),P23,"") | AA23: =IF(AND(U23=1,V23="Lớn"),P23,"") | AB23: =IF(U23=1,L23,"") | AC23: =IF(AND(U23=1,V23="Nhỏ–vừa"),L23,"") | AD23: =IF(AND(U23=1,V23="Lớn"),L23,"") | AE23: =IF(U23=1,M23,"") | AF23: =IF(AND(U23=1,V23="Nhỏ–vừa"),M23,"") | AG23: =IF(AND(U23=1,V23="Lớn"),M23,"") | AH23: =IF(U23=1,N23,"") | AI23: =IF(AND(U23=1,V23="Nhỏ–vừa"),N23,"") | AJ23: =IF(AND(U23=1,V23="Lớn"),N23,"") | AK23: =IF(U23=1,Q23,"") | AL23: =IF(AND(U23=1,R23<>""),R23,"") | AM23: =A23&"-"&B23 -> GIL-2023
A24: GIL | B24: 2024 | C24: FiinTrade_..._HUG_20261018.xlsx | D24: 711479404991 | E24: 0.20564329 | F24: 3262218779672 | G24: 2771023974593 | H24: 484495567200 | I24: 280120276760 | J24: 1647039456155 | K24: 26067162087 | L24: 58.868473 | M24: 973.12742 | N24: 198.65331 | O24: =IF(OR(D24="",E24=""),"",D24*(1-E24)) -> 5.6516844e+11 | P24: =IF(OR(H24="",D24=""),"",IF(D24<=0,"",(H24+N(I24))/D24)) -> 1.0746844 | Q24: =IF(OR(H24="",D24=""),"",IF(D24<=0,"",H24/D24)) -> 0.68096921 | R24: =IF(OR(A23<>A24,B24<=ThamSo!$C$22,H24="",H23="",D24=""),"",IF(D24<=0,"",(H24-H23)/D24)) -> -0.26748439 | S24: =INDEX(HoSoDN!$H$5:$H$32,MATCH(A24,HoSoDN!$A$5:$A$32,0)) -> Loại | T24: =INDEX(HoSoDN!$I$5:$I$32,MATCH(A24,HoSoDN!$A$5:$A$32,0)) -> Có | U24: =IF(AND(S24="FOB",T24<>"Có",B24>=ThamSo!$C$22,B24<=ThamSo!$C$23,D24<>"",E24<>"",G24<>"",P24<>"",L24<>"",M24<>"",N24<>""),IF(D24>=ThamSo!$C$11,1,0),0) -> 0 | V24: =IF(D24="","",IF(D24<=ThamSo!$C$12,"Nhỏ–vừa","Lớn")) -> Nhỏ–vừa | W24: =IF(D24="","",IF(OR(D24<=ThamSo!$C$13,F24<=ThamSo!$C$14),"Có","Không")) -> Không | X24: =IF(AND(T24<>"Có",M24<>"",D24<>""),IF(D24>=ThamSo!$C$11,M24,""),"") | Y24: =IF(U24=1,P24,"") | Z24: =IF(AND(U24=1,V24="Nhỏ–vừa"),P24,"") | AA24: =IF(AND(U24=1,V24="Lớn"),P24,"") | AB24: =IF(U24=1,L24,"") | AC24: =IF(AND(U24=1,V24="Nhỏ–vừa"),L24,"") | AD24: =IF(AND(U24=1,V24="Lớn"),L24,"") | AE24: =IF(U24=1,M24,"") | AF24: =IF(AND(U24=1,V24="Nhỏ–vừa"),M24,"") | AG24: =IF(AND(U24=1,V24="Lớn"),M24,"") | AH24: =IF(U24=1,N24,"") | AI24: =IF(AND(U24=1,V24="Nhỏ–vừa"),N24,"") | AJ24: =IF(AND(U24=1,V24="Lớn"),N24,"") | AK24: =IF(U24=1,Q24,"") | AL24: =IF(AND(U24=1,R24<>""),R24,"") | AM24: =A24&"-"&B24 -> GIL-2024
A25: GIL | B25: 2025 | C25: FiinTrade_..._HUG_20261018.xlsx | D25: 713620988088 | E25: 0.22769664 | F25: 3797912574384 | G25: 3122146930242 | H25: 333080969102 | I25: 438991141644 | J25: 1915794251541 | K25: 31392539477 | L25: 36.281576 | M25: 1179.7851 | N25: 112.02979 | O25: =IF(OR(D25="",E25=""),"",D25*(1-E25)) -> 5.5113189e+11 | P25: =IF(OR(H25="",D25=""),"",IF(D25<=0,"",(H25+N(I25))/D25)) -> 1.0819078 | Q25: =IF(OR(H25="",D25=""),"",IF(D25<=0,"",H25/D25)) -> 0.46674772 | R25: =IF(OR(A24<>A25,B25<=ThamSo!$C$22,H25="",H24="",D25=""),"",IF(D25<=0,"",(H25-H24)/D25)) -> -0.21217789 | S25: =INDEX(HoSoDN!$H$5:$H$32,MATCH(A25,HoSoDN!$A$5:$A$32,0)) -> Loại | T25: =INDEX(HoSoDN!$I$5:$I$32,MATCH(A25,HoSoDN!$A$5:$A$32,0)) -> Có | U25: =IF(AND(S25="FOB",T25<>"Có",B25>=ThamSo!$C$22,B25<=ThamSo!$C$23,D25<>"",E25<>"",G25<>"",P25<>"",L25<>"",M25<>"",N25<>""),IF(D25>=ThamSo!$C$11,1,0),0) -> 0 | V25: =IF(D25="","",IF(D25<=ThamSo!$C$12,"Nhỏ–vừa","Lớn")) -> Nhỏ–vừa | W25: =IF(D25="","",IF(OR(D25<=ThamSo!$C$13,F25<=ThamSo!$C$14),"Có","Không")) -> Không | X25: =IF(AND(T25<>"Có",M25<>"",D25<>""),IF(D25>=ThamSo!$C$11,M25,""),"") | Y25: =IF(U25=1,P25,"") | Z25: =IF(AND(U25=1,V25="Nhỏ–vừa"),P25,"") | AA25: =IF(AND(U25=1,V25="Lớn"),P25,"") | AB25: =IF(U25=1,L25,"") | AC25: =IF(AND(U25=1,V25="Nhỏ–vừa"),L25,"") | AD25: =IF(AND(U25=1,V25="Lớn"),L25,"") | AE25: =IF(U25=1,M25,"") | AF25: =IF(AND(U25=1,V25="Nhỏ–vừa"),M25,"") | AG25: =IF(AND(U25=1,V25="Lớn"),M25,"") | AH25: =IF(U25=1,N25,"") | AI25: =IF(AND(U25=1,V25="Nhỏ–vừa"),N25,"") | AJ25: =IF(AND(U25=1,V25="Lớn"),N25,"") | AK25: =IF(U25=1,Q25,"") | AL25: =IF(AND(U25=1,R25<>""),R25,"") | AM25: =A25&"-"&B25 -> GIL-2025
A26: GMC | B26: 2023 | C26: FiinTrade_..._BMG_20261018.xlsx | D26: 8296582790 | E26: -0.48253725 | F26: 419077780479 | G26: 204687573043 | H26: 26403193718 | I26: 65968685907 | J26: 94266805036 | K26: -51944754105 | L26: 346.01817 | M26: 3805.0826 | N26: 158.31598 | O26: =IF(OR(D26="",E26=""),"",D26*(1-E26)) -> 1.2299993e+10 | P26: =IF(OR(H26="",D26=""),"",IF(D26<=0,"",(H26+N(I26))/D26)) -> 11.133726 | Q26: =IF(OR(H26="",D26=""),"",IF(D26<=0,"",H26/D26)) -> 3.1824179 | R26: =IF(OR(A25<>A26,B26<=ThamSo!$C$22,H26="",H25="",D26=""),"",IF(D26<=0,"",(H26-H25)/D26)) | S26: =INDEX(HoSoDN!$H$5:$H$32,MATCH(A26,HoSoDN!$A$5:$A$32,0)) -> Chưa rõ | T26: =INDEX(HoSoDN!$I$5:$I$32,MATCH(A26,HoSoDN!$A$5:$A$32,0)) -> Không | U26: =IF(AND(S26="FOB",T26<>"Có",B26>=ThamSo!$C$22,B26<=ThamSo!$C$23,D26<>"",E26<>"",G26<>"",P26<>"",L26<>"",M26<>"",N26<>""),IF(D26>=ThamSo!$C$11,1,0),0) -> 0 | V26: =IF(D26="","",IF(D26<=ThamSo!$C$12,"Nhỏ–vừa","Lớn")) -> Nhỏ–vừa | W26: =IF(D26="","",IF(OR(D26<=ThamSo!$C$13,F26<=ThamSo!$C$14),"Có","Không")) -> Có | X26: =IF(AND(T26<>"Có",M26<>"",D26<>""),IF(D26>=ThamSo!$C$11,M26,""),"") | Y26: =IF(U26=1,P26,"") | Z26: =IF(AND(U26=1,V26="Nhỏ–vừa"),P26,"") | AA26: =IF(AND(U26=1,V26="Lớn"),P26,"") | AB26: =IF(U26=1,L26,"") | AC26: =IF(AND(U26=1,V26="Nhỏ–vừa"),L26,"") | AD26: =IF(AND(U26=1,V26="Lớn"),L26,"") | AE26: =IF(U26=1,M26,"") | AF26: =IF(AND(U26=1,V26="Nhỏ–vừa"),M26,"") | AG26: =IF(AND(U26=1,V26="Lớn"),M26,"") | AH26: =IF(U26=1,N26,"") | AI26: =IF(AND(U26=1,V26="Nhỏ–vừa"),N26,"") | AJ26: =IF(AND(U26=1,V26="Lớn"),N26,"") | AK26: =IF(U26=1,Q26,"") | AL26: =IF(AND(U26=1,R26<>""),R26,"") | AM26: =A26&"-"&B26 -> GMC-2023
A27: GMC | B27: 2024 | C27: FiinTrade_..._BMG_20261018.xlsx | D27: 2127943650 | E27: 0.90971234 | F27: 375947251647 | G27: 187315471035 | H27: 78791314690 | I27: 680000000 | J27: 94249844471 | K27: -29881480249 | L27: 757.01119 | M27: 227094.56 | N27: 5701.1492 | O27: =IF(OR(D27="",E27=""),"",D27*(1-E27)) -> 1.9212705e+08 | P27: =IF(OR(H27="",D27=""),"",IF(D27<=0,"",(H27+N(I27))/D27)) -> 37.346532 | Q27: =IF(OR(H27="",D27=""),"",IF(D27<=0,"",H27/D27)) -> 37.026974 | R27: =IF(OR(A26<>A27,B27<=ThamSo!$C$22,H27="",H26="",D27=""),"",IF(D27<=0,"",(H27-H26)/D27)) -> 24.61913 | S27: =INDEX(HoSoDN!$H$5:$H$32,MATCH(A27,HoSoDN!$A$5:$A$32,0)) -> Chưa rõ | T27: =INDEX(HoSoDN!$I$5:$I$32,MATCH(A27,HoSoDN!$A$5:$A$32,0)) -> Không | U27: =IF(AND(S27="FOB",T27<>"Có",B27>=ThamSo!$C$22,B27<=ThamSo!$C$23,D27<>"",E27<>"",G27<>"",P27<>"",L27<>"",M27<>"",N27<>""),IF(D27>=ThamSo!$C$11,1,0),0) -> 0 | V27: =IF(D27="","",IF(D27<=ThamSo!$C$12,"Nhỏ–vừa","Lớn")) -> Nhỏ–vừa | W27: =IF(D27="","",IF(OR(D27<=ThamSo!$C$13,F27<=ThamSo!$C$14),"Có","Không")) -> Có | X27: =IF(AND(T27<>"Có",M27<>"",D27<>""),IF(D27>=ThamSo!$C$11,M27,""),"") | Y27: =IF(U27=1,P27,"") | Z27: =IF(AND(U27=1,V27="Nhỏ–vừa"),P27,"") | AA27: =IF(AND(U27=1,V27="Lớn"),P27,"") | AB27: =IF(U27=1,L27,"") | AC27: =IF(AND(U27=1,V27="Nhỏ–vừa"),L27,"") | AD27: =IF(AND(U27=1,V27="Lớn"),L27,"") | AE27: =IF(U27=1,M27,"") | AF27: =IF(AND(U27=1,V27="Nhỏ–vừa"),M27,"") | AG27: =IF(AND(U27=1,V27="Lớn"),M27,"") | AH27: =IF(U27=1,N27,"") | AI27: =IF(AND(U27=1,V27="Nhỏ–vừa"),N27,"") | AJ27: =IF(AND(U27=1,V27="Lớn"),N27,"") | AK27: =IF(U27=1,Q27,"") | AL27: =IF(AND(U27=1,R27<>""),R27,"") | AM27: =A27&"-"&B27 -> GMC-2024
A28: GMC | B28: 2025 | C28: FiinTrade_..._BMG_20261018.xlsx | D28: 1836710093 | E28: 0.87205885 | F28: 351968632281 | G28: 177235424199 | H28: 13360524006 | I28: 56129451054 | J28: 94226120335 | K28: -23970522360 | L28: 852.36336 | M28: 169196.11 | N28: 772.5178 | O28: =IF(OR(D28="",E28=""),"",D28*(1-E28)) -> 2.349908e+08 | P28: =IF(OR(H28="",D28=""),"",IF(D28<=0,"",(H28+N(I28))/D28)) -> 37.833938 | Q28: =IF(OR(H28="",D28=""),"",IF(D28<=0,"",H28/D28)) -> 7.2741605 | R28: =IF(OR(A27<>A28,B28<=ThamSo!$C$22,H28="",H27="",D28=""),"",IF(D28<=0,"",(H28-H27)/D28)) -> -35.623908 | S28: =INDEX(HoSoDN!$H$5:$H$32,MATCH(A28,HoSoDN!$A$5:$A$32,0)) -> Chưa rõ | T28: =INDEX(HoSoDN!$I$5:$I$32,MATCH(A28,HoSoDN!$A$5:$A$32,0)) -> Không | U28: =IF(AND(S28="FOB",T28<>"Có",B28>=ThamSo!$C$22,B28<=ThamSo!$C$23,D28<>"",E28<>"",G28<>"",P28<>"",L28<>"",M28<>"",N28<>""),IF(D28>=ThamSo!$C$11,1,0),0) -> 0 | V28: =IF(D28="","",IF(D28<=ThamSo!$C$12,"Nhỏ–vừa","Lớn")) -> Nhỏ–vừa | W28: =IF(D28="","",IF(OR(D28<=ThamSo!$C$13,F28<=ThamSo!$C$14),"Có","Không")) -> Có | X28: =IF(AND(T28<>"Có",M28<>"",D28<>""),IF(D28>=ThamSo!$C$11,M28,""),"") | Y28: =IF(U28=1,P28,"") | Z28: =IF(AND(U28=1,V28="Nhỏ–vừa"),P28,"") | AA28: =IF(AND(U28=1,V28="Lớn"),P28,"") | AB28: =IF(U28=1,L28,"") | AC28: =IF(AND(U28=1,V28="Nhỏ–vừa"),L28,"") | AD28: =IF(AND(U28=1,V28="Lớn"),L28,"") | AE28: =IF(U28=1,M28,"") | AF28: =IF(AND(U28=1,V28="Nhỏ–vừa"),M28,"") | AG28: =IF(AND(U28=1,V28="Lớn"),M28,"") | AH28: =IF(U28=1,N28,"") | AI28: =IF(AND(U28=1,V28="Nhỏ–vừa"),N28,"") | AJ28: =IF(AND(U28=1,V28="Lớn"),N28,"") | AK28: =IF(U28=1,Q28,"") | AL28: =IF(AND(U28=1,R28<>""),R28,"") | AM28: =A28&"-"&B28 -> GMC-2025
A29: HLT | B29: 2023 | C29: FiinTrade_..._DM7_20261018.xlsx | D29: 780824095814 | E29: 0.00874756 | F29: 447608602640 | G29: 303661082534 | H29: 49644512298 | I29: 24050192963 | J29: 170439079778 | K29: -49853538168 | L29: 21.528217 | M29: 87.245942 | N29: 6.9067689 | O29: =IF(OR(D29="",E29=""),"",D29*(1-E29)) -> 7.7399379e+11 | P29: =IF(OR(H29="",D29=""),"",IF(D29<=0,"",(H29+N(I29))/D29)) -> 0.094380675 | Q29: =IF(OR(H29="",D29=""),"",IF(D29<=0,"",H29/D29)) -> 0.063579637 | R29: =IF(OR(A28<>A29,B29<=ThamSo!$C$22,H29="",H28="",D29=""),"",IF(D29<=0,"",(H29-H28)/D29)) | S29: =INDEX(HoSoDN!$H$5:$H$32,MATCH(A29,HoSoDN!$A$5:$A$32,0)) -> FOB | T29: =INDEX(HoSoDN!$I$5:$I$32,MATCH(A29,HoSoDN!$A$5:$A$32,0)) -> Không | U29: =IF(AND(S29="FOB",T29<>"Có",B29>=ThamSo!$C$22,B29<=ThamSo!$C$23,D29<>"",E29<>"",G29<>"",P29<>"",L29<>"",M29<>"",N29<>""),IF(D29>=ThamSo!$C$11,1,0),0) -> 1 | V29: =IF(D29="","",IF(D29<=ThamSo!$C$12,"Nhỏ–vừa","Lớn")) -> Nhỏ–vừa | W29: =IF(D29="","",IF(OR(D29<=ThamSo!$C$13,F29<=ThamSo!$C$14),"Có","Không")) -> Không | X29: =IF(AND(T29<>"Có",M29<>"",D29<>""),IF(D29>=ThamSo!$C$11,M29,""),"") -> 87.245942 | Y29: =IF(U29=1,P29,"") -> 0.094380675 | Z29: =IF(AND(U29=1,V29="Nhỏ–vừa"),P29,"") -> 0.094380675 | AA29: =IF(AND(U29=1,V29="Lớn"),P29,"") | AB29: =IF(U29=1,L29,"") -> 21.528217 | AC29: =IF(AND(U29=1,V29="Nhỏ–vừa"),L29,"") -> 21.528217 | AD29: =IF(AND(U29=1,V29="Lớn"),L29,"") | AE29: =IF(U29=1,M29,"") -> 87.245942 | AF29: =IF(AND(U29=1,V29="Nhỏ–vừa"),M29,"") -> 87.245942 | AG29: =IF(AND(U29=1,V29="Lớn"),M29,"") | AH29: =IF(U29=1,N29,"") -> 6.9067689 | AI29: =IF(AND(U29=1,V29="Nhỏ–vừa"),N29,"") -> 6.9067689 | AJ29: =IF(AND(U29=1,V29="Lớn"),N29,"") | AK29: =IF(U29=1,Q29,"") -> 0.063579637 | AL29: =IF(AND(U29=1,R29<>""),R29,"") | AM29: =A29&"-"&B29 -> HLT-2023
A30: HLT | B30: 2024 | C30: FiinTrade_..._DM7_20261018.xlsx | D30: 808339562494 | E30: 0.01364139 | F30: 288508672620 | G30: 165103351958 | H30: 35773573770 | I30: 5213280671 | J30: 92839078919 | K30: -47810959701 | L30: 17.97537 | M30: 61.560533 | N30: 8.1371547 | O30: =IF(OR(D30="",E30=""),"",D30*(1-E30)) -> 7.9731269e+11 | P30: =IF(OR(H30="",D30=""),"",IF(D30<=0,"",(H30+N(I30))/D30)) -> 0.050704996 | Q30: =IF(OR(H30="",D30=""),"",IF(D30<=0,"",H30/D30)) -> 0.044255627 | R30: =IF(OR(A29<>A30,B30<=ThamSo!$C$22,H30="",H29="",D30=""),"",IF(D30<=0,"",(H30-H29)/D30)) -> -0.017159792 | S30: =INDEX(HoSoDN!$H$5:$H$32,MATCH(A30,HoSoDN!$A$5:$A$32,0)) -> FOB | T30: =INDEX(HoSoDN!$I$5:$I$32,MATCH(A30,HoSoDN!$A$5:$A$32,0)) -> Không | U30: =IF(AND(S30="FOB",T30<>"Có",B30>=ThamSo!$C$22,B30<=ThamSo!$C$23,D30<>"",E30<>"",G30<>"",P30<>"",L30<>"",M30<>"",N30<>""),IF(D30>=ThamSo!$C$11,1,0),0) -> 1 | V30: =IF(D30="","",IF(D30<=ThamSo!$C$12,"Nhỏ–vừa","Lớn")) -> Nhỏ–vừa | W30: =IF(D30="","",IF(OR(D30<=ThamSo!$C$13,F30<=ThamSo!$C$14),"Có","Không")) -> Không | X30: =IF(AND(T30<>"Có",M30<>"",D30<>""),IF(D30>=ThamSo!$C$11,M30,""),"") -> 61.560533 | Y30: =IF(U30=1,P30,"") -> 0.050704996 | Z30: =IF(AND(U30=1,V30="Nhỏ–vừa"),P30,"") -> 0.050704996 | AA30: =IF(AND(U30=1,V30="Lớn"),P30,"") | AB30: =IF(U30=1,L30,"") -> 17.97537 | AC30: =IF(AND(U30=1,V30="Nhỏ–vừa"),L30,"") -> 17.97537 | AD30: =IF(AND(U30=1,V30="Lớn"),L30,"") | AE30: =IF(U30=1,M30,"") -> 61.560533 | AF30: =IF(AND(U30=1,V30="Nhỏ–vừa"),M30,"") -> 61.560533 | AG30: =IF(AND(U30=1,V30="Lớn"),M30,"") | AH30: =IF(U30=1,N30,"") -> 8.1371547 | AI30: =IF(AND(U30=1,V30="Nhỏ–vừa"),N30,"") -> 8.1371547 | AJ30: =IF(AND(U30=1,V30="Lớn"),N30,"") | AK30: =IF(U30=1,Q30,"") -> 0.044255627 | AL30: =IF(AND(U30=1,R30<>""),R30,"") -> -0.017159792 | AM30: =A30&"-"&B30 -> HLT-2024
A31: HLT | B31: 2025 | C31: FiinTrade_..._DM7_20261018.xlsx | D31: 240789814001 | E31: 0.03135765 | F31: 236693219145 | G31: 130486354054 | H31: 30366870618 | I31: 0 | J31: 77127089636 | K31: -18721793141 | L31: 39.379637 | M31: 137.0893 | N31: 19.250563 | O31: =IF(OR(D31="",E31=""),"",D31*(1-E31)) -> 2.3323921e+11 | P31: =IF(OR(H31="",D31=""),"",IF(D31<=0,"",(H31+N(I31))/D31)) -> 0.1261136 | Q31: =IF(OR(H31="",D31=""),"",IF(D31<=0,"",H31/D31)) -> 0.1261136 | R31: =IF(OR(A30<>A31,B31<=ThamSo!$C$22,H31="",H30="",D31=""),"",IF(D31<=0,"",(H31-H30)/D31)) -> -0.022454036 | S31: =INDEX(HoSoDN!$H$5:$H$32,MATCH(A31,HoSoDN!$A$5:$A$32,0)) -> FOB | T31: =INDEX(HoSoDN!$I$5:$I$32,MATCH(A31,HoSoDN!$A$5:$A$32,0)) -> Không | U31: =IF(AND(S31="FOB",T31<>"Có",B31>=ThamSo!$C$22,B31<=ThamSo!$C$23,D31<>"",E31<>"",G31<>"",P31<>"",L31<>"",M31<>"",N31<>""),IF(D31>=ThamSo!$C$11,1,0),0) -> 1 | V31: =IF(D31="","",IF(D31<=ThamSo!$C$12,"Nhỏ–vừa","Lớn")) -> Nhỏ–vừa | W31: =IF(D31="","",IF(OR(D31<=ThamSo!$C$13,F31<=ThamSo!$C$14),"Có","Không")) -> Không | X31: =IF(AND(T31<>"Có",M31<>"",D31<>""),IF(D31>=ThamSo!$C$11,M31,""),"") -> 137.0893 | Y31: =IF(U31=1,P31,"") -> 0.1261136 | Z31: =IF(AND(U31=1,V31="Nhỏ–vừa"),P31,"") -> 0.1261136 | AA31: =IF(AND(U31=1,V31="Lớn"),P31,"") | AB31: =IF(U31=1,L31,"") -> 39.379637 | AC31: =IF(AND(U31=1,V31="Nhỏ–vừa"),L31,"") -> 39.379637 | AD31: =IF(AND(U31=1,V31="Lớn"),L31,"") | AE31: =IF(U31=1,M31,"") -> 137.0893 | AF31: =IF(AND(U31=1,V31="Nhỏ–vừa"),M31,"") -> 137.0893 | AG31: =IF(AND(U31=1,V31="Lớn"),M31,"") | AH31: =IF(U31=1,N31,"") -> 19.250563 | AI31: =IF(AND(U31=1,V31="Nhỏ–vừa"),N31,"") -> 19.250563 | AJ31: =IF(AND(U31=1,V31="Lớn"),N31,"") | AK31: =IF(U31=1,Q31,"") -> 0.1261136 | AL31: =IF(AND(U31=1,R31<>""),R31,"") -> -0.022454036 | AM31: =A31&"-"&B31 -> HLT-2025
A32: HNI | B32: 2023 | C32: FiinTrade_..._DM7_20261018.xlsx | D32: 869534864259 | E32: 0.16414938 | F32: 649681496210 | G32: 520762094698 | H32: 257963398852 | I32: 0 | J32: 73196478616 | K32: 73473859086 | L32: 37.844702 | M32: 31.899606 | N32: 12.94332 | O32: =IF(OR(D32="",E32=""),"",D32*(1-E32)) -> 7.2680126e+11 | P32: =IF(OR(H32="",D32=""),"",IF(D32<=0,"",(H32+N(I32))/D32)) -> 0.29666826 | Q32: =IF(OR(H32="",D32=""),"",IF(D32<=0,"",H32/D32)) -> 0.29666826 | R32: =IF(OR(A31<>A32,B32<=ThamSo!$C$22,H32="",H31="",D32=""),"",IF(D32<=0,"",(H32-H31)/D32)) | S32: =INDEX(HoSoDN!$H$5:$H$32,MATCH(A32,HoSoDN!$A$5:$A$32,0)) -> FOB | T32: =INDEX(HoSoDN!$I$5:$I$32,MATCH(A32,HoSoDN!$A$5:$A$32,0)) -> Không | U32: =IF(AND(S32="FOB",T32<>"Có",B32>=ThamSo!$C$22,B32<=ThamSo!$C$23,D32<>"",E32<>"",G32<>"",P32<>"",L32<>"",M32<>"",N32<>""),IF(D32>=ThamSo!$C$11,1,0),0) -> 1 | V32: =IF(D32="","",IF(D32<=ThamSo!$C$12,"Nhỏ–vừa","Lớn")) -> Nhỏ–vừa | W32: =IF(D32="","",IF(OR(D32<=ThamSo!$C$13,F32<=ThamSo!$C$14),"Có","Không")) -> Không | X32: =IF(AND(T32<>"Có",M32<>"",D32<>""),IF(D32>=ThamSo!$C$11,M32,""),"") -> 31.899606 | Y32: =IF(U32=1,P32,"") -> 0.29666826 | Z32: =IF(AND(U32=1,V32="Nhỏ–vừa"),P32,"") -> 0.29666826 | AA32: =IF(AND(U32=1,V32="Lớn"),P32,"") | AB32: =IF(U32=1,L32,"") -> 37.844702 | AC32: =IF(AND(U32=1,V32="Nhỏ–vừa"),L32,"") -> 37.844702 | AD32: =IF(AND(U32=1,V32="Lớn"),L32,"") | AE32: =IF(U32=1,M32,"") -> 31.899606 | AF32: =IF(AND(U32=1,V32="Nhỏ–vừa"),M32,"") -> 31.899606 | AG32: =IF(AND(U32=1,V32="Lớn"),M32,"") | AH32: =IF(U32=1,N32,"") -> 12.94332 | AI32: =IF(AND(U32=1,V32="Nhỏ–vừa"),N32,"") -> 12.94332 | AJ32: =IF(AND(U32=1,V32="Lớn"),N32,"") | AK32: =IF(U32=1,Q32,"") -> 0.29666826 | AL32: =IF(AND(U32=1,R32<>""),R32,"") | AM32: =A32&"-"&B32 -> HNI-2023
A33: HNI | B33: 2024 | C33: FiinTrade_..._DM7_20261018.xlsx | D33: 1182125636807 | E33: 0.16780598 | F33: 758725727595 | G33: 620029094940 | H33: 323365091248 | I33: 0 | J33: 64717891381 | K33: 105903870569 | L33: 41.237603 | M33: 25.584926 | N33: 12.055209 | O33: =IF(OR(D33="",E33=""),"",D33*(1-E33)) -> 9.8375789e+11 | P33: =IF(OR(H33="",D33=""),"",IF(D33<=0,"",(H33+N(I33))/D33)) -> 0.27354545 | Q33: =IF(OR(H33="",D33=""),"",IF(D33<=0,"",H33/D33)) -> 0.27354545 | R33: =IF(OR(A32<>A33,B33<=ThamSo!$C$22,H33="",H32="",D33=""),"",IF(D33<=0,"",(H33-H32)/D33)) -> 0.0553255 | S33: =INDEX(HoSoDN!$H$5:$H$32,MATCH(A33,HoSoDN!$A$5:$A$32,0)) -> FOB | T33: =INDEX(HoSoDN!$I$5:$I$32,MATCH(A33,HoSoDN!$A$5:$A$32,0)) -> Không | U33: =IF(AND(S33="FOB",T33<>"Có",B33>=ThamSo!$C$22,B33<=ThamSo!$C$23,D33<>"",E33<>"",G33<>"",P33<>"",L33<>"",M33<>"",N33<>""),IF(D33>=ThamSo!$C$11,1,0),0) -> 1 | V33: =IF(D33="","",IF(D33<=ThamSo!$C$12,"Nhỏ–vừa","Lớn")) -> Nhỏ–vừa | W33: =IF(D33="","",IF(OR(D33<=ThamSo!$C$13,F33<=ThamSo!$C$14),"Có","Không")) -> Không | X33: =IF(AND(T33<>"Có",M33<>"",D33<>""),IF(D33>=ThamSo!$C$11,M33,""),"") -> 25.584926 | Y33: =IF(U33=1,P33,"") -> 0.27354545 | Z33: =IF(AND(U33=1,V33="Nhỏ–vừa"),P33,"") -> 0.27354545 | AA33: =IF(AND(U33=1,V33="Lớn"),P33,"") | AB33: =IF(U33=1,L33,"") -> 41.237603 | AC33: =IF(AND(U33=1,V33="Nhỏ–vừa"),L33,"") -> 41.237603 | AD33: =IF(AND(U33=1,V33="Lớn"),L33,"") | AE33: =IF(U33=1,M33,"") -> 25.584926 | AF33: =IF(AND(U33=1,V33="Nhỏ–vừa"),M33,"") -> 25.584926 | AG33: =IF(AND(U33=1,V33="Lớn"),M33,"") | AH33: =IF(U33=1,N33,"") -> 12.055209 | AI33: =IF(AND(U33=1,V33="Nhỏ–vừa"),N33,"") -> 12.055209 | AJ33: =IF(AND(U33=1,V33="Lớn"),N33,"") | AK33: =IF(U33=1,Q33,"") -> 0.27354545 | AL33: =IF(AND(U33=1,R33<>""),R33,"") -> 0.0553255 | AM33: =A33&"-"&B33 -> HNI-2024
A34: HNI | B34: 2025 | C34: FiinTrade_..._DM7_20261018.xlsx | D34: 980292288149 | E34: 0.17679612 | F34: 828028754633 | G34: 624387760545 | H34: 335399301943 | I34: 0 | J34: 54572964061 | K34: 93735184164 | L34: 63.252339 | M34: 26.977831 | N34: 25.8665 | O34: =IF(OR(D34="",E34=""),"",D34*(1-E34)) -> 8.0698042e+11 | P34: =IF(OR(H34="",D34=""),"",IF(D34<=0,"",(H34+N(I34))/D34)) -> 0.34214214 | Q34: =IF(OR(H34="",D34=""),"",IF(D34<=0,"",H34/D34)) -> 0.34214214 | R34: =IF(OR(A33<>A34,B34<=ThamSo!$C$22,H34="",H33="",D34=""),"",IF(D34<=0,"",(H34-H33)/D34)) -> 0.012276145 | S34: =INDEX(HoSoDN!$H$5:$H$32,MATCH(A34,HoSoDN!$A$5:$A$32,0)) -> FOB | T34: =INDEX(HoSoDN!$I$5:$I$32,MATCH(A34,HoSoDN!$A$5:$A$32,0)) -> Không | U34: =IF(AND(S34="FOB",T34<>"Có",B34>=ThamSo!$C$22,B34<=ThamSo!$C$23,D34<>"",E34<>"",G34<>"",P34<>"",L34<>"",M34<>"",N34<>""),IF(D34>=ThamSo!$C$11,1,0),0) -> 1 | V34: =IF(D34="","",IF(D34<=ThamSo!$C$12,"Nhỏ–vừa","Lớn")) -> Nhỏ–vừa | W34: =IF(D34="","",IF(OR(D34<=ThamSo!$C$13,F34<=ThamSo!$C$14),"Có","Không")) -> Không | X34: =IF(AND(T34<>"Có",M34<>"",D34<>""),IF(D34>=ThamSo!$C$11,M34,""),"") -> 26.977831 | Y34: =IF(U34=1,P34,"") -> 0.34214214 | Z34: =IF(AND(U34=1,V34="Nhỏ–vừa"),P34,"") -> 0.34214214 | AA34: =IF(AND(U34=1,V34="Lớn"),P34,"") | AB34: =IF(U34=1,L34,"") -> 63.252339 | AC34: =IF(AND(U34=1,V34="Nhỏ–vừa"),L34,"") -> 63.252339 | AD34: =IF(AND(U34=1,V34="Lớn"),L34,"") | AE34: =IF(U34=1,M34,"") -> 26.977831 | AF34: =IF(AND(U34=1,V34="Nhỏ–vừa"),M34,"") -> 26.977831 | AG34: =IF(AND(U34=1,V34="Lớn"),M34,"") | AH34: =IF(U34=1,N34,"") -> 25.8665 | AI34: =IF(AND(U34=1,V34="Nhỏ–vừa"),N34,"") -> 25.8665 | AJ34: =IF(AND(U34=1,V34="Lớn"),N34,"") | AK34: =IF(U34=1,Q34,"") -> 0.34214214 | AL34: =IF(AND(U34=1,R34<>""),R34,"") -> 0.012276145 | AM34: =A34&"-"&B34 -> HNI-2025
... A49: MNB | B49: 2025 | C49: FiinTrade_..._MSH_20261018.xlsx | D49: 5249810552745 | E49: 0.18661124 | F49: 3451997999981 | G49: 2668413771619 | H49: 507882290593 | I49: 115186973261 | J49: 697698480176 | K49: 153881686164 | L49: 71.097731 | M49: 59.789629 | N49: 24.57389 | O49: =IF(OR(D49="",E49=""),"",D49*(1-E49)) -> 4.2701369e+12 | P49: =IF(OR(H49="",D49=""),"",IF(D49<=0,"",(H49+N(I49))/D49)) -> 0.11868414 | Q49: =IF(OR(H49="",D49=""),"",IF(D49<=0,"",H49/D49)) -> 0.096742975 | R49: =IF(OR(A48<>A49,B49<=ThamSo!$C$22,H49="",H48="",D49=""),"",IF(D49<=0,"",(H49-H48)/D49)) -> 0.032478817 | S49: =INDEX(HoSoDN!$H$5:$H$32,MATCH(A49,HoSoDN!$A$5:$A$32,0)) -> FOB | T49: =INDEX(HoSoDN!$I$5:$I$32,MATCH(A49,HoSoDN!$A$5:$A$32,0)) -> Không | U49: =IF(AND(S49="FOB",T49<>"Có",B49>=ThamSo!$C$22,B49<=ThamSo!$C$23,D49<>"",E49<>"",G49<>"",P49<>"",L49<>"",M49<>"",N49<>""),IF(D49>=ThamSo!$C$11,1,0),0) -> 1 | V49: =IF(D49="","",IF(D49<=ThamSo!$C$12,"Nhỏ–vừa","Lớn")) -> Lớn | W49: =IF(D49="","",IF(OR(D49<=ThamSo!$C$13,F49<=ThamSo!$C$14),"Có","Không")) -> Không | X49: =IF(AND(T49<>"Có",M49<>"",D49<>""),IF(D49>=ThamSo!$C$11,M49,""),"") -> 59.789629 | Y49: =IF(U49=1,P49,"") -> 0.11868414 | Z49: =IF(AND(U49=1,V49="Nhỏ–vừa"),P49,"") | AA49: =IF(AND(U49=1,V49="Lớn"),P49,"") -> 0.11868414 | AB49: =IF(U49=1,L49,"") -> 71.097731 | AC49: =IF(AND(U49=1,V49="Nhỏ–vừa"),L49,"") | AD49: =IF(AND(U49=1,V49="Lớn"),L49,"") -> 71.097731 | AE49: =IF(U49=1,M49,"") -> 59.789629 | AF49: =IF(AND(U49=1,V49="Nhỏ–vừa"),M49,"") | AG49: =IF(AND(U49=1,V49="Lớn"),M49,"") -> 59.789629 | AH49: =IF(U49=1,N49,"") -> 24.57389 | AI49: =IF(AND(U49=1,V49="Nhỏ–vừa"),N49,"") | AJ49: =IF(AND(U49=1,V49="Lớn"),N49,"") -> 24.57389 | AK49: =IF(U49=1,Q49,"") -> 0.096742975 | AL49: =IF(AND(U49=1,R49<>""),R49,"") -> 0.032478817 | AM49: =A49&"-"&B49 -> MNB-2025
A50: MPT | B50: 2023 | C50: FiinTrade_..._BMG_20261018.xlsx | D50: 0 | F50: 196555589947 | G50: 184628385677 | H50: 53007887 | I50: 0 | J50: 36995516576 | K50: -2543550575 | O50: =IF(OR(D50="",E50=""),"",D50*(1-E50)) | P50: =IF(OR(H50="",D50=""),"",IF(D50<=0,"",(H50+N(I50))/D50)) | Q50: =IF(OR(H50="",D50=""),"",IF(D50<=0,"",H50/D50)) | R50: =IF(OR(A49<>A50,B50<=ThamSo!$C$22,H50="",H49="",D50=""),"",IF(D50<=0,"",(H50-H49)/D50)) | S50: =INDEX(HoSoDN!$H$5:$H$32,MATCH(A50,HoSoDN!$A$5:$A$32,0)) -> Chưa rõ | T50: =INDEX(HoSoDN!$I$5:$I$32,MATCH(A50,HoSoDN!$A$5:$A$32,0)) -> Không | U50: =IF(AND(S50="FOB",T50<>"Có",B50>=ThamSo!$C$22,B50<=ThamSo!$C$23,D50<>"",E50<>"",G50<>"",P50<>"",L50<>"",M50<>"",N50<>""),IF(D50>=ThamSo!$C$11,1,0),0) -> 0 | V50: =IF(D50="","",IF(D50<=ThamSo!$C$12,"Nhỏ–vừa","Lớn")) -> Nhỏ–vừa | W50: =IF(D50="","",IF(OR(D50<=ThamSo!$C$13,F50<=ThamSo!$C$14),"Có","Không")) -> Có | X50: =IF(AND(T50<>"Có",M50<>"",D50<>""),IF(D50>=ThamSo!$C$11,M50,""),"") | Y50: =IF(U50=1,P50,"") | Z50: =IF(AND(U50=1,V50="Nhỏ–vừa"),P50,"") | AA50: =IF(AND(U50=1,V50="Lớn"),P50,"") | AB50: =IF(U50=1,L50,"") | AC50: =IF(AND(U50=1,V50="Nhỏ–vừa"),L50,"") | AD50: =IF(AND(U50=1,V50="Lớn"),L50,"") | AE50: =IF(U50=1,M50,"") | AF50: =IF(AND(U50=1,V50="Nhỏ–vừa"),M50,"") | AG50: =IF(AND(U50=1,V50="Lớn"),M50,"") | AH50: =IF(U50=1,N50,"") | AI50: =IF(AND(U50=1,V50="Nhỏ–vừa"),N50,"") | AJ50: =IF(AND(U50=1,V50="Lớn"),N50,"") | AK50: =IF(U50=1,Q50,"") | AL50: =IF(AND(U50=1,R50<>""),R50,"") | AM50: =A50&"-"&B50 -> MPT-2023
A51: MPT | B51: 2024 | C51: FiinTrade_..._BMG_20261018.xlsx | D51: 0 | F51: 177584811910 | G51: 165767046455 | H51: 50144066 | I51: 0 | J51: 20288454566 | K51: -17456621515 | M51: 808.24285 | N51: 175.69286 | O51: =IF(OR(D51="",E51=""),"",D51*(1-E51)) | P51: =IF(OR(H51="",D51=""),"",IF(D51<=0,"",(H51+N(I51))/D51)) | Q51: =IF(OR(H51="",D51=""),"",IF(D51<=0,"",H51/D51)) | R51: =IF(OR(A50<>A51,B51<=ThamSo!$C$22,H51="",H50="",D51=""),"",IF(D51<=0,"",(H51-H50)/D51)) | S51: =INDEX(HoSoDN!$H$5:$H$32,MATCH(A51,HoSoDN!$A$5:$A$32,0)) -> Chưa rõ | T51: =INDEX(HoSoDN!$I$5:$I$32,MATCH(A51,HoSoDN!$A$5:$A$32,0)) -> Không | U51: =IF(AND(S51="FOB",T51<>"Có",B51>=ThamSo!$C$22,B51<=ThamSo!$C$23,D51<>"",E51<>"",G51<>"",P51<>"",L51<>"",M51<>"",N51<>""),IF(D51>=ThamSo!$C$11,1,0),0) -> 0 | V51: =IF(D51="","",IF(D51<=ThamSo!$C$12,"Nhỏ–vừa","Lớn")) -> Nhỏ–vừa | W51: =IF(D51="","",IF(OR(D51<=ThamSo!$C$13,F51<=ThamSo!$C$14),"Có","Không")) -> Có | X51: =IF(AND(T51<>"Có",M51<>"",D51<>""),IF(D51>=ThamSo!$C$11,M51,""),"") | Y51: =IF(U51=1,P51,"") | Z51: =IF(AND(U51=1,V51="Nhỏ–vừa"),P51,"") | AA51: =IF(AND(U51=1,V51="Lớn"),P51,"") | AB51: =IF(U51=1,L51,"") | AC51: =IF(AND(U51=1,V51="Nhỏ–vừa"),L51,"") | AD51: =IF(AND(U51=1,V51="Lớn"),L51,"") | AE51: =IF(U51=1,M51,"") | AF51: =IF(AND(U51=1,V51="Nhỏ–vừa"),M51,"") | AG51: =IF(AND(U51=1,V51="Lớn"),M51,"") | AH51: =IF(U51=1,N51,"") | AI51: =IF(AND(U51=1,V51="Nhỏ–vừa"),N51,"") | AJ51: =IF(AND(U51=1,V51="Lớn"),N51,"") | AK51: =IF(U51=1,Q51,"") | AL51: =IF(AND(U51=1,R51<>""),R51,"") | AM51: =A51&"-"&B51 -> MPT-2024
A52: MPT | B52: 2025 | C52: FiinTrade_..._BMG_20261018.xlsx | D52: 0 | F52: 176981211631 | G52: 165282974176 | H52: 44927247 | I52: 0 | J52: 20288454566 | K52: -719347648 | O52: =IF(OR(D52="",E52=""),"",D52*(1-E52)) | P52: =IF(OR(H52="",D52=""),"",IF(D52<=0,"",(H52+N(I52))/D52)) | Q52: =IF(OR(H52="",D52=""),"",IF(D52<=0,"",H52/D52)) | R52: =IF(OR(A51<>A52,B52<=ThamSo!$C$22,H52="",H51="",D52=""),"",IF(D52<=0,"",(H52-H51)/D52)) | S52: =INDEX(HoSoDN!$H$5:$H$32,MATCH(A52,HoSoDN!$A$5:$A$32,0)) -> Chưa rõ | T52: =INDEX(HoSoDN!$I$5:$I$32,MATCH(A52,HoSoDN!$A$5:$A$32,0)) -> Không | U52: =IF(AND(S52="FOB",T52<>"Có",B52>=ThamSo!$C$22,B52<=ThamSo!$C$23,D52<>"",E52<>"",G52<>"",P52<>"",L52<>"",M52<>"",N52<>""),IF(D52>=ThamSo!$C$11,1,0),0) -> 0 | V52: =IF(D52="","",IF(D52<=ThamSo!$C$12,"Nhỏ–vừa","Lớn")) -> Nhỏ–vừa | W52: =IF(D52="","",IF(OR(D52<=ThamSo!$C$13,F52<=ThamSo!$C$14),"Có","Không")) -> Có | X52: =IF(AND(T52<>"Có",M52<>"",D52<>""),IF(D52>=ThamSo!$C$11,M52,""),"") | Y52: =IF(U52=1,P52,"") | Z52: =IF(AND(U52=1,V52="Nhỏ–vừa"),P52,"") | AA52: =IF(AND(U52=1,V52="Lớn"),P52,"") | AB52: =IF(U52=1,L52,"") | AC52: =IF(AND(U52=1,V52="Nhỏ–vừa"),L52,"") | AD52: =IF(AND(U52=1,V52="Lớn"),L52,"") | AE52: =IF(U52=1,M52,"") | AF52: =IF(AND(U52=1,V52="Nhỏ–vừa"),M52,"") | AG52: =IF(AND(U52=1,V52="Lớn"),M52,"") | AH52: =IF(U52=1,N52,"") | AI52: =IF(AND(U52=1,V52="Nhỏ–vừa"),N52,"") | AJ52: =IF(AND(U52=1,V52="Lớn"),N52,"") | AK52: =IF(U52=1,Q52,"") | AL52: =IF(AND(U52=1,R52<>""),R52,"") | AM52: =A52&"-"&B52 -> MPT-2025
A53: MSH | B53: 2023 | C53: FiinTrade_..._MSH_20261018.xlsx | D53: 4541917426355 | E53: 0.12417302 | F53: 3453089147362 | G53: 2552594388012 | H53: 455323804538 | I53: 970784740090 | J53: 506531306409 | K53: 244549614845 | L53: 37.575738 | M53: 51.880806 | N53: 16.66394 | O53: =IF(OR(D53="",E53=""),"",D53*(1-E53)) -> 3.9779338e+12 | P53: =IF(OR(H53="",D53=""),"",IF(D53<=0,"",(H53+N(I53))/D53)) -> 0.31398821 | Q53: =IF(OR(H53="",D53=""),"",IF(D53<=0,"",H53/D53)) -> 0.10024925 | R53: =IF(OR(A52<>A53,B53<=ThamSo!$C$22,H53="",H52="",D53=""),"",IF(D53<=0,"",(H53-H52)/D53)) | S53: =INDEX(HoSoDN!$H$5:$H$32,MATCH(A53,HoSoDN!$A$5:$A$32,0)) -> FOB | T53: =INDEX(HoSoDN!$I$5:$I$32,MATCH(A53,HoSoDN!$A$5:$A$32,0)) -> Không | U53: =IF(AND(S53="FOB",T53<>"Có",B53>=ThamSo!$C$22,B53<=ThamSo!$C$23,D53<>"",E53<>"",G53<>"",P53<>"",L53<>"",M53<>"",N53<>""),IF(D53>=ThamSo!$C$11,1,0),0) -> 1 | V53: =IF(D53="","",IF(D53<=ThamSo!$C$12,"Nhỏ–vừa","Lớn")) -> Lớn | W53: =IF(D53="","",IF(OR(D53<=ThamSo!$C$13,F53<=ThamSo!$C$14),"Có","Không")) -> Không | X53: =IF(AND(T53<>"Có",M53<>"",D53<>""),IF(D53>=ThamSo!$C$11,M53,""),"") -> 51.880806 | Y53: =IF(U53=1,P53,"") -> 0.31398821 | Z53: =IF(AND(U53=1,V53="Nhỏ–vừa"),P53,"") | AA53: =IF(AND(U53=1,V53="Lớn"),P53,"") -> 0.31398821 | AB53: =IF(U53=1,L53,"") -> 37.575738 | AC53: =IF(AND(U53=1,V53="Nhỏ–vừa"),L53,"") | AD53: =IF(AND(U53=1,V53="Lớn"),L53,"") -> 37.575738 | AE53: =IF(U53=1,M53,"") -> 51.880806 | AF53: =IF(AND(U53=1,V53="Nhỏ–vừa"),M53,"") | AG53: =IF(AND(U53=1,V53="Lớn"),M53,"") -> 51.880806 | AH53: =IF(U53=1,N53,"") -> 16.66394 | AI53: =IF(AND(U53=1,V53="Nhỏ–vừa"),N53,"") | AJ53: =IF(AND(U53=1,V53="Lớn"),N53,"") -> 16.66394 | AK53: =IF(U53=1,Q53,"") -> 0.10024925 | AL53: =IF(AND(U53=1,R53<>""),R53,"") | AM53: =A53&"-"&B53 -> MSH-2023
A54: MSH | B54: 2024 | C54: FiinTrade_..._MSH_20261018.xlsx | D54: 5280403155194 | E54: 0.15709183 | F54: 4523188931186 | G54: 3249615903700 | H54: 886350410790 | I54: 653102618812 | J54: 645400140922 | K54: 412522765304 | L54: 54.083058 | M54: 48.039351 | N54: 12.947473 | O54: =IF(OR(D54="",E54=""),"",D54*(1-E54)) -> 4.450895e+12 | P54: =IF(OR(H54="",D54=""),"",IF(D54<=0,"",(H54+N(I54))/D54)) -> 0.29154081 | Q54: =IF(OR(H54="",D54=""),"",IF(D54<=0,"",H54/D54)) -> 0.16785658 | R54: =IF(OR(A53<>A54,B54<=ThamSo!$C$22,H54="",H53="",D54=""),"",IF(D54<=0,"",(H54-H53)/D54)) -> 0.081627594 | S54: =INDEX(HoSoDN!$H$5:$H$32,MATCH(A54,HoSoDN!$A$5:$A$32,0)) -> FOB | T54: =INDEX(HoSoDN!$I$5:$I$32,MATCH(A54,HoSoDN!$A$5:$A$32,0)) -> Không | U54: =IF(AND(S54="FOB",T54<>"Có",B54>=ThamSo!$C$22,B54<=ThamSo!$C$23,D54<>"",E54<>"",G54<>"",P54<>"",L54<>"",M54<>"",N54<>""),IF(D54>=ThamSo!$C$11,1,0),0) -> 1 | V54: =IF(D54="","",IF(D54<=ThamSo!$C$12,"Nhỏ–vừa","Lớn")) -> Lớn | W54: =IF(D54="","",IF(OR(D54<=ThamSo!$C$13,F54<=ThamSo!$C$14),"Có","Không")) -> Không | X54: =IF(AND(T54<>"Có",M54<>"",D54<>""),IF(D54>=ThamSo!$C$11,M54,""),"") -> 48.039351 | Y54: =IF(U54=1,P54,"") -> 0.29154081 | Z54: =IF(AND(U54=1,V54="Nhỏ–vừa"),P54,"") | AA54: =IF(AND(U54=1,V54="Lớn"),P54,"") -> 0.29154081 | AB54: =IF(U54=1,L54,"") -> 54.083058 | AC54: =IF(AND(U54=1,V54="Nhỏ–vừa"),L54,"") | AD54: =IF(AND(U54=1,V54="Lớn"),L54,"") -> 54.083058 | AE54: =IF(U54=1,M54,"") -> 48.039351 | AF54: =IF(AND(U54=1,V54="Nhỏ–vừa"),M54,"") | AG54: =IF(AND(U54=1,V54="Lớn"),M54,"") -> 48.039351 | AH54: =IF(U54=1,N54,"") -> 12.947473 | AI54: =IF(AND(U54=1,V54="Nhỏ–vừa"),N54,"") | AJ54: =IF(AND(U54=1,V54="Lớn"),N54,"") -> 12.947473 | AK54: =IF(U54=1,Q54,"") -> 0.16785658 | AL54: =IF(AND(U54=1,R54<>""),R54,"") -> 0.081627594 | AM54: =A54&"-"&B54 -> MSH-2024
A55: MSH | B55: 2025 | C55: FiinTrade_..._MSH_20261018.xlsx | D55: 5538068232450 | E55: 0.21206088 | F55: 4677754975723 | G55: 3275000080003 | H55: 739632646576 | I55: 880144449074 | J55: 546122052854 | K55: 613919710840 | L55: 63.237965 | M55: 50.400766 | N55: 15.363061 | O55: =IF(OR(D55="",E55=""),"",D55*(1-E55)) -> 4.3636606e+12 | P55: =IF(OR(H55="",D55=""),"",IF(D55<=0,"",(H55+N(I55))/D55)) -> 0.29248052 | Q55: =IF(OR(H55="",D55=""),"",IF(D55<=0,"",H55/D55)) -> 0.13355427 | R55: =IF(OR(A54<>A55,B55<=ThamSo!$C$22,H55="",H54="",D55=""),"",IF(D55<=0,"",(H55-H54)/D55)) -> -0.026492589 | S55: =INDEX(HoSoDN!$H$5:$H$32,MATCH(A55,HoSoDN!$A$5:$A$32,0)) -> FOB | T55: =INDEX(HoSoDN!$I$5:$I$32,MATCH(A55,HoSoDN!$A$5:$A$32,0)) -> Không | U55: =IF(AND(S55="FOB",T55<>"Có",B55>=ThamSo!$C$22,B55<=ThamSo!$C$23,D55<>"",E55<>"",G55<>"",P55<>"",L55<>"",M55<>"",N55<>""),IF(D55>=ThamSo!$C$11,1,0),0) -> 1 | V55: =IF(D55="","",IF(D55<=ThamSo!$C$12,"Nhỏ–vừa","Lớn")) -> Lớn | W55: =IF(D55="","",IF(OR(D55<=ThamSo!$C$13,F55<=ThamSo!$C$14),"Có","Không")) -> Không | X55: =IF(AND(T55<>"Có",M55<>"",D55<>""),IF(D55>=ThamSo!$C$11,M55,""),"") -> 50.400766 | Y55: =IF(U55=1,P55,"") -> 0.29248052 | Z55: =IF(AND(U55=1,V55="Nhỏ–vừa"),P55,"") | AA55: =IF(AND(U55=1,V55="Lớn"),P55,"") -> 0.29248052 | AB55: =IF(U55=1,L55,"") -> 63.237965 | AC55: =IF(AND(U55=1,V55="Nhỏ–vừa"),L55,"") | AD55: =IF(AND(U55=1,V55="Lớn"),L55,"") -> 63.237965 | AE55: =IF(U55=1,M55,"") -> 50.400766 | AF55: =IF(AND(U55=1,V55="Nhỏ–vừa"),M55,"") | AG55: =IF(AND(U55=1,V55="Lớn"),M55,"") -> 50.400766 | AH55: =IF(U55=1,N55,"") -> 15.363061 | AI55: =IF(AND(U55=1,V55="Nhỏ–vừa"),N55,"") | AJ55: =IF(AND(U55=1,V55="Lớn"),N55,"") -> 15.363061 | AK55: =IF(U55=1,Q55,"") -> 0.13355427 | AL55: =IF(AND(U55=1,R55<>""),R55,"") -> -0.026492589 | AM55: =A55&"-"&B55 -> MSH-2025
A56: NJC | B56: 2023 | C56: FiinTrade_..._BMG_20261018.xlsx | D56: 524132187401 | E56: 0.08668146 | F56: 414680865439 | G56: 349606688651 | H56: 38851243245 | I56: 7080657534 | J56: 177328997577 | K56: 6298539183 | L56: 61.065652 | M56: 111.13703 | N56: 17.897413 | O56: =IF(OR(D56="",E56=""),"",D56*(1-E56)) -> 4.7869964e+11 | P56: =IF(OR(H56="",D56=""),"",IF(D56<=0,"",(H56+N(I56))/D56)) -> 0.087634192 | Q56: =IF(OR(H56="",D56=""),"",IF(D56<=0,"",H56/D56)) -> 0.074124895 | R56: =IF(OR(A55<>A56,B56<=ThamSo!$C$22,H56="",H55="",D56=""),"",IF(D56<=0,"",(H56-H55)/D56)) | S56: =INDEX(HoSoDN!$H$5:$H$32,MATCH(A56,HoSoDN!$A$5:$A$32,0)) -> FOB | T56: =INDEX(HoSoDN!$I$5:$I$32,MATCH(A56,HoSoDN!$A$5:$A$32,0)) -> Không | U56: =IF(AND(S56="FOB",T56<>"Có",B56>=ThamSo!$C$22,B56<=ThamSo!$C$23,D56<>"",E56<>"",G56<>"",P56<>"",L56<>"",M56<>"",N56<>""),IF(D56>=ThamSo!$C$11,1,0),0) -> 1 | V56: =IF(D56="","",IF(D56<=ThamSo!$C$12,"Nhỏ–vừa","Lớn")) -> Nhỏ–vừa | W56: =IF(D56="","",IF(OR(D56<=ThamSo!$C$13,F56<=ThamSo!$C$14),"Có","Không")) -> Không | X56: =IF(AND(T56<>"Có",M56<>"",D56<>""),IF(D56>=ThamSo!$C$11,M56,""),"") -> 111.13703 | Y56: =IF(U56=1,P56,"") -> 0.087634192 | Z56: =IF(AND(U56=1,V56="Nhỏ–vừa"),P56,"") -> 0.087634192 | AA56: =IF(AND(U56=1,V56="Lớn"),P56,"") | AB56: =IF(U56=1,L56,"") -> 61.065652 | AC56: =IF(AND(U56=1,V56="Nhỏ–vừa"),L56,"") -> 61.065652 | AD56: =IF(AND(U56=1,V56="Lớn"),L56,"") | AE56: =IF(U56=1,M56,"") -> 111.13703 | AF56: =IF(AND(U56=1,V56="Nhỏ–vừa"),M56,"") -> 111.13703 | AG56: =IF(AND(U56=1,V56="Lớn"),M56,"") | AH56: =IF(U56=1,N56,"") -> 17.897413 | AI56: =IF(AND(U56=1,V56="Nhỏ–vừa"),N56,"") -> 17.897413 | AJ56: =IF(AND(U56=1,V56="Lớn"),N56,"") | AK56: =IF(U56=1,Q56,"") -> 0.074124895 | AL56: =IF(AND(U56=1,R56<>""),R56,"") | AM56: =A56&"-"&B56 -> NJC-2023
A57: NJC | B57: 2024 | C57: FiinTrade_..._BMG_20261018.xlsx | D57: 804895415372 | E57: 0.09076951 | F57: 367055608018 | G57: 283454335161 | H57: 33515279071 | I57: 16000000000 | J57: 119417428962 | K57: 11897445676 | L57: 47.95098 | M57: 77.730203 | N57: 14.874344 | O57: =IF(OR(D57="",E57=""),"",D57*(1-E57)) -> 7.3183545e+11 | P57: =IF(OR(H57="",D57=""),"",IF(D57<=0,"",(H57+N(I57))/D57)) -> 0.061517656 | Q57: =IF(OR(H57="",D57=""),"",IF(D57<=0,"",H57/D57)) -> 0.041639297 | R57: =IF(OR(A56<>A57,B57<=ThamSo!$C$22,H57="",H56="",D57=""),"",IF(D57<=0,"",(H57-H56)/D57)) -> -0.0066293882 | S57: =INDEX(HoSoDN!$H$5:$H$32,MATCH(A57,HoSoDN!$A$5:$A$32,0)) -> FOB | T57: =INDEX(HoSoDN!$I$5:$I$32,MATCH(A57,HoSoDN!$A$5:$A$32,0)) -> Không | U57: =IF(AND(S57="FOB",T57<>"Có",B57>=ThamSo!$C$22,B57<=ThamSo!$C$23,D57<>"",E57<>"",G57<>"",P57<>"",L57<>"",M57<>"",N57<>""),IF(D57>=ThamSo!$C$11,1,0),0) -> 1 | V57: =IF(D57="","",IF(D57<=ThamSo!$C$12,"Nhỏ–vừa","Lớn")) -> Nhỏ–vừa | W57: =IF(D57="","",IF(OR(D57<=ThamSo!$C$13,F57<=ThamSo!$C$14),"Có","Không")) -> Không | X57: =IF(AND(T57<>"Có",M57<>"",D57<>""),IF(D57>=ThamSo!$C$11,M57,""),"") -> 77.730203 | Y57: =IF(U57=1,P57,"") -> 0.061517656 | Z57: =IF(AND(U57=1,V57="Nhỏ–vừa"),P57,"") -> 0.061517656 | AA57: =IF(AND(U57=1,V57="Lớn"),P57,"") | AB57: =IF(U57=1,L57,"") -> 47.95098 | AC57: =IF(AND(U57=1,V57="Nhỏ–vừa"),L57,"") -> 47.95098 | AD57: =IF(AND(U57=1,V57="Lớn"),L57,"") | AE57: =IF(U57=1,M57,"") -> 77.730203 | AF57: =IF(AND(U57=1,V57="Nhỏ–vừa"),M57,"") -> 77.730203 | AG57: =IF(AND(U57=1,V57="Lớn"),M57,"") | AH57: =IF(U57=1,N57,"") -> 14.874344 | AI57: =IF(AND(U57=1,V57="Nhỏ–vừa"),N57,"") -> 14.874344 | AJ57: =IF(AND(U57=1,V57="Lớn"),N57,"") | AK57: =IF(U57=1,Q57,"") -> 0.041639297 | AL57: =IF(AND(U57=1,R57<>""),R57,"") -> -0.0066293882 | AM57: =A57&"-"&B57 -> NJC-2024
A58: NJC | B58: 2025 | C58: FiinTrade_..._BMG_20261018.xlsx | D58: 661508276276 | E58: 0.09258787 | F58: 409330851696 | G58: 347100136454 | H58: 22599716278 | I58: 15000000000 | J58: 153206226113 | K58: 12595341779 | L58: 67.146842 | M58: 86.7301 | N58: 20.986708 | O58: =IF(OR(D58="",E58=""),"",D58*(1-E58)) -> 6.0026063e+11 | P58: =IF(OR(H58="",D58=""),"",IF(D58<=0,"",(H58+N(I58))/D58)) -> 0.056839374 | Q58: =IF(OR(H58="",D58=""),"",IF(D58<=0,"",H58/D58)) -> 0.034163921 | R58: =IF(OR(A57<>A58,B58<=ThamSo!$C$22,H58="",H57="",D58=""),"",IF(D58<=0,"",(H58-H57)/D58)) -> -0.016501022 | S58: =INDEX(HoSoDN!$H$5:$H$32,MATCH(A58,HoSoDN!$A$5:$A$32,0)) -> FOB | T58: =INDEX(HoSoDN!$I$5:$I$32,MATCH(A58,HoSoDN!$A$5:$A$32,0)) -> Không | U58: =IF(AND(S58="FOB",T58<>"Có",B58>=ThamSo!$C$22,B58<=ThamSo!$C$23,D58<>"",E58<>"",G58<>"",P58<>"",L58<>"",M58<>"",N58<>""),IF(D58>=ThamSo!$C$11,1,0),0) -> 1 | V58: =IF(D58="","",IF(D58<=ThamSo!$C$12,"Nhỏ–vừa","Lớn")) -> Nhỏ–vừa | W58: =IF(D58="","",IF(OR(D58<=ThamSo!$C$13,F58<=ThamSo!$C$14),"Có","Không")) -> Không | X58: =IF(AND(T58<>"Có",M58<>"",D58<>""),IF(D58>=ThamSo!$C$11,M58,""),"") -> 86.7301 | Y58: =IF(U58=1,P58,"") -> 0.056839374 | Z58: =IF(AND(U58=1,V58="Nhỏ–vừa"),P58,"") -> 0.056839374 | AA58: =IF(AND(U58=1,V58="Lớn"),P58,"") | AB58: =IF(U58=1,L58,"") -> 67.146842 | AC58: =IF(AND(U58=1,V58="Nhỏ–vừa"),L58,"") -> 67.146842 | AD58: =IF(AND(U58=1,V58="Lớn"),L58,"") | AE58: =IF(U58=1,M58,"") -> 86.7301 | AF58: =IF(AND(U58=1,V58="Nhỏ–vừa"),M58,"") -> 86.7301 | AG58: =IF(AND(U58=1,V58="Lớn"),M58,"") | AH58: =IF(U58=1,N58,"") -> 20.986708 | AI58: =IF(AND(U58=1,V58="Nhỏ–vừa"),N58,"") -> 20.986708 | AJ58: =IF(AND(U58=1,V58="Lớn"),N58,"") | AK58: =IF(U58=1,Q58,"") -> 0.034163921 | AL58: =IF(AND(U58=1,R58<>""),R58,"") -> -0.016501022 | AM58: =A58&"-"&B58 -> NJC-2025
A59: NTT | B59: 2023 | C59: FiinTrade_..._AG1_20261018.xlsx | D59: 801781567706 | E59: 0.04385932 | F59: 1040987023950 | G59: 477965760493 | H59: 58132985214 | I59: 44620000000 | J59: 262231841788 | K59: -16483653623 | L59: 59.46983 | M59: 154.65072 | N59: 112.52079 | O59: =IF(OR(D59="",E59=""),"",D59*(1-E59)) -> 7.6661597e+11 | P59: =IF(OR(H59="",D59=""),"",IF(D59<=0,"",(H59+N(I59))/D59)) -> 0.12815583 | Q59: =IF(OR(H59="",D59=""),"",IF(D59<=0,"",H59/D59)) -> 0.072504766 | R59: =IF(OR(A58<>A59,B59<=ThamSo!$C$22,H59="",H58="",D59=""),"",IF(D59<=0,"",(H59-H58)/D59)) | S59: =INDEX(HoSoDN!$H$5:$H$32,MATCH(A59,HoSoDN!$A$5:$A$32,0)) -> FOB | T59: =INDEX(HoSoDN!$I$5:$I$32,MATCH(A59,HoSoDN!$A$5:$A$32,0)) -> Không | U59: =IF(AND(S59="FOB",T59<>"Có",B59>=ThamSo!$C$22,B59<=ThamSo!$C$23,D59<>"",E59<>"",G59<>"",P59<>"",L59<>"",M59<>"",N59<>""),IF(D59>=ThamSo!$C$11,1,0),0) -> 1 | V59: =IF(D59="","",IF(D59<=ThamSo!$C$12,"Nhỏ–vừa","Lớn")) -> Nhỏ–vừa | W59: =IF(D59="","",IF(OR(D59<=ThamSo!$C$13,F59<=ThamSo!$C$14),"Có","Không")) -> Không | X59: =IF(AND(T59<>"Có",M59<>"",D59<>""),IF(D59>=ThamSo!$C$11,M59,""),"") -> 154.65072 | Y59: =IF(U59=1,P59,"") -> 0.12815583 | Z59: =IF(AND(U59=1,V59="Nhỏ–vừa"),P59,"") -> 0.12815583 | AA59: =IF(AND(U59=1,V59="Lớn"),P59,"") | AB59: =IF(U59=1,L59,"") -> 59.46983 | AC59: =IF(AND(U59=1,V59="Nhỏ–vừa"),L59,"") -> 59.46983 | AD59: =IF(AND(U59=1,V59="Lớn"),L59,"") | AE59: =IF(U59=1,M59,"") -> 154.65072 | AF59: =IF(AND(U59=1,V59="Nhỏ–vừa"),M59,"") -> 154.65072 | AG59: =IF(AND(U59=1,V59="Lớn"),M59,"") | AH59: =IF(U59=1,N59,"") -> 112.52079 | AI59: =IF(AND(U59=1,V59="Nhỏ–vừa"),N59,"") -> 112.52079 | AJ59: =IF(AND(U59=1,V59="Lớn"),N59,"") | AK59: =IF(U59=1,Q59,"") -> 0.072504766 | AL59: =IF(AND(U59=1,R59<>""),R59,"") | AM59: =A59&"-"&B59 -> NTT-2023
A60: NTT | B60: 2024 | C60: FiinTrade_..._AG1_20261018.xlsx | D60: 1233648206745 | E60: 0.0771879 | F60: 1234813575320 | G60: 739726368206 | H60: 34093204093 | I60: 67570000000 | J60: 389790016266 | K60: 29511755656 | L60: 51.586102 | M60: 104.63331 | N60: 73.679788 | O60: =IF(OR(D60="",E60=""),"",D60*(1-E60)) -> 1.1384255e+12 | P60: =IF(OR(H60="",D60=""),"",IF(D60<=0,"",(H60+N(I60))/D60)) -> 0.082408586 | Q60: =IF(OR(H60="",D60=""),"",IF(D60<=0,"",H60/D60)) -> 0.027636083 | R60: =IF(OR(A59<>A60,B60<=ThamSo!$C$22,H60="",H59="",D60=""),"",IF(D60<=0,"",(H60-H59)/D60)) -> -0.019486739 | S60: =INDEX(HoSoDN!$H$5:$H$32,MATCH(A60,HoSoDN!$A$5:$A$32,0)) -> FOB | T60: =INDEX(HoSoDN!$I$5:$I$32,MATCH(A60,HoSoDN!$A$5:$A$32,0)) -> Không | U60: =IF(AND(S60="FOB",T60<>"Có",B60>=ThamSo!$C$22,B60<=ThamSo!$C$23,D60<>"",E60<>"",G60<>"",P60<>"",L60<>"",M60<>"",N60<>""),IF(D60>=ThamSo!$C$11,1,0),0) -> 1 | V60: =IF(D60="","",IF(D60<=ThamSo!$C$12,"Nhỏ–vừa","Lớn")) -> Nhỏ–vừa | W60: =IF(D60="","",IF(OR(D60<=ThamSo!$C$13,F60<=ThamSo!$C$14),"Có","Không")) -> Không | X60: =IF(AND(T60<>"Có",M60<>"",D60<>""),IF(D60>=ThamSo!$C$11,M60,""),"") -> 104.63331 | Y60: =IF(U60=1,P60,"") -> 0.082408586 | Z60: =IF(AND(U60=1,V60="Nhỏ–vừa"),P60,"") -> 0.082408586 | AA60: =IF(AND(U60=1,V60="Lớn"),P60,"") | AB60: =IF(U60=1,L60,"") -> 51.586102 | AC60: =IF(AND(U60=1,V60="Nhỏ–vừa"),L60,"") -> 51.586102 | AD60: =IF(AND(U60=1,V60="Lớn"),L60,"") | AE60: =IF(U60=1,M60,"") -> 104.63331 | AF60: =IF(AND(U60=1,V60="Nhỏ–vừa"),M60,"") -> 104.63331 | AG60: =IF(AND(U60=1,V60="Lớn"),M60,"") | AH60: =IF(U60=1,N60,"") -> 73.679788 | AI60: =IF(AND(U60=1,V60="Nhỏ–vừa"),N60,"") -> 73.679788 | AJ60: =IF(AND(U60=1,V60="Lớn"),N60,"") | AK60: =IF(U60=1,Q60,"") -> 0.027636083 | AL60: =IF(AND(U60=1,R60<>""),R60,"") -> -0.019486739 | AM60: =A60&"-"&B60 -> NTT-2024
A61: NTT | B61: 2025 | C61: FiinTrade_..._AG1_20261018.xlsx | D61: 1526835689293 | E61: 0.08361146 | F61: 1123848048291 | G61: 608874680858 | H61: 51125520814 | I61: 11000000000 | J61: 239393005368 | K61: 39500751050 | L61: 51.667854 | M61: 82.099853 | N61: 58.330559 | O61: =IF(OR(D61="",E61=""),"",D61*(1-E61)) -> 1.3991747e+12 | P61: =IF(OR(H61="",D61=""),"",IF(D61<=0,"",(H61+N(I61))/D61)) -> 0.040689068 | Q61: =IF(OR(H61="",D61=""),"",IF(D61<=0,"",H61/D61)) -> 0.033484625 | R61: =IF(OR(A60<>A61,B61<=ThamSo!$C$22,H61="",H60="",D61=""),"",IF(D61<=0,"",(H61-H60)/D61)) -> 0.011155304 | S61: =INDEX(HoSoDN!$H$5:$H$32,MATCH(A61,HoSoDN!$A$5:$A$32,0)) -> FOB | T61: =INDEX(HoSoDN!$I$5:$I$32,MATCH(A61,HoSoDN!$A$5:$A$32,0)) -> Không | U61: =IF(AND(S61="FOB",T61<>"Có",B61>=ThamSo!$C$22,B61<=ThamSo!$C$23,D61<>"",E61<>"",G61<>"",P61<>"",L61<>"",M61<>"",N61<>""),IF(D61>=ThamSo!$C$11,1,0),0) -> 1 | V61: =IF(D61="","",IF(D61<=ThamSo!$C$12,"Nhỏ–vừa","Lớn")) -> Lớn | W61: =IF(D61="","",IF(OR(D61<=ThamSo!$C$13,F61<=ThamSo!$C$14),"Có","Không")) -> Không | X61: =IF(AND(T61<>"Có",M61<>"",D61<>""),IF(D61>=ThamSo!$C$11,M61,""),"") -> 82.099853 | Y61: =IF(U61=1,P61,"") -> 0.040689068 | Z61: =IF(AND(U61=1,V61="Nhỏ–vừa"),P61,"") | AA61: =IF(AND(U61=1,V61="Lớn"),P61,"") -> 0.040689068 | AB61: =IF(U61=1,L61,"") -> 51.667854 | AC61: =IF(AND(U61=1,V61="Nhỏ–vừa"),L61,"") | AD61: =IF(AND(U61=1,V61="Lớn"),L61,"") -> 51.667854 | AE61: =IF(U61=1,M61,"") -> 82.099853 | AF61: =IF(AND(U61=1,V61="Nhỏ–vừa"),M61,"") | AG61: =IF(AND(U61=1,V61="Lớn"),M61,"") -> 82.099853 | AH61: =IF(U61=1,N61,"") -> 58.330559 | AI61: =IF(AND(U61=1,V61="Nhỏ–vừa"),N61,"") | AJ61: =IF(AND(U61=1,V61="Lớn"),N61,"") -> 58.330559 | AK61: =IF(U61=1,Q61,"") -> 0.033484625 | AL61: =IF(AND(U61=1,R61<>""),R61,"") -> 0.011155304 | AM61: =A61&"-"&B61 -> NTT-2025
A62: PTG | B62: 2023 | C62: FiinTrade_..._BMG_20261018.xlsx | D62: 460825919834 | E62: 0.12309845 | F62: 321783059013 | G62: 281295211998 | H62: 80773892017 | I62: 146000000000 | J62: 6041107368 | K62: 46722206980 | L62: 28.44142 | M62: 4.9542144 | N62: 4.701281 | O62: =IF(OR(D62="",E62=""),"",D62*(1-E62)) -> 4.0409896e+11 | P62: =IF(OR(H62="",D62=""),"",IF(D62<=0,"",(H62+N(I62))/D62)) -> 0.49210316 | Q62: =IF(OR(H62="",D62=""),"",IF(D62<=0,"",H62/D62)) -> 0.1752807 | R62: =IF(OR(A61<>A62,B62<=ThamSo!$C$22,H62="",H61="",D62=""),"",IF(D62<=0,"",(H62-H61)/D62)) | S62: =INDEX(HoSoDN!$H$5:$H$32,MATCH(A62,HoSoDN!$A$5:$A$32,0)) -> CMT | T62: =INDEX(HoSoDN!$I$5:$I$32,MATCH(A62,HoSoDN!$A$5:$A$32,0)) -> Không | U62: =IF(AND(S62="FOB",T62<>"Có",B62>=ThamSo!$C$22,B62<=ThamSo!$C$23,D62<>"",E62<>"",G62<>"",P62<>"",L62<>"",M62<>"",N62<>""),IF(D62>=ThamSo!$C$11,1,0),0) -> 0 | V62: =IF(D62="","",IF(D62<=ThamSo!$C$12,"Nhỏ–vừa","Lớn")) -> Nhỏ–vừa | W62: =IF(D62="","",IF(OR(D62<=ThamSo!$C$13,F62<=ThamSo!$C$14),"Có","Không")) -> Không | X62: =IF(AND(T62<>"Có",M62<>"",D62<>""),IF(D62>=ThamSo!$C$11,M62,""),"") -> 4.9542144 | Y62: =IF(U62=1,P62,"") | Z62: =IF(AND(U62=1,V62="Nhỏ–vừa"),P62,"") | AA62: =IF(AND(U62=1,V62="Lớn"),P62,"") | AB62: =IF(U62=1,L62,"") | AC62: =IF(AND(U62=1,V62="Nhỏ–vừa"),L62,"") | AD62: =IF(AND(U62=1,V62="Lớn"),L62,"") | AE62: =IF(U62=1,M62,"") | AF62: =IF(AND(U62=1,V62="Nhỏ–vừa"),M62,"") | AG62: =IF(AND(U62=1,V62="Lớn"),M62,"") | AH62: =IF(U62=1,N62,"") | AI62: =IF(AND(U62=1,V62="Nhỏ–vừa"),N62,"") | AJ62: =IF(AND(U62=1,V62="Lớn"),N62,"") | AK62: =IF(U62=1,Q62,"") | AL62: =IF(AND(U62=1,R62<>""),R62,"") | AM62: =A62&"-"&B62 -> PTG-2023
A63: PTG | B63: 2024 | C63: FiinTrade_..._BMG_20261018.xlsx | D63: 488148803973 | E63: 0.1322806 | F63: 363679213348 | G63: 331710162955 | H63: 121108811298 | I63: 141500000000 | J63: 4095403133 | K63: 52468288084 | L63: 26.766573 | M63: 4.3673682 | N63: 4.1139862 | O63: =IF(OR(D63="",E63=""),"",D63*(1-E63)) -> 4.2357619e+11 | P63: =IF(OR(H63="",D63=""),"",IF(D63<=0,"",(H63+N(I63))/D63)) -> 0.53796877 | Q63: =IF(OR(H63="",D63=""),"",IF(D63<=0,"",H63/D63)) -> 0.24809814 | R63: =IF(OR(A62<>A63,B63<=ThamSo!$C$22,H63="",H62="",D63=""),"",IF(D63<=0,"",(H63-H62)/D63)) -> 0.082628328 | S63: =INDEX(HoSoDN!$H$5:$H$32,MATCH(A63,HoSoDN!$A$5:$A$32,0)) -> CMT | T63: =INDEX(HoSoDN!$I$5:$I$32,MATCH(A63,HoSoDN!$A$5:$A$32,0)) -> Không | U63: =IF(AND(S63="FOB",T63<>"Có",B63>=ThamSo!$C$22,B63<=ThamSo!$C$23,D63<>"",E63<>"",G63<>"",P63<>"",L63<>"",M63<>"",N63<>""),IF(D63>=ThamSo!$C$11,1,0),0) -> 0 | V63: =IF(D63="","",IF(D63<=ThamSo!$C$12,"Nhỏ–vừa","Lớn")) -> Nhỏ–vừa | W63: =IF(D63="","",IF(OR(D63<=ThamSo!$C$13,F63<=ThamSo!$C$14),"Có","Không")) -> Không | X63: =IF(AND(T63<>"Có",M63<>"",D63<>""),IF(D63>=ThamSo!$C$11,M63,""),"") -> 4.3673682 | Y63: =IF(U63=1,P63,"") | Z63: =IF(AND(U63=1,V63="Nhỏ–vừa"),P63,"") | AA63: =IF(AND(U63=1,V63="Lớn"),P63,"") | AB63: =IF(U63=1,L63,"") | AC63: =IF(AND(U63=1,V63="Nhỏ–vừa"),L63,"") | AD63: =IF(AND(U63=1,V63="Lớn"),L63,"") | AE63: =IF(U63=1,M63,"") | AF63: =IF(AND(U63=1,V63="Nhỏ–vừa"),M63,"") | AG63: =IF(AND(U63=1,V63="Lớn"),M63,"") | AH63: =IF(U63=1,N63,"") | AI63: =IF(AND(U63=1,V63="Nhỏ–vừa"),N63,"") | AJ63: =IF(AND(U63=1,V63="Lớn"),N63,"") | AK63: =IF(U63=1,Q63,"") | AL63: =IF(AND(U63=1,R63<>""),R63,"") | AM63: =A63&"-"&B63 -> PTG-2024
A64: PTG | B64: 2025 | C64: FiinTrade_..._BMG_20261018.xlsx | D64: 556072935990 | E64: 0.15441648 | F64: 385385118703 | G64: 348155715067 | H64: 195187650284 | I64: 86500000000 | J64: 4065247758 | K64: 64662527370 | L64: 30.21139 | M64: 3.1673744 | N64: 4.3346419 | O64: =IF(OR(D64="",E64=""),"",D64*(1-E64)) -> 4.7020611e+11 | P64: =IF(OR(H64="",D64=""),"",IF(D64<=0,"",(H64+N(I64))/D64)) -> 0.50656601 | Q64: =IF(OR(H64="",D64=""),"",IF(D64<=0,"",H64/D64)) -> 0.35101088 | R64: =IF(OR(A63<>A64,B64<=ThamSo!$C$22,H64="",H63="",D64=""),"",IF(D64<=0,"",(H64-H63)/D64)) -> 0.13321785 | S64: =INDEX(HoSoDN!$H$5:$H$32,MATCH(A64,HoSoDN!$A$5:$A$32,0)) -> CMT | T64: =INDEX(HoSoDN!$I$5:$I$32,MATCH(A64,HoSoDN!$A$5:$A$32,0)) -> Không | U64: =IF(AND(S64="FOB",T64<>"Có",B64>=ThamSo!$C$22,B64<=ThamSo!$C$23,D64<>"",E64<>"",G64<>"",P64<>"",L64<>"",M64<>"",N64<>""),IF(D64>=ThamSo!$C$11,1,0),0) -> 0 | V64: =IF(D64="","",IF(D64<=ThamSo!$C$12,"Nhỏ–vừa","Lớn")) -> Nhỏ–vừa | W64: =IF(D64="","",IF(OR(D64<=ThamSo!$C$13,F64<=ThamSo!$C$14),"Có","Không")) -> Không | X64: =IF(AND(T64<>"Có",M64<>"",D64<>""),IF(D64>=ThamSo!$C$11,M64,""),"") -> 3.1673744 | Y64: =IF(U64=1,P64,"") | Z64: =IF(AND(U64=1,V64="Nhỏ–vừa"),P64,"") | AA64: =IF(AND(U64=1,V64="Lớn"),P64,"") | AB64: =IF(U64=1,L64,"") | AC64: =IF(AND(U64=1,V64="Nhỏ–vừa"),L64,"") | AD64: =IF(AND(U64=1,V64="Lớn"),L64,"") | AE64: =IF(U64=1,M64,"") | AF64: =IF(AND(U64=1,V64="Nhỏ–vừa"),M64,"") | AG64: =IF(AND(U64=1,V64="Lớn"),M64,"") | AH64: =IF(U64=1,N64,"") | AI64: =IF(AND(U64=1,V64="Nhỏ–vừa"),N64,"") | AJ64: =IF(AND(U64=1,V64="Lớn"),N64,"") | AK64: =IF(U64=1,Q64,"") | AL64: =IF(AND(U64=1,R64<>""),R64,"") | AM64: =A64&"-"&B64 -> PTG-2025
... A88: X26 | B88: 2025 | C88: FiinTrade_..._AG1_20261018.xlsx | D88: 1073011778159 | E88: 0.10492067 | F88: 640153730142 | G88: 477731916291 | H88: 123757098577 | I88: 16012470000 | J88: 179093363144 | K88: 26936869665 | L88: 48.098369 | M88: 73.87967 | N88: 67.286497 | O88: =IF(OR(D88="",E88=""),"",D88*(1-E88)) -> 9.6043066e+11 | P88: =IF(OR(H88="",D88=""),"",IF(D88<=0,"",(H88+N(I88))/D88)) -> 0.13025912 | Q88: =IF(OR(H88="",D88=""),"",IF(D88<=0,"",H88/D88)) -> 0.1153362 | R88: =IF(OR(A87<>A88,B88<=ThamSo!$C$22,H88="",H87="",D88=""),"",IF(D88<=0,"",(H88-H87)/D88)) -> -0.048148279 | S88: =INDEX(HoSoDN!$H$5:$H$32,MATCH(A88,HoSoDN!$A$5:$A$32,0)) -> FOB | T88: =INDEX(HoSoDN!$I$5:$I$32,MATCH(A88,HoSoDN!$A$5:$A$32,0)) -> Không | U88: =IF(AND(S88="FOB",T88<>"Có",B88>=ThamSo!$C$22,B88<=ThamSo!$C$23,D88<>"",E88<>"",G88<>"",P88<>"",L88<>"",M88<>"",N88<>""),IF(D88>=ThamSo!$C$11,1,0),0) -> 1 | V88: =IF(D88="","",IF(D88<=ThamSo!$C$12,"Nhỏ–vừa","Lớn")) -> Nhỏ–vừa | W88: =IF(D88="","",IF(OR(D88<=ThamSo!$C$13,F88<=ThamSo!$C$14),"Có","Không")) -> Không | X88: =IF(AND(T88<>"Có",M88<>"",D88<>""),IF(D88>=ThamSo!$C$11,M88,""),"") -> 73.87967 | Y88: =IF(U88=1,P88,"") -> 0.13025912 | Z88: =IF(AND(U88=1,V88="Nhỏ–vừa"),P88,"") -> 0.13025912 | AA88: =IF(AND(U88=1,V88="Lớn"),P88,"") | AB88: =IF(U88=1,L88,"") -> 48.098369 | AC88: =IF(AND(U88=1,V88="Nhỏ–vừa"),L88,"") -> 48.098369 | AD88: =IF(AND(U88=1,V88="Lớn"),L88,"") | AE88: =IF(U88=1,M88,"") -> 73.87967 | AF88: =IF(AND(U88=1,V88="Nhỏ–vừa"),M88,"") -> 73.87967 | AG88: =IF(AND(U88=1,V88="Lớn"),M88,"") | AH88: =IF(U88=1,N88,"") -> 67.286497 | AI88: =IF(AND(U88=1,V88="Nhỏ–vừa"),N88,"") -> 67.286497 | AJ88: =IF(AND(U88=1,V88="Lớn"),N88,"") | AK88: =IF(U88=1,Q88,"") -> 0.1153362 | AL88: =IF(AND(U88=1,R88<>""),R88,"") -> -0.048148279 | AM88: =A88&"-"&B88 -> X26-2025

Sheet B1_ChuanNganh
A1: BƯỚC 1 – CHUẨN NGÀNH FOB: phân phối của năm–DN may FOB đang hoạt động, 2023–2025
A2: “Data ngành” = 20 DN may FOB × 3 năm gần nhất (cột “– FOB” ở DuLieu). Ngưỡng ngành = phân vị của phân phối này.
A3: Công thức: Pk = PERCENTILE(tập giá trị của mọi năm–DN FOB đang hoạt động 2023–2025; k), k = 0,10 / 0,25 / 0,50 / 0,75 / 0,90
A4: Chỉ tiêu | B4: Số quan sát | C4: P10 | D4: P25 | E4: P50 (tham chiếu) | F4: P75 (có nguy cơ) | G4: P90 (trầm trọng) | H4: Dùng cho
A5: DSO – số ngày thu tiền | B5: =COUNT(DuLieu!$AB$5:$AB$88) -> 60 | C5: =PERCENTILE(DuLieu!$AB$5:$AB$88,ThamSo!$C$7) -> 25.769231 | D5: =PERCENTILE(DuLieu!$AB$5:$AB$88,ThamSo!$C$8) -> 34.408949 | E5: =PERCENTILE(DuLieu!$AB$5:$AB$88,ThamSo!$C$4) -> 43.247052 | F5: =PERCENTILE(DuLieu!$AB$5:$AB$88,ThamSo!$C$5) -> 58.207139 | G5: =PERCENTILE(DuLieu!$AB$5:$AB$88,ThamSo!$C$6) -> 66.263266 | H5: Khoản mục PHẢI THU
A6: DIO – số ngày tồn kho | B6: =COUNT(DuLieu!$AE$5:$AE$88) -> 60 | C6: =PERCENTILE(DuLieu!$AE$5:$AE$88,ThamSo!$C$7) -> 33.857892 | D6: =PERCENTILE(DuLieu!$AE$5:$AE$88,ThamSo!$C$8) -> 57.276635 | E6: =PERCENTILE(DuLieu!$AE$5:$AE$88,ThamSo!$C$4) -> 69.751755 | F6: =PERCENTILE(DuLieu!$AE$5:$AE$88,ThamSo!$C$5) -> 86.118055 | G6: =PERCENTILE(DuLieu!$AE$5:$AE$88,ThamSo!$C$6) -> 137.96515 | H6: Khoản mục TỒN KHO
A7: DPO – số ngày trả NCC | B7: =COUNT(DuLieu!$AH$5:$AH$88) -> 60 | C7: =PERCENTILE(DuLieu!$AH$5:$AH$88,ThamSo!$C$7) -> 14.892653 | D7: =PERCENTILE(DuLieu!$AH$5:$AH$88,ThamSo!$C$8) -> 19.375703 | E7: =PERCENTILE(DuLieu!$AH$5:$AH$88,ThamSo!$C$4) -> 34.262287 | F7: =PERCENTILE(DuLieu!$AH$5:$AH$88,ThamSo!$C$5) -> 68.309204 | G7: =PERCENTILE(DuLieu!$AH$5:$AH$88,ThamSo!$C$6) -> 88.215245 | H7: Khoản mục PHẢI TRẢ (P10: NCC cho nợ ít)
A8: Đệm tiền (Tiền + ĐTNH) / DT | B8: =COUNT(DuLieu!$Y$5:$Y$88) -> 60 | C8: =PERCENTILE(DuLieu!$Y$5:$Y$88,ThamSo!$C$7) -> 0.044512172 | D8: =PERCENTILE(DuLieu!$Y$5:$Y$88,ThamSo!$C$8) -> 0.083007995 | E8: =PERCENTILE(DuLieu!$Y$5:$Y$88,ThamSo!$C$4) -> 0.11883177 | F8: =PERCENTILE(DuLieu!$Y$5:$Y$88,ThamSo!$C$5) -> 0.18340151 | G8: =PERCENTILE(DuLieu!$Y$5:$Y$88,ThamSo!$C$6) -> 0.29840026 | H8: Điều kiện “tiền mỏng” (P25) đi kèm DPO thấp
A9: Tiền / DT | B9: =COUNT(DuLieu!$AK$5:$AK$88) -> 60 | C9: =PERCENTILE(DuLieu!$AK$5:$AK$88,ThamSo!$C$7) -> 0.032899771 | D9: =PERCENTILE(DuLieu!$AK$5:$AK$88,ThamSo!$C$8) -> 0.041798621 | E9: =PERCENTILE(DuLieu!$AK$5:$AK$88,ThamSo!$C$4) -> 0.072628007 | F9: =PERCENTILE(DuLieu!$AK$5:$AK$88,ThamSo!$C$5) -> 0.1207739 | G9: =PERCENTILE(DuLieu!$AK$5:$AK$88,ThamSo!$C$6) -> 0.17077613 | H9: UC02 – Miller–Orr: giới hạn dưới L (P25)
A10: Ghi chú: cột P10 dùng phân vị ThamSo P4, cột P25 dùng ThamSo P5, các cột còn lại dùng P1–P3. Dòng Tiền / DT dùng P21 ở sheet B6.
A12: Đối chiếu với số “Toàn ngành” FiinTrade (ngành dệt may tổng cộng – gồm cả sợi, dệt và doanh nghiệp lớn)
A13: Năm | B13: DSO toàn ngành | C13: DIO toàn ngành | D13: DPO toàn ngành
A14: 2023 | B14: 36.189052 | C14: 106.57561 | D14: 32.953303
A15: 2024 | B15: 36.264634 | C15: 98.268141 | D15: 31.08133
A16: 2025 | B16: 38.182085 | C16: 108.39891 | D16: 32.972015
A17: Trung vị 2023–2025 | B17: =MEDIAN(B14:B16) -> 36.264634 | C17: =MEDIAN(C14:C16) -> 106.57561 | D17: =MEDIAN(D14:D16) -> 32.953303
A18: Trung vị mẫu FOB (dòng 5–7) | B18: =E5 -> 43.247052 | C18: =E6 -> 69.751755 | D18: =E7 -> 34.262287
A19: Đọc: DIO “toàn ngành” cao hơn mẫu FOB vì gộp DN sợi, dệt (tích bông, xơ nhiều tháng). Vì vậy ngưỡng dùng phân phối của mẫu FOB, số toàn ngành chỉ để đối chiếu.

Sheet B2_BienDieuTiet
A1: BƯỚC 2 – BIẾN ĐIỀU TIẾT: điều chỉnh chuẩn ngành FOB theo quy mô và mùa vụ
A2: Hệ số = trung vị của nhóm / trung vị ngành FOB. Chỉ áp dụng khi khác biệt có ý nghĩa thống kê (p < ThamSo P13), chặn trong [P14; P15]. Không có ý nghĩa thì hệ số = 1.
A3: Công thức: Hệ số áp dụng = IF(p < 0,05; MIN(MAX(Trung vị nhóm / Trung vị ngành FOB; 0,1); 3); 1)
A4: Chỉ tiêu | B4: Biến điều tiết | C4: Nhóm | D4: Trung vị nhóm | E4: Trung vị ngành FOB | F4: Hệ số thô | G4: p-value (cấp DN) | H4: Hệ số ÁP DỤNG | I4: Kết luận
A5: DSO | B5: Quy mô | C5: Nhỏ–vừa | D5: =MEDIAN(DuLieu!$AC$5:$AC$88) -> 36.135937 | E5: =MEDIAN(DuLieu!$AB$5:$AB$88) -> 43.247052 | F5: =IF(E5=0,1,D5/E5) -> 0.83556993 | G5: =B2a_KiemDinhMannWhitney!L37 -> 0.17146021 | H5: =IF(G5<ThamSo!$C$16,MIN(MAX(F5,ThamSo!$C$17),ThamSo!$C$18),1) -> 1 | I5: =IF(G5<ThamSo!$C$16,IF(OR(F5<ThamSo!$C$17,F5>ThamSo!$C$18),"Có ý nghĩa → áp dụng (đã chặn min/max)","Có ý nghĩa → áp dụng"),"Không có ý nghĩa → hệ số = 1") -> Không có ý nghĩa → hệ số = 1
A6: DSO | B6: Quy mô | C6: Lớn | D6: =MEDIAN(DuLieu!$AD$5:$AD$88) -> 49.733718 | E6: =MEDIAN(DuLieu!$AB$5:$AB$88) -> 43.247052 | F6: =IF(E6=0,1,D6/E6) -> 1.1499909 | G6: =B2a_KiemDinhMannWhitney!L37 -> 0.17146021 | H6: =IF(G6<ThamSo!$C$16,MIN(MAX(F6,ThamSo!$C$17),ThamSo!$C$18),1) -> 1 | I6: =IF(G6<ThamSo!$C$16,IF(OR(F6<ThamSo!$C$17,F6>ThamSo!$C$18),"Có ý nghĩa → áp dụng (đã chặn min/max)","Có ý nghĩa → áp dụng"),"Không có ý nghĩa → hệ số = 1") -> Không có ý nghĩa → hệ số = 1
A7: DIO | B7: Quy mô | C7: Nhỏ–vừa | D7: =MEDIAN(DuLieu!$AF$5:$AF$88) -> 75.804937 | E7: =MEDIAN(DuLieu!$AE$5:$AE$88) -> 69.751755 | F7: =IF(E7=0,1,D7/E7) -> 1.0867818 | G7: =B2a_KiemDinhMannWhitney!L38 -> 0.28749542 | H7: =IF(G7<ThamSo!$C$16,MIN(MAX(F7,ThamSo!$C$17),ThamSo!$C$18),1) -> 1 | I7: =IF(G7<ThamSo!$C$16,IF(OR(F7<ThamSo!$C$17,F7>ThamSo!$C$18),"Có ý nghĩa → áp dụng (đã chặn min/max)","Có ý nghĩa → áp dụng"),"Không có ý nghĩa → hệ số = 1") -> Không có ý nghĩa → hệ số = 1
A8: DIO | B8: Quy mô | C8: Lớn | D8: =MEDIAN(DuLieu!$AG$5:$AG$88) -> 65.926231 | E8: =MEDIAN(DuLieu!$AE$5:$AE$88) -> 69.751755 | F8: =IF(E8=0,1,D8/E8) -> 0.94515515 | G8: =B2a_KiemDinhMannWhitney!L38 -> 0.28749542 | H8: =IF(G8<ThamSo!$C$16,MIN(MAX(F8,ThamSo!$C$17),ThamSo!$C$18),1) -> 1 | I8: =IF(G8<ThamSo!$C$16,IF(OR(F8<ThamSo!$C$17,F8>ThamSo!$C$18),"Có ý nghĩa → áp dụng (đã chặn min/max)","Có ý nghĩa → áp dụng"),"Không có ý nghĩa → hệ số = 1") -> Không có ý nghĩa → hệ số = 1
A9: DPO | B9: Quy mô | C9: Nhỏ–vừa | D9: =MEDIAN(DuLieu!$AI$5:$AI$88) -> 29.967555 | E9: =MEDIAN(DuLieu!$AH$5:$AH$88) -> 34.262287 | F9: =IF(E9=0,1,D9/E9) -> 0.87465134 | G9: =B2a_KiemDinhMannWhitney!L39 -> 0.59485342 | H9: =IF(G9<ThamSo!$C$16,MIN(MAX(F9,ThamSo!$C$17),ThamSo!$C$18),1) -> 1 | I9: =IF(G9<ThamSo!$C$16,IF(OR(F9<ThamSo!$C$17,F9>ThamSo!$C$18),"Có ý nghĩa → áp dụng (đã chặn min/max)","Có ý nghĩa → áp dụng"),"Không có ý nghĩa → hệ số = 1") -> Không có ý nghĩa → hệ số = 1
A10: DPO | B10: Quy mô | C10: Lớn | D10: =MEDIAN(DuLieu!$AJ$5:$AJ$88) -> 36.938105 | E10: =MEDIAN(DuLieu!$AH$5:$AH$88) -> 34.262287 | F10: =IF(E10=0,1,D10/E10) -> 1.0780981 | G10: =B2a_KiemDinhMannWhitney!L39 -> 0.59485342 | H10: =IF(G10<ThamSo!$C$16,MIN(MAX(F10,ThamSo!$C$17),ThamSo!$C$18),1) -> 1 | I10: =IF(G10<ThamSo!$C$16,IF(OR(F10<ThamSo!$C$17,F10>ThamSo!$C$18),"Có ý nghĩa → áp dụng (đã chặn min/max)","Có ý nghĩa → áp dụng"),"Không có ý nghĩa → hệ số = 1") -> Không có ý nghĩa → hệ số = 1
A11: Đệm tiền | B11: Quy mô | C11: Nhỏ–vừa | D11: =MEDIAN(DuLieu!$Z$5:$Z$88) -> 0.11797957 | E11: =MEDIAN(DuLieu!$Y$5:$Y$88) -> 0.11883177 | F11: =IF(E11=0,1,D11/E11) -> 0.99282856 | G11: =B2a_KiemDinhMannWhitney!L40 -> 0.4474117 | H11: =IF(G11<ThamSo!$C$16,MIN(MAX(F11,ThamSo!$C$17),ThamSo!$C$18),1) -> 1 | I11: =IF(G11<ThamSo!$C$16,IF(OR(F11<ThamSo!$C$17,F11>ThamSo!$C$18),"Có ý nghĩa → áp dụng (đã chặn min/max)","Có ý nghĩa → áp dụng"),"Không có ý nghĩa → hệ số = 1") -> Không có ý nghĩa → hệ số = 1
A12: Đệm tiền | B12: Quy mô | C12: Lớn | D12: =MEDIAN(DuLieu!$AA$5:$AA$88) -> 0.13286291 | E12: =MEDIAN(DuLieu!$Y$5:$Y$88) -> 0.11883177 | F12: =IF(E12=0,1,D12/E12) -> 1.1180757 | G12: =B2a_KiemDinhMannWhitney!L40 -> 0.4474117 | H12: =IF(G12<ThamSo!$C$16,MIN(MAX(F12,ThamSo!$C$17),ThamSo!$C$18),1) -> 1 | I12: =IF(G12<ThamSo!$C$16,IF(OR(F12<ThamSo!$C$17,F12>ThamSo!$C$18),"Có ý nghĩa → áp dụng (đã chặn min/max)","Có ý nghĩa → áp dụng"),"Không có ý nghĩa → hệ số = 1") -> Không có ý nghĩa → hệ số = 1
A13: DSO, DIO | B13: Mùa vụ | C13: Mọi DN | H13: =ThamSo!$C$19 -> 1 | I13: Chưa hiệu chỉnh (số liệu năm) – xem ThamSo P16
A15: p-value: kiểm định Mann–Whitney ở cấp doanh nghiệp (sheet B2a), mỗi DN 1 giá trị trung vị 2023–2025 để không đếm trùng nhiều năm của cùng DN.
A16: Đọc: trong mẫu FOB, DN nhỏ–vừa và DN lớn không khác biệt có ý nghĩa ở cả 4 chỉ tiêu → SME FOB dùng chung chuẩn ngành FOB (hệ số = 1).

Sheet B2a_KiemDinhMannWhitney
A1: KIỂM ĐỊNH MANN–WHITNEY BẰNG CÔNG THỨC: DN FOB nhỏ–vừa và DN FOB lớn có khác nhau thật không?
A2: Mỗi DN FOB = 1 quan sát (trung vị 2023–2025, lấy từ HoSoDN). Xếp hạng tất cả DN từ nhỏ đến lớn; nếu một nhóm dồn về một phía của bảng xếp hạng thì khác biệt có ý nghĩa.
A3: Hạng (có xử lý hòa) = RANK(x; dãy; tăng dần) + (COUNTIF(dãy; x) − 1) / 2
A5: Mã | B5: Thuộc mẫu FOB? | C5: Nhóm quy mô | D5: DSO trung vị | E5: Hạng DSO | F5: DIO trung vị | G5: Hạng DIO | H5: DPO trung vị | I5: Hạng DPO | J5: Đệm tiền trung vị | K5: Hạng đệm tiền
A6: =HoSoDN!A5 -> AG1 | B6: =HoSoDN!Q5 -> Có | C6: =HoSoDN!L5 -> Nhỏ–vừa | D6: =IF(B6<>"Có","",HoSoDN!M5) -> 25.857809 | E6: =IF(D6="","",RANK(D6,D$6:D$33,1)+(COUNTIF(D$6:D$33,D6)-1)/2) -> 3 | F6: =IF(B6<>"Có","",HoSoDN!N5) -> 105.53788 | G6: =IF(F6="","",RANK(F6,F$6:F$33,1)+(COUNTIF(F$6:F$33,F6)-1)/2) -> 18 | H6: =IF(B6<>"Có","",HoSoDN!O5) -> 84.012707 | I6: =IF(H6="","",RANK(H6,H$6:H$33,1)+(COUNTIF(H$6:H$33,H6)-1)/2) -> 19 | J6: =IF(B6<>"Có","",HoSoDN!P5) -> 0.04477945 | K6: =IF(J6="","",RANK(J6,J$6:J$33,1)+(COUNTIF(J$6:J$33,J6)-1)/2) -> 1
A7: =HoSoDN!A6 -> BDG | B7: =HoSoDN!Q6 -> Có | C7: =HoSoDN!L6 -> Lớn | D7: =IF(B7<>"Có","",HoSoDN!M6) -> 47.799581 | E7: =IF(D7="","",RANK(D7,D$6:D$33,1)+(COUNTIF(D$6:D$33,D7)-1)/2) -> 12 | F7: =IF(B7<>"Có","",HoSoDN!N6) -> 59.720353 | G7: =IF(F7="","",RANK(F7,F$6:F$33,1)+(COUNTIF(F$6:F$33,F7)-1)/2) -> 7 | H7: =IF(B7<>"Có","",HoSoDN!O6) -> 32.642841 | I7: =IF(H7="","",RANK(H7,H$6:H$33,1)+(COUNTIF(H$6:H$33,H7)-1)/2) -> 9 | J7: =IF(B7<>"Có","",HoSoDN!P6) -> 0.15094065 | K7: =IF(J7="","",RANK(J7,J$6:J$33,1)+(COUNTIF(J$6:J$33,J7)-1)/2) -> 14
A8: =HoSoDN!A7 -> BMG | B8: =HoSoDN!Q7 -> Có | C8: =HoSoDN!L7 -> Nhỏ–vừa | D8: =IF(B8<>"Có","",HoSoDN!M7) -> 31.714545 | E8: =IF(D8="","",RANK(D8,D$6:D$33,1)+(COUNTIF(D$6:D$33,D8)-1)/2) -> 4 | F8: =IF(B8<>"Có","",HoSoDN!N7) -> 64.140082 | G8: =IF(F8="","",RANK(F8,F$6:F$33,1)+(COUNTIF(F$6:F$33,F8)-1)/2) -> 8 | H8: =IF(B8<>"Có","",HoSoDN!O7) -> 34.06861 | I8: =IF(H8="","",RANK(H8,H$6:H$33,1)+(COUNTIF(H$6:H$33,H8)-1)/2) -> 10 | J8: =IF(B8<>"Có","",HoSoDN!P7) -> 0.11842199 | K8: =IF(J8="","",RANK(J8,J$6:J$33,1)+(COUNTIF(J$6:J$33,J8)-1)/2) -> 11
A9: =HoSoDN!A8 -> DCG | B9: =HoSoDN!Q8 -> Không | C9: =HoSoDN!L8 | D9: =IF(B9<>"Có","",HoSoDN!M8) | E9: =IF(D9="","",RANK(D9,D$6:D$33,1)+(COUNTIF(D$6:D$33,D9)-1)/2) | F9: =IF(B9<>"Có","",HoSoDN!N8) | G9: =IF(F9="","",RANK(F9,F$6:F$33,1)+(COUNTIF(F$6:F$33,F9)-1)/2) | H9: =IF(B9<>"Có","",HoSoDN!O8) | I9: =IF(H9="","",RANK(H9,H$6:H$33,1)+(COUNTIF(H$6:H$33,H9)-1)/2) | J9: =IF(B9<>"Có","",HoSoDN!P8) | K9: =IF(J9="","",RANK(J9,J$6:J$33,1)+(COUNTIF(J$6:J$33,J9)-1)/2)
A10: =HoSoDN!A9 -> DM7 | B10: =HoSoDN!Q9 -> Có | C10: =HoSoDN!L9 -> Nhỏ–vừa | D10: =IF(B10<>"Có","",HoSoDN!M9) -> 83.307468 | E10: =IF(D10="","",RANK(D10,D$6:D$33,1)+(COUNTIF(D$6:D$33,D10)-1)/2) -> 20 | F10: =IF(B10<>"Có","",HoSoDN!N9) -> 55.712532 | G10: =IF(F10="","",RANK(F10,F$6:F$33,1)+(COUNTIF(F$6:F$33,F10)-1)/2) -> 5 | H10: =IF(B10<>"Có","",HoSoDN!O9) -> 46.200039 | I10: =IF(H10="","",RANK(H10,H$6:H$33,1)+(COUNTIF(H$6:H$33,H10)-1)/2) -> 13 | J10: =IF(B10<>"Có","",HoSoDN!P9) -> 0.07036637 | K10: =IF(J10="","",RANK(J10,J$6:J$33,1)+(COUNTIF(J$6:J$33,J10)-1)/2) -> 3
A11: =HoSoDN!A10 -> G20 | B11: =HoSoDN!Q10 -> Không | C11: =HoSoDN!L10 | D11: =IF(B11<>"Có","",HoSoDN!M10) | E11: =IF(D11="","",RANK(D11,D$6:D$33,1)+(COUNTIF(D$6:D$33,D11)-1)/2) | F11: =IF(B11<>"Có","",HoSoDN!N10) | G11: =IF(F11="","",RANK(F11,F$6:F$33,1)+(COUNTIF(F$6:F$33,F11)-1)/2) | H11: =IF(B11<>"Có","",HoSoDN!O10) | I11: =IF(H11="","",RANK(H11,H$6:H$33,1)+(COUNTIF(H$6:H$33,H11)-1)/2) | J11: =IF(B11<>"Có","",HoSoDN!P10) | K11: =IF(J11="","",RANK(J11,J$6:J$33,1)+(COUNTIF(J$6:J$33,J11)-1)/2)
A12: =HoSoDN!A11 -> GIL | B12: =HoSoDN!Q11 -> Không | C12: =HoSoDN!L11 | D12: =IF(B12<>"Có","",HoSoDN!M11) | E12: =IF(D12="","",RANK(D12,D$6:D$33,1)+(COUNTIF(D$6:D$33,D12)-1)/2) | F12: =IF(B12<>"Có","",HoSoDN!N11) | G12: =IF(F12="","",RANK(F12,F$6:F$33,1)+(COUNTIF(F$6:F$33,F12)-1)/2) | H12: =IF(B12<>"Có","",HoSoDN!O11) | I12: =IF(H12="","",RANK(H12,H$6:H$33,1)+(COUNTIF(H$6:H$33,H12)-1)/2) | J12: =IF(B12<>"Có","",HoSoDN!P11) | K12: =IF(J12="","",RANK(J12,J$6:J$33,1)+(COUNTIF(J$6:J$33,J12)-1)/2)
A13: =HoSoDN!A12 -> GMC | B13: =HoSoDN!Q12 -> Không | C13: =HoSoDN!L12 | D13: =IF(B13<>"Có","",HoSoDN!M12) | E13: =IF(D13="","",RANK(D13,D$6:D$33,1)+(COUNTIF(D$6:D$33,D13)-1)/2) | F13: =IF(B13<>"Có","",HoSoDN!N12) | G13: =IF(F13="","",RANK(F13,F$6:F$33,1)+(COUNTIF(F$6:F$33,F13)-1)/2) | H13: =IF(B13<>"Có","",HoSoDN!O12) | I13: =IF(H13="","",RANK(H13,H$6:H$33,1)+(COUNTIF(H$6:H$33,H13)-1)/2) | J13: =IF(B13<>"Có","",HoSoDN!P12) | K13: =IF(J13="","",RANK(J13,J$6:J$33,1)+(COUNTIF(J$6:J$33,J13)-1)/2)
A14: =HoSoDN!A13 -> HLT | B14: =HoSoDN!Q13 -> Có | C14: =HoSoDN!L13 -> Nhỏ–vừa | D14: =IF(B14<>"Có","",HoSoDN!M13) -> 21.528217 | E14: =IF(D14="","",RANK(D14,D$6:D$33,1)+(COUNTIF(D$6:D$33,D14)-1)/2) -> 1 | F14: =IF(B14<>"Có","",HoSoDN!N13) -> 87.245942 | G14: =IF(F14="","",RANK(F14,F$6:F$33,1)+(COUNTIF(F$6:F$33,F14)-1)/2) -> 16 | H14: =IF(B14<>"Có","",HoSoDN!O13) -> 8.1371547 | I14: =IF(H14="","",RANK(H14,H$6:H$33,1)+(COUNTIF(H$6:H$33,H14)-1)/2) -> 1 | J14: =IF(B14<>"Có","",HoSoDN!P13) -> 0.094380675 | K14: =IF(J14="","",RANK(J14,J$6:J$33,1)+(COUNTIF(J$6:J$33,J14)-1)/2) -> 7
A15: =HoSoDN!A14 -> HNI | B15: =HoSoDN!Q14 -> Có | C15: =HoSoDN!L14 -> Nhỏ–vừa | D15: =IF(B15<>"Có","",HoSoDN!M14) -> 41.237603 | E15: =IF(D15="","",RANK(D15,D$6:D$33,1)+(COUNTIF(D$6:D$33,D15)-1)/2) -> 9 | F15: =IF(B15<>"Có","",HoSoDN!N14) -> 26.977831 | G15: =IF(F15="","",RANK(F15,F$6:F$33,1)+(COUNTIF(F$6:F$33,F15)-1)/2) -> 2 | H15: =IF(B15<>"Có","",HoSoDN!O14) -> 12.94332 | I15: =IF(H15="","",RANK(H15,H$6:H$33,1)+(COUNTIF(H$6:H$33,H15)-1)/2) -> 2 | J15: =IF(B15<>"Có","",HoSoDN!P14) -> 0.29666826 | K15: =IF(J15="","",RANK(J15,J$6:J$33,1)+(COUNTIF(J$6:J$33,J15)-1)/2) -> 19
A16: =HoSoDN!A15 -> HTG | B16: =HoSoDN!Q15 -> Có | C16: =HoSoDN!L15 -> Lớn | D16: =IF(B16<>"Có","",HoSoDN!M15) -> 38.70394 | E16: =IF(D16="","",RANK(D16,D$6:D$33,1)+(COUNTIF(D$6:D$33,D16)-1)/2) -> 8 | F16: =IF(B16<>"Có","",HoSoDN!N15) -> 64.557923 | G16: =IF(F16="","",RANK(F16,F$6:F$33,1)+(COUNTIF(F$6:F$33,F16)-1)/2) -> 9 | H16: =IF(B16<>"Có","",HoSoDN!O15) -> 20.486733 | I16: =IF(H16="","",RANK(H16,H$6:H$33,1)+(COUNTIF(H$6:H$33,H16)-1)/2) -> 7 | J16: =IF(B16<>"Có","",HoSoDN!P15) -> 0.14111784 | K16: =IF(J16="","",RANK(J16,J$6:J$33,1)+(COUNTIF(J$6:J$33,J16)-1)/2) -> 12
A17: =HoSoDN!A16 -> HUG | B17: =HoSoDN!Q16 -> Có | C17: =HoSoDN!L16 -> Nhỏ–vừa | D17: =IF(B17<>"Có","",HoSoDN!M16) -> 33.706796 | E17: =IF(D17="","",RANK(D17,D$6:D$33,1)+(COUNTIF(D$6:D$33,D17)-1)/2) -> 6 | F17: =IF(B17<>"Có","",HoSoDN!N16) -> 38.479621 | G17: =IF(F17="","",RANK(F17,F$6:F$33,1)+(COUNTIF(F$6:F$33,F17)-1)/2) -> 3 | H17: =IF(B17<>"Có","",HoSoDN!O16) -> 18.735776 | I17: =IF(H17="","",RANK(H17,H$6:H$33,1)+(COUNTIF(H$6:H$33,H17)-1)/2) -> 6 | J17: =IF(B17<>"Có","",HoSoDN!P16) -> 0.337957 | K17: =IF(J17="","",RANK(J17,J$6:J$33,1)+(COUNTIF(J$6:J$33,J17)-1)/2) -> 20
... A33: =HoSoDN!A32 -> X26 | B33: =HoSoDN!Q32 -> Có | C33: =HoSoDN!L32 -> Nhỏ–vừa | D33: =IF(B33<>"Có","",HoSoDN!M32) -> 48.098369 | E33: =IF(D33="","",RANK(D33,D$6:D$33,1)+(COUNTIF(D$6:D$33,D33)-1)/2) -> 13 | F33: =IF(B33<>"Có","",HoSoDN!N32) -> 73.87967 | G33: =IF(F33="","",RANK(F33,F$6:F$33,1)+(COUNTIF(F$6:F$33,F33)-1)/2) -> 14 | H33: =IF(B33<>"Có","",HoSoDN!O32) -> 74.86254 | I33: =IF(H33="","",RANK(H33,H$6:H$33,1)+(COUNTIF(H$6:H$33,H33)-1)/2) -> 17 | J33: =IF(B33<>"Có","",HoSoDN!P32) -> 0.1541313 | K33: =IF(J33="","",RANK(J33,J$6:J$33,1)+(COUNTIF(J$6:J$33,J33)-1)/2) -> 15
A35: BẢNG KIỂM ĐỊNH (xấp xỉ chuẩn, có hiệu chỉnh liên tục) – biến điều tiết: quy mô trong nhóm FOB
A36: Chỉ tiêu | B36: Biến điều tiết | C36: Nhóm 1 | D36: n1 | E36: n2 | F36: R1 = tổng hạng nhóm 1 | G36: U1 = R1 − n1(n1+1)/2 | H36: U = MIN(U1; n1·n2 − U1) | I36: μ = n1·n2 / 2 | J36: σ = √(n1·n2·(n1+n2+1)/12) | K36: z = (U − μ + 0,5) / σ | L36: p = 2·Φ(z) | M36: Kết luận (p < 0,05?)
A37: DSO | B37: Quy mô | C37: Nhỏ–vừa | D37: =COUNTIFS(C$6:C$33,C37,E$6:E$33,">0") -> 11 | E37: =COUNTIF(E$6:E$33,">0")-D37 -> 9 | F37: =SUMIFS(E$6:E$33,C$6:C$33,C37) -> 97 | G37: =F37-D37*(D37+1)/2 -> 31 | H37: =MIN(G37,D37*E37-G37) -> 31 | I37: =D37*E37/2 -> 49.5 | J37: =SQRT(D37*E37*(D37+E37+1)/12) -> 13.162447 | K37: =MIN(0,(H37-I37+0.5)/J37) -> -1.3675269 | L37: =MIN(1,2*NORMSDIST(K37)) -> 0.17146021 | M37: =IF(L37<ThamSo!$C$16,"Có – khác biệt có ý nghĩa","Không – coi như cùng chuẩn") -> Không – coi như cùng chuẩn
A38: DIO | B38: Quy mô | C38: Nhỏ–vừa | D38: =COUNTIFS(C$6:C$33,C38,G$6:G$33,">0") -> 11 | E38: =COUNTIF(G$6:G$33,">0")-D38 -> 9 | F38: =SUMIFS(G$6:G$33,C$6:C$33,C38) -> 130 | G38: =F38-D38*(D38+1)/2 -> 64 | H38: =MIN(G38,D38*E38-G38) -> 35 | I38: =D38*E38/2 -> 49.5 | J38: =SQRT(D38*E38*(D38+E38+1)/12) -> 13.162447 | K38: =MIN(0,(H38-I38+0.5)/J38) -> -1.063632 | L38: =MIN(1,2*NORMSDIST(K38)) -> 0.28749542 | M38: =IF(L38<ThamSo!$C$16,"Có – khác biệt có ý nghĩa","Không – coi như cùng chuẩn") -> Không – coi như cùng chuẩn
A39: DPO | B39: Quy mô | C39: Nhỏ–vừa | D39: =COUNTIFS(C$6:C$33,C39,I$6:I$33,">0") -> 11 | E39: =COUNTIF(I$6:I$33,">0")-D39 -> 9 | F39: =SUMIFS(I$6:I$33,C$6:C$33,C39) -> 108 | G39: =F39-D39*(D39+1)/2 -> 42 | H39: =MIN(G39,D39*E39-G39) -> 42 | I39: =D39*E39/2 -> 49.5 | J39: =SQRT(D39*E39*(D39+E39+1)/12) -> 13.162447 | K39: =MIN(0,(H39-I39+0.5)/J39) -> -0.53181602 | L39: =MIN(1,2*NORMSDIST(K39)) -> 0.59485342 | M39: =IF(L39<ThamSo!$C$16,"Có – khác biệt có ý nghĩa","Không – coi như cùng chuẩn") -> Không – coi như cùng chuẩn
A40: Đệm tiền | B40: Quy mô | C40: Nhỏ–vừa | D40: =COUNTIFS(C$6:C$33,C40,K$6:K$33,">0") -> 11 | E40: =COUNTIF(K$6:K$33,">0")-D40 -> 9 | F40: =SUMIFS(K$6:K$33,C$6:C$33,C40) -> 105 | G40: =F40-D40*(D40+1)/2 -> 39 | H40: =MIN(G40,D40*E40-G40) -> 39 | I40: =D40*E40/2 -> 49.5 | J40: =SQRT(D40*E40*(D40+E40+1)/12) -> 13.162447 | K40: =MIN(0,(H40-I40+0.5)/J40) -> -0.75973718 | L40: =MIN(1,2*NORMSDIST(K40)) -> 0.4474117 | M40: =IF(L40<ThamSo!$C$16,"Có – khác biệt có ý nghĩa","Không – coi như cùng chuẩn") -> Không – coi như cùng chuẩn
A43: Cách đọc:
A44: • R1 nhỏ bất thường (nhóm 1 dồn về đầu bảng) hoặc lớn bất thường (dồn về cuối) → U nhỏ → z âm lớn → p nhỏ → hai nhóm khác nhau thật.
A45: • Mẫu FOB chỉ còn một biến điều tiết là quy mô (mô hình CMT/FOB đã được lọc ở HoSoDN).
A46: • Dùng kiểm định phi tham số (không cần giả định phân phối chuẩn) vì số ngày lệch phải và mẫu nhỏ (20 DN).
A47: • Nguồn phương pháp: Mann & Whitney (1947).

Sheet CongThuc
A1: TỪ ĐIỂN CÔNG THỨC – từng chỉ số, cách tính và ví dụ số thật
A2: Nhập mã–năm muốn xem ví dụ vào ô C3 (vd DM7-2025, NJC-2025, AG1-2024). Cột F tự thay số thật vào công thức.
B3: Ví dụ cho: | C3: DM7-2025 | D3: =IFERROR(MATCH(C3,B4_PhanLopW!$C$5:$C$64,0),"không tìm thấy") -> 12
A5: # | B5: Nhóm | C5: Chỉ số | D5: Công thức | E5: Diễn giải | F5: Ví dụ với số thật | G5: Ở sheet
A6: 1 | B6: Dữ liệu | C6: Doanh thu thuần (DT) | D6: Lấy nguyên văn FiinTrade | E6: Doanh thu bán hàng thuần trong năm | F6: ="DT = "&TEXT(INDEX(B4_PhanLopW!$F$5:$F$64,$D$3)/1000000000,"#,##0.0")&" tỷ đồng" -> DT = 741.1 tỷ đồng | G6: DuLieu
A7: 2 | B7: Dữ liệu | C7: Giá vốn | D7: Giá vốn = DT × (1 − Biên LN gộp) | E7: FiinTrade không xuất giá vốn, suy ra từ biên gộp | F7: ="Giá vốn = "&TEXT(INDEX(B4_PhanLopW!$G$5:$G$64,$D$3)/1000000000,"#,##0.0")&" tỷ đồng" -> Giá vốn = 620.7 tỷ đồng | G7: DuLieu
A8: 3 | B8: Dữ liệu | C8: DSO – số ngày thu tiền | D8: DSO = Phải thu KH bình quân / DT × 365 | E8: Bình quân 1 đồng doanh thu mất bao nhiêu ngày mới thu được tiền | F8: ="DSO = "&TEXT(INDEX(B4_PhanLopW!$I$5:$I$64,$D$3),"#,##0.0")&" ngày" -> DSO = 112.9 ngày | G8: DuLieu
A9: 4 | B9: Dữ liệu | C9: DIO – số ngày tồn kho | D9: DIO = Hàng tồn kho bình quân / Giá vốn × 365 | E9: Hàng nằm trong kho bao nhiêu ngày | F9: ="DIO = "&TEXT(INDEX(B4_PhanLopW!$J$5:$J$64,$D$3),"#,##0.0")&" ngày" -> DIO = 55.7 ngày | G9: DuLieu
A10: 5 | B10: Dữ liệu | C10: DPO – số ngày trả NCC | D10: DPO = Phải trả người bán bình quân / Giá vốn × 365 | E10: NCC cho nợ bao nhiêu ngày | F10: ="DPO = "&TEXT(INDEX(B4_PhanLopW!$K$5:$K$64,$D$3),"#,##0.0")&" ngày" -> DPO = 36.1 ngày | G10: DuLieu
A11: 6 | B11: Dữ liệu | C11: Đệm tiền | D11: Đệm tiền = (Tiền + ĐTTC ngắn hạn) / DT | E11: Tiền sẵn có bằng bao nhiêu % doanh thu | F11: ="Đệm tiền = "&TEXT(INDEX(B4_PhanLopW!$L$5:$L$64,$D$3),"0.0%") -> Đệm tiền = 7.0% | G11: DuLieu
A12: 7 | B12: Lọc mẫu | C12: Mẫu FOB | D12: FOB nếu DIO trung vị 2023–2025 ≥ 20 ngày, DN không bị loại, DT ≥ 50 tỷ | E12: Chỉ DN tự mua nguyên liệu (FOB) vào chuẩn ngành | F12: =HoSoDN!Q34&" DN FOB trong mẫu" -> 20 DN FOB trong mẫu | G12: HoSoDN
A13: 8 | B13: Bước 1 | C13: Phân vị ngành Pk | D13: Pk = PERCENTILE(mọi năm–DN FOB 2023–2025; k) | E13: P75 = mức mà 75% năm–DN FOB thấp hơn | F13: ="P75 DSO = "&TEXT(B1_ChuanNganh!F5,"0.0")&" ngày; P90 = "&TEXT(B1_ChuanNganh!G5,"0.0")&" ngày" -> P75 DSO = 58.2 ngày; P90 = 66.3 ngày | G13: B1_ChuanNganh
A14: 9 | B14: Bước 2 | C14: Hệ số điều tiết quy mô | D14: HS = IF(p<0,05; MIN(MAX(Trung vị nhóm / Trung vị FOB; 0,1); 3); 1) | E14: Chỉ áp dụng khi khác biệt có ý nghĩa | F14: ="p DSO theo quy mô = "&TEXT(B2_BienDieuTiet!G5,"0.000")&" → hệ số "&TEXT(B2_BienDieuTiet!H5,"0.00") -> p DSO theo quy mô = 0.171 → hệ số 1.00 | G14: B2_BienDieuTiet
A15: 10 | B15: Bước 3 | C15: Ngưỡng của DN | D15: Ngưỡng = Pk FOB × HS quy mô × HS mùa vụ | E15: Chuẩn ngành điều chỉnh theo đặc điểm DN | F15: ="DSO có nguy cơ = "&TEXT(INDEX(B4_PhanLopW!$M$5:$M$64,$D$3),"0.0")&" ngày; trầm trọng = "&TEXT(INDEX(B4_PhanLopW!$N$5:$N$64,$D$3),"0.0")&" ngày" -> DSO có nguy cơ = 58.2 ngày; trầm trọng = 66.3 ngày | G15: B3_NguongKhoanMuc
A16: 11 | B16: Bước 4 | C16: Mức tín hiệu | D16: Mức = 2 nếu > ngưỡng trầm trọng; 1 nếu > ngưỡng có nguy cơ; 0 | E16: Áp riêng cho phải thu và tồn kho | F16: ="Phải thu: "&INDEX(B4_PhanLopW!$AA$5:$AA$64,$D$3)&"; Tồn kho: "&INDEX(B4_PhanLopW!$AB$5:$AB$64,$D$3) -> Phải thu: Trầm trọng; Tồn kho: An toàn | G16: B4_PhanLopW
A17: 12 | B17: Bước 4 | C17: Vốn vượt ngưỡng – phải thu | D17: (DSO − ngưỡng có nguy cơ) × DT / 365 | E17: Tiền nằm ở khách vượt mức bình thường | F17: =TEXT(INDEX(B4_PhanLopW!$X$5:$X$64,$D$3)/1000000000,"#,##0.0")&" tỷ đồng" -> 111.0 tỷ đồng | G17: B4_PhanLopW
A18: 13 | B18: Bước 4 | C18: Vốn vượt ngưỡng – tồn kho | D18: (DIO − ngưỡng có nguy cơ) × Giá vốn / 365 | E18: Tiền nằm trong kho vượt mức bình thường | F18: =TEXT(INDEX(B4_PhanLopW!$Y$5:$Y$64,$D$3)/1000000000,"#,##0.0")&" tỷ đồng" -> 0.0 tỷ đồng | G18: B4_PhanLopW
A19: 14 | B19: Bước 4 | C19: Tỷ lệ trọng yếu | D19: MAX(vốn vượt phải thu; vốn vượt tồn kho) / TSNH | E19: So với mức trọng yếu 5% TSNH | F19: =TEXT(INDEX(B4_PhanLopW!$Z$5:$Z$64,$D$3),"0.0%") -> 27.3% | G19: B4_PhanLopW
A20: 15 | B20: Bước 4 | C20: Phải trả – áp lực NCC | D20: 1 nếu DPO < DPO thấp VÀ đệm tiền < đệm tiền mỏng | E20: NCC không cho nợ trong khi DN ít tiền | F20: =INDEX(B4_PhanLopW!$AC$5:$AC$64,$D$3) -> An toàn | G20: B4_PhanLopW
A21: 16 | B21: Bước 4 | C21: TRỤC W – 3 mức UC01 | D21: W2 nếu (mức 2) hoặc (mức ≥1 và tỷ lệ ≥ trọng yếu); W1 nếu có tín hiệu; W0 nếu không | E21: Hàng của ma trận 6 ô | F21: =INDEX(B4_PhanLopW!$AD$5:$AD$64,$D$3)&" – "&INDEX(B4_PhanLopW!$AE$5:$AE$64,$D$3)&" ("&INDEX(B4_PhanLopW!$AG$5:$AG$64,$D$3)&")" -> W2 – Thiếu trầm trọng (R-AR-2 R-MAT) | G21: B4_PhanLopW
A22: 17 | B22: Bước 5 | C22: Biến cố năm sau | D22: 1 nếu năm sau LNST < 0 HOẶC DT năm sau < DT × (1 − 30%) | E22: Dùng để kiểm định ngưỡng | F22: ="Biến cố năm sau = "&INDEX(B4_PhanLopW!$AI$5:$AI$64,$D$3) -> Biến cố năm sau = | G22: B5_KiemDinh
A23: 18 | B23: Bước 6 | C23: Giới hạn dưới L | D23: L = MAX(ℓ × DT; L tối thiểu) | E23: ℓ = P25 Tiền / DT ngành FOB | F23: ="ℓ = "&TEXT(B6_MillerOrr!C17,"0.0%")&" doanh thu" -> ℓ = 4.2% doanh thu | G23: B6_MillerOrr
A24: 19 | B24: Bước 6 | C24: Khoảng dao động S | D24: S = 3 × (3/4 × F × σ² / r)^(1/3) | E24: σ ngày, r ngày; Miller & Orr (1966) | F24: ="DN DT 300 tỷ: S = "&TEXT(B6_MillerOrr!D30,"0.00")&" tỷ đồng" -> DN DT 300 tỷ: S = 4.45 tỷ đồng | G24: B6_MillerOrr
A25: 20 | B25: Bước 6 | C25: Điểm hồi Z, giới hạn trên H | D25: Z = L + S/3; H = L + S | E25: Tiền < L → Thiếu; Tiền > H → Thừa | F25: ="DN DT 300 tỷ: L = "&TEXT(B6_MillerOrr!B30,"0.0")&"; Z = "&TEXT(B6_MillerOrr!E30,"0.0")&"; H = "&TEXT(B6_MillerOrr!F30,"0.0")&" tỷ" -> DN DT 300 tỷ: L = 12.5; Z = 14.0; H = 17.0 tỷ | G25: B6_MillerOrr
A26: 21 | B26: Ma trận | C26: Ô M1–M6 | D26: M = 2 × chỉ số W (0/1/2) + (1 nếu Thiếu; 2 nếu Thừa) | E26: Ma trận 6 ô | F26: ="W2 + Thiếu → M5" -> W2 + Thiếu → M5 | G26: MaTran_6O

Sheet B3_NguongKhoanMuc
A1: BƯỚC 3 – NGƯỠNG TỪNG KHOẢN MỤC CHO DN FOB = ngưỡng ngành FOB × hệ số quy mô (× hệ số mùa vụ cho DSO, DIO)
A2: Ba mức của UC01: AN TOÀN (≤ ngưỡng có nguy cơ) – CÓ NGUY CƠ (> P75) – THIẾU TRẦM TRỌNG (> P90). Mức tham chiếu P50 là trung vị ngành FOB.
A3: Khóa (mô hình|quy mô) | B3: Mô hình | C3: Quy mô | D3: DSO tham chiếu (P50) | E3: DSO CÓ NGUY CƠ (P75) | F3: DSO TRẦM TRỌNG (P90) | G3: DIO tham chiếu (P50) | H3: DIO CÓ NGUY CƠ (P75) | I3: DIO TRẦM TRỌNG (P90) | J3: DPO tham chiếu (P50) | K3: DPO cao (chỉ thông tin, P75) | L3: DPO THẤP (P10) | M3: Đệm tiền MỎNG (P25)
A4: =B4&"|"&C4 -> FOB|Nhỏ–vừa | B4: FOB | C4: Nhỏ–vừa | D4: =B1_ChuanNganh!$E$5*B2_BienDieuTiet!$H$5*B2_BienDieuTiet!$H$13 -> 43.247052 | E4: =B1_ChuanNganh!$F$5*B2_BienDieuTiet!$H$5*B2_BienDieuTiet!$H$13 -> 58.207139 | F4: =B1_ChuanNganh!$G$5*B2_BienDieuTiet!$H$5*B2_BienDieuTiet!$H$13 -> 66.263266 | G4: =B1_ChuanNganh!$E$6*B2_BienDieuTiet!$H$7*B2_BienDieuTiet!$H$13 -> 69.751755 | H4: =B1_ChuanNganh!$F$6*B2_BienDieuTiet!$H$7*B2_BienDieuTiet!$H$13 -> 86.118055 | I4: =B1_ChuanNganh!$G$6*B2_BienDieuTiet!$H$7*B2_BienDieuTiet!$H$13 -> 137.96515 | J4: =B1_ChuanNganh!$E$7*B2_BienDieuTiet!$H$9 -> 34.262287 | K4: =B1_ChuanNganh!$F$7*B2_BienDieuTiet!$H$9 -> 68.309204 | L4: =B1_ChuanNganh!$C$7*B2_BienDieuTiet!$H$9 -> 14.892653 | M4: =B1_ChuanNganh!$D$8*B2_BienDieuTiet!$H$11 -> 0.083007995
A5: =B5&"|"&C5 -> FOB|Lớn | B5: FOB | C5: Lớn | D5: =B1_ChuanNganh!$E$5*B2_BienDieuTiet!$H$6*B2_BienDieuTiet!$H$13 -> 43.247052 | E5: =B1_ChuanNganh!$F$5*B2_BienDieuTiet!$H$6*B2_BienDieuTiet!$H$13 -> 58.207139 | F5: =B1_ChuanNganh!$G$5*B2_BienDieuTiet!$H$6*B2_BienDieuTiet!$H$13 -> 66.263266 | G5: =B1_ChuanNganh!$E$6*B2_BienDieuTiet!$H$8*B2_BienDieuTiet!$H$13 -> 69.751755 | H5: =B1_ChuanNganh!$F$6*B2_BienDieuTiet!$H$8*B2_BienDieuTiet!$H$13 -> 86.118055 | I5: =B1_ChuanNganh!$G$6*B2_BienDieuTiet!$H$8*B2_BienDieuTiet!$H$13 -> 137.96515 | J5: =B1_ChuanNganh!$E$7*B2_BienDieuTiet!$H$10 -> 34.262287 | K5: =B1_ChuanNganh!$F$7*B2_BienDieuTiet!$H$10 -> 68.309204 | L5: =B1_ChuanNganh!$C$7*B2_BienDieuTiet!$H$10 -> 14.892653 | M5: =B1_ChuanNganh!$D$8*B2_BienDieuTiet!$H$12 -> 0.083007995
A7: Đơn vị: ngày (DSO, DIO, DPO); % doanh thu (đệm tiền). Ví dụ đọc: DN FOB nhỏ–vừa có DSO > ngưỡng CÓ NGUY CƠ tức là tiền nằm ở khách lâu hơn 75% năm–DN FOB.
A9: QUY TẮC TÍN HIỆU TỪNG KHOẢN MỤC
A10: Mã quy tắc | B10: Khoản mục | C10: Điều kiện | D10: Mức | E10: Vì sao
A11: R-AR-1 | B11: Phải thu | C11: DSO > DSO có nguy cơ (P75) | D11: Có nguy cơ | E11: Vốn nằm ở khách lâu hơn 75% DN FOB.
A12: R-AR-2 | B12: Phải thu | C12: DSO > DSO trầm trọng (P90) | D12: Trầm trọng | E12: Thuộc 10% chậm thu nhất ngành FOB.
A13: R-INV-1 | B13: Tồn kho | C13: DIO > DIO có nguy cơ (P75) | D13: Có nguy cơ | E13: Vốn nằm trong kho lâu hơn 75% DN FOB.
A14: R-INV-2 | B14: Tồn kho | C14: DIO > DIO trầm trọng (P90) | D14: Trầm trọng | E14: Thuộc 10% tồn kho lâu nhất ngành FOB.
A15: R-AP-1 | B15: Phải trả | C15: DPO < DPO thấp VÀ đệm tiền < đệm tiền mỏng | D15: Có nguy cơ | E15: NCC gần như không cho nợ trong khi DN ít tiền: áp lực thanh toán.
A16: R-AP-INFO | B16: Phải trả | C16: DPO > DPO cao | D16: Chỉ thông tin | E16: Có thể đang chậm trả NCC. Không vào trục W; cần kiểm tra quá hạn ở cấp hóa đơn.
A17: R-MAT | B17: Trọng yếu | C17: Vốn vượt ngưỡng có nguy cơ / TSNH ≥ mức trọng yếu (ThamSo P6) | D17: Nâng lên Trầm trọng (W2) | E17: Vốn vượt ngưỡng = (số ngày − ngưỡng có nguy cơ) × doanh thu (phải thu) hoặc giá vốn (tồn kho) / 365.

Sheet B4_PhanLopW
A1: BƯỚC 4 – ÁP NGƯỠNG CHO TỪNG NĂM–DN FOB → TRỤC W (3 MỨC CỦA UC01)
A2: Dòng 3 (chữ đỏ) ghi công thức của từng cột. W2 – Thiếu trầm trọng = có khoản vượt P90, hoặc vượt P75 và vốn vượt ngưỡng ≥ mức trọng yếu. W1 – Có nguy cơ = có tín hiệu nhưng chưa trọng yếu. W0 – An toàn = không có tín hiệu. Giả định doanh nghiệp luôn tải đủ dữ liệu; W chỉ gồm W0, W1 và W2.
L3: (Tiền+ĐTNH)/DT | M3: Ngưỡng B3 theo khóa | N3: Ngưỡng B3 | O3: Ngưỡng B3 | P3: Ngưỡng B3 | Q3: Ngưỡng B3 | R3: Ngưỡng B3 | S3: Ngưỡng B3 | T3: 2 nếu DSO>N; 1 nếu DSO>M; 0 | U3: 2 nếu DIO>P; 1 nếu DIO>O; 0 | V3: 1 nếu DPO<R VÀ đệm tiền<S | W3: 1 nếu DPO>Q | X3: (DSO−M)×DT/365 nếu T≥1 | Y3: (DIO−O)×Giá vốn/365 nếu U≥1 | Z3: MAX(X;Y)/TSNH | AD3: W2 nếu MAX(T;U)=2 hoặc (MAX(T;U)≥1 và Z≥5%); W1 nếu có tín hiệu; W0 nếu không | AH3: X + Y | AI3: 1 nếu năm sau lỗ hoặc DT giảm >30%
A4: Mã | B4: Năm | C4: Khóa Mã-Năm | D4: Mô hình|quy mô | E4: Hoạt động | F4: Doanh thu (đồng) | G4: Giá vốn (đồng) | H4: TSNH (đồng) | I4: DSO | J4: DIO | K4: DPO | L4: Đệm tiền | M4: Ngưỡng DSO có nguy cơ | N4: Ngưỡng DSO trầm trọng | O4: Ngưỡng DIO có nguy cơ | P4: Ngưỡng DIO trầm trọng | Q4: Ngưỡng DPO cao | R4: Ngưỡng DPO thấp | S4: Ngưỡng đệm tiền mỏng | T4: Mức phải thu (0/1/2) | U4: Mức tồn kho (0/1/2) | V4: Phải trả: DPO thấp + tiền mỏng (1/0) | W4: DPO cao – thông tin (1/0) | X4: Vốn vượt ngưỡng ở phải thu (đồng) | Y4: Vốn vượt ngưỡng ở tồn kho (đồng) | Z4: Tỷ lệ lớn nhất / TSNH | AA4: Trạng thái PHẢI THU | AB4: Trạng thái TỒN KHO | AC4: Trạng thái PHẢI TRẢ | AD4: TRỤC W | AE4: Mức UC01 | AF4: Điểm nghẽn chính | AG4: Quy tắc đã kích hoạt | AH4: Tiền có rủi ro – money_at_risk (đồng) | AI4: Biến cố năm sau (1/0)
A5: =DuLieu!A5 -> AG1 | B5: =DuLieu!B5 -> 2023 | C5: =A5&"-"&B5 -> AG1-2023 | D5: =DuLieu!S5&"|"&DuLieu!V5 -> FOB|Nhỏ–vừa | E5: =DuLieu!U5 -> 1 | F5: =IF(E5=1,DuLieu!D5,"") -> 269017127126 | G5: =IF(E5=1,DuLieu!O5,"") -> 2.2967216e+11 | H5: =IF(E5=1,DuLieu!G5,"") -> 128660408494 | I5: =IF(E5=1,DuLieu!L5,"") -> 25.857809 | J5: =IF(E5=1,DuLieu!M5,"") -> 145.84777 | K5: =IF(E5=1,DuLieu!N5,"") -> 107.20841 | L5: =IF(E5=1,DuLieu!P5,"") -> 0.025292812 | M5: =IF(E5=1,INDEX(B3_NguongKhoanMuc!$E$4:$E$5,MATCH(D5,B3_NguongKhoanMuc!$A$4:$A$5,0)),"") -> 58.207139 | N5: =IF(E5=1,INDEX(B3_NguongKhoanMuc!$F$4:$F$5,MATCH(D5,B3_NguongKhoanMuc!$A$4:$A$5,0)),"") -> 66.263266 | O5: =IF(E5=1,INDEX(B3_NguongKhoanMuc!$H$4:$H$5,MATCH(D5,B3_NguongKhoanMuc!$A$4:$A$5,0)),"") -> 86.118055 | P5: =IF(E5=1,INDEX(B3_NguongKhoanMuc!$I$4:$I$5,MATCH(D5,B3_NguongKhoanMuc!$A$4:$A$5,0)),"") -> 137.96515 | Q5: =IF(E5=1,INDEX(B3_NguongKhoanMuc!$K$4:$K$5,MATCH(D5,B3_NguongKhoanMuc!$A$4:$A$5,0)),"") -> 68.309204 | R5: =IF(E5=1,INDEX(B3_NguongKhoanMuc!$L$4:$L$5,MATCH(D5,B3_NguongKhoanMuc!$A$4:$A$5,0)),"") -> 14.892653 | S5: =IF(E5=1,INDEX(B3_NguongKhoanMuc!$M$4:$M$5,MATCH(D5,B3_NguongKhoanMuc!$A$4:$A$5,0)),"") -> 0.083007995 | T5: =IF(E5<>1,"",IF(I5>N5,2,IF(I5>M5,1,0))) -> 0 | U5: =IF(E5<>1,"",IF(J5>P5,2,IF(J5>O5,1,0))) -> 2 | V5: =IF(E5<>1,"",IF(AND(K5<R5,L5<S5),1,0)) -> 0 | W5: =IF(E5<>1,"",IF(K5>Q5,1,0)) -> 1 | X5: =IF(E5<>1,"",IF(T5>=1,(I5-M5)*F5/365,0)) -> 0 | Y5: =IF(E5<>1,"",IF(U5>=1,(J5-O5)*G5/365,0)) -> 3.7584252e+10 | Z5: =IF(E5<>1,"",IF(H5>0,MAX(X5,Y5)/H5,0)) -> 0.29211979 | AA5: =IF(E5<>1,"",CHOOSE(T5+1,"An toàn","Có nguy cơ","Trầm trọng")) -> An toàn | AB5: =IF(E5<>1,"",CHOOSE(U5+1,"An toàn","Có nguy cơ","Trầm trọng")) -> Trầm trọng | AC5: =IF(E5<>1,"",IF(V5=1,"Có nguy cơ: NCC cho nợ ít + tiền mỏng",IF(W5=1,"Lưu ý: DPO cao – kiểm tra quá hạn NCC","An toàn"))) -> Lưu ý: DPO cao – kiểm tra quá hạn NCC | AD5: =IF(OR(AND(ThamSo!$C$10=1,MAX(T5,U5)=2),AND(MAX(T5,U5)>=1,Z5>=ThamSo!$C$9)),"W2",IF(OR(MAX(T5,U5)>=1,V5=1),"W1","W0")) -> W2 | AE5: =CHOOSE(MATCH(AD5,{"W0","W1","W2"},0),"An toàn","Có nguy cơ","Thiếu trầm trọng") -> Thiếu trầm trọng | AF5: =IF(OR(E5<>1,AD5="W0"),"",IF(AND(T5=0,U5=0),"Phải trả",IF(T5>U5,"Phải thu",IF(U5>T5,"Tồn kho",IF(X5>=Y5,"Phải thu","Tồn kho"))))) -> Tồn kho | AG5: =TRIM(IF(T5=2,"R-AR-2 ",IF(T5=1,"R-AR-1 ",""))&IF(U5=2,"R-INV-2 ",IF(U5=1,"R-INV-1 ",""))&IF(V5=1,"R-AP-1 ","")&IF(AND(MAX(T5,U5)>=1,Z5>=ThamSo!$C$9),"R-MAT","")) -> R-INV-2 R-MAT | AH5: =IF(E5<>1,"",X5+Y5) -> 3.7584252e+10 | AI5: =IF(OR(E5<>1,DuLieu!A6<>DuLieu!A5,DuLieu!B6>ThamSo!$C$23,DuLieu!D6="",DuLieu!K6=""),"",IF(OR(DuLieu!K6<0,DuLieu!D6<DuLieu!D5*(1-ThamSo!$C$20)),1,0)) -> 0
A6: =DuLieu!A6 -> AG1 | B6: =DuLieu!B6 -> 2024 | C6: =A6&"-"&B6 -> AG1-2024 | D6: =DuLieu!S6&"|"&DuLieu!V6 -> FOB|Nhỏ–vừa | E6: =DuLieu!U6 -> 1 | F6: =IF(E6=1,DuLieu!D6,"") -> 337512371714 | G6: =IF(E6=1,DuLieu!O6,"") -> 2.9782497e+11 | H6: =IF(E6=1,DuLieu!G6,"") -> 135967622195 | I6: =IF(E6=1,DuLieu!L6,"") -> 20.640644 | J6: =IF(E6=1,DuLieu!M6,"") -> 105.53788 | K6: =IF(E6=1,DuLieu!N6,"") -> 84.012707 | L6: =IF(E6=1,DuLieu!P6,"") -> 0.11897939 | M6: =IF(E6=1,INDEX(B3_NguongKhoanMuc!$E$4:$E$5,MATCH(D6,B3_NguongKhoanMuc!$A$4:$A$5,0)),"") -> 58.207139 | N6: =IF(E6=1,INDEX(B3_NguongKhoanMuc!$F$4:$F$5,MATCH(D6,B3_NguongKhoanMuc!$A$4:$A$5,0)),"") -> 66.263266 | O6: =IF(E6=1,INDEX(B3_NguongKhoanMuc!$H$4:$H$5,MATCH(D6,B3_NguongKhoanMuc!$A$4:$A$5,0)),"") -> 86.118055 | P6: =IF(E6=1,INDEX(B3_NguongKhoanMuc!$I$4:$I$5,MATCH(D6,B3_NguongKhoanMuc!$A$4:$A$5,0)),"") -> 137.96515 | Q6: =IF(E6=1,INDEX(B3_NguongKhoanMuc!$K$4:$K$5,MATCH(D6,B3_NguongKhoanMuc!$A$4:$A$5,0)),"") -> 68.309204 | R6: =IF(E6=1,INDEX(B3_NguongKhoanMuc!$L$4:$L$5,MATCH(D6,B3_NguongKhoanMuc!$A$4:$A$5,0)),"") -> 14.892653 | S6: =IF(E6=1,INDEX(B3_NguongKhoanMuc!$M$4:$M$5,MATCH(D6,B3_NguongKhoanMuc!$A$4:$A$5,0)),"") -> 0.083007995 | T6: =IF(E6<>1,"",IF(I6>N6,2,IF(I6>M6,1,0))) -> 0 | U6: =IF(E6<>1,"",IF(J6>P6,2,IF(J6>O6,1,0))) -> 1 | V6: =IF(E6<>1,"",IF(AND(K6<R6,L6<S6),1,0)) -> 0 | W6: =IF(E6<>1,"",IF(K6>Q6,1,0)) -> 1 | X6: =IF(E6<>1,"",IF(T6>=1,(I6-M6)*F6/365,0)) -> 0 | Y6: =IF(E6<>1,"",IF(U6>=1,(J6-O6)*G6/365,0)) -> 1.5845781e+10 | Z6: =IF(E6<>1,"",IF(H6>0,MAX(X6,Y6)/H6,0)) -> 0.11654084 | AA6: =IF(E6<>1,"",CHOOSE(T6+1,"An toàn","Có nguy cơ","Trầm trọng")) -> An toàn | AB6: =IF(E6<>1,"",CHOOSE(U6+1,"An toàn","Có nguy cơ","Trầm trọng")) -> Có nguy cơ | AC6: =IF(E6<>1,"",IF(V6=1,"Có nguy cơ: NCC cho nợ ít + tiền mỏng",IF(W6=1,"Lưu ý: DPO cao – kiểm tra quá hạn NCC","An toàn"))) -> Lưu ý: DPO cao – kiểm tra quá hạn NCC | AD6: =IF(OR(AND(ThamSo!$C$10=1,MAX(T6,U6)=2),AND(MAX(T6,U6)>=1,Z6>=ThamSo!$C$9)),"W2",IF(OR(MAX(T6,U6)>=1,V6=1),"W1","W0")) -> W2 | AE6: =CHOOSE(MATCH(AD6,{"W0","W1","W2"},0),"An toàn","Có nguy cơ","Thiếu trầm trọng") -> Thiếu trầm trọng | AF6: =IF(OR(E6<>1,AD6="W0"),"",IF(AND(T6=0,U6=0),"Phải trả",IF(T6>U6,"Phải thu",IF(U6>T6,"Tồn kho",IF(X6>=Y6,"Phải thu","Tồn kho"))))) -> Tồn kho | AG6: =TRIM(IF(T6=2,"R-AR-2 ",IF(T6=1,"R-AR-1 ",""))&IF(U6=2,"R-INV-2 ",IF(U6=1,"R-INV-1 ",""))&IF(V6=1,"R-AP-1 ","")&IF(AND(MAX(T6,U6)>=1,Z6>=ThamSo!$C$9),"R-MAT","")) -> R-INV-1 R-MAT | AH6: =IF(E6<>1,"",X6+Y6) -> 1.5845781e+10 | AI6: =IF(OR(E6<>1,DuLieu!A7<>DuLieu!A6,DuLieu!B7>ThamSo!$C$23,DuLieu!D7="",DuLieu!K7=""),"",IF(OR(DuLieu!K7<0,DuLieu!D7<DuLieu!D6*(1-ThamSo!$C$20)),1,0)) -> 0
A7: =DuLieu!A7 -> AG1 | B7: =DuLieu!B7 -> 2025 | C7: =A7&"-"&B7 -> AG1-2025 | D7: =DuLieu!S7&"|"&DuLieu!V7 -> FOB|Nhỏ–vừa | E7: =DuLieu!U7 -> 1 | F7: =IF(E7=1,DuLieu!D7,"") -> 384757383278 | G7: =IF(E7=1,DuLieu!O7,"") -> 3.4023569e+11 | H7: =IF(E7=1,DuLieu!G7,"") -> 145047321035 | I7: =IF(E7=1,DuLieu!L7,"") -> 26.756938 | J7: =IF(E7=1,DuLieu!M7,"") -> 83.614772 | K7: =IF(E7=1,DuLieu!N7,"") -> 69.834385 | L7: =IF(E7=1,DuLieu!P7,"") -> 0.04477945 | M7: =IF(E7=1,INDEX(B3_NguongKhoanMuc!$E$4:$E$5,MATCH(D7,B3_NguongKhoanMuc!$A$4:$A$5,0)),"") -> 58.207139 | N7: =IF(E7=1,INDEX(B3_NguongKhoanMuc!$F$4:$F$5,MATCH(D7,B3_NguongKhoanMuc!$A$4:$A$5,0)),"") -> 66.263266 | O7: =IF(E7=1,INDEX(B3_NguongKhoanMuc!$H$4:$H$5,MATCH(D7,B3_NguongKhoanMuc!$A$4:$A$5,0)),"") -> 86.118055 | P7: =IF(E7=1,INDEX(B3_NguongKhoanMuc!$I$4:$I$5,MATCH(D7,B3_NguongKhoanMuc!$A$4:$A$5,0)),"") -> 137.96515 | Q7: =IF(E7=1,INDEX(B3_NguongKhoanMuc!$K$4:$K$5,MATCH(D7,B3_NguongKhoanMuc!$A$4:$A$5,0)),"") -> 68.309204 | R7: =IF(E7=1,INDEX(B3_NguongKhoanMuc!$L$4:$L$5,MATCH(D7,B3_NguongKhoanMuc!$A$4:$A$5,0)),"") -> 14.892653 | S7: =IF(E7=1,INDEX(B3_NguongKhoanMuc!$M$4:$M$5,MATCH(D7,B3_NguongKhoanMuc!$A$4:$A$5,0)),"") -> 0.083007995 | T7: =IF(E7<>1,"",IF(I7>N7,2,IF(I7>M7,1,0))) -> 0 | U7: =IF(E7<>1,"",IF(J7>P7,2,IF(J7>O7,1,0))) -> 0 | V7: =IF(E7<>1,"",IF(AND(K7<R7,L7<S7),1,0)) -> 0 | W7: =IF(E7<>1,"",IF(K7>Q7,1,0)) -> 1 | X7: =IF(E7<>1,"",IF(T7>=1,(I7-M7)*F7/365,0)) -> 0 | Y7: =IF(E7<>1,"",IF(U7>=1,(J7-O7)*G7/365,0)) -> 0 | Z7: =IF(E7<>1,"",IF(H7>0,MAX(X7,Y7)/H7,0)) -> 0 | AA7: =IF(E7<>1,"",CHOOSE(T7+1,"An toàn","Có nguy cơ","Trầm trọng")) -> An toàn | AB7: =IF(E7<>1,"",CHOOSE(U7+1,"An toàn","Có nguy cơ","Trầm trọng")) -> An toàn | AC7: =IF(E7<>1,"",IF(V7=1,"Có nguy cơ: NCC cho nợ ít + tiền mỏng",IF(W7=1,"Lưu ý: DPO cao – kiểm tra quá hạn NCC","An toàn"))) -> Lưu ý: DPO cao – kiểm tra quá hạn NCC | AD7: =IF(OR(AND(ThamSo!$C$10=1,MAX(T7,U7)=2),AND(MAX(T7,U7)>=1,Z7>=ThamSo!$C$9)),"W2",IF(OR(MAX(T7,U7)>=1,V7=1),"W1","W0")) -> W0 | AE7: =CHOOSE(MATCH(AD7,{"W0","W1","W2"},0),"An toàn","Có nguy cơ","Thiếu trầm trọng") -> An toàn | AF7: =IF(OR(E7<>1,AD7="W0"),"",IF(AND(T7=0,U7=0),"Phải trả",IF(T7>U7,"Phải thu",IF(U7>T7,"Tồn kho",IF(X7>=Y7,"Phải thu","Tồn kho"))))) | AG7: =TRIM(IF(T7=2,"R-AR-2 ",IF(T7=1,"R-AR-1 ",""))&IF(U7=2,"R-INV-2 ",IF(U7=1,"R-INV-1 ",""))&IF(V7=1,"R-AP-1 ","")&IF(AND(MAX(T7,U7)>=1,Z7>=ThamSo!$C$9),"R-MAT","")) | AH7: =IF(E7<>1,"",X7+Y7) -> 0 | AI7: =IF(OR(E7<>1,DuLieu!A8<>DuLieu!A7,DuLieu!B8>ThamSo!$C$23,DuLieu!D8="",DuLieu!K8=""),"",IF(OR(DuLieu!K8<0,DuLieu!D8<DuLieu!D7*(1-ThamSo!$C$20)),1,0))
A8: =DuLieu!A8 -> BDG | B8: =DuLieu!B8 -> 2023 | C8: =A8&"-"&B8 -> BDG-2023 | D8: =DuLieu!S8&"|"&DuLieu!V8 -> FOB|Lớn | E8: =DuLieu!U8 -> 1 | F8: =IF(E8=1,DuLieu!D8,"") -> 1565802348007 | G8: =IF(E8=1,DuLieu!O8,"") -> 1.2986263e+12 | H8: =IF(E8=1,DuLieu!G8,"") -> 762014891824 | I8: =IF(E8=1,DuLieu!L8,"") -> 46.399479 | J8: =IF(E8=1,DuLieu!M8,"") -> 75.031069 | K8: =IF(E8=1,DuLieu!N8,"") -> 38.543819 | L8: =IF(E8=1,DuLieu!P8,"") -> 0.15094065 | M8: =IF(E8=1,INDEX(B3_NguongKhoanMuc!$E$4:$E$5,MATCH(D8,B3_NguongKhoanMuc!$A$4:$A$5,0)),"") -> 58.207139 | N8: =IF(E8=1,INDEX(B3_NguongKhoanMuc!$F$4:$F$5,MATCH(D8,B3_NguongKhoanMuc!$A$4:$A$5,0)),"") -> 66.263266 | O8: =IF(E8=1,INDEX(B3_NguongKhoanMuc!$H$4:$H$5,MATCH(D8,B3_NguongKhoanMuc!$A$4:$A$5,0)),"") -> 86.118055 | P8: =IF(E8=1,INDEX(B3_NguongKhoanMuc!$I$4:$I$5,MATCH(D8,B3_NguongKhoanMuc!$A$4:$A$5,0)),"") -> 137.96515 | Q8: =IF(E8=1,INDEX(B3_NguongKhoanMuc!$K$4:$K$5,MATCH(D8,B3_NguongKhoanMuc!$A$4:$A$5,0)),"") -> 68.309204 | R8: =IF(E8=1,INDEX(B3_NguongKhoanMuc!$L$4:$L$5,MATCH(D8,B3_NguongKhoanMuc!$A$4:$A$5,0)),"") -> 14.892653 | S8: =IF(E8=1,INDEX(B3_NguongKhoanMuc!$M$4:$M$5,MATCH(D8,B3_NguongKhoanMuc!$A$4:$A$5,0)),"") -> 0.083007995 | T8: =IF(E8<>1,"",IF(I8>N8,2,IF(I8>M8,1,0))) -> 0 | U8: =IF(E8<>1,"",IF(J8>P8,2,IF(J8>O8,1,0))) -> 0 | V8: =IF(E8<>1,"",IF(AND(K8<R8,L8<S8),1,0)) -> 0 | W8: =IF(E8<>1,"",IF(K8>Q8,1,0)) -> 0 | X8: =IF(E8<>1,"",IF(T8>=1,(I8-M8)*F8/365,0)) -> 0 | Y8: =IF(E8<>1,"",IF(U8>=1,(J8-O8)*G8/365,0)) -> 0 | Z8: =IF(E8<>1,"",IF(H8>0,MAX(X8,Y8)/H8,0)) -> 0 | AA8: =IF(E8<>1,"",CHOOSE(T8+1,"An toàn","Có nguy cơ","Trầm trọng")) -> An toàn | AB8: =IF(E8<>1,"",CHOOSE(U8+1,"An toàn","Có nguy cơ","Trầm trọng")) -> An toàn | AC8: =IF(E8<>1,"",IF(V8=1,"Có nguy cơ: NCC cho nợ ít + tiền mỏng",IF(W8=1,"Lưu ý: DPO cao – kiểm tra quá hạn NCC","An toàn"))) -> An toàn | AD8: =IF(OR(AND(ThamSo!$C$10=1,MAX(T8,U8)=2),AND(MAX(T8,U8)>=1,Z8>=ThamSo!$C$9)),"W2",IF(OR(MAX(T8,U8)>=1,V8=1),"W1","W0")) -> W0 | AE8: =CHOOSE(MATCH(AD8,{"W0","W1","W2"},0),"An toàn","Có nguy cơ","Thiếu trầm trọng") -> An toàn | AF8: =IF(OR(E8<>1,AD8="W0"),"",IF(AND(T8=0,U8=0),"Phải trả",IF(T8>U8,"Phải thu",IF(U8>T8,"Tồn kho",IF(X8>=Y8,"Phải thu","Tồn kho"))))) | AG8: =TRIM(IF(T8=2,"R-AR-2 ",IF(T8=1,"R-AR-1 ",""))&IF(U8=2,"R-INV-2 ",IF(U8=1,"R-INV-1 ",""))&IF(V8=1,"R-AP-1 ","")&IF(AND(MAX(T8,U8)>=1,Z8>=ThamSo!$C$9),"R-MAT","")) | AH8: =IF(E8<>1,"",X8+Y8) -> 0 | AI8: =IF(OR(E8<>1,DuLieu!A9<>DuLieu!A8,DuLieu!B9>ThamSo!$C$23,DuLieu!D9="",DuLieu!K9=""),"",IF(OR(DuLieu!K9<0,DuLieu!D9<DuLieu!D8*(1-ThamSo!$C$20)),1,0)) -> 0
A9: =DuLieu!A9 -> BDG | B9: =DuLieu!B9 -> 2024 | C9: =A9&"-"&B9 -> BDG-2024 | D9: =DuLieu!S9&"|"&DuLieu!V9 -> FOB|Lớn | E9: =DuLieu!U9 -> 1 | F9: =IF(E9=1,DuLieu!D9,"") -> 1821385866875 | G9: =IF(E9=1,DuLieu!O9,"") -> 1.508175e+12 | H9: =IF(E9=1,DuLieu!G9,"") -> 892610103449 | I9: =IF(E9=1,DuLieu!L9,"") -> 47.799581 | J9: =IF(E9=1,DuLieu!M9,"") -> 59.720353 | K9: =IF(E9=1,DuLieu!N9,"") -> 31.093713 | L9: =IF(E9=1,DuLieu!P9,"") -> 0.17254128 | M9: =IF(E9=1,INDEX(B3_NguongKhoanMuc!$E$4:$E$5,MATCH(D9,B3_NguongKhoanMuc!$A$4:$A$5,0)),"") -> 58.207139 | N9: =IF(E9=1,INDEX(B3_NguongKhoanMuc!$F$4:$F$5,MATCH(D9,B3_NguongKhoanMuc!$A$4:$A$5,0)),"") -> 66.263266 | O9: =IF(E9=1,INDEX(B3_NguongKhoanMuc!$H$4:$H$5,MATCH(D9,B3_NguongKhoanMuc!$A$4:$A$5,0)),"") -> 86.118055 | P9: =IF(E9=1,INDEX(B3_NguongKhoanMuc!$I$4:$I$5,MATCH(D9,B3_NguongKhoanMuc!$A$4:$A$5,0)),"") -> 137.96515 | Q9: =IF(E9=1,INDEX(B3_NguongKhoanMuc!$K$4:$K$5,MATCH(D9,B3_NguongKhoanMuc!$A$4:$A$5,0)),"") -> 68.309204 | R9: =IF(E9=1,INDEX(B3_NguongKhoanMuc!$L$4:$L$5,MATCH(D9,B3_NguongKhoanMuc!$A$4:$A$5,0)),"") -> 14.892653 | S9: =IF(E9=1,INDEX(B3_NguongKhoanMuc!$M$4:$M$5,MATCH(D9,B3_NguongKhoanMuc!$A$4:$A$5,0)),"") -> 0.083007995 | T9: =IF(E9<>1,"",IF(I9>N9,2,IF(I9>M9,1,0))) -> 0 | U9: =IF(E9<>1,"",IF(J9>P9,2,IF(J9>O9,1,0))) -> 0 | V9: =IF(E9<>1,"",IF(AND(K9<R9,L9<S9),1,0)) -> 0 | W9: =IF(E9<>1,"",IF(K9>Q9,1,0)) -> 0 | X9: =IF(E9<>1,"",IF(T9>=1,(I9-M9)*F9/365,0)) -> 0 | Y9: =IF(E9<>1,"",IF(U9>=1,(J9-O9)*G9/365,0)) -> 0 | Z9: =IF(E9<>1,"",IF(H9>0,MAX(X9,Y9)/H9,0)) -> 0 | AA9: =IF(E9<>1,"",CHOOSE(T9+1,"An toàn","Có nguy cơ","Trầm trọng")) -> An toàn | AB9: =IF(E9<>1,"",CHOOSE(U9+1,"An toàn","Có nguy cơ","Trầm trọng")) -> An toàn | AC9: =IF(E9<>1,"",IF(V9=1,"Có nguy cơ: NCC cho nợ ít + tiền mỏng",IF(W9=1,"Lưu ý: DPO cao – kiểm tra quá hạn NCC","An toàn"))) -> An toàn | AD9: =IF(OR(AND(ThamSo!$C$10=1,MAX(T9,U9)=2),AND(MAX(T9,U9)>=1,Z9>=ThamSo!$C$9)),"W2",IF(OR(MAX(T9,U9)>=1,V9=1),"W1","W0")) -> W0 | AE9: =CHOOSE(MATCH(AD9,{"W0","W1","W2"},0),"An toàn","Có nguy cơ","Thiếu trầm trọng") -> An toàn | AF9: =IF(OR(E9<>1,AD9="W0"),"",IF(AND(T9=0,U9=0),"Phải trả",IF(T9>U9,"Phải thu",IF(U9>T9,"Tồn kho",IF(X9>=Y9,"Phải thu","Tồn kho"))))) | AG9: =TRIM(IF(T9=2,"R-AR-2 ",IF(T9=1,"R-AR-1 ",""))&IF(U9=2,"R-INV-2 ",IF(U9=1,"R-INV-1 ",""))&IF(V9=1,"R-AP-1 ","")&IF(AND(MAX(T9,U9)>=1,Z9>=ThamSo!$C$9),"R-MAT","")) | AH9: =IF(E9<>1,"",X9+Y9) -> 0 | AI9: =IF(OR(E9<>1,DuLieu!A10<>DuLieu!A9,DuLieu!B10>ThamSo!$C$23,DuLieu!D10="",DuLieu!K10=""),"",IF(OR(DuLieu!K10<0,DuLieu!D10<DuLieu!D9*(1-ThamSo!$C$20)),1,0)) -> 0
A10: =DuLieu!A10 -> BDG | B10: =DuLieu!B10 -> 2025 | C10: =A10&"-"&B10 -> BDG-2025 | D10: =DuLieu!S10&"|"&DuLieu!V10 -> FOB|Lớn | E10: =DuLieu!U10 -> 1 | F10: =IF(E10=1,DuLieu!D10,"") -> 1765786732419 | G10: =IF(E10=1,DuLieu!O10,"") -> 1.4783451e+12 | H10: =IF(E10=1,DuLieu!G10,"") -> 836089871106 | I10: =IF(E10=1,DuLieu!L10,"") -> 58.115114 | J10: =IF(E10=1,DuLieu!M10,"") -> 58.325885 | K10: =IF(E10=1,DuLieu!N10,"") -> 32.642841 | L10: =IF(E10=1,DuLieu!P10,"") -> 0.12833947 | M10: =IF(E10=1,INDEX(B3_NguongKhoanMuc!$E$4:$E$5,MATCH(D10,B3_NguongKhoanMuc!$A$4:$A$5,0)),"") -> 58.207139 | N10: =IF(E10=1,INDEX(B3_NguongKhoanMuc!$F$4:$F$5,MATCH(D10,B3_NguongKhoanMuc!$A$4:$A$5,0)),"") -> 66.263266 | O10: =IF(E10=1,INDEX(B3_NguongKhoanMuc!$H$4:$H$5,MATCH(D10,B3_NguongKhoanMuc!$A$4:$A$5,0)),"") -> 86.118055 | P10: =IF(E10=1,INDEX(B3_NguongKhoanMuc!$I$4:$I$5,MATCH(D10,B3_NguongKhoanMuc!$A$4:$A$5,0)),"") -> 137.96515 | Q10: =IF(E10=1,INDEX(B3_NguongKhoanMuc!$K$4:$K$5,MATCH(D10,B3_NguongKhoanMuc!$A$4:$A$5,0)),"") -> 68.309204 | R10: =IF(E10=1,INDEX(B3_NguongKhoanMuc!$L$4:$L$5,MATCH(D10,B3_NguongKhoanMuc!$A$4:$A$5,0)),"") -> 14.892653 | S10: =IF(E10=1,INDEX(B3_NguongKhoanMuc!$M$4:$M$5,MATCH(D10,B3_NguongKhoanMuc!$A$4:$A$5,0)),"") -> 0.083007995 | T10: =IF(E10<>1,"",IF(I10>N10,2,IF(I10>M10,1,0))) -> 0 | U10: =IF(E10<>1,"",IF(J10>P10,2,IF(J10>O10,1,0))) -> 0 | V10: =IF(E10<>1,"",IF(AND(K10<R10,L10<S10),1,0)) -> 0 | W10: =IF(E10<>1,"",IF(K10>Q10,1,0)) -> 0 | X10: =IF(E10<>1,"",IF(T10>=1,(I10-M10)*F10/365,0)) -> 0 | Y10: =IF(E10<>1,"",IF(U10>=1,(J10-O10)*G10/365,0)) -> 0 | Z10: =IF(E10<>1,"",IF(H10>0,MAX(X10,Y10)/H10,0)) -> 0 | AA10: =IF(E10<>1,"",CHOOSE(T10+1,"An toàn","Có nguy cơ","Trầm trọng")) -> An toàn | AB10: =IF(E10<>1,"",CHOOSE(U10+1,"An toàn","Có nguy cơ","Trầm trọng")) -> An toàn | AC10: =IF(E10<>1,"",IF(V10=1,"Có nguy cơ: NCC cho nợ ít + tiền mỏng",IF(W10=1,"Lưu ý: DPO cao – kiểm tra quá hạn NCC","An toàn"))) -> An toàn | AD10: =IF(OR(AND(ThamSo!$C$10=1,MAX(T10,U10)=2),AND(MAX(T10,U10)>=1,Z10>=ThamSo!$C$9)),"W2",IF(OR(MAX(T10,U10)>=1,V10=1),"W1","W0")) -> W0 | AE10: =CHOOSE(MATCH(AD10,{"W0","W1","W2"},0),"An toàn","Có nguy cơ","Thiếu trầm trọng") -> An toàn | AF10: =IF(OR(E10<>1,AD10="W0"),"",IF(AND(T10=0,U10=0),"Phải trả",IF(T10>U10,"Phải thu",IF(U10>T10,"Tồn kho",IF(X10>=Y10,"Phải thu","Tồn kho"))))) | AG10: =TRIM(IF(T10=2,"R-AR-2 ",IF(T10=1,"R-AR-1 ",""))&IF(U10=2,"R-INV-2 ",IF(U10=1,"R-INV-1 ",""))&IF(V10=1,"R-AP-1 ","")&IF(AND(MAX(T10,U10)>=1,Z10>=ThamSo!$C$9),"R-MAT","")) | AH10: =IF(E10<>1,"",X10+Y10) -> 0 | AI10: =IF(OR(E10<>1,DuLieu!A11<>DuLieu!A10,DuLieu!B11>ThamSo!$C$23,DuLieu!D11="",DuLieu!K11=""),"",IF(OR(DuLieu!K11<0,DuLieu!D11<DuLieu!D10*(1-ThamSo!$C$20)),1,0))
A11: =DuLieu!A11 -> BMG | B11: =DuLieu!B11 -> 2023 | C11: =A11&"-"&B11 -> BMG-2023 | D11: =DuLieu!S11&"|"&DuLieu!V11 -> FOB|Nhỏ–vừa | E11: =DuLieu!U11 -> 1 | F11: =IF(E11=1,DuLieu!D11,"") -> 295724897278 | G11: =IF(E11=1,DuLieu!O11,"") -> 2.461225e+11 | H11: =IF(E11=1,DuLieu!G11,"") -> 99960557124 | I11: =IF(E11=1,DuLieu!L11,"") -> 35.013296 | J11: =IF(E11=1,DuLieu!M11,"") -> 61.04222 | K11: =IF(E11=1,DuLieu!N11,"") -> 24.979894 | L11: =IF(E11=1,DuLieu!P11,"") -> 0.11842199 | M11: =IF(E11=1,INDEX(B3_NguongKhoanMuc!$E$4:$E$5,MATCH(D11,B3_NguongKhoanMuc!$A$4:$A$5,0)),"") -> 58.207139 | N11: =IF(E11=1,INDEX(B3_NguongKhoanMuc!$F$4:$F$5,MATCH(D11,B3_NguongKhoanMuc!$A$4:$A$5,0)),"") -> 66.263266 | O11: =IF(E11=1,INDEX(B3_NguongKhoanMuc!$H$4:$H$5,MATCH(D11,B3_NguongKhoanMuc!$A$4:$A$5,0)),"") -> 86.118055 | P11: =IF(E11=1,INDEX(B3_NguongKhoanMuc!$I$4:$I$5,MATCH(D11,B3_NguongKhoanMuc!$A$4:$A$5,0)),"") -> 137.96515 | Q11: =IF(E11=1,INDEX(B3_NguongKhoanMuc!$K$4:$K$5,MATCH(D11,B3_NguongKhoanMuc!$A$4:$A$5,0)),"") -> 68.309204 | R11: =IF(E11=1,INDEX(B3_NguongKhoanMuc!$L$4:$L$5,MATCH(D11,B3_NguongKhoanMuc!$A$4:$A$5,0)),"") -> 14.892653 | S11: =IF(E11=1,INDEX(B3_NguongKhoanMuc!$M$4:$M$5,MATCH(D11,B3_NguongKhoanMuc!$A$4:$A$5,0)),"") -> 0.083007995 | T11: =IF(E11<>1,"",IF(I11>N11,2,IF(I11>M11,1,0))) -> 0 | U11: =IF(E11<>1,"",IF(J11>P11,2,IF(J11>O11,1,0))) -> 0 | V11: =IF(E11<>1,"",IF(AND(K11<R11,L11<S11),1,0)) -> 0 | W11: =IF(E11<>1,"",IF(K11>Q11,1,0)) -> 0 | X11: =IF(E11<>1,"",IF(T11>=1,(I11-M11)*F11/365,0)) -> 0 | Y11: =IF(E11<>1,"",IF(U11>=1,(J11-O11)*G11/365,0)) -> 0 | Z11: =IF(E11<>1,"",IF(H11>0,MAX(X11,Y11)/H11,0)) -> 0 | AA11: =IF(E11<>1,"",CHOOSE(T11+1,"An toàn","Có nguy cơ","Trầm trọng")) -> An toàn | AB11: =IF(E11<>1,"",CHOOSE(U11+1,"An toàn","Có nguy cơ","Trầm trọng")) -> An toàn | AC11: =IF(E11<>1,"",IF(V11=1,"Có nguy cơ: NCC cho nợ ít + tiền mỏng",IF(W11=1,"Lưu ý: DPO cao – kiểm tra quá hạn NCC","An toàn"))) -> An toàn | AD11: =IF(OR(AND(ThamSo!$C$10=1,MAX(T11,U11)=2),AND(MAX(T11,U11)>=1,Z11>=ThamSo!$C$9)),"W2",IF(OR(MAX(T11,U11)>=1,V11=1),"W1","W0")) -> W0 | AE11: =CHOOSE(MATCH(AD11,{"W0","W1","W2"},0),"An toàn","Có nguy cơ","Thiếu trầm trọng") -> An toàn | AF11: =IF(OR(E11<>1,AD11="W0"),"",IF(AND(T11=0,U11=0),"Phải trả",IF(T11>U11,"Phải thu",IF(U11>T11,"Tồn kho",IF(X11>=Y11,"Phải thu","Tồn kho"))))) | AG11: =TRIM(IF(T11=2,"R-AR-2 ",IF(T11=1,"R-AR-1 ",""))&IF(U11=2,"R-INV-2 ",IF(U11=1,"R-INV-1 ",""))&IF(V11=1,"R-AP-1 ","")&IF(AND(MAX(T11,U11)>=1,Z11>=ThamSo!$C$9),"R-MAT","")) | AH11: =IF(E11<>1,"",X11+Y11) -> 0 | AI11: =IF(OR(E11<>1,DuLieu!A12<>DuLieu!A11,DuLieu!B12>ThamSo!$C$23,DuLieu!D12="",DuLieu!K12=""),"",IF(OR(DuLieu!K12<0,DuLieu!D12<DuLieu!D11*(1-ThamSo!$C$20)),1,0)) -> 0
A12: =DuLieu!A12 -> BMG | B12: =DuLieu!B12 -> 2024 | C12: =A12&"-"&B12 -> BMG-2024 | D12: =DuLieu!S12&"|"&DuLieu!V12 -> FOB|Nhỏ–vừa | E12: =DuLieu!U12 -> 1 | F12: =IF(E12=1,DuLieu!D12,"") -> 275980198004 | G12: =IF(E12=1,DuLieu!O12,"") -> 2.2640539e+11 | H12: =IF(E12=1,DuLieu!G12,"") -> 110968220994 | I12: =IF(E12=1,DuLieu!L12,"") -> 31.714545 | J12: =IF(E12=1,DuLieu!M12,"") -> 64.140082 | K12: =IF(E12=1,DuLieu!N12,"") -> 34.455964 | L12: =IF(E12=1,DuLieu!P12,"") -> 0.14194827 | M12: =IF(E12=1,INDEX(B3_NguongKhoanMuc!$E$4:$E$5,MATCH(D12,B3_NguongKhoanMuc!$A$4:$A$5,0)),"") -> 58.207139 | N12: =IF(E12=1,INDEX(B3_NguongKhoanMuc!$F$4:$F$5,MATCH(D12,B3_NguongKhoanMuc!$A$4:$A$5,0)),"") -> 66.263266 | O12: =IF(E12=1,INDEX(B3_NguongKhoanMuc!$H$4:$H$5,MATCH(D12,B3_NguongKhoanMuc!$A$4:$A$5,0)),"") -> 86.118055 | P12: =IF(E12=1,INDEX(B3_NguongKhoanMuc!$I$4:$I$5,MATCH(D12,B3_NguongKhoanMuc!$A$4:$A$5,0)),"") -> 137.96515 | Q12: =IF(E12=1,INDEX(B3_NguongKhoanMuc!$K$4:$K$5,MATCH(D12,B3_NguongKhoanMuc!$A$4:$A$5,0)),"") -> 68.309204 | R12: =IF(E12=1,INDEX(B3_NguongKhoanMuc!$L$4:$L$5,MATCH(D12,B3_NguongKhoanMuc!$A$4:$A$5,0)),"") -> 14.892653 | S12: =IF(E12=1,INDEX(B3_NguongKhoanMuc!$M$4:$M$5,MATCH(D12,B3_NguongKhoanMuc!$A$4:$A$5,0)),"") -> 0.083007995 | T12: =IF(E12<>1,"",IF(I12>N12,2,IF(I12>M12,1,0))) -> 0 | U12: =IF(E12<>1,"",IF(J12>P12,2,IF(J12>O12,1,0))) -> 0 | V12: =IF(E12<>1,"",IF(AND(K12<R12,L12<S12),1,0)) -> 0 | W12: =IF(E12<>1,"",IF(K12>Q12,1,0)) -> 0 | X12: =IF(E12<>1,"",IF(T12>=1,(I12-M12)*F12/365,0)) -> 0 | Y12: =IF(E12<>1,"",IF(U12>=1,(J12-O12)*G12/365,0)) -> 0 | Z12: =IF(E12<>1,"",IF(H12>0,MAX(X12,Y12)/H12,0)) -> 0 | AA12: =IF(E12<>1,"",CHOOSE(T12+1,"An toàn","Có nguy cơ","Trầm trọng")) -> An toàn | AB12: =IF(E12<>1,"",CHOOSE(U12+1,"An toàn","Có nguy cơ","Trầm trọng")) -> An toàn | AC12: =IF(E12<>1,"",IF(V12=1,"Có nguy cơ: NCC cho nợ ít + tiền mỏng",IF(W12=1,"Lưu ý: DPO cao – kiểm tra quá hạn NCC","An toàn"))) -> An toàn | AD12: =IF(OR(AND(ThamSo!$C$10=1,MAX(T12,U12)=2),AND(MAX(T12,U12)>=1,Z12>=ThamSo!$C$9)),"W2",IF(OR(MAX(T12,U12)>=1,V12=1),"W1","W0")) -> W0 | AE12: =CHOOSE(MATCH(AD12,{"W0","W1","W2"},0),"An toàn","Có nguy cơ","Thiếu trầm trọng") -> An toàn | AF12: =IF(OR(E12<>1,AD12="W0"),"",IF(AND(T12=0,U12=0),"Phải trả",IF(T12>U12,"Phải thu",IF(U12>T12,"Tồn kho",IF(X12>=Y12,"Phải thu","Tồn kho"))))) | AG12: =TRIM(IF(T12=2,"R-AR-2 ",IF(T12=1,"R-AR-1 ",""))&IF(U12=2,"R-INV-2 ",IF(U12=1,"R-INV-1 ",""))&IF(V12=1,"R-AP-1 ","")&IF(AND(MAX(T12,U12)>=1,Z12>=ThamSo!$C$9),"R-MAT","")) | AH12: =IF(E12<>1,"",X12+Y12) -> 0 | AI12: =IF(OR(E12<>1,DuLieu!A13<>DuLieu!A12,DuLieu!B13>ThamSo!$C$23,DuLieu!D13="",DuLieu!K13=""),"",IF(OR(DuLieu!K13<0,DuLieu!D13<DuLieu!D12*(1-ThamSo!$C$20)),1,0)) -> 0
A13: =DuLieu!A13 -> BMG | B13: =DuLieu!B13 -> 2025 | C13: =A13&"-"&B13 -> BMG-2025 | D13: =DuLieu!S13&"|"&DuLieu!V13 -> FOB|Nhỏ–vừa | E13: =DuLieu!U13 -> 1 | F13: =IF(E13=1,DuLieu!D13,"") -> 295940834048 | G13: =IF(E13=1,DuLieu!O13,"") -> 2.4099671e+11 | H13: =IF(E13=1,DuLieu!G13,"") -> 113467882537 | I13: =IF(E13=1,DuLieu!L13,"") -> 22.351583 | J13: =IF(E13=1,DuLieu!M13,"") -> 73.812934 | K13: =IF(E13=1,DuLieu!N13,"") -> 34.06861 | L13: =IF(E13=1,DuLieu!P13,"") -> 0.041458427 | M13: =IF(E13=1,INDEX(B3_NguongKhoanMuc!$E$4:$E$5,MATCH(D13,B3_NguongKhoanMuc!$A$4:$A$5,0)),"") -> 58.207139 | N13: =IF(E13=1,INDEX(B3_NguongKhoanMuc!$F$4:$F$5,MATCH(D13,B3_NguongKhoanMuc!$A$4:$A$5,0)),"") -> 66.263266 | O13: =IF(E13=1,INDEX(B3_NguongKhoanMuc!$H$4:$H$5,MATCH(D13,B3_NguongKhoanMuc!$A$4:$A$5,0)),"") -> 86.118055 | P13: =IF(E13=1,INDEX(B3_NguongKhoanMuc!$I$4:$I$5,MATCH(D13,B3_NguongKhoanMuc!$A$4:$A$5,0)),"") -> 137.96515 | Q13: =IF(E13=1,INDEX(B3_NguongKhoanMuc!$K$4:$K$5,MATCH(D13,B3_NguongKhoanMuc!$A$4:$A$5,0)),"") -> 68.309204 | R13: =IF(E13=1,INDEX(B3_NguongKhoanMuc!$L$4:$L$5,MATCH(D13,B3_NguongKhoanMuc!$A$4:$A$5,0)),"") -> 14.892653 | S13: =IF(E13=1,INDEX(B3_NguongKhoanMuc!$M$4:$M$5,MATCH(D13,B3_NguongKhoanMuc!$A$4:$A$5,0)),"") -> 0.083007995 | T13: =IF(E13<>1,"",IF(I13>N13,2,IF(I13>M13,1,0))) -> 0 | U13: =IF(E13<>1,"",IF(J13>P13,2,IF(J13>O13,1,0))) -> 0 | V13: =IF(E13<>1,"",IF(AND(K13<R13,L13<S13),1,0)) -> 0 | W13: =IF(E13<>1,"",IF(K13>Q13,1,0)) -> 0 | X13: =IF(E13<>1,"",IF(T13>=1,(I13-M13)*F13/365,0)) -> 0 | Y13: =IF(E13<>1,"",IF(U13>=1,(J13-O13)*G13/365,0)) -> 0 | Z13: =IF(E13<>1,"",IF(H13>0,MAX(X13,Y13)/H13,0)) -> 0 | AA13: =IF(E13<>1,"",CHOOSE(T13+1,"An toàn","Có nguy cơ","Trầm trọng")) -> An toàn | AB13: =IF(E13<>1,"",CHOOSE(U13+1,"An toàn","Có nguy cơ","Trầm trọng")) -> An toàn | AC13: =IF(E13<>1,"",IF(V13=1,"Có nguy cơ: NCC cho nợ ít + tiền mỏng",IF(W13=1,"Lưu ý: DPO cao – kiểm tra quá hạn NCC","An toàn"))) -> An toàn | AD13: =IF(OR(AND(ThamSo!$C$10=1,MAX(T13,U13)=2),AND(MAX(T13,U13)>=1,Z13>=ThamSo!$C$9)),"W2",IF(OR(MAX(T13,U13)>=1,V13=1),"W1","W0")) -> W0 | AE13: =CHOOSE(MATCH(AD13,{"W0","W1","W2"},0),"An toàn","Có nguy cơ","Thiếu trầm trọng") -> An toàn | AF13: =IF(OR(E13<>1,AD13="W0"),"",IF(AND(T13=0,U13=0),"Phải trả",IF(T13>U13,"Phải thu",IF(U13>T13,"Tồn kho",IF(X13>=Y13,"Phải thu","Tồn kho"))))) | AG13: =TRIM(IF(T13=2,"R-AR-2 ",IF(T13=1,"R-AR-1 ",""))&IF(U13=2,"R-INV-2 ",IF(U13=1,"R-INV-1 ",""))&IF(V13=1,"R-AP-1 ","")&IF(AND(MAX(T13,U13)>=1,Z13>=ThamSo!$C$9),"R-MAT","")) | AH13: =IF(E13<>1,"",X13+Y13) -> 0 | AI13: =IF(OR(E13<>1,DuLieu!A14<>DuLieu!A13,DuLieu!B14>ThamSo!$C$23,DuLieu!D14="",DuLieu!K14=""),"",IF(OR(DuLieu!K14<0,DuLieu!D14<DuLieu!D13*(1-ThamSo!$C$20)),1,0))
A14: =DuLieu!A17 -> DM7 | B14: =DuLieu!B17 -> 2023 | C14: =A14&"-"&B14 -> DM7-2023 | D14: =DuLieu!S17&"|"&DuLieu!V17 -> FOB|Nhỏ–vừa | E14: =DuLieu!U17 -> 1 | F14: =IF(E14=1,DuLieu!D17,"") -> 620231260463 | G14: =IF(E14=1,DuLieu!O17,"") -> 5.3522865e+11 | H14: =IF(E14=1,DuLieu!G17,"") -> 333140259403 | I14: =IF(E14=1,DuLieu!L17,"") -> 83.307468 | J14: =IF(E14=1,DuLieu!M17,"") -> 81.818822 | K14: =IF(E14=1,DuLieu!N17,"") -> 53.507638 | L14: =IF(E14=1,DuLieu!P17,"") -> 0.024667698 | M14: =IF(E14=1,INDEX(B3_NguongKhoanMuc!$E$4:$E$5,MATCH(D14,B3_NguongKhoanMuc!$A$4:$A$5,0)),"") -> 58.207139 | N14: =IF(E14=1,INDEX(B3_NguongKhoanMuc!$F$4:$F$5,MATCH(D14,B3_NguongKhoanMuc!$A$4:$A$5,0)),"") -> 66.263266 | O14: =IF(E14=1,INDEX(B3_NguongKhoanMuc!$H$4:$H$5,MATCH(D14,B3_NguongKhoanMuc!$A$4:$A$5,0)),"") -> 86.118055 | P14: =IF(E14=1,INDEX(B3_NguongKhoanMuc!$I$4:$I$5,MATCH(D14,B3_NguongKhoanMuc!$A$4:$A$5,0)),"") -> 137.96515 | Q14: =IF(E14=1,INDEX(B3_NguongKhoanMuc!$K$4:$K$5,MATCH(D14,B3_NguongKhoanMuc!$A$4:$A$5,0)),"") -> 68.309204 | R14: =IF(E14=1,INDEX(B3_NguongKhoanMuc!$L$4:$L$5,MATCH(D14,B3_NguongKhoanMuc!$A$4:$A$5,0)),"") -> 14.892653 | S14: =IF(E14=1,INDEX(B3_NguongKhoanMuc!$M$4:$M$5,MATCH(D14,B3_NguongKhoanMuc!$A$4:$A$5,0)),"") -> 0.083007995 | T14: =IF(E14<>1,"",IF(I14>N14,2,IF(I14>M14,1,0))) -> 2 | U14: =IF(E14<>1,"",IF(J14>P14,2,IF(J14>O14,1,0))) -> 0 | V14: =IF(E14<>1,"",IF(AND(K14<R14,L14<S14),1,0)) -> 0 | W14: =IF(E14<>1,"",IF(K14>Q14,1,0)) -> 0 | X14: =IF(E14<>1,"",IF(T14>=1,(I14-M14)*F14/365,0)) -> 4.265208e+10 | Y14: =IF(E14<>1,"",IF(U14>=1,(J14-O14)*G14/365,0)) -> 0 | Z14: =IF(E14<>1,"",IF(H14>0,MAX(X14,Y14)/H14,0)) -> 0.1280304 | AA14: =IF(E14<>1,"",CHOOSE(T14+1,"An toàn","Có nguy cơ","Trầm trọng")) -> Trầm trọng | AB14: =IF(E14<>1,"",CHOOSE(U14+1,"An toàn","Có nguy cơ","Trầm trọng")) -> An toàn | AC14: =IF(E14<>1,"",IF(V14=1,"Có nguy cơ: NCC cho nợ ít + tiền mỏng",IF(W14=1,"Lưu ý: DPO cao – kiểm tra quá hạn NCC","An toàn"))) -> An toàn | AD14: =IF(OR(AND(ThamSo!$C$10=1,MAX(T14,U14)=2),AND(MAX(T14,U14)>=1,Z14>=ThamSo!$C$9)),"W2",IF(OR(MAX(T14,U14)>=1,V14=1),"W1","W0")) -> W2 | AE14: =CHOOSE(MATCH(AD14,{"W0","W1","W2"},0),"An toàn","Có nguy cơ","Thiếu trầm trọng") -> Thiếu trầm trọng | AF14: =IF(OR(E14<>1,AD14="W0"),"",IF(AND(T14=0,U14=0),"Phải trả",IF(T14>U14,"Phải thu",IF(U14>T14,"Tồn kho",IF(X14>=Y14,"Phải thu","Tồn kho"))))) -> Phải thu | AG14: =TRIM(IF(T14=2,"R-AR-2 ",IF(T14=1,"R-AR-1 ",""))&IF(U14=2,"R-INV-2 ",IF(U14=1,"R-INV-1 ",""))&IF(V14=1,"R-AP-1 ","")&IF(AND(MAX(T14,U14)>=1,Z14>=ThamSo!$C$9),"R-MAT","")) -> R-AR-2 R-MAT | AH14: =IF(E14<>1,"",X14+Y14) -> 4.265208e+10 | AI14: =IF(OR(E14<>1,DuLieu!A18<>DuLieu!A17,DuLieu!B18>ThamSo!$C$23,DuLieu!D18="",DuLieu!K18=""),"",IF(OR(DuLieu!K18<0,DuLieu!D18<DuLieu!D17*(1-ThamSo!$C$20)),1,0)) -> 0
A15: =DuLieu!A18 -> DM7 | B15: =DuLieu!B18 -> 2024 | C15: =A15&"-"&B15 -> DM7-2024 | D15: =DuLieu!S18&"|"&DuLieu!V18 -> FOB|Nhỏ–vừa | E15: =DuLieu!U18 -> 1 | F15: =IF(E15=1,DuLieu!D18,"") -> 868155807971 | G15: =IF(E15=1,DuLieu!O18,"") -> 7.4006032e+11 | H15: =IF(E15=1,DuLieu!G18,"") -> 389114842980 | I15: =IF(E15=1,DuLieu!L18,"") -> 77.615172 | J15: =IF(E15=1,DuLieu!M18,"") -> 51.79639 | K15: =IF(E15=1,DuLieu!N18,"") -> 46.200039 | L15: =IF(E15=1,DuLieu!P18,"") -> 0.10658386 | M15: =IF(E15=1,INDEX(B3_NguongKhoanMuc!$E$4:$E$5,MATCH(D15,B3_NguongKhoanMuc!$A$4:$A$5,0)),"") -> 58.207139 | N15: =IF(E15=1,INDEX(B3_NguongKhoanMuc!$F$4:$F$5,MATCH(D15,B3_NguongKhoanMuc!$A$4:$A$5,0)),"") -> 66.263266 | O15: =IF(E15=1,INDEX(B3_NguongKhoanMuc!$H$4:$H$5,MATCH(D15,B3_NguongKhoanMuc!$A$4:$A$5,0)),"") -> 86.118055 | P15: =IF(E15=1,INDEX(B3_NguongKhoanMuc!$I$4:$I$5,MATCH(D15,B3_NguongKhoanMuc!$A$4:$A$5,0)),"") -> 137.96515 | Q15: =IF(E15=1,INDEX(B3_NguongKhoanMuc!$K$4:$K$5,MATCH(D15,B3_NguongKhoanMuc!$A$4:$A$5,0)),"") -> 68.309204 | R15: =IF(E15=1,INDEX(B3_NguongKhoanMuc!$L$4:$L$5,MATCH(D15,B3_NguongKhoanMuc!$A$4:$A$5,0)),"") -> 14.892653 | S15: =IF(E15=1,INDEX(B3_NguongKhoanMuc!$M$4:$M$5,MATCH(D15,B3_NguongKhoanMuc!$A$4:$A$5,0)),"") -> 0.083007995 | T15: =IF(E15<>1,"",IF(I15>N15,2,IF(I15>M15,1,0))) -> 2 | U15: =IF(E15<>1,"",IF(J15>P15,2,IF(J15>O15,1,0))) -> 0 | V15: =IF(E15<>1,"",IF(AND(K15<R15,L15<S15),1,0)) -> 0 | W15: =IF(E15<>1,"",IF(K15>Q15,1,0)) -> 0 | X15: =IF(E15<>1,"",IF(T15>=1,(I15-M15)*F15/365,0)) -> 4.6162183e+10 | Y15: =IF(E15<>1,"",IF(U15>=1,(J15-O15)*G15/365,0)) -> 0 | Z15: =IF(E15<>1,"",IF(H15>0,MAX(X15,Y15)/H15,0)) -> 0.11863383 | AA15: =IF(E15<>1,"",CHOOSE(T15+1,"An toàn","Có nguy cơ","Trầm trọng")) -> Trầm trọng | AB15: =IF(E15<>1,"",CHOOSE(U15+1,"An toàn","Có nguy cơ","Trầm trọng")) -> An toàn | AC15: =IF(E15<>1,"",IF(V15=1,"Có nguy cơ: NCC cho nợ ít + tiền mỏng",IF(W15=1,"Lưu ý: DPO cao – kiểm tra quá hạn NCC","An toàn"))) -> An toàn | AD15: =IF(OR(AND(ThamSo!$C$10=1,MAX(T15,U15)=2),AND(MAX(T15,U15)>=1,Z15>=ThamSo!$C$9)),"W2",IF(OR(MAX(T15,U15)>=1,V15=1),"W1","W0")) -> W2 | AE15: =CHOOSE(MATCH(AD15,{"W0","W1","W2"},0),"An toàn","Có nguy cơ","Thiếu trầm trọng") -> Thiếu trầm trọng | AF15: =IF(OR(E15<>1,AD15="W0"),"",IF(AND(T15=0,U15=0),"Phải trả",IF(T15>U15,"Phải thu",IF(U15>T15,"Tồn kho",IF(X15>=Y15,"Phải thu","Tồn kho"))))) -> Phải thu | AG15: =TRIM(IF(T15=2,"R-AR-2 ",IF(T15=1,"R-AR-1 ",""))&IF(U15=2,"R-INV-2 ",IF(U15=1,"R-INV-1 ",""))&IF(V15=1,"R-AP-1 ","")&IF(AND(MAX(T15,U15)>=1,Z15>=ThamSo!$C$9),"R-MAT","")) -> R-AR-2 R-MAT | AH15: =IF(E15<>1,"",X15+Y15) -> 4.6162183e+10 | AI15: =IF(OR(E15<>1,DuLieu!A19<>DuLieu!A18,DuLieu!B19>ThamSo!$C$23,DuLieu!D19="",DuLieu!K19=""),"",IF(OR(DuLieu!K19<0,DuLieu!D19<DuLieu!D18*(1-ThamSo!$C$20)),1,0)) -> 0
A16: =DuLieu!A19 -> DM7 | B16: =DuLieu!B19 -> 2025 | C16: =A16&"-"&B16 -> DM7-2025 | D16: =DuLieu!S19&"|"&DuLieu!V19 -> FOB|Nhỏ–vừa | E16: =DuLieu!U19 -> 1 | F16: =IF(E16=1,DuLieu!D19,"") -> 741070971989 | G16: =IF(E16=1,DuLieu!O19,"") -> 6.2068431e+11 | H16: =IF(E16=1,DuLieu!G19,"") -> 406303984542 | I16: =IF(E16=1,DuLieu!L19,"") -> 112.89637 | J16: =IF(E16=1,DuLieu!M19,"") -> 55.712532 | K16: =IF(E16=1,DuLieu!N19,"") -> 36.144411 | L16: =IF(E16=1,DuLieu!P19,"") -> 0.07036637 | M16: =IF(E16=1,INDEX(B3_NguongKhoanMuc!$E$4:$E$5,MATCH(D16,B3_NguongKhoanMuc!$A$4:$A$5,0)),"") -> 58.207139 | N16: =IF(E16=1,INDEX(B3_NguongKhoanMuc!$F$4:$F$5,MATCH(D16,B3_NguongKhoanMuc!$A$4:$A$5,0)),"") -> 66.263266 | O16: =IF(E16=1,INDEX(B3_NguongKhoanMuc!$H$4:$H$5,MATCH(D16,B3_NguongKhoanMuc!$A$4:$A$5,0)),"") -> 86.118055 | P16: =IF(E16=1,INDEX(B3_NguongKhoanMuc!$I$4:$I$5,MATCH(D16,B3_NguongKhoanMuc!$A$4:$A$5,0)),"") -> 137.96515 | Q16: =IF(E16=1,INDEX(B3_NguongKhoanMuc!$K$4:$K$5,MATCH(D16,B3_NguongKhoanMuc!$A$4:$A$5,0)),"") -> 68.309204 | R16: =IF(E16=1,INDEX(B3_NguongKhoanMuc!$L$4:$L$5,MATCH(D16,B3_NguongKhoanMuc!$A$4:$A$5,0)),"") -> 14.892653 | S16: =IF(E16=1,INDEX(B3_NguongKhoanMuc!$M$4:$M$5,MATCH(D16,B3_NguongKhoanMuc!$A$4:$A$5,0)),"") -> 0.083007995 | T16: =IF(E16<>1,"",IF(I16>N16,2,IF(I16>M16,1,0))) -> 2 | U16: =IF(E16<>1,"",IF(J16>P16,2,IF(J16>O16,1,0))) -> 0 | V16: =IF(E16<>1,"",IF(AND(K16<R16,L16<S16),1,0)) -> 0 | W16: =IF(E16<>1,"",IF(K16>Q16,1,0)) -> 0 | X16: =IF(E16<>1,"",IF(T16>=1,(I16-M16)*F16/365,0)) -> 1.1103728e+11 | Y16: =IF(E16<>1,"",IF(U16>=1,(J16-O16)*G16/365,0)) -> 0 | Z16: =IF(E16<>1,"",IF(H16>0,MAX(X16,Y16)/H16,0)) -> 0.27328621 | AA16: =IF(E16<>1,"",CHOOSE(T16+1,"An toàn","Có nguy cơ","Trầm trọng")) -> Trầm trọng | AB16: =IF(E16<>1,"",CHOOSE(U16+1,"An toàn","Có nguy cơ","Trầm trọng")) -> An toàn | AC16: =IF(E16<>1,"",IF(V16=1,"Có nguy cơ: NCC cho nợ ít + tiền mỏng",IF(W16=1,"Lưu ý: DPO cao – kiểm tra quá hạn NCC","An toàn"))) -> An toàn | AD16: =IF(OR(AND(ThamSo!$C$10=1,MAX(T16,U16)=2),AND(MAX(T16,U16)>=1,Z16>=ThamSo!$C$9)),"W2",IF(OR(MAX(T16,U16)>=1,V16=1),"W1","W0")) -> W2 | AE16: =CHOOSE(MATCH(AD16,{"W0","W1","W2"},0),"An toàn","Có nguy cơ","Thiếu trầm trọng") -> Thiếu trầm trọng | AF16: =IF(OR(E16<>1,AD16="W0"),"",IF(AND(T16=0,U16=0),"Phải trả",IF(T16>U16,"Phải thu",IF(U16>T16,"Tồn kho",IF(X16>=Y16,"Phải thu","Tồn kho"))))) -> Phải thu | AG16: =TRIM(IF(T16=2,"R-AR-2 ",IF(T16=1,"R-AR-1 ",""))&IF(U16=2,"R-INV-2 ",IF(U16=1,"R-INV-1 ",""))&IF(V16=1,"R-AP-1 ","")&IF(AND(MAX(T16,U16)>=1,Z16>=ThamSo!$C$9),"R-MAT","")) -> R-AR-2 R-MAT | AH16: =IF(E16<>1,"",X16+Y16) -> 1.1103728e+11 | AI16: =IF(OR(E16<>1,DuLieu!A20<>DuLieu!A19,DuLieu!B20>ThamSo!$C$23,DuLieu!D20="",DuLieu!K20=""),"",IF(OR(DuLieu!K20<0,DuLieu!D20<DuLieu!D19*(1-ThamSo!$C$20)),1,0))
A17: =DuLieu!A29 -> HLT | B17: =DuLieu!B29 -> 2023 | C17: =A17&"-"&B17 -> HLT-2023 | D17: =DuLieu!S29&"|"&DuLieu!V29 -> FOB|Nhỏ–vừa | E17: =DuLieu!U29 -> 1 | F17: =IF(E17=1,DuLieu!D29,"") -> 780824095814 | G17: =IF(E17=1,DuLieu!O29,"") -> 7.7399379e+11 | H17: =IF(E17=1,DuLieu!G29,"") -> 303661082534 | I17: =IF(E17=1,DuLieu!L29,"") -> 21.528217 | J17: =IF(E17=1,DuLieu!M29,"") -> 87.245942 | K17: =IF(E17=1,DuLieu!N29,"") -> 6.9067689 | L17: =IF(E17=1,DuLieu!P29,"") -> 0.094380675 | M17: =IF(E17=1,INDEX(B3_NguongKhoanMuc!$E$4:$E$5,MATCH(D17,B3_NguongKhoanMuc!$A$4:$A$5,0)),"") -> 58.207139 | N17: =IF(E17=1,INDEX(B3_NguongKhoanMuc!$F$4:$F$5,MATCH(D17,B3_NguongKhoanMuc!$A$4:$A$5,0)),"") -> 66.263266 | O17: =IF(E17=1,INDEX(B3_NguongKhoanMuc!$H$4:$H$5,MATCH(D17,B3_NguongKhoanMuc!$A$4:$A$5,0)),"") -> 86.118055 | P17: =IF(E17=1,INDEX(B3_NguongKhoanMuc!$I$4:$I$5,MATCH(D17,B3_NguongKhoanMuc!$A$4:$A$5,0)),"") -> 137.96515 | Q17: =IF(E17=1,INDEX(B3_NguongKhoanMuc!$K$4:$K$5,MATCH(D17,B3_NguongKhoanMuc!$A$4:$A$5,0)),"") -> 68.309204 | R17: =IF(E17=1,INDEX(B3_NguongKhoanMuc!$L$4:$L$5,MATCH(D17,B3_NguongKhoanMuc!$A$4:$A$5,0)),"") -> 14.892653 | S17: =IF(E17=1,INDEX(B3_NguongKhoanMuc!$M$4:$M$5,MATCH(D17,B3_NguongKhoanMuc!$A$4:$A$5,0)),"") -> 0.083007995 | T17: =IF(E17<>1,"",IF(I17>N17,2,IF(I17>M17,1,0))) -> 0 | U17: =IF(E17<>1,"",IF(J17>P17,2,IF(J17>O17,1,0))) -> 1 | V17: =IF(E17<>1,"",IF(AND(K17<R17,L17<S17),1,0)) -> 0 | W17: =IF(E17<>1,"",IF(K17>Q17,1,0)) -> 0 | X17: =IF(E17<>1,"",IF(T17>=1,(I17-M17)*F17/365,0)) -> 0 | Y17: =IF(E17<>1,"",IF(U17>=1,(J17-O17)*G17/365,0)) -> 2.3917199e+09 | Z17: =IF(E17<>1,"",IF(H17>0,MAX(X17,Y17)/H17,0)) -> 0.0078762806 | AA17: =IF(E17<>1,"",CHOOSE(T17+1,"An toàn","Có nguy cơ","Trầm trọng")) -> An toàn | AB17: =IF(E17<>1,"",CHOOSE(U17+1,"An toàn","Có nguy cơ","Trầm trọng")) -> Có nguy cơ | AC17: =IF(E17<>1,"",IF(V17=1,"Có nguy cơ: NCC cho nợ ít + tiền mỏng",IF(W17=1,"Lưu ý: DPO cao – kiểm tra quá hạn NCC","An toàn"))) -> An toàn | AD17: =IF(OR(AND(ThamSo!$C$10=1,MAX(T17,U17)=2),AND(MAX(T17,U17)>=1,Z17>=ThamSo!$C$9)),"W2",IF(OR(MAX(T17,U17)>=1,V17=1),"W1","W0")) -> W1 | AE17: =CHOOSE(MATCH(AD17,{"W0","W1","W2"},0),"An toàn","Có nguy cơ","Thiếu trầm trọng") -> Có nguy cơ | AF17: =IF(OR(E17<>1,AD17="W0"),"",IF(AND(T17=0,U17=0),"Phải trả",IF(T17>U17,"Phải thu",IF(U17>T17,"Tồn kho",IF(X17>=Y17,"Phải thu","Tồn kho"))))) -> Tồn kho | AG17: =TRIM(IF(T17=2,"R-AR-2 ",IF(T17=1,"R-AR-1 ",""))&IF(U17=2,"R-INV-2 ",IF(U17=1,"R-INV-1 ",""))&IF(V17=1,"R-AP-1 ","")&IF(AND(MAX(T17,U17)>=1,Z17>=ThamSo!$C$9),"R-MAT","")) -> R-INV-1 | AH17: =IF(E17<>1,"",X17+Y17) -> 2.3917199e+09 | AI17: =IF(OR(E17<>1,DuLieu!A30<>DuLieu!A29,DuLieu!B30>ThamSo!$C$23,DuLieu!D30="",DuLieu!K30=""),"",IF(OR(DuLieu!K30<0,DuLieu!D30<DuLieu!D29*(1-ThamSo!$C$20)),1,0)) -> 1
A18: =DuLieu!A30 -> HLT | B18: =DuLieu!B30 -> 2024 | C18: =A18&"-"&B18 -> HLT-2024 | D18: =DuLieu!S30&"|"&DuLieu!V30 -> FOB|Nhỏ–vừa | E18: =DuLieu!U30 -> 1 | F18: =IF(E18=1,DuLieu!D30,"") -> 808339562494 | G18: =IF(E18=1,DuLieu!O30,"") -> 7.9731269e+11 | H18: =IF(E18=1,DuLieu!G30,"") -> 165103351958 | I18: =IF(E18=1,DuLieu!L30,"") -> 17.97537 | J18: =IF(E18=1,DuLieu!M30,"") -> 61.560533 | K18: =IF(E18=1,DuLieu!N30,"") -> 8.1371547 | L18: =IF(E18=1,DuLieu!P30,"") -> 0.050704996 | M18: =IF(E18=1,INDEX(B3_NguongKhoanMuc!$E$4:$E$5,MATCH(D18,B3_NguongKhoanMuc!$A$4:$A$5,0)),"") -> 58.207139 | N18: =IF(E18=1,INDEX(B3_NguongKhoanMuc!$F$4:$F$5,MATCH(D18,B3_NguongKhoanMuc!$A$4:$A$5,0)),"") -> 66.263266 | O18: =IF(E18=1,INDEX(B3_NguongKhoanMuc!$H$4:$H$5,MATCH(D18,B3_NguongKhoanMuc!$A$4:$A$5,0)),"") -> 86.118055 | P18: =IF(E18=1,INDEX(B3_NguongKhoanMuc!$I$4:$I$5,MATCH(D18,B3_NguongKhoanMuc!$A$4:$A$5,0)),"") -> 137.96515 | Q18: =IF(E18=1,INDEX(B3_NguongKhoanMuc!$K$4:$K$5,MATCH(D18,B3_NguongKhoanMuc!$A$4:$A$5,0)),"") -> 68.309204 | R18: =IF(E18=1,INDEX(B3_NguongKhoanMuc!$L$4:$L$5,MATCH(D18,B3_NguongKhoanMuc!$A$4:$A$5,0)),"") -> 14.892653 | S18: =IF(E18=1,INDEX(B3_NguongKhoanMuc!$M$4:$M$5,MATCH(D18,B3_NguongKhoanMuc!$A$4:$A$5,0)),"") -> 0.083007995 | T18: =IF(E18<>1,"",IF(I18>N18,2,IF(I18>M18,1,0))) -> 0 | U18: =IF(E18<>1,"",IF(J18>P18,2,IF(J18>O18,1,0))) -> 0 | V18: =IF(E18<>1,"",IF(AND(K18<R18,L18<S18),1,0)) -> 1 | W18: =IF(E18<>1,"",IF(K18>Q18,1,0)) -> 0 | X18: =IF(E18<>1,"",IF(T18>=1,(I18-M18)*F18/365,0)) -> 0 | Y18: =IF(E18<>1,"",IF(U18>=1,(J18-O18)*G18/365,0)) -> 0 | Z18: =IF(E18<>1,"",IF(H18>0,MAX(X18,Y18)/H18,0)) -> 0 | AA18: =IF(E18<>1,"",CHOOSE(T18+1,"An toàn","Có nguy cơ","Trầm trọng")) -> An toàn | AB18: =IF(E18<>1,"",CHOOSE(U18+1,"An toàn","Có nguy cơ","Trầm trọng")) -> An toàn | AC18: =IF(E18<>1,"",IF(V18=1,"Có nguy cơ: NCC cho nợ ít + tiền mỏng",IF(W18=1,"Lưu ý: DPO cao – kiểm tra quá hạn NCC","An toàn"))) -> Có nguy cơ: NCC cho nợ ít + tiền mỏng | AD18: =IF(OR(AND(ThamSo!$C$10=1,MAX(T18,U18)=2),AND(MAX(T18,U18)>=1,Z18>=ThamSo!$C$9)),"W2",IF(OR(MAX(T18,U18)>=1,V18=1),"W1","W0")) -> W1 | AE18: =CHOOSE(MATCH(AD18,{"W0","W1","W2"},0),"An toàn","Có nguy cơ","Thiếu trầm trọng") -> Có nguy cơ | AF18: =IF(OR(E18<>1,AD18="W0"),"",IF(AND(T18=0,U18=0),"Phải trả",IF(T18>U18,"Phải thu",IF(U18>T18,"Tồn kho",IF(X18>=Y18,"Phải thu","Tồn kho"))))) -> Phải trả | AG18: =TRIM(IF(T18=2,"R-AR-2 ",IF(T18=1,"R-AR-1 ",""))&IF(U18=2,"R-INV-2 ",IF(U18=1,"R-INV-1 ",""))&IF(V18=1,"R-AP-1 ","")&IF(AND(MAX(T18,U18)>=1,Z18>=ThamSo!$C$9),"R-MAT","")) -> R-AP-1 | AH18: =IF(E18<>1,"",X18+Y18) -> 0 | AI18: =IF(OR(E18<>1,DuLieu!A31<>DuLieu!A30,DuLieu!B31>ThamSo!$C$23,DuLieu!D31="",DuLieu!K31=""),"",IF(OR(DuLieu!K31<0,DuLieu!D31<DuLieu!D30*(1-ThamSo!$C$20)),1,0)) -> 1
A19: =DuLieu!A31 -> HLT | B19: =DuLieu!B31 -> 2025 | C19: =A19&"-"&B19 -> HLT-2025 | D19: =DuLieu!S31&"|"&DuLieu!V31 -> FOB|Nhỏ–vừa | E19: =DuLieu!U31 -> 1 | F19: =IF(E19=1,DuLieu!D31,"") -> 240789814001 | G19: =IF(E19=1,DuLieu!O31,"") -> 2.3323921e+11 | H19: =IF(E19=1,DuLieu!G31,"") -> 130486354054 | I19: =IF(E19=1,DuLieu!L31,"") -> 39.379637 | J19: =IF(E19=1,DuLieu!M31,"") -> 137.0893 | K19: =IF(E19=1,DuLieu!N31,"") -> 19.250563 | L19: =IF(E19=1,DuLieu!P31,"") -> 0.1261136 | M19: =IF(E19=1,INDEX(B3_NguongKhoanMuc!$E$4:$E$5,MATCH(D19,B3_NguongKhoanMuc!$A$4:$A$5,0)),"") -> 58.207139 | N19: =IF(E19=1,INDEX(B3_NguongKhoanMuc!$F$4:$F$5,MATCH(D19,B3_NguongKhoanMuc!$A$4:$A$5,0)),"") -> 66.263266 | O19: =IF(E19=1,INDEX(B3_NguongKhoanMuc!$H$4:$H$5,MATCH(D19,B3_NguongKhoanMuc!$A$4:$A$5,0)),"") -> 86.118055 | P19: =IF(E19=1,INDEX(B3_NguongKhoanMuc!$I$4:$I$5,MATCH(D19,B3_NguongKhoanMuc!$A$4:$A$5,0)),"") -> 137.96515 | Q19: =IF(E19=1,INDEX(B3_NguongKhoanMuc!$K$4:$K$5,MATCH(D19,B3_NguongKhoanMuc!$A$4:$A$5,0)),"") -> 68.309204 | R19: =IF(E19=1,INDEX(B3_NguongKhoanMuc!$L$4:$L$5,MATCH(D19,B3_NguongKhoanMuc!$A$4:$A$5,0)),"") -> 14.892653 | S19: =IF(E19=1,INDEX(B3_NguongKhoanMuc!$M$4:$M$5,MATCH(D19,B3_NguongKhoanMuc!$A$4:$A$5,0)),"") -> 0.083007995 | T19: =IF(E19<>1,"",IF(I19>N19,2,IF(I19>M19,1,0))) -> 0 | U19: =IF(E19<>1,"",IF(J19>P19,2,IF(J19>O19,1,0))) -> 1 | V19: =IF(E19<>1,"",IF(AND(K19<R19,L19<S19),1,0)) -> 0 | W19: =IF(E19<>1,"",IF(K19>Q19,1,0)) -> 0 | X19: =IF(E19<>1,"",IF(T19>=1,(I19-M19)*F19/365,0)) -> 0 | Y19: =IF(E19<>1,"",IF(U19>=1,(J19-O19)*G19/365,0)) -> 3.2571214e+10 | Z19: =IF(E19<>1,"",IF(H19>0,MAX(X19,Y19)/H19,0)) -> 0.24961395 | AA19: =IF(E19<>1,"",CHOOSE(T19+1,"An toàn","Có nguy cơ","Trầm trọng")) -> An toàn | AB19: =IF(E19<>1,"",CHOOSE(U19+1,"An toàn","Có nguy cơ","Trầm trọng")) -> Có nguy cơ | AC19: =IF(E19<>1,"",IF(V19=1,"Có nguy cơ: NCC cho nợ ít + tiền mỏng",IF(W19=1,"Lưu ý: DPO cao – kiểm tra quá hạn NCC","An toàn"))) -> An toàn | AD19: =IF(OR(AND(ThamSo!$C$10=1,MAX(T19,U19)=2),AND(MAX(T19,U19)>=1,Z19>=ThamSo!$C$9)),"W2",IF(OR(MAX(T19,U19)>=1,V19=1),"W1","W0")) -> W2 | AE19: =CHOOSE(MATCH(AD19,{"W0","W1","W2"},0),"An toàn","Có nguy cơ","Thiếu trầm trọng") -> Thiếu trầm trọng | AF19: =IF(OR(E19<>1,AD19="W0"),"",IF(AND(T19=0,U19=0),"Phải trả",IF(T19>U19,"Phải thu",IF(U19>T19,"Tồn kho",IF(X19>=Y19,"Phải thu","Tồn kho"))))) -> Tồn kho | AG19: =TRIM(IF(T19=2,"R-AR-2 ",IF(T19=1,"R-AR-1 ",""))&IF(U19=2,"R-INV-2 ",IF(U19=1,"R-INV-1 ",""))&IF(V19=1,"R-AP-1 ","")&IF(AND(MAX(T19,U19)>=1,Z19>=ThamSo!$C$9),"R-MAT","")) -> R-INV-1 R-MAT | AH19: =IF(E19<>1,"",X19+Y19) -> 3.2571214e+10 | AI19: =IF(OR(E19<>1,DuLieu!A32<>DuLieu!A31,DuLieu!B32>ThamSo!$C$23,DuLieu!D32="",DuLieu!K32=""),"",IF(OR(DuLieu!K32<0,DuLieu!D32<DuLieu!D31*(1-ThamSo!$C$20)),1,0))
A20: =DuLieu!A32 -> HNI | B20: =DuLieu!B32 -> 2023 | C20: =A20&"-"&B20 -> HNI-2023 | D20: =DuLieu!S32&"|"&DuLieu!V32 -> FOB|Nhỏ–vừa | E20: =DuLieu!U32 -> 1 | F20: =IF(E20=1,DuLieu!D32,"") -> 869534864259 | G20: =IF(E20=1,DuLieu!O32,"") -> 7.2680126e+11 | H20: =IF(E20=1,DuLieu!G32,"") -> 520762094698 | I20: =IF(E20=1,DuLieu!L32,"") -> 37.844702 | J20: =IF(E20=1,DuLieu!M32,"") -> 31.899606 | K20: =IF(E20=1,DuLieu!N32,"") -> 12.94332 | L20: =IF(E20=1,DuLieu!P32,"") -> 0.29666826 | M20: =IF(E20=1,INDEX(B3_NguongKhoanMuc!$E$4:$E$5,MATCH(D20,B3_NguongKhoanMuc!$A$4:$A$5,0)),"") -> 58.207139 | N20: =IF(E20=1,INDEX(B3_NguongKhoanMuc!$F$4:$F$5,MATCH(D20,B3_NguongKhoanMuc!$A$4:$A$5,0)),"") -> 66.263266 | O20: =IF(E20=1,INDEX(B3_NguongKhoanMuc!$H$4:$H$5,MATCH(D20,B3_NguongKhoanMuc!$A$4:$A$5,0)),"") -> 86.118055 | P20: =IF(E20=1,INDEX(B3_NguongKhoanMuc!$I$4:$I$5,MATCH(D20,B3_NguongKhoanMuc!$A$4:$A$5,0)),"") -> 137.96515 | Q20: =IF(E20=1,INDEX(B3_NguongKhoanMuc!$K$4:$K$5,MATCH(D20,B3_NguongKhoanMuc!$A$4:$A$5,0)),"") -> 68.309204 | R20: =IF(E20=1,INDEX(B3_NguongKhoanMuc!$L$4:$L$5,MATCH(D20,B3_NguongKhoanMuc!$A$4:$A$5,0)),"") -> 14.892653 | S20: =IF(E20=1,INDEX(B3_NguongKhoanMuc!$M$4:$M$5,MATCH(D20,B3_NguongKhoanMuc!$A$4:$A$5,0)),"") -> 0.083007995 | T20: =IF(E20<>1,"",IF(I20>N20,2,IF(I20>M20,1,0))) -> 0 | U20: =IF(E20<>1,"",IF(J20>P20,2,IF(J20>O20,1,0))) -> 0 | V20: =IF(E20<>1,"",IF(AND(K20<R20,L20<S20),1,0)) -> 0 | W20: =IF(E20<>1,"",IF(K20>Q20,1,0)) -> 0 | X20: =IF(E20<>1,"",IF(T20>=1,(I20-M20)*F20/365,0)) -> 0 | Y20: =IF(E20<>1,"",IF(U20>=1,(J20-O20)*G20/365,0)) -> 0 | Z20: =IF(E20<>1,"",IF(H20>0,MAX(X20,Y20)/H20,0)) -> 0 | AA20: =IF(E20<>1,"",CHOOSE(T20+1,"An toàn","Có nguy cơ","Trầm trọng")) -> An toàn | AB20: =IF(E20<>1,"",CHOOSE(U20+1,"An toàn","Có nguy cơ","Trầm trọng")) -> An toàn | AC20: =IF(E20<>1,"",IF(V20=1,"Có nguy cơ: NCC cho nợ ít + tiền mỏng",IF(W20=1,"Lưu ý: DPO cao – kiểm tra quá hạn NCC","An toàn"))) -> An toàn | AD20: =IF(OR(AND(ThamSo!$C$10=1,MAX(T20,U20)=2),AND(MAX(T20,U20)>=1,Z20>=ThamSo!$C$9)),"W2",IF(OR(MAX(T20,U20)>=1,V20=1),"W1","W0")) -> W0 | AE20: =CHOOSE(MATCH(AD20,{"W0","W1","W2"},0),"An toàn","Có nguy cơ","Thiếu trầm trọng") -> An toàn | AF20: =IF(OR(E20<>1,AD20="W0"),"",IF(AND(T20=0,U20=0),"Phải trả",IF(T20>U20,"Phải thu",IF(U20>T20,"Tồn kho",IF(X20>=Y20,"Phải thu","Tồn kho"))))) | AG20: =TRIM(IF(T20=2,"R-AR-2 ",IF(T20=1,"R-AR-1 ",""))&IF(U20=2,"R-INV-2 ",IF(U20=1,"R-INV-1 ",""))&IF(V20=1,"R-AP-1 ","")&IF(AND(MAX(T20,U20)>=1,Z20>=ThamSo!$C$9),"R-MAT","")) | AH20: =IF(E20<>1,"",X20+Y20) -> 0 | AI20: =IF(OR(E20<>1,DuLieu!A33<>DuLieu!A32,DuLieu!B33>ThamSo!$C$23,DuLieu!D33="",DuLieu!K33=""),"",IF(OR(DuLieu!K33<0,DuLieu!D33<DuLieu!D32*(1-ThamSo!$C$20)),1,0)) -> 0
A21: =DuLieu!A33 -> HNI | B21: =DuLieu!B33 -> 2024 | C21: =A21&"-"&B21 -> HNI-2024 | D21: =DuLieu!S33&"|"&DuLieu!V33 -> FOB|Nhỏ–vừa | E21: =DuLieu!U33 -> 1 | F21: =IF(E21=1,DuLieu!D33,"") -> 1182125636807 | G21: =IF(E21=1,DuLieu!O33,"") -> 9.8375789e+11 | H21: =IF(E21=1,DuLieu!G33,"") -> 620029094940 | I21: =IF(E21=1,DuLieu!L33,"") -> 41.237603 | J21: =IF(E21=1,DuLieu!M33,"") -> 25.584926 | K21: =IF(E21=1,DuLieu!N33,"") -> 12.055209 | L21: =IF(E21=1,DuLieu!P33,"") -> 0.27354545 | M21: =IF(E21=1,INDEX(B3_NguongKhoanMuc!$E$4:$E$5,MATCH(D21,B3_NguongKhoanMuc!$A$4:$A$5,0)),"") -> 58.207139 | N21: =IF(E21=1,INDEX(B3_NguongKhoanMuc!$F$4:$F$5,MATCH(D21,B3_NguongKhoanMuc!$A$4:$A$5,0)),"") -> 66.263266 | O21: =IF(E21=1,INDEX(B3_NguongKhoanMuc!$H$4:$H$5,MATCH(D21,B3_NguongKhoanMuc!$A$4:$A$5,0)),"") -> 86.118055 | P21: =IF(E21=1,INDEX(B3_NguongKhoanMuc!$I$4:$I$5,MATCH(D21,B3_NguongKhoanMuc!$A$4:$A$5,0)),"") -> 137.96515 | Q21: =IF(E21=1,INDEX(B3_NguongKhoanMuc!$K$4:$K$5,MATCH(D21,B3_NguongKhoanMuc!$A$4:$A$5,0)),"") -> 68.309204 | R21: =IF(E21=1,INDEX(B3_NguongKhoanMuc!$L$4:$L$5,MATCH(D21,B3_NguongKhoanMuc!$A$4:$A$5,0)),"") -> 14.892653 | S21: =IF(E21=1,INDEX(B3_NguongKhoanMuc!$M$4:$M$5,MATCH(D21,B3_NguongKhoanMuc!$A$4:$A$5,0)),"") -> 0.083007995 | T21: =IF(E21<>1,"",IF(I21>N21,2,IF(I21>M21,1,0))) -> 0 | U21: =IF(E21<>1,"",IF(J21>P21,2,IF(J21>O21,1,0))) -> 0 | V21: =IF(E21<>1,"",IF(AND(K21<R21,L21<S21),1,0)) -> 0 | W21: =IF(E21<>1,"",IF(K21>Q21,1,0)) -> 0 | X21: =IF(E21<>1,"",IF(T21>=1,(I21-M21)*F21/365,0)) -> 0 | Y21: =IF(E21<>1,"",IF(U21>=1,(J21-O21)*G21/365,0)) -> 0 | Z21: =IF(E21<>1,"",IF(H21>0,MAX(X21,Y21)/H21,0)) -> 0 | AA21: =IF(E21<>1,"",CHOOSE(T21+1,"An toàn","Có nguy cơ","Trầm trọng")) -> An toàn | AB21: =IF(E21<>1,"",CHOOSE(U21+1,"An toàn","Có nguy cơ","Trầm trọng")) -> An toàn | AC21: =IF(E21<>1,"",IF(V21=1,"Có nguy cơ: NCC cho nợ ít + tiền mỏng",IF(W21=1,"Lưu ý: DPO cao – kiểm tra quá hạn NCC","An toàn"))) -> An toàn | AD21: =IF(OR(AND(ThamSo!$C$10=1,MAX(T21,U21)=2),AND(MAX(T21,U21)>=1,Z21>=ThamSo!$C$9)),"W2",IF(OR(MAX(T21,U21)>=1,V21=1),"W1","W0")) -> W0 | AE21: =CHOOSE(MATCH(AD21,{"W0","W1","W2"},0),"An toàn","Có nguy cơ","Thiếu trầm trọng") -> An toàn | AF21: =IF(OR(E21<>1,AD21="W0"),"",IF(AND(T21=0,U21=0),"Phải trả",IF(T21>U21,"Phải thu",IF(U21>T21,"Tồn kho",IF(X21>=Y21,"Phải thu","Tồn kho"))))) | AG21: =TRIM(IF(T21=2,"R-AR-2 ",IF(T21=1,"R-AR-1 ",""))&IF(U21=2,"R-INV-2 ",IF(U21=1,"R-INV-1 ",""))&IF(V21=1,"R-AP-1 ","")&IF(AND(MAX(T21,U21)>=1,Z21>=ThamSo!$C$9),"R-MAT","")) | AH21: =IF(E21<>1,"",X21+Y21) -> 0 | AI21: =IF(OR(E21<>1,DuLieu!A34<>DuLieu!A33,DuLieu!B34>ThamSo!$C$23,DuLieu!D34="",DuLieu!K34=""),"",IF(OR(DuLieu!K34<0,DuLieu!D34<DuLieu!D33*(1-ThamSo!$C$20)),1,0)) -> 0
A22: =DuLieu!A34 -> HNI | B22: =DuLieu!B34 -> 2025 | C22: =A22&"-"&B22 -> HNI-2025 | D22: =DuLieu!S34&"|"&DuLieu!V34 -> FOB|Nhỏ–vừa | E22: =DuLieu!U34 -> 1 | F22: =IF(E22=1,DuLieu!D34,"") -> 980292288149 | G22: =IF(E22=1,DuLieu!O34,"") -> 8.0698042e+11 | H22: =IF(E22=1,DuLieu!G34,"") -> 624387760545 | I22: =IF(E22=1,DuLieu!L34,"") -> 63.252339 | J22: =IF(E22=1,DuLieu!M34,"") -> 26.977831 | K22: =IF(E22=1,DuLieu!N34,"") -> 25.8665 | L22: =IF(E22=1,DuLieu!P34,"") -> 0.34214214 | M22: =IF(E22=1,INDEX(B3_NguongKhoanMuc!$E$4:$E$5,MATCH(D22,B3_NguongKhoanMuc!$A$4:$A$5,0)),"") -> 58.207139 | N22: =IF(E22=1,INDEX(B3_NguongKhoanMuc!$F$4:$F$5,MATCH(D22,B3_NguongKhoanMuc!$A$4:$A$5,0)),"") -> 66.263266 | O22: =IF(E22=1,INDEX(B3_NguongKhoanMuc!$H$4:$H$5,MATCH(D22,B3_NguongKhoanMuc!$A$4:$A$5,0)),"") -> 86.118055 | P22: =IF(E22=1,INDEX(B3_NguongKhoanMuc!$I$4:$I$5,MATCH(D22,B3_NguongKhoanMuc!$A$4:$A$5,0)),"") -> 137.96515 | Q22: =IF(E22=1,INDEX(B3_NguongKhoanMuc!$K$4:$K$5,MATCH(D22,B3_NguongKhoanMuc!$A$4:$A$5,0)),"") -> 68.309204 | R22: =IF(E22=1,INDEX(B3_NguongKhoanMuc!$L$4:$L$5,MATCH(D22,B3_NguongKhoanMuc!$A$4:$A$5,0)),"") -> 14.892653 | S22: =IF(E22=1,INDEX(B3_NguongKhoanMuc!$M$4:$M$5,MATCH(D22,B3_NguongKhoanMuc!$A$4:$A$5,0)),"") -> 0.083007995 | T22: =IF(E22<>1,"",IF(I22>N22,2,IF(I22>M22,1,0))) -> 1 | U22: =IF(E22<>1,"",IF(J22>P22,2,IF(J22>O22,1,0))) -> 0 | V22: =IF(E22<>1,"",IF(AND(K22<R22,L22<S22),1,0)) -> 0 | W22: =IF(E22<>1,"",IF(K22>Q22,1,0)) -> 0 | X22: =IF(E22<>1,"",IF(T22>=1,(I22-M22)*F22/365,0)) -> 1.3550059e+10 | Y22: =IF(E22<>1,"",IF(U22>=1,(J22-O22)*G22/365,0)) -> 0 | Z22: =IF(E22<>1,"",IF(H22>0,MAX(X22,Y22)/H22,0)) -> 0.021701352 | AA22: =IF(E22<>1,"",CHOOSE(T22+1,"An toàn","Có nguy cơ","Trầm trọng")) -> Có nguy cơ | AB22: =IF(E22<>1,"",CHOOSE(U22+1,"An toàn","Có nguy cơ","Trầm trọng")) -> An toàn | AC22: =IF(E22<>1,"",IF(V22=1,"Có nguy cơ: NCC cho nợ ít + tiền mỏng",IF(W22=1,"Lưu ý: DPO cao – kiểm tra quá hạn NCC","An toàn"))) -> An toàn | AD22: =IF(OR(AND(ThamSo!$C$10=1,MAX(T22,U22)=2),AND(MAX(T22,U22)>=1,Z22>=ThamSo!$C$9)),"W2",IF(OR(MAX(T22,U22)>=1,V22=1),"W1","W0")) -> W1 | AE22: =CHOOSE(MATCH(AD22,{"W0","W1","W2"},0),"An toàn","Có nguy cơ","Thiếu trầm trọng") -> Có nguy cơ | AF22: =IF(OR(E22<>1,AD22="W0"),"",IF(AND(T22=0,U22=0),"Phải trả",IF(T22>U22,"Phải thu",IF(U22>T22,"Tồn kho",IF(X22>=Y22,"Phải thu","Tồn kho"))))) -> Phải thu | AG22: =TRIM(IF(T22=2,"R-AR-2 ",IF(T22=1,"R-AR-1 ",""))&IF(U22=2,"R-INV-2 ",IF(U22=1,"R-INV-1 ",""))&IF(V22=1,"R-AP-1 ","")&IF(AND(MAX(T22,U22)>=1,Z22>=ThamSo!$C$9),"R-MAT","")) -> R-AR-1 | AH22: =IF(E22<>1,"",X22+Y22) -> 1.3550059e+10 | AI22: =IF(OR(E22<>1,DuLieu!A35<>DuLieu!A34,DuLieu!B35>ThamSo!$C$23,DuLieu!D35="",DuLieu!K35=""),"",IF(OR(DuLieu!K35<0,DuLieu!D35<DuLieu!D34*(1-ThamSo!$C$20)),1,0))
A23: =DuLieu!A35 -> HTG | B23: =DuLieu!B35 -> 2023 | C23: =A23&"-"&B23 -> HTG-2023 | D23: =DuLieu!S35&"|"&DuLieu!V35 -> FOB|Lớn | E23: =DuLieu!U35 -> 1 | F23: =IF(E23=1,DuLieu!D35,"") -> 4703966718679 | G23: =IF(E23=1,DuLieu!O35,"") -> 4.2714881e+12 | H23: =IF(E23=1,DuLieu!G35,"") -> 1761375593537 | I23: =IF(E23=1,DuLieu!L35,"") -> 38.70394 | J23: =IF(E23=1,DuLieu!M35,"") -> 74.002796 | K23: =IF(E23=1,DuLieu!N35,"") -> 20.486733 | L23: =IF(E23=1,DuLieu!P35,"") -> 0.082396901 | M23: =IF(E23=1,INDEX(B3_NguongKhoanMuc!$E$4:$E$5,MATCH(D23,B3_NguongKhoanMuc!$A$4:$A$5,0)),"") -> 58.207139 | N23: =IF(E23=1,INDEX(B3_NguongKhoanMuc!$F$4:$F$5,MATCH(D23,B3_NguongKhoanMuc!$A$4:$A$5,0)),"") -> 66.263266 | O23: =IF(E23=1,INDEX(B3_NguongKhoanMuc!$H$4:$H$5,MATCH(D23,B3_NguongKhoanMuc!$A$4:$A$5,0)),"") -> 86.118055 | P23: =IF(E23=1,INDEX(B3_NguongKhoanMuc!$I$4:$I$5,MATCH(D23,B3_NguongKhoanMuc!$A$4:$A$5,0)),"") -> 137.96515 | Q23: =IF(E23=1,INDEX(B3_NguongKhoanMuc!$K$4:$K$5,MATCH(D23,B3_NguongKhoanMuc!$A$4:$A$5,0)),"") -> 68.309204 | R23: =IF(E23=1,INDEX(B3_NguongKhoanMuc!$L$4:$L$5,MATCH(D23,B3_NguongKhoanMuc!$A$4:$A$5,0)),"") -> 14.892653 | S23: =IF(E23=1,INDEX(B3_NguongKhoanMuc!$M$4:$M$5,MATCH(D23,B3_NguongKhoanMuc!$A$4:$A$5,0)),"") -> 0.083007995 | T23: =IF(E23<>1,"",IF(I23>N23,2,IF(I23>M23,1,0))) -> 0 | U23: =IF(E23<>1,"",IF(J23>P23,2,IF(J23>O23,1,0))) -> 0 | V23: =IF(E23<>1,"",IF(AND(K23<R23,L23<S23),1,0)) -> 0 | W23: =IF(E23<>1,"",IF(K23>Q23,1,0)) -> 0 | X23: =IF(E23<>1,"",IF(T23>=1,(I23-M23)*F23/365,0)) -> 0 | Y23: =IF(E23<>1,"",IF(U23>=1,(J23-O23)*G23/365,0)) -> 0 | Z23: =IF(E23<>1,"",IF(H23>0,MAX(X23,Y23)/H23,0)) -> 0 | AA23: =IF(E23<>1,"",CHOOSE(T23+1,"An toàn","Có nguy cơ","Trầm trọng")) -> An toàn | AB23: =IF(E23<>1,"",CHOOSE(U23+1,"An toàn","Có nguy cơ","Trầm trọng")) -> An toàn | AC23: =IF(E23<>1,"",IF(V23=1,"Có nguy cơ: NCC cho nợ ít + tiền mỏng",IF(W23=1,"Lưu ý: DPO cao – kiểm tra quá hạn NCC","An toàn"))) -> An toàn | AD23: =IF(OR(AND(ThamSo!$C$10=1,MAX(T23,U23)=2),AND(MAX(T23,U23)>=1,Z23>=ThamSo!$C$9)),"W2",IF(OR(MAX(T23,U23)>=1,V23=1),"W1","W0")) -> W0 | AE23: =CHOOSE(MATCH(AD23,{"W0","W1","W2"},0),"An toàn","Có nguy cơ","Thiếu trầm trọng") -> An toàn | AF23: =IF(OR(E23<>1,AD23="W0"),"",IF(AND(T23=0,U23=0),"Phải trả",IF(T23>U23,"Phải thu",IF(U23>T23,"Tồn kho",IF(X23>=Y23,"Phải thu","Tồn kho"))))) | AG23: =TRIM(IF(T23=2,"R-AR-2 ",IF(T23=1,"R-AR-1 ",""))&IF(U23=2,"R-INV-2 ",IF(U23=1,"R-INV-1 ",""))&IF(V23=1,"R-AP-1 ","")&IF(AND(MAX(T23,U23)>=1,Z23>=ThamSo!$C$9),"R-MAT","")) | AH23: =IF(E23<>1,"",X23+Y23) -> 0 | AI23: =IF(OR(E23<>1,DuLieu!A36<>DuLieu!A35,DuLieu!B36>ThamSo!$C$23,DuLieu!D36="",DuLieu!K36=""),"",IF(OR(DuLieu!K36<0,DuLieu!D36<DuLieu!D35*(1-ThamSo!$C$20)),1,0)) -> 0
A24: =DuLieu!A36 -> HTG | B24: =DuLieu!B36 -> 2024 | C24: =A24&"-"&B24 -> HTG-2024 | D24: =DuLieu!S36&"|"&DuLieu!V36 -> FOB|Lớn | E24: =DuLieu!U36 -> 1 | F24: =IF(E24=1,DuLieu!D36,"") -> 5111153311349 | G24: =IF(E24=1,DuLieu!O36,"") -> 4.5179866e+12 | H24: =IF(E24=1,DuLieu!G36,"") -> 2095059428168 | I24: =IF(E24=1,DuLieu!L36,"") -> 36.914008 | J24: =IF(E24=1,DuLieu!M36,"") -> 63.407383 | K24: =IF(E24=1,DuLieu!N36,"") -> 20.511289 | L24: =IF(E24=1,DuLieu!P36,"") -> 0.14111784 | M24: =IF(E24=1,INDEX(B3_NguongKhoanMuc!$E$4:$E$5,MATCH(D24,B3_NguongKhoanMuc!$A$4:$A$5,0)),"") -> 58.207139 | N24: =IF(E24=1,INDEX(B3_NguongKhoanMuc!$F$4:$F$5,MATCH(D24,B3_NguongKhoanMuc!$A$4:$A$5,0)),"") -> 66.263266 | O24: =IF(E24=1,INDEX(B3_NguongKhoanMuc!$H$4:$H$5,MATCH(D24,B3_NguongKhoanMuc!$A$4:$A$5,0)),"") -> 86.118055 | P24: =IF(E24=1,INDEX(B3_NguongKhoanMuc!$I$4:$I$5,MATCH(D24,B3_NguongKhoanMuc!$A$4:$A$5,0)),"") -> 137.96515 | Q24: =IF(E24=1,INDEX(B3_NguongKhoanMuc!$K$4:$K$5,MATCH(D24,B3_NguongKhoanMuc!$A$4:$A$5,0)),"") -> 68.309204 | R24: =IF(E24=1,INDEX(B3_NguongKhoanMuc!$L$4:$L$5,MATCH(D24,B3_NguongKhoanMuc!$A$4:$A$5,0)),"") -> 14.892653 | S24: =IF(E24=1,INDEX(B3_NguongKhoanMuc!$M$4:$M$5,MATCH(D24,B3_NguongKhoanMuc!$A$4:$A$5,0)),"") -> 0.083007995 | T24: =IF(E24<>1,"",IF(I24>N24,2,IF(I24>M24,1,0))) -> 0 | U24: =IF(E24<>1,"",IF(J24>P24,2,IF(J24>O24,1,0))) -> 0 | V24: =IF(E24<>1,"",IF(AND(K24<R24,L24<S24),1,0)) -> 0 | W24: =IF(E24<>1,"",IF(K24>Q24,1,0)) -> 0 | X24: =IF(E24<>1,"",IF(T24>=1,(I24-M24)*F24/365,0)) -> 0 | Y24: =IF(E24<>1,"",IF(U24>=1,(J24-O24)*G24/365,0)) -> 0 | Z24: =IF(E24<>1,"",IF(H24>0,MAX(X24,Y24)/H24,0)) -> 0 | AA24: =IF(E24<>1,"",CHOOSE(T24+1,"An toàn","Có nguy cơ","Trầm trọng")) -> An toàn | AB24: =IF(E24<>1,"",CHOOSE(U24+1,"An toàn","Có nguy cơ","Trầm trọng")) -> An toàn | AC24: =IF(E24<>1,"",IF(V24=1,"Có nguy cơ: NCC cho nợ ít + tiền mỏng",IF(W24=1,"Lưu ý: DPO cao – kiểm tra quá hạn NCC","An toàn"))) -> An toàn | AD24: =IF(OR(AND(ThamSo!$C$10=1,MAX(T24,U24)=2),AND(MAX(T24,U24)>=1,Z24>=ThamSo!$C$9)),"W2",IF(OR(MAX(T24,U24)>=1,V24=1),"W1","W0")) -> W0 | AE24: =CHOOSE(MATCH(AD24,{"W0","W1","W2"},0),"An toàn","Có nguy cơ","Thiếu trầm trọng") -> An toàn | AF24: =IF(OR(E24<>1,AD24="W0"),"",IF(AND(T24=0,U24=0),"Phải trả",IF(T24>U24,"Phải thu",IF(U24>T24,"Tồn kho",IF(X24>=Y24,"Phải thu","Tồn kho"))))) | AG24: =TRIM(IF(T24=2,"R-AR-2 ",IF(T24=1,"R-AR-1 ",""))&IF(U24=2,"R-INV-2 ",IF(U24=1,"R-INV-1 ",""))&IF(V24=1,"R-AP-1 ","")&IF(AND(MAX(T24,U24)>=1,Z24>=ThamSo!$C$9),"R-MAT","")) | AH24: =IF(E24<>1,"",X24+Y24) -> 0 | AI24: =IF(OR(E24<>1,DuLieu!A37<>DuLieu!A36,DuLieu!B37>ThamSo!$C$23,DuLieu!D37="",DuLieu!K37=""),"",IF(OR(DuLieu!K37<0,DuLieu!D37<DuLieu!D36*(1-ThamSo!$C$20)),1,0)) -> 0
