Workbook

Sheet Read_me
A2: Hướng dẫn đọc và phạm vi dữ liệu
A4: Mục | B4: Nội dung | C4: Đọc / kiểm tra ở đâu
A5: Phạm vi | B5: Đặc tả và workbook minh họa UC01–UC04 cho doanh nghiệp may F01 theo mô hình FOB: tự mua NVL, sản xuất và bán thành phẩm. Dữ liệu F01 hoàn toàn hư cấu. | C5: Bản v11 đồng bộ nguồn ngưỡng FOB 2023–2025 và Miller–Orr; giữ bố cục gốc.
A6: Kỳ UC01 | B6: 01/01–30/06/2026 (bán niên), N=181 ngày. Ngày chốt chung 30/06/2026. | C6: D_F01; F01_UC1
A7: Kỳ UC02 | B7: 01/07–29/09/2026, 13 tuần/91 ngày. Không lấy 181 ngày làm kỳ dự báo. | C7: F01_UC2
A8: Cách đọc | B8: 1. Đọc Read_me → 2. Xem bảng công thức UC1/UC2/UC3/UC4 → 3. Kiểm tra Nguong → 4. Xem các bảng minh họa F01 → 5. Đối soát Kiem_thu và kiểm tra UC04. | C8: Các sheet D_* là đầu vào dùng chung, không có F02/F03.
A9: Cách viết công thức | B9: Mỗi dòng có tên biến, phép tính, phạm vi, đơn vị và ngoại lệ. Dấu Σ là cộng các dòng thỏa điều kiện; MAX(0;x) là chỉ giữ phần dương. | C9: Không dùng công thức dài thay định nghĩa nghiệp vụ.
A10: Dữ liệu được giữ | B10: 117 hóa đơn bán, 135 hóa đơn mua, 36 lô sở hữu F01. Giá trị và cấu hình kinh doanh được tạo sinh lại cho FOB; doanh thu/giá vốn tính từ bảng dữ liệu. | C10: D_sales, D_purchases, D_inventory
A11: Điều chỉnh ngày | B11: Giữ khóa giao dịch v10 và nối dài dữ liệu đến ngày chốt 30/06/2026 (hóa đơn, lô tồn, dòng tiền ngày 21–30/06). Hóa đơn đã trả trong 21–30/06 ghi PaidDate; số ngày quá hạn / lưu kho tính lại tại ngày chốt mới. | C11: Số ngày quá hạn / lưu kho tại chốt giữ khi không bị giới hạn đầu kỳ; lưu vết tại D_F01.
A12: Không giữ kết quả cũ bằng ép số | B12: Không ép W hoặc TH về một nhãn định sẵn. Kết quả được tính lại từ đầu vào FOB và ngưỡng nguồn. | C12: Ví dụ mới được tính độc lập trong Kiem_thu.
A13: Bổ sung để chạy UC02 | B13: Lịch lương, thuế, thuê xưởng, trả nợ và một lịch thu xác nhận đều là giả lập biết tại ngày chốt; không có trong dữ liệu gốc. | C13: D_flows có source_type, source_ref, known_at và cờ essential.
A14: Nguồn ưu tiên | B14: Nguồn chuẩn duy nhất về ngưỡng và ma trận: Nguong_SMEs_FOB_2023_2025 (1).xlsx, config fob.threshold.v3. Công thức dự báo giữ cơ chế sự kiện và chống cộng trùng. | C14: Nguong ghi nguồn theo sheet/ô; không thay ngưỡng bằng số đã làm tròn trong SRS.
A15: Khác cơ sở ngành | B15: Ngành dùng năm và số dư bình quân; F01 dùng 181 ngày và số dư cuối kỳ. So sánh có nhãn provisional, chỉ định hướng. | C15: Không đổi ngưỡng ngày theo tỷ lệ 181/365. Quy đổi vốn vượt dùng Rev/N hoặc COGS/N.
... A58: MinCash Base; TH; ô ma trận | B58: 4,64 tỷ (21/06); TH01; M3 | C58: 4,14 tỷ (02/07); TH01; M3

Sheet UC1_Cong_thuc
A2: UC01 Chẩn đoán vốn lưu động
A4: Mã | B4: Nhóm công thức | C4: Chỉ tiêu | D4: Ý nghĩa dễ hiểu | E4: Công thức từng bước | F4: Dữ liệu đầu vào | G4: Phạm vi / điều kiện | H4: Đơn vị / hiển thị | I4: Ngoại lệ / kiểm soát
A5: T1-01 | B5: 01. Số dư và chu kỳ | C5: Doanh thu kỳ (Rev) | D5: Quy mô bán hàng trong N ngày | E5: Rev = financials.revenue_vnd | F5: financials.revenue_vnd; workbook D_F01!B9 | G5: firm_id của phiên; firm_id = F01; ngày chốt 30/06/2026. Kỳ phát sinh 01/01–30/06 nếu áp dụng. | H5: VND | I5: Rev=0: chỉ tiêu phụ thuộc not_applicable. Thiếu Rev: missing_data. Demo dùng tổng doanh thu như proxy bán chịu.
A6: T1-02 | B6: 01. Số dư và chu kỳ | C6: Giá vốn kỳ (COGS) | D6: Chi phí làm ra hàng đã bán, gồm cả lương công nhân | E6: COGS = financials.cogs_vnd | F6: financials.cogs_vnd; workbook D_F01!B10 | G6: firm_id của phiên; firm_id = F01; ngày chốt 30/06/2026. Kỳ phát sinh 01/01–30/06 nếu áp dụng. | H6: VND | I6: COGS=0: tỷ số phụ thuộc not_applicable. Thiếu COGS: missing_data.
A7: T1-03 | B7: 01. Số dư và chu kỳ | C7: Phải thu (AR) | D7: Tiền khách còn nợ | E7: AR = Σ OpenAmount của hóa đơn bán | F7: sales_invoices.Amount | G7: Hóa đơn mở tại AsOf; firm_id = F01; ngày chốt 30/06/2026. Kỳ phát sinh 01/01–30/06 nếu áp dụng. | H7: VND | I7: Không có hóa đơn mở → AR = 0 (hợp lệ)
A8: T1-04 | B8: 01. Số dư và chu kỳ | C8: Tồn kho (INV) | D8: Tiền nằm trong kho dưới dạng hàng | E8: INV = Σ Qty × UnitCost của lô thuộc F01 | F8: inventory.qty, unit_cost_vnd, inventory_type | G8: inventory_type ≠ HGC; firm_id = F01; ngày chốt 30/06/2026. Kỳ phát sinh 01/01–30/06 nếu áp dụng. | H8: VND | I8: Thiếu loại/quyền sở hữu: chưa xác định, không tự coi NVL. Demo HGC loại; cost chưa NRV có nhãn.
A9: T1-05 | B9: 01. Số dư và chu kỳ | C9: Phải trả (AP) | D9: Số tiền doanh nghiệp còn nợ nhà cung cấp | E9: AP = Σ OpenAmount của hóa đơn mua | F9: purchase_invoices.Amount | G9: Hóa đơn mở tại AsOf; firm_id = F01; ngày chốt 30/06/2026. Kỳ phát sinh 01/01–30/06 nếu áp dụng. | H9: VND | I9: Không có hóa đơn mở → AP = 0 (hợp lệ)
A10: T1-06 | B10: 01. Số dư và chu kỳ | C10: Mua hàng trong kỳ (PUR) | D10: Giá trị mua chịu từ nhà cung cấp trong N ngày | E10: PUR = Σ Amount hóa đơn mua phát hành trong kỳ | F10: purchase_invoices.Amount, issue_date | G10: AsOf − N + 1 ≤ issue_date ≤ AsOf; firm_id = F01; ngày chốt 30/06/2026. Kỳ phát sinh 01/01–30/06 nếu áp dụng. | H10: VND | I10: PUR = 0 → bỏ T1-11
A11: T1-07 | B11: 01. Số dư và chu kỳ | C11: DSO | D11: Phải thu quy đổi thành số ngày theo doanh thu kỳ; không là ngày tiền chắc chắn về. | E11: DSO = AR / Rev × N | F11: T1-03, T1-01 | G11: –; firm_id = F01; ngày chốt 30/06/2026. Kỳ phát sinh 01/01–30/06 nếu áp dụng. | H11: ngày; 1 số lẻ khi xuất | I11: Rev=0: not_applicable. Thiếu trường: missing_data.
A12: T1-08 | B12: 01. Số dư và chu kỳ | C12: DIO | D12: Tồn kho quy đổi theo giá vốn kỳ; khác số ngày một lô đã lưu kho. | E12: DIO = INV / COGS × N | F12: T1-04, T1-02 | G12: –; firm_id = F01; ngày chốt 30/06/2026. Kỳ phát sinh 01/01–30/06 nếu áp dụng. | H12: ngày; 1 số lẻ | I12: COGS=0: not_applicable. Thiếu trường: missing_data.
A13: T1-09 | B13: 01. Số dư và chu kỳ | C13: DPO | D13: Phải trả cuối kỳ quy đổi theo giá vốn kỳ; không phải kỳ hạn hợp đồng thực tế. | E13: DPO = AP / COGS × N | F13: T1-05, T1-02 | G13: –; firm_id = F01; ngày chốt 30/06/2026. Kỳ phát sinh 01/01–30/06 nếu áp dụng. | H13: ngày; 1 số lẻ | I13: COGS=0: not_applicable. Thiếu trường: missing_data.
A14: T1-10 | B14: 01. Số dư và chu kỳ | C14: CCC | D14: DSO + DIO − DPO theo cùng phương pháp và kỳ. | E14: CCC = DSO + DIO − DPO | F14: T1-07..T1-09 (chưa làm tròn) | G14: –; firm_id = F01; ngày chốt 30/06/2026. Kỳ phát sinh 01/01–30/06 nếu áp dụng. | H14: ngày; làm tròn bước cuối | I14: Metric phụ thuộc không khả dụng: CCC null cùng reason; giữ phần tính được.
A15: T1-11 | B15: 01. Số dư và chu kỳ | C15: DPO trên mua hàng (chẩn đoán) | D15: Phải trả cuối kỳ quy đổi theo giá trị mua hàng; vẫn không phải kỳ hạn hợp đồng. | E15: DPO_mua = AP / PUR × N | F15: T1-05, T1-06 | G15: –; firm_id = F01; ngày chốt 30/06/2026. Kỳ phát sinh 01/01–30/06 nếu áp dụng. | H15: ngày; 1 số lẻ | I15: PUR = 0 → null
... A61: T1-95 | B61: 09. Chi tiết và liên kết | C61: Quan hệ đối tác | D61: Đặc điểm quan hệ khác mức độ rủi ro thanh toán. | E61: Mới nếu RelationshipAge ≤60 Thường xuyên nếu InvoiceCount ≥12 VÀ ActiveMonths ≥4 Còn lại Vãng lai | F61: D_sales; hồ sơ đối tác | G61: Quy tắc demo, không phải ngưỡng ngành. Ít lịch sử không đồng nghĩa khách xấu. | H61: Nhãn | I61: Không làm tròn giữa các bước; truy vết nguồn và phiên bản.

Sheet UC2_Cong_thuc
A2: UC02 Dự báo tiền và cảnh báo
A4: Mã | B4: Nhóm công thức | C4: Chỉ tiêu | D4: Ý nghĩa dễ hiểu | E4: Công thức từng bước | F4: Dữ liệu đầu vào | G4: Phạm vi / điều kiện | H4: Đơn vị / hiển thị | I4: Ngoại lệ / kiểm soát
A5: T2-01 | B5: 01. Tiền đầu kỳ và nghĩa vụ | C5: Tiền khả dụng đầu dự báo | D5: Tiền doanh nghiệp có thể chi ngay sau ngày chốt. | E5: Cash0 = cash_AsOf_vnd − restricted_vnd | F5: cash_snapshot.cash_vnd, restricted_vnd | G5: Đúng doanh nghiệp, ngày chốt, tiền tệ. | H5: VND; raw | I5: Thiếu Cash0: chỉ dùng proxy được xác định và gắn nhãn trong chính sách → provisional. Nếu không có proxy hợp lệ → missing_data; không tự điền 0. Tiền bị hạn chế phải tách riêng.
A6: T2-02 | B6: 01. Tiền đầu kỳ và nghĩa vụ | C6: Phải thu dùng lập lịch tiền | D6: Chỉ dự báo phần khách chưa trả. | E6: AR_cash = gross_invoice − receipts_to_AsOf − credits_to_AsOf | F6: sales_invoices; receipt_allocations; credit_notes | G6: Đã ghi nhận đến ngày chốt; chọn phần dư dương. | H6: VND gồm thuế | I6: Demo net/noVAT, trả toàn bộ một lần. Dư âm tách ứng trước. Không tự dùng VAT 10%.
A7: T2-03 | B7: 01. Tiền đầu kỳ và nghĩa vụ | C7: Phải trả dùng lập lịch tiền | D7: Chỉ dự báo phần nghĩa vụ chưa trả. | E7: AP_cash = gross_invoice − payments_to_AsOf − credits_to_AsOf | F7: purchase_invoices; payment_allocations | G7: Đúng phạm vi thương mại và ngày chốt. | H7: VND gồm thuế | I7: Lương, thuế, nợ vay vào plan riêng. Một nghĩa vụ chỉ tính một lần.
A8: T2-04 | B8: 02. Lập lịch và tính số dư | C8: Trễ thu bình quân dương | D8: Ước ngày thu theo lịch sử từng khách. Khoản lớn có trọng số lớn. | E8: CompletedLate = MAX(0; PaidDate − DueDate) OpenLowerBound = MAX(0; AsOf − DueDate) ModelDelay = CompletedLate hoặc OpenLowerBound DelayBase = Σ ModelAmount × ModelDelay / Σ ModelAmount | F8: receipt_allocations; due_date | G8: DueDate trong (AsOf − 180; AsOf]; mẫu mở có cờ censored, mẫu trả xong có cờ completed. Chọn khách khi ≥5 mẫu; nếu không dùng toàn F01 ≥5; cuối cùng mặc định 7 ngày. | H8: Ngày; giữ raw | I8: Theo SRS 2.7.11.1: mẫu mở chỉ là cận dưới. Không gọi trung bình hỗn hợp là ngày thanh toán thực tế. UC01 vẫn dùng riêng mẫu đã thanh toán.
A9: T2-05 | B9: 02. Lập lịch và tính số dư | C9: Ngày thu dự kiến | D9: Ưu tiên lịch xác nhận, sau đó mới ước tính. | E9: Ngày thu = ConfirmedDate nếu lịch được biết tại AsOf Chưa quá hạn: MAX(Start; DueDate + CEILING(DelayScenario; 1)) Đã quá hạn: xem T2-19; không tự gom mọi khoản về Start. | F9: receipt_schedule; T2-04; due_date | G9: Lịch biết tại ngày chốt; portions không vượt dư. | H9: Ngày lịch | I9: Ngày đã qua chuyển về Start chỉ theo policy có nhãn. Thiếu ngày: unscheduled. Không dùng paid_date tương lai.
A10: T2-06 | B10: 02. Lập lịch và tính số dư | C10: Ngày chi dự kiến | D10: Giữ nghĩa vụ đến hạn và nói rõ giả định khoản quá hạn. | E10: Ngày chi = ApprovedDate nếu có Chưa quá hạn: DueDate + lịch sử trễ theo chính sách NCC thiết yếu / Conservative: DueDate Quá hạn: AsOf + OffsetScenario + MOD(Rank; 5) | F10: payment_schedule; purchase_invoices | G10: Lịch đã duyệt, biết tại ngày chốt. | H10: Ngày lịch | I10: Đây là chính sách mô phỏng theo SRS, không phải gia hạn đã được NCC chấp thuận. Lịch được duyệt ưu tiên. Offset: Conservative 1, Base 5, Optimistic 10 ngày.
A11: T2-07 | B11: 02. Lập lịch và tính số dư | C11: Tiền vào ngày hoặc tuần | D11: Cộng khoản thu được xếp vào đúng kỳ. | E11: In = Σ Amount [direction = IN; date ∈ kỳ] | F11: cash_events | G11: Cùng firm, run, case, currency; không trùng nguồn. | H11: VND | I11: Thu hóa đơn và thu khác có căn cứ. Không lấy Rev/N làm tiền thu, không tự coi tồn kho sẽ bán được.
A12: T2-08 | B12: 02. Lập lịch và tính số dư | C12: Tiền ra ngày hoặc tuần | D12: Trả nhà cung cấp và các khoản chi có lịch. | E12: Out = Σ Amount [direction = OUT; date ∈ kỳ] | F12: cash_events; planned_events | G12: Cùng scope và kỳ; một phần nghĩa vụ một lần. | H12: VND | I12: Không cộng COGS như tiền chi. Gốc/lãi vay, lương, thuế, đầu tư cần lịch riêng.
A13: T2-09 | B13: 02. Lập lịch và tính số dư | C13: Số dư tiền | D13: Một phép tính cho ngày và tuần, liên kết kỳ trước sang kỳ sau. | E13: CashEnd = CashStart + In − Out CashStart_next = CashEnd | F13: T2-01; T2-07; T2-08 | G13: Ngày đầu bằng Cash0; tuần cộng cùng event ledger. | H13: VND; giữ số âm | I13: Ví dụ đầu100 triệu, thu100, chi150 → cuối50; vẫn có thể âm giữa tuần. Không ép số âm về0.
A14: T2-10 | B14: 03. Cảnh báo thiếu tiền | C14: Thiếu so mức dự phòng | D14: Chỉ phát sinh nhu cầu điều chỉnh khi dưới L; số tiền cần bổ sung đưa về Z. | E14: GapRestore_d = IF(CashEnd_d < L; Z − CashEnd_d; 0) GapFloor_d = MAX(0; L − CashEnd_d) | F14: buffer_vnd; T2-09 | G14: Dự phòng đã xác nhận; ghi rõ ngày/cuối tuần. | H14: VND | I14: Tiền còn350 triệu, buffer500 → thiếu150; chưa phải tiền âm.
A15: T2-11 | B15: 03. Cảnh báo thiếu tiền | C15: Thiếu để không âm | D15: Khoản bù để số dư dự kiến trở lại0. | E15: GapZero = MAX(0; −CashEnd) | F15: T2-09 | G15: Cùng ngày/tuần đang xét. | H15: VND | I15: Tiền−50 triệu → thiếu50 để không âm. Không cộng với GapBuffer.
... A41: T2-37 | B41: 06. Chất lượng và bàn giao | C41: Trạng thái dữ liệu | D41: Phân biệt giả định đủ dữ liệu với kiểm soát quyền và nguồn. | E41: Giả định doanh nghiệp luôn tải đủ dữ liệu; phân lớp W và tiền luôn tính được. Giữ kiểm soát quyền truy cập, snapshot, thời điểm biết dữ liệu và chống trùng. | F41: Nguồn, validation, manifest | G41: Dữ liệu F01 vẫn ghi provisional vì là dữ liệu tạo sinh, không có trạng thái W chưa xác định. | H41: Enum | I41: Không làm tròn giữa các bước; truy vết nguồn và phiên bản.

Sheet UC3_Cong_thuc
A2: UC03 So khớp phương án tài trợ
A4: Mã | B4: Nhóm công thức | C4: Chỉ tiêu | D4: Ý nghĩa dễ hiểu | E4: Công thức từng bước | F4: Dữ liệu đầu vào | G4: Phạm vi / điều kiện | H4: Đơn vị / hiển thị | I4: Ngoại lệ / kiểm soát
A5: T3-01 | B5: 01. Khoảng thiếu và đợt cần tiền | C5: Mức thiếu theo khối 2 tuần | D5: Cho biết mỗi khối 2 tuần thiếu bao nhiêu so với mức dự trữ muốn giữ. | E5: Deficit_k = IF(MinDaily_k < L; Z−MinDaily_k; 0) k là khối 2 tuần trong 13 tuần. | F5: UC02: Rtarget; MinDaily theo khối (T2-13) | G5: Chỉ khối có ngày dưới L mới tạo nhu cầu; số tiền điều chỉnh đưa về Z. | H5: VND; raw | I5: Không cộng Deficit_k qua các khối. Chưa phải số tiền cần vay.
A6: T3-02 | B6: 01. Khoảng thiếu và đợt cần tiền | C6: Ngưỡng đổi mức và mức trọng yếu | D6: Lọc nhiễu: chỉ coi là đổi mức khi chênh lệch đủ lớn và giữ đủ lâu. | E6: θ = Rtarget × PARAM_THETA_PCT Is_Material_Gap = 1 nếu |ΔDeficit| ≥ θ VÀ mức mới giữ ≥ PARAM_MIN_DAYS ngày; ngược lại 0 | F6: T3-01; PARAM_THETA_PCT (25%); PARAM_MIN_DAYS (14) | G6: So hai khối liền kề; mức không giữ đủ 14 ngày gộp vào mức trước. | H6: VND; ngày | I6: Dao động nhỏ hoặc xen kẽ bị coi là nhiễu, không tạo đợt mới.
A7: T3-03 | B7: 01. Khoảng thiếu và đợt cần tiền | C7: Dạng khoảng thiếu (gap_shape) | D7: Phân loại đường thiếu theo số lần đổi mức: tối đa một lần. | E7: Đếm n = số lần Is_Material_Gap = 1 trong kỳ n = 0 → đồng đều n = 1 và mức tăng → tăng một lần n = 1 và mức giảm → giảm một lần n ≥ 2 → không phân loại được | F7: T3-02 | G7: Chỉ TH01 tạo khoảng cần tài trợ; TH02 là thừa tiền; trong vùng L–H tiếp tục theo dõi. | H7: enum | I7: n ≥ 2: dùng mức thiếu lớn nhất cho cả kỳ và gắn cờ REVIEW_MANUAL. Không mô hình hóa bật tắt xen kẽ.
A8: T3-04 | B8: 01. Khoảng thiếu và đợt cần tiền | C8: Cắt đợt cần tiền (gap_request) | D8: Đổi đường thiếu thành tối đa 2 đợt có ngày và số tiền cần. | E8: Đồng đều/giảm một lần: need_date = ngày đầu CashEnd<L; G_cum là mức điều chỉnh lớn nhất về Z. Tăng một lần: tối đa 2 đợt; G_incr_j=G_cum_j−G_cum_(j−1). | F8: UC02: gap_shape, gap_request; T3-03 | G8: Mỗi đợt có need_date và G_cum; G_incr đợt 1 = G_cum đợt 1. | H8: VND; ngày | I8: Giảm một lần: kỳ hạn chỉ cần phủ đến ngày chuyển mức. Hóa đơn hoặc lô đã dùng ở đợt 1 bị loại khỏi đợt 2.
A9: T3-05 | B9: 01. Khoảng thiếu và đợt cần tiền | C9: Mức nhẹ / nặng của khoảng thiếu | D9: Phân nhẹ hoặc nặng để chọn cách xử lý. | E9: gap_severity = NẶNG nếu PeakGap ≥ θ; NHẸ nếu nhỏ hơn | F9: T3-02; PeakGap của đợt | G9: Tính riêng từng đợt. | H9: enum | I9: Ngưỡng dùng chung với T3-02.
A10: T3-06 | B10: 01. Khoảng thiếu và đợt cần tiền | C10: Số ngày còn lại và chế độ Khẩn | D10: Còn bao nhiêu ngày đến lúc cần tiền; sát hạn thì ưu tiên tiền nhanh nhất. | E10: DaysLeft = need_date − ngày yêu cầu Urgent_Mode = 1 nếu DaysLeft ≤ PARAM_URGENT_DAYS (7) | F10: gap_request; PARAM_URGENT_DAYS | G10: Tính riêng từng đợt; ngày yêu cầu là ngày chạy UC03. | H10: Ngày; 0/1 | I10: DaysLeft ≤ 0: không có nguồn nào kịp ngoài tiền nội bộ; hiển thị “không kịp ngày cần tiền”.
A11: T3-07 | B11: 01. Khoảng thiếu và đợt cần tiền | C11: Thời gian thiếu kéo dài (duration) | D11: Số ngày khoảng thiếu còn tồn tại kể từ ngày cần tiền; dùng để tính chi phí thực. | E11: duration_j tính từ need_date đến ngày cuối CashEnd<L; giảm một lần tính đến ngày chuyển mức. | F11: UC02: daily[] | G11: Từng đợt. | H11: Ngày | I11: duration < PARAM_MIN_TENOR (14): loại sản phẩm khóa kỳ hạn hoặc có phí cố định, ưu tiên tiền nội bộ và giãn lịch.
A12: T3-08 | B12: 02. Yếu tố góp phần và kịch bản | C12: Tỷ lệ tham chiếu của yếu tố góp phần | D12: Dùng để định tuyến kịch bản, không phải phần thiếu do yếu tố gây ra. | E12: Share_k = MIN(100%; số tiền yếu tố k / PeakGap), k ∈ {E_AR, E_INV, E_AP} Vai trò: CHÍNH nếu ≥ PARAM_CAUSE_MAIN (50%); PHỤ nếu ≥ PARAM_CAUSE_SEC (15%); còn lại BỎ QUA | F12: UC01: E_AR, E_INV, E_AP; PeakGap | G12: Số tiền yếu tố là số tham chiếu, không cộng được (SRS 2.7.11.9). | H12: Tỷ lệ; 1 số lẻ% | I12: Với người dùng chỉ nói “yếu tố góp phần” kèm loại liên kết và mức bằng chứng; candidate phải gắn “chưa kiểm chứng”. Không gọi là nguyên nhân chính.
A13: T3-09 | B13: 02. Yếu tố góp phần và kịch bản | C13: Sự kiện trọng yếu | D13: Nhận biết khoản chi hoặc nhập NVL lớn làm mức thiếu tăng vọt. | E13: Major_Event = 1 nếu giá trị khoản đơn lẻ / PeakGap ≥ PARAM_MAJOR_EVENT (30%) | F13: cash_events OUT; PeakGap | G13: Trong ±7 ngày quanh ngày chuyển mức. | H13: 0/1 | I13: Không có sự kiện nào: ghi “đổi mức không gắn được sự kiện”.
A14: T3-10 | B14: 02. Yếu tố góp phần và kịch bản | C14: Chọn kịch bản một đợt A1–A4 | D14: Chọn nhóm nguồn theo yếu tố chính của khoảng thiếu. | E14: Không chuỗi gap (TH01): main = AR → A1; main = INV → A2; main = AP → A4; còn lại (BN0, L3) → A3 | F14: UC01: main_bottleneck, bn_pattern; T3-08 | G14: Chỉ TH01 và chưa thỏa điều kiện chuỗi gap ở T3-11. | H14: enum | I14: Yếu tố PHỤ mở thêm nhóm sản phẩm nhưng không đổi kịch bản.
A15: T3-11 | B15: 02. Yếu tố góp phần và kịch bản | C15: Chuỗi gap B1 / B2 | D15: Thiếu kéo dài mang tính cấu trúc nên cần gói đa nguồn. | E15: Persistent = 1 nếu TH01 và số khối thiếu liên tiếp ≥ min_blocks (2) Persistent = 1: B2 nếu (W2 và n_yếu_tố ≥ 2) HOẶC BestC < G B1 nếu n_yếu_tố > 0, không có yếu tố tồn kho và mọi liên kết L1 Còn lại B2 | F15: UC02: số khối; UC01: W, bn_pattern, loại liên kết; BestC = MAX C của nguồn qua lọc và kịp hạn | G15: n_yếu_tố = c_AR + c_INV + c_AP. | H15: enum | I15: Thay cách chọn B1/B2 ở phiên bản trước; khớp bộ tính tham chiếu.
... A42: T3-38 | B42: 06. Thừa tiền và kiểm soát | C42: Ca quyết định của con người | D42: Đánh dấu bước UC03 không thể tự thực hiện. | E42: requires_human_decision = 1 nếu gói có AP_EXT, AR_EARLY, ghi đè hoặc cờ REVIEW_MANUAL | F42: T3-32; cờ cấp phiên | G42: Cả phiên. | H42: 0/1 | I42: UC03 chỉ đề xuất; UC04 soạn nội dung, người có thẩm quyền duyệt.
A44: Tham số ngưỡng UC03 (giá trị mặc định, tách khỏi công thức)
A46: Mã | B46: Tham số | C46: Giá trị mặc định | D46: Ý nghĩa dễ hiểu | E46: Công thức dùng | F46: Ghi chú
A47: T3-P01 | B47: PARAM_THETA_PCT | C47: 25% (% Rtarget) | D47: Chênh lệch tối thiểu công nhận đổi mức; ranh giới gap nhẹ / nặng | E47: T3-02, T3-05 | F47: Mặc định; đổi theo quy mô doanh nghiệp
A48: T3-P02 | B48: PARAM_MIN_DAYS | C48: 14 (ngày) | D48: Thời gian giữ mức mới (2 khối 2 tuần, khớp min_blocks = 2) | E48: T3-02 | F48: Mặc định
A49: T3-P03 | B49: PARAM_CAUSE_MAIN | C49: 50% (% PeakGap) | D49: Từ ngưỡng này là yếu tố góp phần chính (chỉ để định tuyến) | E49: T3-08 | F49: Mặc định
A50: T3-P04 | B50: PARAM_CAUSE_SEC | C50: 15% (% PeakGap) | D50: Từ ngưỡng này đến dưới 50% là yếu tố phụ | E50: T3-08 | F50: Mặc định
A51: T3-P05 | B51: PARAM_MAJOR_EVENT | C51: 30% (% PeakGap) | D51: Khoản đơn lẻ từ ngưỡng này là sự kiện trọng yếu | E51: T3-09 | F51: Mặc định
A52: T3-P06 | B52: PARAM_MIN_DRAW_PCT | C52: 5% (% PeakGap) | D52: Số rút tối thiểu mỗi nguồn | E52: T3-32 | F52: Mặc định
A53: T3-P07 | B53: PARAM_MAX_SOURCES | C53: 4 (nguồn) | D53: Số nguồn tối đa trong một gói | E53: T3-32 | F53: Mặc định
A54: T3-P08 | B54: PARAM_URGENT_DAYS | C54: 7 (ngày) | D54: DaysLeft nhỏ hơn hoặc bằng ngưỡng là chế độ Khẩn | E54: T3-06, T3-27 | F54: Mặc định
A55: T3-P09 | B55: PARAM_MIN_TENOR | C55: 14 (ngày) | D55: Thời gian thiếu ngắn hơn ngưỡng thì loại sản phẩm khóa kỳ hạn hoặc phí cố định | E55: T3-07 | F55: Mặc định
A56: T3-P10 | B56: PARAM_KEY_PARTNER | C56: 30% (% mua/bán) | D56: Nhà cung cấp từ ngưỡng này bị loại khỏi giãn nợ; khách hàng từ ngưỡng này chuyển cấp quản lý | E56: T3-14, T3-19 | F56: Mặc định

Sheet UC4_Cong_thuc
A2: UC04 Mô phỏng tác động lên dòng tiền
A4: Mã | B4: Nhóm công thức | C4: Chỉ tiêu | D4: Ý nghĩa dễ hiểu | E4: Công thức từng bước | F4: Dữ liệu đầu vào | G4: Phạm vi / điều kiện | H4: Đơn vị / hiển thị | I4: Ngoại lệ / kiểm soát
A5: U4-01 | B5: 01. Phạm vi và dữ liệu | C5: Đường tiền đối chiếu | D5: Lấy kết quả UC02 làm điểm xuất phát, không dựng lại lịch tùy ý. | E5: Base = UC02.daily Events = UC02.cash_events Giữ firm, snapshot, kỳ, Cash0, dự trữ và phiên bản | F5: F01_UC2!A70:M160; A220:Y341; D_F01 | G5: Workbook bắt đầu bằng D_F01!B19=1 (Base). Có thể thử nền UC02 khác, nhãn phải đổi theo. | H5: Ngày; VND | I5: Run UC01/UC02 khác firm/snapshot → chặn. Không ghép run-off và continuing như cùng cơ sở.
A6: U4-02 | B6: 01. Phạm vi và dữ liệu | C6: Đối tượng mô phỏng | D6: Chọn khách, NCC và lô từ kết quả chẩn đoán, rồi nối đến sự kiện tiền. | E6: Candidate = UC01.drivers AffectedEvents = Events có entity_id/source_id được chọn | F6: UC01; D_sales; D_purchases; D_inventory | G6: ID gốc, không nối bằng tên. Bản minh họa chọn 1 khách, 1 NCC, 1 lô; backend nhận danh sách event. | H6: ID / danh sách | I6: Điểm nghẽn UC01 chưa chắc tạo gap. Chỉ mô tả tác động do phép thử; không khẳng định quan hệ nhân quả đã được chứng minh.
A7: U4-03 | B7: 01. Phạm vi và dữ liệu | C7: Kiểm tra giả định | D7: Phân biệt giá trị 0 đã nhập với thiếu đầu vào. | E7: 0 ≤ Share ≤1; Days ≥0 và nguyên 0 ≤ Discount, Fee, Recovery, SaleCost ≤1 ID có thật; ngày hợp lệ; số tiền không vượt dư | F7: F01_UC4!B5:B27 | G7: 0%/0 ngày là lựa chọn không tác động. Rmin≤Rtarget≤Rupper; Rtarget>0. | H7: Hợp lệ / lỗi | I7: Sai tham số → rejected; nguồn mâu thuẫn → invalid_data; thiếu dữ liệu cần thiết → missing_data. Không cắt số sai về mức hợp lệ.
A8: U4-04 | B8: 02. Thu sớm hoặc thu chậm | C8: Phần tiền chuyển lịch | D8: Chỉ chuyển một phần khoản thu; phần còn lại giữ lịch cũ. | E8: Moved_i = Amount_i × ShareAR Remain_i = Amount_i − Moved_i | F8: UC02 event IN, category Thu công nợ; AR_share | G8: Đúng customer_id, hóa đơn mở. Lịch confirmed giữ nguyên trừ khi bật giả định thay cam kết. | H8: VND | I8: Một phần hóa đơn chỉ được phân bổ một lần. Không dùng Rev/ngày × số ngày như tiền sẽ thu.
A9: U4-05 | B9: 02. Thu sớm hoặc thu chậm | C9: Ngày thu mới | D9: Có thể thử cả thu sớm và khách trả chậm. | E9: Thu sớm: NewDate_i = MAX(Start; OldDate_i − EarlyDays) Stress chậm: NewDate_i = OldDate_i + LateDays | F9: Ngày thu UC02; số ngày do người dùng nhập | G9: Chỉ tương lai sau AsOf; stress mới thay thế thao tác thu sớm trên cùng phần tiền. | H9: Ngày lịch | I9: Không dịch lịch sử, không coi khách đã đồng ý. Lịch xác nhận bị thay phải có cờ và lý do.
A10: U4-06 | B10: 02. Thu sớm hoặc thu chậm | C10: Thu ròng và chiết khấu | D10: Thu nhanh hơn có thể phải chấp nhận giảm số tiền. | E10: DiscountCost_i = Moved_i × Discount NewReceipt_i = Moved_i − DiscountCost_i | F10: AR_discount; U4-04 | G10: Chiết khấu chỉ áp phần thực sự được thu sớm; không áp ngày không thay đổi hoặc stress thu chậm. | H10: VND | I10: Workbook ghi khoản chiết khấu bằng giảm thu, không ghi thêm OUT lần hai. Không tự đặt chiết khấu 0 khi chưa biết trong vận hành.
A11: U4-07 | B11: 03. Giãn trả nhà cung cấp | C11: Phần chi chuyển lịch | D11: Giãn chi tạo khoảng đệm thời gian, không xóa nợ. | E11: MovedPay_i = Amount_i × ShareAP RemainPay_i = Amount_i − MovedPay_i NewPayDate_i = OldDate_i + ExtendDays | F11: UC02 OUT / Trả NCC; supplier_id | G11: Chỉ khoản thương mại đã chọn. Lương, thuế, gốc/lãi vay không áp đòn bẩy này. | H11: VND; ngày | I11: NCC thiết yếu chỉ mô phỏng khi có xác nhận giả định được phép thử. Không coi xác nhận mô phỏng là thỏa thuận thật.
A12: U4-08 | B12: 03. Giãn trả nhà cung cấp | C12: Phí giãn trả | D12: Đưa đủ chi phí vào lịch trả mới. | E12: ExtensionFee_i = MovedPay_i × FeeAP NewPayment_i = MovedPay_i + ExtensionFee_i | F12: AP_fee_pct; U4-07 | G12: Phí phần trăm một lần trong bản đầu; biết ngày chi cùng ngày trả mới. | H12: VND | I12: NCC từ chối trong stress → giữ lịch cũ, không phí. Mất chiết khấu chỉ tính khi đã mô hình trong nền, không cộng tùy ý.
A13: U4-09 | B13: 04. Bán một phần tồn kho | C13: Lô được phép thử bán | D13: Không lấy hàng của khách hoặc hàng vướng quyền làm tiền của F01. | E13: EligibleLot = Owner=F01 AND Pledged=không AND UserSaleAssumption=1 ReleasedBook = OwnedValue × SaleShare | F13: D_inventory!A:M; sale_assumption | G13: Kiểm tra lượng bán≤lượng lô. Bản đầu chỉ bán lô chưa có khoản thu bán tương ứng trong nền. | H13: VND giá ghi sổ | I13: Hàng HGC, cầm cố hoặc chưa rõ cầm cố → chặn đòn bẩy lô đó. Muốn thử cần bổ sung bằng chứng, không sửa D_inventory để vượt chặn.
A14: U4-10 | B14: 04. Bán một phần tồn kho | C14: Tiền bán hàng và phí | D14: Giá ghi sổ giảm không đồng nghĩa thu được từng ấy tiền. | E14: SaleGross = ReleasedBook × RecoveryRate SaleCashCost = SaleGross × SaleCostRate SaleNet = SaleGross − SaleCashCost | F14: Tỷ lệ bán; tỷ lệ thu hồi; tỷ lệ chi phí | G14: Demo RecoveryRate từ 0 đến 100% giá ghi sổ; không tự đặt giá thị trường. | H14: VND | I14: Chênh lệch giá ghi sổ và tiền bán là tổn thất giá trị mô phỏng, không là một dòng tiền chi thêm.
A15: U4-11 | B15: 04. Bán một phần tồn kho | C15: Ngày bán và ngày thu | D15: Chỉ phát sinh tiền khi giả định có giao dịch và thời điểm thu rõ. | E15: SaleDate = Start + SaleLag SaleReceiptDate = SaleDate + ReceiptLag Kho giảm tại SaleDate; tiền về tại SaleReceiptDate | F15: F01_UC4 tham số lô; nhật ký giả định | G15: Bản minh họa ReceiptLag=0, thu ngay; backend cho phép trả chậm. | H15: Ngày; VND | I15: Tái sử dụng nguyên liệu hoặc ghi giảm giá trị chưa tạo tiền; chỉ ghi giảm chi mua khi có kế hoạch mua thay thế tương ứng được điều chỉnh.
... A34: U4-30 | B34: 08. Giới hạn chỉ số và đầu ra | C34: Đợt thiếu sau và ma trận | D34: Đánh giá trạng thái tiền mới nhưng không xóa chẩn đoán cũ. | E34: TH_after = quy tắc UC02 trên đường tiền sau Matrix_after = M(3×W_index+TH_index) | F34: W tại AsOf; TH_after; cùng cơ sở nền | G34: Nếu không phải nền Base thì TH/matrix chỉ là tham khảo; W không thay do thao tác tương lai. | H34: W / TH / M | I34: Không đổi W2 thành W0 vì tiền tạm dư. Mức màu tính riêng, không suy từ ô M.

Sheet UC4_Huong_dan
A2: UC04 Phạm vi và hướng dẫn triển khai
A4: Nhóm | B4: Nội dung | C4: Quy tắc áp dụng | D4: Vị trí / ví dụ
A5: Luồng tổng thể | B5: UC01 chọn đối tượng → UC02 cung cấp lịch tiền → UC04 thay giả định trên bản sao → so trước/sau và stress. | C5: Không cần chạy UC03. Không mặc định khách/NCC đã chấp thuận. | D5: F01_UC4: thiết lập A4:C40; kết quả E4:H40; ngày dòng 50; sự kiện dòng 150; tuần dòng 306.
A6: Phạm vi bản đầu | B6: Ba đòn bẩy nội bộ: thu sớm/chậm, giãn trả NCC, bán lô tồn sở hữu. | C6: Không gồm vay, tài trợ hóa đơn, đầu tư tiền dư, gửi thư hoặc phê duyệt hành động. Không đổi SRS trong lần này. | D6: Bản thiết kế công thức chờ duyệt. UC03 vẫn có thể nối thêm sau.
A7: Đối chiếu draft cũ | B7: Giữ bản sao bất biến, dịch sự kiện, kiểm tra gap mới, chi phí và bằng chứng. | C7: Bỏ phụ thuộc TV3_Nguong/TV3_Dot_thieu/D_catalogue; bỏ bộ F02/F03, bảng bản nháp và submit_action. | D7: Draft cũ có 30 sheet, gồm cả UC03 và dữ liệu cũ. Bản mới chỉ bổ sung 3 sheet.
A8: Sửa điểm nghiệp vụ | B8: Không dùng doanh thu bình quân×ngày để thay AR/AP tại ngày chốt; không mặc định tài trợ được loại AR; không coi toàn bộ thiếu biến mất khi hết một đợt. | C8: Giữ CCC lịch sử; tập trung tiền theo ngày, ngày xấu đi và nghĩa vụ ngoài kỳ. | D8: U4-14, U4-17, U4-26. Không suy tiết kiệm lãi khi chưa có lịch dư nợ thực.
A9: Dùng chung dữ liệu | B9: F01, ngày chốt 30/06/2026; chẩn đoán 01/01–30/06; forecast 01/07–29/09. | C9: Không chép lại D_* từ TV4 draft. UC04 nối trực tiếp sự kiện UC02 và lô từ D_inventory. | D9: D_F01, D_sales, D_purchases, D_inventory, D_flows giữ nguyên.
A10: Mã công thức | B10: UC04 dùng mã U4-01…U4-30 để phân biệt bản draft T4 cũ. | C10: Bảng 9 cột giống UC1/UC2_Cong_thuc; mỗi phép có đầu vào, điều kiện và ngoại lệ. | D10: Không gộp công thức và yêu cầu quyền thành một phép toán.
A11: Kịch bản đang chọn | B11: 0 Giữ nguyên; 1 Thực hiện giả định; 2 Chỉ thu sớm được 50%; 3 NCC từ chối; 4 Bán tồn chậm; 5 Ba bất lợi kết hợp; 6 Khách trả chậm. | C11: Một selector ở F01_UC4!B5; tất cả dùng cùng một ledger và một đường tiền. | D11: B6 đọc nhãn; B28:B34 là giả định hiệu lực tính từ selector và thông số.
A12: Nhóm khách hàng | B12: Gợi ý chọn từ UC01 theo vốn đang giữ, trễ bao lâu, quan hệ và mức tập trung; người dùng chọn ID. | C12: Không tự siết khách mới/vãng lai hoặc nới khách lớn. Nhãn quan hệ là ngữ cảnh, không phải sự chấp thuận. | D12: B7 customer_id. Có thể lọc từng event_id ở backend; workbook áp theo khách và tỷ lệ chung.
A13: Nhóm nhà cung cấp | B13: Chỉ dịch khoản Trả NCC thuộc supplier_id; giữ lương, thuế và nghĩa vụ tài chính. | C13: NCC thiết yếu cần bật xác nhận giả định mô phỏng. Không dùng công cụ what-if để sửa hợp đồng. | D13: B13 supplier_id; B17 chỉ xác nhận được phép thử, không xác nhận đối tác đã đồng ý.
A14: Nhóm hàng tồn kho | B14: Bán lô phải thuộc F01, không cầm cố và có giả định thị trường. | C14: Mặc định L27 không cầm cố; lô phụ liệu đơn hủy L06 chưa rõ cầm cố nên không chọn sẵn để tạo tiền. | D14: B18 lot_id; B24 xác nhận giả định; nếu đổi sang L06 mà chưa có dữ liệu thì trạng thái chặn.
A15: Điều kiện lịch xác nhận | B15: Mặc định không đổi lịch thu được xác nhận ở UC02. | C15: B12=1 cho phép thử thay lịch xác nhận; phải nói rõ giả định này trong kết quả. | D15: Không lấy paid_date tương lai làm chứng cứ có tại ngày chốt.
... A63: U4-T14 | B63: Sai firm/snapshot, thiếu quyền, lời giải thích không có fact hoặc ghi audit lỗi. | C63: Chặn đúng điểm; không thực thi hoặc phát hành ngoài quyền; Decimal và kiểm chứng cùng run. | D63: Ca nghiệm thu backend; không tuyên bố đã có ứng dụng.

Sheet Nguong
A2: Ngưỡng SMEs, biến điều tiết và quy tắc áp dụng
A4: Khóa cấu hình | B4: Giá trị nguồn | C4: Đơn vị | D4: Áp dụng | E4: Nguồn | F4: Giới hạn
A5: cash.mo.lower_ratio | B5: 0.041798621 | C5: tỷ lệ DT năm | D5: L ngành (P25 Tiền/DT) | E5: B6_MillerOrr!C17 | F5: 20 DN FOB, 60 năm–DN, 2023–2025
A6: cash.mo.lower_min_owner | B6: 0 | C6: VND | D6: Sàn do chủ DN đặt | E6: ThamSo!P25 | F6: Giá trị mặc định nguồn
A7: cash.mo.sigma_annual_ratio | B7: 0.047874988 | C7: tỷ lệ | D7: σ năm ngành / DT | E7: B6_MillerOrr!C18 | F7: 40 biến động năm 2024–2025
A8: cash.mo.sigma_daily_ratio | B8: =B7/SQRT(B12) -> 0.0025058914 | C8: tỷ lệ | D8: σ ngày ngành / DT | E8: B6_MillerOrr!C20 | F8: Dự phòng ngành; không dùng nếu đủ lịch sử DN
A9: cash.mo.min_daily_obs | B9: 90 | C9: ngày | D9: Số quan sát ngày tối thiểu | E9: ThamSo!P26 | F9: Dùng lịch sử trong tối đa 3 năm
A10: cash.mo.transaction_cost | B10: 1000000 | C10: VND/lần | D10: F: chi phí chuyển đổi | E10: ThamSo!P22 | F10: demo_assumption
A11: cash.mo.rate_annual | B11: 0.0475 | C11: tỷ lệ/năm | D11: r năm: chi phí cơ hội | E11: ThamSo!P23 | F11: demo_assumption; không là lãi suất vay
A12: cash.mo.days_per_year | B12: 365 | C12: ngày | D12: Quy đổi về ngày | E12: ThamSo!P24
A13: cash.mo.annual_change_obs | B13: 40 | C13: quan sát | D13: Số quan sát biến động ngành | E13: B6_MillerOrr!C19
A14: wc.dso.reference.fob | B14: 43.247052 | C14: ngày | D14: Phải thu – tham chiếu (P50) | E14: verified_reference: FiinTrade 2023–2025, 20 DN may FOB
A15: wc.dso.watch.fob | B15: 58.207139 | C15: ngày | D15: Phải thu – R-AR-1 → Có nguy cơ | E15: verified_reference: FiinTrade 2023–2025, 20 DN may FOB
A16: wc.dso.severe.fob | B16: 66.263266 | C16: ngày | D16: Phải thu – R-AR-2 → Thiếu trầm trọng | E16: verified_reference: FiinTrade 2023–2025, 20 DN may FOB
A17: wc.dio.reference.fob | B17: 69.751755 | C17: ngày | D17: Tồn kho – tham chiếu (P50) | E17: verified_reference: FiinTrade 2023–2025, 20 DN may FOB
A18: wc.dio.watch.fob | B18: 86.118055 | C18: ngày | D18: Tồn kho – R-INV-1 → Có nguy cơ | E18: verified_reference: FiinTrade 2023–2025, 20 DN may FOB
A19: wc.dio.severe.fob | B19: 137.96515 | C19: ngày | D19: Tồn kho – R-INV-2 → Thiếu trầm trọng | E19: verified_reference: FiinTrade 2023–2025, 20 DN may FOB
A20: wc.dpo.high_info.fob | B20: 68.309204 | C20: ngày | D20: Phải trả – R-AP-INFO | E20: verified_reference: FiinTrade 2023–2025, 20 DN may FOB
A21: wc.dpo.low.fob | B21: 14.892653 | C21: ngày | D21: Phải trả – R-AP-1 | E21: verified_reference: FiinTrade 2023–2025, 20 DN may FOB
A22: liq.cash_buffer.thin.fob | B22: 0.083007995 | C22: % doanh thu | D22: Phải trả – R-AP-1 (điều kiện kèm) | E22: verified_reference: FiinTrade 2023–2025, 20 DN may FOB
A23: wc.materiality_share | B23: 0.05 | C23: tỷ lệ TSNH | D23: R-MAT → W2 | E23: owner_policy (mặc định demo) | F23: Chủ DN duyệt; độ nhạy ở B5
A24: wc.severe_forces_w2 | B24: 1 | C24: cờ | D24: R-AR-2 / R-INV-2 → W2 | E24: owner_policy
A25: scope.reference_start | B25: 2023 | C25: năm | D25: Đầu cửa sổ chuẩn ngành | E25: ThamSo!P19 | F25: Chỉ FOB
A26: scope.reference_end | B26: 2025 | C26: năm | D26: Cuối cửa sổ chuẩn ngành | E26: ThamSo!P20 | F26: 20 DN, 60 năm–DN
A27: wc.factor.size | B27: 1 | C27: hệ số | D27: Mọi ngưỡng | E27: verified_reference | F27: Không khác biệt có ý nghĩa → 1
A28: wc.factor.season | B28: 1 | C28: hệ số | D28: Ngưỡng DSO, DIO | E28: demo_assumption | F28: Chưa hiệu chỉnh
A29: ar.invoice.overdue_watch_rho | B29: 0.5 | C29: lần | D29: Cấp hóa đơn: ngày quá hạn / kỳ hạn | E29: demo_assumption | F29: Không hiệu chỉnh được từ BCTC
A30: ar.invoice.overdue_severe_rho | B30: 1 | C30: lần | D30: Cấp hóa đơn | E30: demo_assumption
A31: inv.lot.slow_days.nvl_hh | B31: 60 | C31: ngày | D31: Cấp lô: NVL, hàng hóa | E31: demo_assumption
A32: inv.lot.slow_days.btp_tp | B32: 30 | C32: ngày | D32: Cấp lô: BTP, thành phẩm | E32: demo_assumption
A34: Nguồn chuẩn: Nguong_SMEs_FOB_2023_2025 (1).xlsx; Nguong_SRS config_version fob.threshold.v3. Số liệu nguồn được giữ đủ độ chính xác; F01 là dữ liệu tạo sinh riêng.
A38: Chỉ tiêu | B38: P10 ngành | C38: P25 ngành | D38: P50 ngành | E38: P75 ngành | F38: P90 ngành | G38: Trung vị nhỏ–vừa FOB | H38: Trung vị FOB | I38: p-value | J38: Hệ số quy mô
A39: DSO | B39: 25.769231 | C39: 34.408949 | D39: 43.247052 | E39: 58.207139 | F39: 66.263266 | G39: 36.135937 | H39: 43.247052 | I39: 0.17146021 | J39: =IF(I39<0.05,MIN(3,MAX(0.1,G39/H39)),1) -> 1
A40: DIO | B40: 33.857892 | C40: 57.276635 | D40: 69.751755 | E40: 86.118055 | F40: 137.96515 | G40: 75.804937 | H40: 69.751755 | I40: 0.28749542 | J40: =IF(I40<0.05,MIN(3,MAX(0.1,G40/H40)),1) -> 1
A41: DPO | B41: 14.892653 | C41: 19.375703 | D41: 34.262287 | E41: 68.309204 | F41: 88.215245 | G41: 29.967555 | H41: 34.262287 | I41: 0.59485342 | J41: =IF(I41<0.05,MIN(3,MAX(0.1,G41/H41)),1) -> 1
A42: Cash | B42: 0.044512172 | C42: 0.083007995 | D42: 0.11883177 | E42: 0.18340151 | F42: 0.29840026 | G42: 0.11797957 | H42: 0.11883177 | I42: 0.4474117 | J42: =IF(I42<0.05,MIN(3,MAX(0.1,G42/H42)),1) -> 1
A45: Ngưỡng FOB tính lại | B45: Giá trị | C45: Cách đọc
A46: DSO theo dõi | B46: =E39*J39*B28 -> 58.207139 | C46: P75 DSO FOB × hệ số quy mô × mùa vụ
A47: DSO nghiêm trọng | B47: =F39*J39*B28 -> 66.263266 | C47: P90 DSO FOB × hệ số quy mô × mùa vụ
A48: DIO theo dõi | B48: =E40*J40*B28 -> 86.118055 | C48: P75 DIO FOB × hệ số quy mô × mùa vụ
A49: DIO nghiêm trọng | B49: =F40*J40*B28 -> 137.96515 | C49: P90 DIO FOB × hệ số quy mô × mùa vụ
A50: DPO thấp | B50: =B41*J41 -> 14.892653 | C50: P10 DPO FOB × hệ số quy mô
A51: DPO cao (thông tin) | B51: =E41*J41 -> 68.309204 | C51: P75 DPO FOB × hệ số quy mô
A52: Tiền mỏng (tỷ lệ năm) | B52: =C42*J42 -> 0.083007995 | C52: P25 (Tiền+ĐTNH)/DT FOB × hệ số quy mô
A53: L – giới hạn dưới (VND) | B53: =D_F01!B15 -> 5.5645463e+09 | C53: L = MAX(tỷ lệ tiền ngành × TTM; sàn chủ DN)
A54: Z – mức tiền mục tiêu (VND) | B54: =D_F01!B16 -> 6.8559659e+09 | C54: Z = L + S/3; đơn vị VND
A55: H – giới hạn trên (VND) | B55: =D_F01!B17 -> 9.4388051e+09 | C55: H = L + S; đơn vị VND
A59: Quy tắc | B59: Giá trị / phép tính | C59: Phạm vi
A60: Mức trọng yếu | B60: =B23 -> 0.05 | C60: 5% TSNH, owner_policy
A61: Nghiêm trọng tự nâng W2 | B61: =B24 -> 1 | C61: Cờ 1 đúng B4 nguồn
A62: Cảnh báo trong vùng | B62: 0 | C62: L ≤ Tiền ≤ H: không phát cảnh báo thiếu
A63: Cảnh báo thiếu | B63: 3 | C63: Tiền < L: Đỏ; tiền âm ghi riêng
A64: Điều kiện thiếu | B64: Cash < L | C64: Mức cần bổ sung = Z − Cash khi dưới L
A65: Số ngày kích hoạt dư | B65: 1 | C65: Có ngày Cash > H; không yêu cầu 14 ngày theo file ngưỡng
A66: Lô NVL/HH chậm | B66: =B31 -> 60 | C66: Ngày, demo_assumption
A67: Lô BTP/TP chậm | B67: =B32 -> 30 | C67: Ngày, demo_assumption
A68: Rho cảnh báo | B68: =B29 -> 0.5 | C68: Theo hợp đồng, không thay W ngành
A69: Rho nghiêm trọng | B69: =B30 -> 1 | C69: Theo hợp đồng, không thay W ngành
A73: W / trạng thái tiền | B73: TH01 Thiếu: Tiền < L | C73: TH02 Thừa: Tiền > H | D73: L ≤ Tiền ≤ H: theo dõi
A74: W0 | B74: M1 | C74: M2 | D74: Không gán ô, không hành động
A75: W1 | B75: M3 | C75: M4 | D75: Không gán ô, không hành động
A76: W2 | B76: M5 | C76: M6 | D76: Không gán ô, không hành động
A80: Miller–Orr cho F01 | B80: Giá trị | C80: Đơn vị / cách tính | D80: Nguồn
A81: Số ngày lịch sử | B81: =COUNT(D_flows!A65:A245) -> 181 | C81: ngày | D81: D_flows; đủ ngày không đồng nghĩa có giao dịch mỗi ngày
A82: σ ngày của DN | B82: =STDEV(D_flows!E65:E245) -> 6.1132309e+08 | C82: VND/ngày | D82: Dòng tiền ròng đã loại chuyển nội bộ
A83: σ ngày áp dụng | B83: =IF(B81>=B9,B82,B8*D_F01!B21) -> 6.1132309e+08 | C83: VND/ngày | D83: Ưu tiên lịch sử DN; dự phòng ngành theo cấu hình nguồn
A84: Nguồn σ | B84: =IF(B81>=B9,"firm_daily","industry_proxy") -> firm_daily | C84: enum | D84: Cửa sổ tối đa 3 năm trước AsOf
A85: Lãi suất ngày | B85: =B11/B12 -> 0.00013013699 | C85: tỷ lệ/ngày | D85: Lãi suất năm / 365
A86: Khoảng dao động S | B86: =3*(0.75*B10*B83^2/B85)^(1/3) -> 3.8742588e+09 | C86: VND | D86: Miller–Orr: 3 × căn bậc ba(3Fσ²/4r)
A87: Giới hạn dưới L | B87: =D_F01!B15 -> 5.5645463e+09 | C87: VND | D87: Chặn dưới bởi chính sách DN
A88: Mục tiêu Z | B88: =D_F01!B16 -> 6.8559659e+09 | C88: VND | D88: L+S/3
A89: Giới hạn trên H | B89: =D_F01!B17 -> 9.4388051e+09 | C89: VND | D89: L+S = 3Z−2L
A90: Doanh thu TTM | B90: =D_F01!B21 -> 133127509083 | C90: VND | D90: Doanh thu 12 tháng kết thúc AsOf, dữ liệu tạo sinh
A91: Mức tiền bình quân mô hình | B91: =(4*B88-B87)/3 -> 7.2864391e+09 | C91: VND | D91: Không dùng làm ngưỡng phân loại
A92: Cấu hình | B92: fob.threshold.v3 | C92: Nguồn: Nguong_SRS | D92: Giả định DN luôn tải đủ dữ liệu; W0/W1/W2
A93: Ưu tiên trạng thái trong horizon | B93: Thiếu trước; nếu không thiếu thì xét thừa | C93: Quy ước tổng hợp triển khai | D93: Theo ngày vẫn lưu cả hai loại tín hiệu
A94: Đơn vị tiền | B94: VND; giữ số thập phân tính toán | C94: Chỉ làm tròn khi hiển thị | D94: Không cộng thiếu qua các ngày
A97: Căn cứ và phạm vi | B97: Giá trị | C97: Cách sử dụng | D97: Giới hạn
A98: Mẫu ngành | B98: 20 | C98: DN may FOB | D98: Không coi mọi DN niêm yết là SME pháp lý
A99: Số quan sát tỷ số | B99: 60 | C99: 2023–2025 | D99: Mỗi DN tối đa 3 năm
A100: Biến động tiền | B100: 40 | C100: 2024–2025 | D100: Proxy năm không phải dữ liệu dòng tiền ngày
A101: Quy mô nhỏ–vừa | B101: 1500000000000 | C101: Ranh giới doanh thu kiểm định | D101: Không thay định nghĩa SME pháp lý
A102: Phân vị | B102: P50 / P75 / P90 | C102: Tham chiếu / Có nguy cơ / Trầm trọng | D102: DPO thấp P10; tiền mỏng P25
A103: Hệ số quy mô | B103: 1 | C103: p-value từ B2 của nguồn | D103: Chưa tìm thấy khác biệt ở mức 5%
A104: Hệ số mùa vụ | B104: 1 | C104: Chưa hiệu chỉnh | D104: Không suy ra mùa vụ từ dữ liệu năm
A105: Trọng yếu | B105: 0.05 | C105: MAX(vốn AR vượt; vốn INV vượt)/TSNH | D105: owner_policy, chưa tối ưu hóa thống kê
A106: DPO cao | B106: Chỉ thông tin | C106: Không tự nâng W | D106: Kiểm tra quá hạn ở cấp hóa đơn
A107: Tiền ngành và tiền UC01 | B107: Tiền/DT khác (Tiền+ĐTNH)/DT | C107: L dùng Tiền/DT; R-AP-1 dùng Tiền+ĐTNH | D107: Không trộn hai mẫu số/chỉ tiêu
A108: Dữ liệu F01 | B108: Tạo sinh FOB | C108: Tự mua vải, phụ liệu; sở hữu NVL/BTP/TP | D108: Không sử dụng số liệu doanh nghiệp có thật
A109: Nguồn giá F, r | B109: Giả định demo theo file ngưỡng | C109: Chủ DN xác nhận khi dùng thật | D109: Không trình bày như báo giá ngân hàng
A112: Tham số nguồn | B112: Tên | C112: Giá trị | D112: Đơn vị | E112: Căn cứ
A113: P1 | B113: Phân vị mức THAM CHIẾU (bình thường) | C113: 0.5 | D113: phân vị | E113: Trung vị ngành FOB: một nửa năm–DN FOB có số ngày thấp hơn.
A114: P2 | B114: Phân vị ngưỡng CÓ NGUY CƠ (theo dõi) | C114: 0.75 | D114: phân vị | E114: Cao hơn 75% năm–DN FOB → UC01 mức “Có nguy cơ”.
A115: P3 | B115: Phân vị ngưỡng TRẦM TRỌNG | C115: 0.9 | D115: phân vị | E115: Thập phân vị cao nhất ngành FOB → UC01 mức “Thiếu trầm trọng”.
A116: P4 | B116: Phân vị DPO THẤP (NCC gần như không cho nợ) | C116: 0.1 | D116: phân vị | E116: Chỉ là tín hiệu khi đi kèm tiền mỏng (P5) – quy tắc có điều kiện.
A117: P5 | B117: Phân vị ĐỆM TIỀN mỏng ((Tiền + ĐTNH) / Doanh thu) | C117: 0.25 | D117: phân vị | E117: Đệm tiền thấp hơn 75% năm–DN FOB.
A118: P6 | B118: Mức TRỌNG YẾU: vốn vượt ngưỡng có nguy cơ / Tài sản ngắn hạn | C118: 0.05 | D118: tỷ lệ | E118: Chính sách chủ DN duyệt (materiality_share). Độ nhạy ở B5_KiemDinh.
A119: P7 | B119: Vượt ngưỡng TRẦM TRỌNG thì xếp W2 dù chưa đạt trọng yếu (1 = có) | C119: 1 | D119: cờ | E119: Một khoản ở thập phân vị cao nhất ngành đã là điểm nghẽn.
A120: P8 | B120: Doanh thu tối thiểu để coi là đang hoạt động | C120: 50000000000 | D120: đồng | E120: Loại năm gần như ngừng hoạt động (G20, MPT, GMC, VTI trong 2023–2025): số ngày khi đó vô nghĩa.
A121: P9 | B121: Ranh giới nhóm quy mô Nhỏ–vừa / Lớn (doanh thu) | C121: 1500000000000 | D121: đồng | E121: Chia nhóm để kiểm định biến điều tiết quy mô.
...

Sheet F01_UC1
A2: F01 Chẩn đoán tại 30/06/2026
A4: Chỉ tiêu | B4: Giá trị | C4: Cách tính / giới hạn | D4: Đơn vị
A5: Doanh thu | B5: =D_F01!B9 -> 69627509083 | C5: Rev = financials.revenue_vnd | D5: VND
A6: Giá vốn | B6: =D_F01!B10 -> 5.7094557e+10 | C6: COGS = financials.cogs_vnd | D6: VND
A7: Số ngày kỳ | B7: =D_F01!B8 -> 181 | C7: Ngày cuối − ngày đầu +1 | D7: Ngày
A8: Phải thu | B8: =SUM(D_sales!N5:N121) -> 24915591245 | C8: AR = tổng dư hóa đơn bán mở | D8: VND
A9: Tồn sở hữu | B9: =SUM(D_inventory!P5:P40) -> 2.5064351e+10 | C9: INV = tổng giá trị lô thuộc F01 | D9: VND
A10: Phải trả | B10: =SUM(D_purchases!O5:O139) -> 8393038071 | C10: AP = tổng dư hóa đơn mua mở | D10: VND
A11: Tổng mua kỳ | B11: =SUM(D_purchases!G5:G139) -> 42021300381 | C11: PUR; không bằng giá vốn do có lao động và chi phí sản xuất | D11: VND
A12: DSO | B12: =B8/B5*B7 -> 64.769257 | C12: AR / Rev × N | D12: Ngày
A13: DIO | B13: =B9/B6*B7 -> 79.458494 | C13: INV / COGS × N | D13: Ngày
A14: DPO | B14: =B10/B6*B7 -> 26.607438 | C14: AP / COGS × N | D14: Ngày
A15: CCC | B15: =B12+B13-B14 -> 117.62031 | C15: DSO + DIO − DPO | D15: Ngày
A16: Vốn thương mại ròng | B16: =B8+B9-B10 -> 4.1586904e+10 | C16: AR + INV − AP; không phải tiền mặt | D16: VND
A17: Phải thu quá hạn | B17: =SUMIFS(D_sales!N5:N121,D_sales!O5:O121,">0") -> 9778180962 | C17: Chỉ phần đã đến hạn chưa trả | D17: VND
A18: Phải trả quá hạn | B18: =SUMIFS(D_purchases!O5:O139,D_purchases!P5:P139,">0") -> 979364994 | C18: Không tự suy NCC ngừng cung ứng | D18: VND
A19: Tồn lâu hoặc đơn hủy | B19: =SUMPRODUCT(D_inventory!P5:P40,D_inventory!S5:S40) -> 5.4412576e+09 | C19: Hợp của hai cờ; không cộng trùng | D19: VND
A20: Tồn thuộc khách hàng | B20: =SUM(D_inventory!O5:O40)-B9 -> 0 | C20: Loại khỏi INV, TWC và TSNH | D20: VND
A21: Tài sản ngắn hạn | B21: =D_F01!B11+D_F01!B13+D_F01!B14+B8+B9 -> 5.9381868e+10 | C21: Tiền + ĐTNH + tài sản khác + AR + INV | D21: VND
A22: Mức AR | B22: =IF(B12>Nguong!B47,2,IF(B12>Nguong!B46,1,0)) -> 1 | C22: So ngưỡng FOB 2023–2025, chưa làm tròn | D22: 0/1/2
A23: Mức INV | B23: =IF(B13>Nguong!B49,2,IF(B13>Nguong!B48,1,0)) -> 0 | C23: So ngưỡng FOB 2023–2025 | D23: 0/1/2
A24: Doanh thu năm tham chiếu | B24: =D_F01!B21 -> 133127509083 | C24: Doanh thu TTM tạo sinh đã đủ; không quy đổi kỳ ngắn | D24: VND
A25: Tỷ lệ tiền trên TTM | B25: =(D_F01!B11+D_F01!B13)/B24 -> 0.048088678 | C25: (Tiền + ĐTNH) / doanh thu TTM | D25: Tỷ lệ
A26: Tín hiệu AP | B26: =IF(AND(B14<Nguong!B50,B25<Nguong!B52),1,0) -> 0 | C26: DPO thấp đồng thời tiền mỏng | D26: 0/1
A27: Vốn AR vượt ngưỡng | B27: =MAX(0,B12-Nguong!B46)*B5/B7 -> 2.5243312e+09 | C27: MAX(DSO − DSOWatch;0) × Rev/N | D27: VND
A28: Vốn tồn vượt ngưỡng | B28: =MAX(0,B13-Nguong!B48)*B6/B7 -> 0 | C28: MAX(DIO − DIOWatch;0) × COGS/N | D28: VND
A29: Tỷ lệ trọng yếu | B29: =MAX(B27,B28)/B21 -> 0.042510134 | C29: MAX(vốn AR vượt; vốn tồn vượt) / TSNH | D29: Tỷ lệ
A30: Phân lớp W | B30: =IF(OR(AND(Nguong!B24=1,MAX(B22,B23)=2),AND(MAX(B22,B23)>=1,B29>=Nguong!B23)),"W2",IF(OR(MAX(B22,B23)>=1,B26=1),"W1","W0")) -> W1 | C30: W0 An toàn / W1 Có nguy cơ / W2 Thiếu trầm trọng; giả định đủ dữ liệu | D30: Enum
A31: Vốn vượt tổng | B31: =B27+B28 -> 2.5243312e+09 | C31: Không cộng vào dòng thu hay mức thiếu UC02 | D31: VND
A32: Lô sở hữu lưu lâu nhất | B32: =_xlfn.MAXIFS(D_inventory!N5:N40,D_inventory!E5:E40,"F01") -> 238 | C32: Lưu kho có thể trước đầu kỳ | D32: Ngày
A33: Mô hình / trạng thái | B33: FOB / provisional | C33: Số dư cuối kỳ 181 ngày khác bình quân năm của ngành | D33: Nhãn
A40: Khách | B40: Tên | C40: Phải thu | D40: Tỷ trọng AR | E40: Góp DSO | F40: Quá hạn tổng | G40: 1–30 ngày | H40: 31–60 ngày | I40: >60 ngày | J40: MaxDPD | K40: Trễ có dấu 180d | L40: Trễ dương 180d | M40: Số hóa đơn đã thu | N40: Kỳ hạn hợp đồng | O40: Quan hệ demo
A41: BYR-F01-002 | B41: =D_F01!B38 -> Khách mua FOB Lớn K1 | C41: =SUMIFS(D_sales!$N$5:$N$121,D_sales!$C$5:$C$121,A41) -> 13893078293 | D41: =IF($B$8>0,C41/$B$8,0) -> 0.5576058 | E41: =C41/$B$5*$B$7 -> 36.115714 | F41: =SUMIFS(D_sales!$N$5:$N$121,D_sales!$C$5:$C$121,A41,D_sales!$O$5:$O$121,">0") -> 4187759307 | G41: =SUMIFS(D_sales!$N$5:$N$121,D_sales!$C$5:$C$121,A41,D_sales!$O$5:$O$121,">0",D_sales!$O$5:$O$121,"<=30") -> 4187759307 | H41: =SUMIFS(D_sales!$N$5:$N$121,D_sales!$C$5:$C$121,A41,D_sales!$O$5:$O$121,">30",D_sales!$O$5:$O$121,"<=60") -> 0 | I41: =SUMIFS(D_sales!$N$5:$N$121,D_sales!$C$5:$C$121,A41,D_sales!$O$5:$O$121,">60",D_sales!$O$5:$O$121,"<=9999") -> 0 | J41: =_xlfn.MAXIFS(D_sales!$O$5:$O$121,D_sales!$C$5:$C$121,A41) -> 21 | K41: =IF(SUMIFS(D_sales!$T$5:$T$121,D_sales!$C$5:$C$121,A41)=0,"n.a.",SUMIFS(D_sales!$Z$5:$Z$121,D_sales!$C$5:$C$121,A41)/SUMIFS(D_sales!$T$5:$T$121,D_sales!$C$5:$C$121,A41)) -> 19.157777 | L41: =IF(SUMIFS(D_sales!$T$5:$T$121,D_sales!$C$5:$C$121,A41)=0,"n.a.",SUMIFS(D_sales!$S$5:$S$121,D_sales!$C$5:$C$121,A41)/SUMIFS(D_sales!$T$5:$T$121,D_sales!$C$5:$C$121,A41)) -> 19.157777 | M41: =COUNTIFS(D_sales!$C$5:$C$121,A41,D_sales!$R$5:$R$121,1) -> 16 | N41: =IF(SUMIFS(D_sales!$T$5:$T$121,D_sales!$C$5:$C$121,A41)=0,"n.a.",SUMIFS(D_sales!$AA$5:$AA$121,D_sales!$C$5:$C$121,A41)/SUMIFS(D_sales!$T$5:$T$121,D_sales!$C$5:$C$121,A41)) -> 45 | O41: =IF(D_F01!$B$7-_xlfn.MINIFS(D_sales!$G$5:$G$121,D_sales!$C$5:$C$121,A41)+1<=60,"Mới",IF(AND(COUNTIF(D_sales!$C$5:$C$121,A41)>=12,6>=4),"Thường xuyên","Vãng lai")) -> Thường xuyên
A42: BYR-F01-001 | B42: =D_F01!B39 -> Khách mua FOB K2 | C42: =SUMIFS(D_sales!$N$5:$N$121,D_sales!$C$5:$C$121,A42) -> 4870640111 | D42: =IF($B$8>0,C42/$B$8,0) -> 0.19548563 | E42: =C42/$B$5*$B$7 -> 12.661459 | F42: =SUMIFS(D_sales!$N$5:$N$121,D_sales!$C$5:$C$121,A42,D_sales!$O$5:$O$121,">0") -> 1998889941 | G42: =SUMIFS(D_sales!$N$5:$N$121,D_sales!$C$5:$C$121,A42,D_sales!$O$5:$O$121,">0",D_sales!$O$5:$O$121,"<=30") -> 1998889941 | H42: =SUMIFS(D_sales!$N$5:$N$121,D_sales!$C$5:$C$121,A42,D_sales!$O$5:$O$121,">30",D_sales!$O$5:$O$121,"<=60") -> 0 | I42: =SUMIFS(D_sales!$N$5:$N$121,D_sales!$C$5:$C$121,A42,D_sales!$O$5:$O$121,">60",D_sales!$O$5:$O$121,"<=9999") -> 0 | J42: =_xlfn.MAXIFS(D_sales!$O$5:$O$121,D_sales!$C$5:$C$121,A42) -> 7 | K42: =IF(SUMIFS(D_sales!$T$5:$T$121,D_sales!$C$5:$C$121,A42)=0,"n.a.",SUMIFS(D_sales!$Z$5:$Z$121,D_sales!$C$5:$C$121,A42)/SUMIFS(D_sales!$T$5:$T$121,D_sales!$C$5:$C$121,A42)) -> -1.1383316 | L42: =IF(SUMIFS(D_sales!$T$5:$T$121,D_sales!$C$5:$C$121,A42)=0,"n.a.",SUMIFS(D_sales!$S$5:$S$121,D_sales!$C$5:$C$121,A42)/SUMIFS(D_sales!$T$5:$T$121,D_sales!$C$5:$C$121,A42)) -> 1.1151265 | M42: =COUNTIFS(D_sales!$C$5:$C$121,A42,D_sales!$R$5:$R$121,1) -> 24 | N42: =IF(SUMIFS(D_sales!$T$5:$T$121,D_sales!$C$5:$C$121,A42)=0,"n.a.",SUMIFS(D_sales!$AA$5:$AA$121,D_sales!$C$5:$C$121,A42)/SUMIFS(D_sales!$T$5:$T$121,D_sales!$C$5:$C$121,A42)) -> 30 | O42: =IF(D_F01!$B$7-_xlfn.MINIFS(D_sales!$G$5:$G$121,D_sales!$C$5:$C$121,A42)+1<=60,"Mới",IF(AND(COUNTIF(D_sales!$C$5:$C$121,A42)>=12,6>=4),"Thường xuyên","Vãng lai")) -> Thường xuyên
A43: BYR-F01-005 | B43: =D_F01!B40 -> Nhà mua hàng FOB K5 | C43: =SUMIFS(D_sales!$N$5:$N$121,D_sales!$C$5:$C$121,A43) -> 2247943156 | D43: =IF($B$8>0,C43/$B$8,0) -> 0.090222348 | E43: =C43/$B$5*$B$7 -> 5.8436345 | F43: =SUMIFS(D_sales!$N$5:$N$121,D_sales!$C$5:$C$121,A43,D_sales!$O$5:$O$121,">0") -> 1323908589 | G43: =SUMIFS(D_sales!$N$5:$N$121,D_sales!$C$5:$C$121,A43,D_sales!$O$5:$O$121,">0",D_sales!$O$5:$O$121,"<=30") -> 0 | H43: =SUMIFS(D_sales!$N$5:$N$121,D_sales!$C$5:$C$121,A43,D_sales!$O$5:$O$121,">30",D_sales!$O$5:$O$121,"<=60") -> 0 | I43: =SUMIFS(D_sales!$N$5:$N$121,D_sales!$C$5:$C$121,A43,D_sales!$O$5:$O$121,">60",D_sales!$O$5:$O$121,"<=9999") -> 1323908589 | J43: =_xlfn.MAXIFS(D_sales!$O$5:$O$121,D_sales!$C$5:$C$121,A43) -> 77 | K43: =IF(SUMIFS(D_sales!$T$5:$T$121,D_sales!$C$5:$C$121,A43)=0,"n.a.",SUMIFS(D_sales!$Z$5:$Z$121,D_sales!$C$5:$C$121,A43)/SUMIFS(D_sales!$T$5:$T$121,D_sales!$C$5:$C$121,A43)) -> 5.3203879 | L43: =IF(SUMIFS(D_sales!$T$5:$T$121,D_sales!$C$5:$C$121,A43)=0,"n.a.",SUMIFS(D_sales!$S$5:$S$121,D_sales!$C$5:$C$121,A43)/SUMIFS(D_sales!$T$5:$T$121,D_sales!$C$5:$C$121,A43)) -> 5.3203879 | M43: =COUNTIFS(D_sales!$C$5:$C$121,A43,D_sales!$R$5:$R$121,1) -> 15 | N43: =IF(SUMIFS(D_sales!$T$5:$T$121,D_sales!$C$5:$C$121,A43)=0,"n.a.",SUMIFS(D_sales!$AA$5:$AA$121,D_sales!$C$5:$C$121,A43)/SUMIFS(D_sales!$T$5:$T$121,D_sales!$C$5:$C$121,A43)) -> 30 | O43: =IF(D_F01!$B$7-_xlfn.MINIFS(D_sales!$G$5:$G$121,D_sales!$C$5:$C$121,A43)+1<=60,"Mới",IF(AND(COUNTIF(D_sales!$C$5:$C$121,A43)>=12,6>=4),"Thường xuyên","Vãng lai")) -> Thường xuyên
A44: BYR-F01-006 | B44: =D_F01!B41 -> Thương hiệu thời trang theo mùa K6 | C44: =SUMIFS(D_sales!$N$5:$N$121,D_sales!$C$5:$C$121,A44) -> 2599202710 | D44: =IF($B$8>0,C44/$B$8,0) -> 0.10432033 | E44: =C44/$B$5*$B$7 -> 6.7567503 | F44: =SUMIFS(D_sales!$N$5:$N$121,D_sales!$C$5:$C$121,A44,D_sales!$O$5:$O$121,">0") -> 1909998793 | G44: =SUMIFS(D_sales!$N$5:$N$121,D_sales!$C$5:$C$121,A44,D_sales!$O$5:$O$121,">0",D_sales!$O$5:$O$121,"<=30") -> 1909998793 | H44: =SUMIFS(D_sales!$N$5:$N$121,D_sales!$C$5:$C$121,A44,D_sales!$O$5:$O$121,">30",D_sales!$O$5:$O$121,"<=60") -> 0 | I44: =SUMIFS(D_sales!$N$5:$N$121,D_sales!$C$5:$C$121,A44,D_sales!$O$5:$O$121,">60",D_sales!$O$5:$O$121,"<=9999") -> 0 | J44: =_xlfn.MAXIFS(D_sales!$O$5:$O$121,D_sales!$C$5:$C$121,A44) -> 3 | K44: =IF(SUMIFS(D_sales!$T$5:$T$121,D_sales!$C$5:$C$121,A44)=0,"n.a.",SUMIFS(D_sales!$Z$5:$Z$121,D_sales!$C$5:$C$121,A44)/SUMIFS(D_sales!$T$5:$T$121,D_sales!$C$5:$C$121,A44)) -> 0.59609935 | L44: =IF(SUMIFS(D_sales!$T$5:$T$121,D_sales!$C$5:$C$121,A44)=0,"n.a.",SUMIFS(D_sales!$S$5:$S$121,D_sales!$C$5:$C$121,A44)/SUMIFS(D_sales!$T$5:$T$121,D_sales!$C$5:$C$121,A44)) -> 1.510146 | M44: =COUNTIFS(D_sales!$C$5:$C$121,A44,D_sales!$R$5:$R$121,1) -> 8 | N44: =IF(SUMIFS(D_sales!$T$5:$T$121,D_sales!$C$5:$C$121,A44)=0,"n.a.",SUMIFS(D_sales!$AA$5:$AA$121,D_sales!$C$5:$C$121,A44)/SUMIFS(D_sales!$T$5:$T$121,D_sales!$C$5:$C$121,A44)) -> 36.389243 | O44: =IF(D_F01!$B$7-_xlfn.MINIFS(D_sales!$G$5:$G$121,D_sales!$C$5:$C$121,A44)+1<=60,"Mới",IF(AND(COUNTIF(D_sales!$C$5:$C$121,A44)>=12,5>=4),"Thường xuyên","Vãng lai")) -> Vãng lai
A45: BYR-F01-003 | B45: =D_F01!B42 -> Thương hiệu nội địa K3 | C45: =SUMIFS(D_sales!$N$5:$N$121,D_sales!$C$5:$C$121,A45) -> 617202404 | D45: =IF($B$8>0,C45/$B$8,0) -> 0.024771734 | E45: =C45/$B$5*$B$7 -> 1.6044468 | F45: =SUMIFS(D_sales!$N$5:$N$121,D_sales!$C$5:$C$121,A45,D_sales!$O$5:$O$121,">0") -> 0 | G45: =SUMIFS(D_sales!$N$5:$N$121,D_sales!$C$5:$C$121,A45,D_sales!$O$5:$O$121,">0",D_sales!$O$5:$O$121,"<=30") -> 0 | H45: =SUMIFS(D_sales!$N$5:$N$121,D_sales!$C$5:$C$121,A45,D_sales!$O$5:$O$121,">30",D_sales!$O$5:$O$121,"<=60") -> 0 | I45: =SUMIFS(D_sales!$N$5:$N$121,D_sales!$C$5:$C$121,A45,D_sales!$O$5:$O$121,">60",D_sales!$O$5:$O$121,"<=9999") -> 0 | J45: =_xlfn.MAXIFS(D_sales!$O$5:$O$121,D_sales!$C$5:$C$121,A45) -> 0 | K45: =IF(SUMIFS(D_sales!$T$5:$T$121,D_sales!$C$5:$C$121,A45)=0,"n.a.",SUMIFS(D_sales!$Z$5:$Z$121,D_sales!$C$5:$C$121,A45)/SUMIFS(D_sales!$T$5:$T$121,D_sales!$C$5:$C$121,A45)) -> 1.8759103 | L45: =IF(SUMIFS(D_sales!$T$5:$T$121,D_sales!$C$5:$C$121,A45)=0,"n.a.",SUMIFS(D_sales!$S$5:$S$121,D_sales!$C$5:$C$121,A45)/SUMIFS(D_sales!$T$5:$T$121,D_sales!$C$5:$C$121,A45)) -> 2.0202039 | M45: =COUNTIFS(D_sales!$C$5:$C$121,A45,D_sales!$R$5:$R$121,1) -> 13 | N45: =IF(SUMIFS(D_sales!$T$5:$T$121,D_sales!$C$5:$C$121,A45)=0,"n.a.",SUMIFS(D_sales!$AA$5:$AA$121,D_sales!$C$5:$C$121,A45)/SUMIFS(D_sales!$T$5:$T$121,D_sales!$C$5:$C$121,A45)) -> 30 | O45: =IF(D_F01!$B$7-_xlfn.MINIFS(D_sales!$G$5:$G$121,D_sales!$C$5:$C$121,A45)+1<=60,"Mới",IF(AND(COUNTIF(D_sales!$C$5:$C$121,A45)>=12,5>=4),"Thường xuyên","Vãng lai")) -> Thường xuyên
A46: BYR-F01-007 | B46: =D_F01!B43 -> Đại lý vãng lai K7 | C46: =SUMIFS(D_sales!$N$5:$N$121,D_sales!$C$5:$C$121,A46) -> 0 | D46: =IF($B$8>0,C46/$B$8,0) -> 0 | E46: =C46/$B$5*$B$7 -> 0 | F46: =SUMIFS(D_sales!$N$5:$N$121,D_sales!$C$5:$C$121,A46,D_sales!$O$5:$O$121,">0") -> 0 | G46: =SUMIFS(D_sales!$N$5:$N$121,D_sales!$C$5:$C$121,A46,D_sales!$O$5:$O$121,">0",D_sales!$O$5:$O$121,"<=30") -> 0 | H46: =SUMIFS(D_sales!$N$5:$N$121,D_sales!$C$5:$C$121,A46,D_sales!$O$5:$O$121,">30",D_sales!$O$5:$O$121,"<=60") -> 0 | I46: =SUMIFS(D_sales!$N$5:$N$121,D_sales!$C$5:$C$121,A46,D_sales!$O$5:$O$121,">60",D_sales!$O$5:$O$121,"<=9999") -> 0 | J46: =_xlfn.MAXIFS(D_sales!$O$5:$O$121,D_sales!$C$5:$C$121,A46) -> 0 | K46: =IF(SUMIFS(D_sales!$T$5:$T$121,D_sales!$C$5:$C$121,A46)=0,"n.a.",SUMIFS(D_sales!$Z$5:$Z$121,D_sales!$C$5:$C$121,A46)/SUMIFS(D_sales!$T$5:$T$121,D_sales!$C$5:$C$121,A46)) -> 1.19485 | L46: =IF(SUMIFS(D_sales!$T$5:$T$121,D_sales!$C$5:$C$121,A46)=0,"n.a.",SUMIFS(D_sales!$S$5:$S$121,D_sales!$C$5:$C$121,A46)/SUMIFS(D_sales!$T$5:$T$121,D_sales!$C$5:$C$121,A46)) -> 2.4512708 | M46: =COUNTIFS(D_sales!$C$5:$C$121,A46,D_sales!$R$5:$R$121,1) -> 3 | N46: =IF(SUMIFS(D_sales!$T$5:$T$121,D_sales!$C$5:$C$121,A46)=0,"n.a.",SUMIFS(D_sales!$AA$5:$AA$121,D_sales!$C$5:$C$121,A46)/SUMIFS(D_sales!$T$5:$T$121,D_sales!$C$5:$C$121,A46)) -> 30 | O46: =IF(D_F01!$B$7-_xlfn.MINIFS(D_sales!$G$5:$G$121,D_sales!$C$5:$C$121,A46)+1<=60,"Mới",IF(AND(COUNTIF(D_sales!$C$5:$C$121,A46)>=12,3>=4),"Thường xuyên","Vãng lai")) -> Vãng lai
A47: BYR-F01-004 | B47: =D_F01!B44 -> Khách mới K4 | C47: =SUMIFS(D_sales!$N$5:$N$121,D_sales!$C$5:$C$121,A47) -> 604815984 | D47: =IF($B$8>0,C47/$B$8,0) -> 0.024274599 | E47: =C47/$B$5*$B$7 -> 1.5722477 | F47: =SUMIFS(D_sales!$N$5:$N$121,D_sales!$C$5:$C$121,A47,D_sales!$O$5:$O$121,">0") -> 274915745 | G47: =SUMIFS(D_sales!$N$5:$N$121,D_sales!$C$5:$C$121,A47,D_sales!$O$5:$O$121,">0",D_sales!$O$5:$O$121,"<=30") -> 274915745 | H47: =SUMIFS(D_sales!$N$5:$N$121,D_sales!$C$5:$C$121,A47,D_sales!$O$5:$O$121,">30",D_sales!$O$5:$O$121,"<=60") -> 0 | I47: =SUMIFS(D_sales!$N$5:$N$121,D_sales!$C$5:$C$121,A47,D_sales!$O$5:$O$121,">60",D_sales!$O$5:$O$121,"<=9999") -> 0 | J47: =_xlfn.MAXIFS(D_sales!$O$5:$O$121,D_sales!$C$5:$C$121,A47) -> 29 | K47: =IF(SUMIFS(D_sales!$T$5:$T$121,D_sales!$C$5:$C$121,A47)=0,"n.a.",SUMIFS(D_sales!$Z$5:$Z$121,D_sales!$C$5:$C$121,A47)/SUMIFS(D_sales!$T$5:$T$121,D_sales!$C$5:$C$121,A47)) -> n.a. | L47: =IF(SUMIFS(D_sales!$T$5:$T$121,D_sales!$C$5:$C$121,A47)=0,"n.a.",SUMIFS(D_sales!$S$5:$S$121,D_sales!$C$5:$C$121,A47)/SUMIFS(D_sales!$T$5:$T$121,D_sales!$C$5:$C$121,A47)) -> n.a. | M47: =COUNTIFS(D_sales!$C$5:$C$121,A47,D_sales!$R$5:$R$121,1) -> 0 | N47: =IF(SUMIFS(D_sales!$T$5:$T$121,D_sales!$C$5:$C$121,A47)=0,"n.a.",SUMIFS(D_sales!$AA$5:$AA$121,D_sales!$C$5:$C$121,A47)/SUMIFS(D_sales!$T$5:$T$121,D_sales!$C$5:$C$121,A47)) -> n.a. | O47: =IF(D_F01!$B$7-_xlfn.MINIFS(D_sales!$G$5:$G$121,D_sales!$C$5:$C$121,A47)+1<=60,"Mới",IF(AND(COUNTIF(D_sales!$C$5:$C$121,A47)>=12,2>=4),"Thường xuyên","Vãng lai")) -> Mới
A48: BYR-F01-008 | B48: =D_F01!B45 -> Cửa hàng nhỏ K8 | C48: =SUMIFS(D_sales!$N$5:$N$121,D_sales!$C$5:$C$121,A48) -> 82708587 | D48: =IF($B$8>0,C48/$B$8,0) -> 0.0033195514 | E48: =C48/$B$5*$B$7 -> 0.21500488 | F48: =SUMIFS(D_sales!$N$5:$N$121,D_sales!$C$5:$C$121,A48,D_sales!$O$5:$O$121,">0") -> 82708587 | G48: =SUMIFS(D_sales!$N$5:$N$121,D_sales!$C$5:$C$121,A48,D_sales!$O$5:$O$121,">0",D_sales!$O$5:$O$121,"<=30") -> 0 | H48: =SUMIFS(D_sales!$N$5:$N$121,D_sales!$C$5:$C$121,A48,D_sales!$O$5:$O$121,">30",D_sales!$O$5:$O$121,"<=60") -> 0 | I48: =SUMIFS(D_sales!$N$5:$N$121,D_sales!$C$5:$C$121,A48,D_sales!$O$5:$O$121,">60",D_sales!$O$5:$O$121,"<=9999") -> 82708587 | J48: =_xlfn.MAXIFS(D_sales!$O$5:$O$121,D_sales!$C$5:$C$121,A48) -> 92 | K48: =IF(SUMIFS(D_sales!$T$5:$T$121,D_sales!$C$5:$C$121,A48)=0,"n.a.",SUMIFS(D_sales!$Z$5:$Z$121,D_sales!$C$5:$C$121,A48)/SUMIFS(D_sales!$T$5:$T$121,D_sales!$C$5:$C$121,A48)) -> 0 | L48: =IF(SUMIFS(D_sales!$T$5:$T$121,D_sales!$C$5:$C$121,A48)=0,"n.a.",SUMIFS(D_sales!$S$5:$S$121,D_sales!$C$5:$C$121,A48)/SUMIFS(D_sales!$T$5:$T$121,D_sales!$C$5:$C$121,A48)) -> 0 | M48: =COUNTIFS(D_sales!$C$5:$C$121,A48,D_sales!$R$5:$R$121,1) -> 3 | N48: =IF(SUMIFS(D_sales!$T$5:$T$121,D_sales!$C$5:$C$121,A48)=0,"n.a.",SUMIFS(D_sales!$AA$5:$AA$121,D_sales!$C$5:$C$121,A48)/SUMIFS(D_sales!$T$5:$T$121,D_sales!$C$5:$C$121,A48)) -> 30 | O48: =IF(D_F01!$B$7-_xlfn.MINIFS(D_sales!$G$5:$G$121,D_sales!$C$5:$C$121,A48)+1<=60,"Mới",IF(AND(COUNTIF(D_sales!$C$5:$C$121,A48)>=12,2>=4),"Thường xuyên","Vãng lai")) -> Vãng lai
A49: BYR-F01-009 | B49: =D_F01!B46 -> Khách ngừng mua K9 | C49: =SUMIFS(D_sales!$N$5:$N$121,D_sales!$C$5:$C$121,A49) -> 0 | D49: =IF($B$8>0,C49/$B$8,0) -> 0 | E49: =C49/$B$5*$B$7 -> 0 | F49: =SUMIFS(D_sales!$N$5:$N$121,D_sales!$C$5:$C$121,A49,D_sales!$O$5:$O$121,">0") -> 0 | G49: =SUMIFS(D_sales!$N$5:$N$121,D_sales!$C$5:$C$121,A49,D_sales!$O$5:$O$121,">0",D_sales!$O$5:$O$121,"<=30") -> 0 | H49: =SUMIFS(D_sales!$N$5:$N$121,D_sales!$C$5:$C$121,A49,D_sales!$O$5:$O$121,">30",D_sales!$O$5:$O$121,"<=60") -> 0 | I49: =SUMIFS(D_sales!$N$5:$N$121,D_sales!$C$5:$C$121,A49,D_sales!$O$5:$O$121,">60",D_sales!$O$5:$O$121,"<=9999") -> 0 | J49: =_xlfn.MAXIFS(D_sales!$O$5:$O$121,D_sales!$C$5:$C$121,A49) -> 0 | K49: =IF(SUMIFS(D_sales!$T$5:$T$121,D_sales!$C$5:$C$121,A49)=0,"n.a.",SUMIFS(D_sales!$Z$5:$Z$121,D_sales!$C$5:$C$121,A49)/SUMIFS(D_sales!$T$5:$T$121,D_sales!$C$5:$C$121,A49)) -> -2.58496 | L49: =IF(SUMIFS(D_sales!$T$5:$T$121,D_sales!$C$5:$C$121,A49)=0,"n.a.",SUMIFS(D_sales!$S$5:$S$121,D_sales!$C$5:$C$121,A49)/SUMIFS(D_sales!$T$5:$T$121,D_sales!$C$5:$C$121,A49)) -> 0 | M49: =COUNTIFS(D_sales!$C$5:$C$121,A49,D_sales!$R$5:$R$121,1) -> 2 | N49: =IF(SUMIFS(D_sales!$T$5:$T$121,D_sales!$C$5:$C$121,A49)=0,"n.a.",SUMIFS(D_sales!$AA$5:$AA$121,D_sales!$C$5:$C$121,A49)/SUMIFS(D_sales!$T$5:$T$121,D_sales!$C$5:$C$121,A49)) -> 30 | O49: =IF(D_F01!$B$7-_xlfn.MINIFS(D_sales!$G$5:$G$121,D_sales!$C$5:$C$121,A49)+1<=60,"Mới",IF(AND(COUNTIF(D_sales!$C$5:$C$121,A49)>=12,1>=4),"Thường xuyên","Vãng lai")) -> Vãng lai
A53: NCC | B53: Tên | C53: Phải trả | D53: Quá hạn | E53: 1–30 ngày | F53: 31–60 ngày | G53: >60 ngày | H53: MaxDPD | I53: Góp DPO | J53: Thiết yếu | K53: Chiết khấu hợp lệ | L53: Tiết kiệm (nếu đủ điều kiện)
A54: SUP-F01-001 | B54: =D_F01!B51 -> Nhà phân phối vải Beta | C54: =SUMIFS(D_purchases!$O$5:$O$139,D_purchases!$C$5:$C$139,A54) -> 2750066214 | D54: =SUMIFS(D_purchases!$O$5:$O$139,D_purchases!$C$5:$C$139,A54,D_purchases!$P$5:$P$139,">0") -> 0 | E54: =SUMIFS(D_purchases!$O$5:$O$139,D_purchases!$C$5:$C$139,A54,D_purchases!$P$5:$P$139,">0",D_purchases!$P$5:$P$139,"<=30") -> 0 | F54: =SUMIFS(D_purchases!$O$5:$O$139,D_purchases!$C$5:$C$139,A54,D_purchases!$P$5:$P$139,">30",D_purchases!$P$5:$P$139,"<=60") -> 0 | G54: =SUMIFS(D_purchases!$O$5:$O$139,D_purchases!$C$5:$C$139,A54,D_purchases!$P$5:$P$139,">60",D_purchases!$P$5:$P$139,"<=9999") -> 0 | H54: =_xlfn.MAXIFS(D_purchases!$P$5:$P$139,D_purchases!$C$5:$C$139,A54) -> 0 | I54: =C54/$B$6*$B$7 -> 8.7182037 | J54: =D_F01!C51 -> có | K54: =SUMIFS(D_purchases!$V$5:$V$139,D_purchases!$C$5:$C$139,A54) -> 2 | L54: =SUMIFS(D_purchases!$W$5:$W$139,D_purchases!$C$5:$C$139,A54) -> 21452622
A55: SUP-F01-002 | B55: =D_F01!B52 -> Bao bì – phụ liệu Gamma | C55: =SUMIFS(D_purchases!$O$5:$O$139,D_purchases!$C$5:$C$139,A55) -> 1624912040 | D55: =SUMIFS(D_purchases!$O$5:$O$139,D_purchases!$C$5:$C$139,A55,D_purchases!$P$5:$P$139,">0") -> 0 | E55: =SUMIFS(D_purchases!$O$5:$O$139,D_purchases!$C$5:$C$139,A55,D_purchases!$P$5:$P$139,">0",D_purchases!$P$5:$P$139,"<=30") -> 0 | F55: =SUMIFS(D_purchases!$O$5:$O$139,D_purchases!$C$5:$C$139,A55,D_purchases!$P$5:$P$139,">30",D_purchases!$P$5:$P$139,"<=60") -> 0 | G55: =SUMIFS(D_purchases!$O$5:$O$139,D_purchases!$C$5:$C$139,A55,D_purchases!$P$5:$P$139,">60",D_purchases!$P$5:$P$139,"<=9999") -> 0 | H55: =_xlfn.MAXIFS(D_purchases!$P$5:$P$139,D_purchases!$C$5:$C$139,A55) -> 0 | I55: =C55/$B$6*$B$7 -> 5.151263 | J55: =D_F01!C52 -> không | K55: =SUMIFS(D_purchases!$V$5:$V$139,D_purchases!$C$5:$C$139,A55) -> 0 | L55: =SUMIFS(D_purchases!$W$5:$W$139,D_purchases!$C$5:$C$139,A55) -> 0
A56: SUP-F01-003 | B56: =D_F01!B53 -> Chỉ – nút – khóa NCC4 | C56: =SUMIFS(D_purchases!$O$5:$O$139,D_purchases!$C$5:$C$139,A56) -> 462141816 | D56: =SUMIFS(D_purchases!$O$5:$O$139,D_purchases!$C$5:$C$139,A56,D_purchases!$P$5:$P$139,">0") -> 0 | E56: =SUMIFS(D_purchases!$O$5:$O$139,D_purchases!$C$5:$C$139,A56,D_purchases!$P$5:$P$139,">0",D_purchases!$P$5:$P$139,"<=30") -> 0 | F56: =SUMIFS(D_purchases!$O$5:$O$139,D_purchases!$C$5:$C$139,A56,D_purchases!$P$5:$P$139,">30",D_purchases!$P$5:$P$139,"<=60") -> 0 | G56: =SUMIFS(D_purchases!$O$5:$O$139,D_purchases!$C$5:$C$139,A56,D_purchases!$P$5:$P$139,">60",D_purchases!$P$5:$P$139,"<=9999") -> 0 | H56: =_xlfn.MAXIFS(D_purchases!$P$5:$P$139,D_purchases!$C$5:$C$139,A56) -> 0 | I56: =C56/$B$6*$B$7 -> 1.4650725 | J56: =D_F01!C53 -> có | K56: =SUMIFS(D_purchases!$V$5:$V$139,D_purchases!$C$5:$C$139,A56) -> 0 | L56: =SUMIFS(D_purchases!$W$5:$W$139,D_purchases!$C$5:$C$139,A56) -> 0
A57: SUP-F01-004 | B57: =D_F01!B54 -> Vận tải nội địa NCC5 | C57: =SUMIFS(D_purchases!$O$5:$O$139,D_purchases!$C$5:$C$139,A57) -> 432413861 | D57: =SUMIFS(D_purchases!$O$5:$O$139,D_purchases!$C$5:$C$139,A57,D_purchases!$P$5:$P$139,">0") -> 0 | E57: =SUMIFS(D_purchases!$O$5:$O$139,D_purchases!$C$5:$C$139,A57,D_purchases!$P$5:$P$139,">0",D_purchases!$P$5:$P$139,"<=30") -> 0 | F57: =SUMIFS(D_purchases!$O$5:$O$139,D_purchases!$C$5:$C$139,A57,D_purchases!$P$5:$P$139,">30",D_purchases!$P$5:$P$139,"<=60") -> 0 | G57: =SUMIFS(D_purchases!$O$5:$O$139,D_purchases!$C$5:$C$139,A57,D_purchases!$P$5:$P$139,">60",D_purchases!$P$5:$P$139,"<=9999") -> 0 | H57: =_xlfn.MAXIFS(D_purchases!$P$5:$P$139,D_purchases!$C$5:$C$139,A57) -> 0 | I57: =C57/$B$6*$B$7 -> 1.3708296 | J57: =D_F01!C54 -> không | K57: =SUMIFS(D_purchases!$V$5:$V$139,D_purchases!$C$5:$C$139,A57) -> 0 | L57: =SUMIFS(D_purchases!$W$5:$W$139,D_purchases!$C$5:$C$139,A57) -> 0
A58: SUP-F01-005 | B58: =D_F01!B55 -> Xưởng thêu – in ngoài NCC6 | C58: =SUMIFS(D_purchases!$O$5:$O$139,D_purchases!$C$5:$C$139,A58) -> 925742208 | D58: =SUMIFS(D_purchases!$O$5:$O$139,D_purchases!$C$5:$C$139,A58,D_purchases!$P$5:$P$139,">0") -> 0 | E58: =SUMIFS(D_purchases!$O$5:$O$139,D_purchases!$C$5:$C$139,A58,D_purchases!$P$5:$P$139,">0",D_purchases!$P$5:$P$139,"<=30") -> 0 | F58: =SUMIFS(D_purchases!$O$5:$O$139,D_purchases!$C$5:$C$139,A58,D_purchases!$P$5:$P$139,">30",D_purchases!$P$5:$P$139,"<=60") -> 0 | G58: =SUMIFS(D_purchases!$O$5:$O$139,D_purchases!$C$5:$C$139,A58,D_purchases!$P$5:$P$139,">60",D_purchases!$P$5:$P$139,"<=9999") -> 0 | H58: =_xlfn.MAXIFS(D_purchases!$P$5:$P$139,D_purchases!$C$5:$C$139,A58) -> 0 | I58: =C58/$B$6*$B$7 -> 2.934769 | J58: =D_F01!C55 -> không | K58: =SUMIFS(D_purchases!$V$5:$V$139,D_purchases!$C$5:$C$139,A58) -> 0 | L58: =SUMIFS(D_purchases!$W$5:$W$139,D_purchases!$C$5:$C$139,A58) -> 0
A59: SUP-F01-006 | B59: =D_F01!B56 -> Điện lực khu công nghiệp | C59: =SUMIFS(D_purchases!$O$5:$O$139,D_purchases!$C$5:$C$139,A59) -> 389201455 | D59: =SUMIFS(D_purchases!$O$5:$O$139,D_purchases!$C$5:$C$139,A59,D_purchases!$P$5:$P$139,">0") -> 0 | E59: =SUMIFS(D_purchases!$O$5:$O$139,D_purchases!$C$5:$C$139,A59,D_purchases!$P$5:$P$139,">0",D_purchases!$P$5:$P$139,"<=30") -> 0 | F59: =SUMIFS(D_purchases!$O$5:$O$139,D_purchases!$C$5:$C$139,A59,D_purchases!$P$5:$P$139,">30",D_purchases!$P$5:$P$139,"<=60") -> 0 | G59: =SUMIFS(D_purchases!$O$5:$O$139,D_purchases!$C$5:$C$139,A59,D_purchases!$P$5:$P$139,">60",D_purchases!$P$5:$P$139,"<=9999") -> 0 | H59: =_xlfn.MAXIFS(D_purchases!$P$5:$P$139,D_purchases!$C$5:$C$139,A59) -> 0 | I59: =C59/$B$6*$B$7 -> 1.2338385 | J59: =D_F01!C56 -> có | K59: =SUMIFS(D_purchases!$V$5:$V$139,D_purchases!$C$5:$C$139,A59) -> 0 | L59: =SUMIFS(D_purchases!$W$5:$W$139,D_purchases!$C$5:$C$139,A59) -> 0
A60: SUP-F01-007 | B60: =D_F01!B57 -> Vải phụ trợ mới NCC7 | C60: =SUMIFS(D_purchases!$O$5:$O$139,D_purchases!$C$5:$C$139,A60) -> 979364994 | D60: =SUMIFS(D_purchases!$O$5:$O$139,D_purchases!$C$5:$C$139,A60,D_purchases!$P$5:$P$139,">0") -> 979364994 | E60: =SUMIFS(D_purchases!$O$5:$O$139,D_purchases!$C$5:$C$139,A60,D_purchases!$P$5:$P$139,">0",D_purchases!$P$5:$P$139,"<=30") -> 0 | F60: =SUMIFS(D_purchases!$O$5:$O$139,D_purchases!$C$5:$C$139,A60,D_purchases!$P$5:$P$139,">30",D_purchases!$P$5:$P$139,"<=60") -> 0 | G60: =SUMIFS(D_purchases!$O$5:$O$139,D_purchases!$C$5:$C$139,A60,D_purchases!$P$5:$P$139,">60",D_purchases!$P$5:$P$139,"<=9999") -> 979364994 | H60: =_xlfn.MAXIFS(D_purchases!$P$5:$P$139,D_purchases!$C$5:$C$139,A60) -> 85 | I60: =C60/$B$6*$B$7 -> 3.1047629 | J60: =D_F01!C57 -> không | K60: =SUMIFS(D_purchases!$V$5:$V$139,D_purchases!$C$5:$C$139,A60) -> 0 | L60: =SUMIFS(D_purchases!$W$5:$W$139,D_purchases!$C$5:$C$139,A60) -> 0
A61: SUP-F01-008 | B61: =D_F01!B58 -> Vật tư tiêu hao NCC8 | C61: =SUMIFS(D_purchases!$O$5:$O$139,D_purchases!$C$5:$C$139,A61) -> 0 | D61: =SUMIFS(D_purchases!$O$5:$O$139,D_purchases!$C$5:$C$139,A61,D_purchases!$P$5:$P$139,">0") -> 0 | E61: =SUMIFS(D_purchases!$O$5:$O$139,D_purchases!$C$5:$C$139,A61,D_purchases!$P$5:$P$139,">0",D_purchases!$P$5:$P$139,"<=30") -> 0 | F61: =SUMIFS(D_purchases!$O$5:$O$139,D_purchases!$C$5:$C$139,A61,D_purchases!$P$5:$P$139,">30",D_purchases!$P$5:$P$139,"<=60") -> 0 | G61: =SUMIFS(D_purchases!$O$5:$O$139,D_purchases!$C$5:$C$139,A61,D_purchases!$P$5:$P$139,">60",D_purchases!$P$5:$P$139,"<=9999") -> 0 | H61: =_xlfn.MAXIFS(D_purchases!$P$5:$P$139,D_purchases!$C$5:$C$139,A61) -> 0 | I61: =C61/$B$6*$B$7 -> 0 | J61: =D_F01!C58 -> không | K61: =SUMIFS(D_purchases!$V$5:$V$139,D_purchases!$C$5:$C$139,A61) -> 0 | L61: =SUMIFS(D_purchases!$W$5:$W$139,D_purchases!$C$5:$C$139,A61) -> 0
A62: SUP-F01-009 | B62: =D_F01!B59 -> Phụ liệu chỉ định NCC9 | C62: =SUMIFS(D_purchases!$O$5:$O$139,D_purchases!$C$5:$C$139,A62) -> 829195483 | D62: =SUMIFS(D_purchases!$O$5:$O$139,D_purchases!$C$5:$C$139,A62,D_purchases!$P$5:$P$139,">0") -> 0 | E62: =SUMIFS(D_purchases!$O$5:$O$139,D_purchases!$C$5:$C$139,A62,D_purchases!$P$5:$P$139,">0",D_purchases!$P$5:$P$139,"<=30") -> 0 | F62: =SUMIFS(D_purchases!$O$5:$O$139,D_purchases!$C$5:$C$139,A62,D_purchases!$P$5:$P$139,">30",D_purchases!$P$5:$P$139,"<=60") -> 0 | G62: =SUMIFS(D_purchases!$O$5:$O$139,D_purchases!$C$5:$C$139,A62,D_purchases!$P$5:$P$139,">60",D_purchases!$P$5:$P$139,"<=9999") -> 0 | H62: =_xlfn.MAXIFS(D_purchases!$P$5:$P$139,D_purchases!$C$5:$C$139,A62) -> 0 | I62: =C62/$B$6*$B$7 -> 2.6286986 | J62: =D_F01!C59 -> có | K62: =SUMIFS(D_purchases!$V$5:$V$139,D_purchases!$C$5:$C$139,A62) -> 1 | L62: =SUMIFS(D_purchases!$W$5:$W$139,D_purchases!$C$5:$C$139,A62) -> 3129450.7
A66: Lô | B66: Mặt hàng | C66: Chủ sở hữu | D66: Giá trị sở hữu | E66: Đã lưu kho (ngày) | F66: Ngưỡng lưu lâu | G66: Tồn lâu | H66: Đơn hủy | I66: Góp DIO | J66: Xếp theo thời gian
A67: =D_inventory!A5 -> L01 | B67: =D_inventory!C5 -> Vải chính tự mua đơn FOB-0826 | C67: =D_inventory!E5 -> F01 | D67: =D_inventory!P5 -> 2195715060 | E67: =D_inventory!N5 -> 42 | F67: =D_inventory!Q5 -> 60 | G67: =D_inventory!R5 -> 0 | H67: =D_inventory!H5 -> Đang hoạt động | I67: =D_inventory!T5 -> 6.960811 | J67: =IF(C67="F01",COUNTIFS($C$67:$C$102,"F01",$E$67:$E$102,">"&E67)+1,"Loại trừ") -> 14
A68: =D_inventory!A6 -> L02 | B68: =D_inventory!C6 -> Phụ liệu lót đơn FOB-0826 | C68: =D_inventory!E6 -> F01 | D68: =D_inventory!P6 -> 5.2033868e+08 | E68: =D_inventory!N6 -> 35 | F68: =D_inventory!Q6 -> 60 | G68: =D_inventory!R6 -> 0 | H68: =D_inventory!H6 -> Đang hoạt động | I68: =D_inventory!T6 -> 1.6495671 | J68: =IF(C68="F01",COUNTIFS($C$67:$C$102,"F01",$E$67:$E$102,">"&E68)+1,"Loại trừ") -> 16
A69: =D_inventory!A7 -> L03 | B69: =D_inventory!C7 -> Vải kaki tồn từ mùa trước | C69: =D_inventory!E7 -> F01 | D69: =D_inventory!P7 -> 784510713 | E69: =D_inventory!N7 -> 181 | F69: =D_inventory!Q7 -> 60 | G69: =D_inventory!R7 -> 1 | H69: =D_inventory!H7 -> Không gắn đơn | I69: =D_inventory!T7 -> 2.4870398 | J69: =IF(C69="F01",COUNTIFS($C$67:$C$102,"F01",$E$67:$E$102,">"&E69)+1,"Loại trừ") -> 3
A70: =D_inventory!A8 -> L04 | B70: =D_inventory!C8 -> Vải ren – lụa mua thử (lô cũ nhất) | C70: =D_inventory!E8 -> F01 | D70: =D_inventory!P8 -> 49174868 | E70: =D_inventory!N8 -> 238 | F70: =D_inventory!Q8 -> 60 | G70: =D_inventory!R8 -> 1 | H70: =D_inventory!H8 -> Không gắn đơn | I70: =D_inventory!T8 -> 0.15589316 | J70: =IF(C70="F01",COUNTIFS($C$67:$C$102,"F01",$E$67:$E$102,">"&E70)+1,"Loại trừ") -> 1
A71: =D_inventory!A9 -> L05 | B71: =D_inventory!C9 -> Phụ liệu chuyên dụng (chỉ, nút, khóa) | C71: =D_inventory!E9 -> F01 | D71: =D_inventory!P9 -> 1219077600 | E71: =D_inventory!N9 -> 38 | F71: =D_inventory!Q9 -> 60 | G71: =D_inventory!R9 -> 0 | H71: =D_inventory!H9 -> Đang hoạt động | I71: =D_inventory!T9 -> 3.8646949 | J71: =IF(C71="F01",COUNTIFS($C$67:$C$102,"F01",$E$67:$E$102,">"&E71)+1,"Loại trừ") -> 15
A72: =D_inventory!A10 -> L06 | B72: =D_inventory!C10 -> Phụ liệu đơn hàng bị hủy mùa Hè | C72: =D_inventory!E10 -> F01 | D72: =D_inventory!P10 -> 819582150 | E72: =D_inventory!N10 -> 128 | F72: =D_inventory!Q10 -> 60 | G72: =D_inventory!R10 -> 1 | H72: =D_inventory!H10 -> Đã hủy | I72: =D_inventory!T10 -> 2.5982226 | J72: =IF(C72="F01",COUNTIFS($C$67:$C$102,"F01",$E$67:$E$102,">"&E72)+1,"Loại trừ") -> 6
A73: =D_inventory!A11 -> L07 | B73: =D_inventory!C11 -> Bao bì carton, túi PE | C73: =D_inventory!E11 -> F01 | D73: =D_inventory!P11 -> 738578100 | E73: =D_inventory!N11 -> 30 | F73: =D_inventory!Q11 -> 60 | G73: =D_inventory!R11 -> 0 | H73: =D_inventory!H11 -> Không gắn đơn | I73: =D_inventory!T11 -> 2.3414252 | J73: =IF(C73="F01",COUNTIFS($C$67:$C$102,"F01",$E$67:$E$102,">"&E73)+1,"Loại trừ") -> 17
A74: =D_inventory!A12 -> L08 | B74: =D_inventory!C12 -> Nhãn dệt, thẻ bài đã đổi thiết kế | C74: =D_inventory!E12 -> F01 | D74: =D_inventory!P12 -> 171540450 | E74: =D_inventory!N12 -> 94 | F74: =D_inventory!Q12 -> 60 | G74: =D_inventory!R12 -> 1 | H74: =D_inventory!H12 -> Thay đổi thiết kế | I74: =D_inventory!T12 -> 0.54381403 | J74: =IF(C74="F01",COUNTIFS($C$67:$C$102,"F01",$E$67:$E$102,">"&E74)+1,"Loại trừ") -> 8
A75: =D_inventory!A13 -> L09 | B75: =D_inventory!C13 -> BTP đã cắt chờ may – đơn FOB-0826 | C75: =D_inventory!E13 -> F01 | D75: =D_inventory!P13 -> 1094045610 | E75: =D_inventory!N13 -> 9 | F75: =D_inventory!Q13 -> 30 | G75: =D_inventory!R13 -> 0 | H75: =D_inventory!H13 -> Đang hoạt động | I75: =D_inventory!T13 -> 3.468321 | J75: =IF(C75="F01",COUNTIFS($C$67:$C$102,"F01",$E$67:$E$102,">"&E75)+1,"Loại trừ") -> 31
A76: =D_inventory!A14 -> L10 | B76: =D_inventory!C14 -> BTP chờ kiểm QC, sửa lỗi | C76: =D_inventory!E14 -> F01 | D76: =D_inventory!P14 -> 376626132 | E76: =D_inventory!N14 -> 47 | F76: =D_inventory!Q14 -> 30 | G76: =D_inventory!R14 -> 1 | H76: =D_inventory!H14 -> Đang hoạt động | I76: =D_inventory!T14 -> 1.1939725 | J76: =IF(C76="F01",COUNTIFS($C$67:$C$102,"F01",$E$67:$E$102,">"&E76)+1,"Loại trừ") -> 12
A77: =D_inventory!A15 -> L11 | B77: =D_inventory!C15 -> BTP đang may – đơn K2 | C77: =D_inventory!E15 -> F01 | D77: =D_inventory!P15 -> 651852855 | E77: =D_inventory!N15 -> 11 | F77: =D_inventory!Q15 -> 30 | G77: =D_inventory!R15 -> 0 | H77: =D_inventory!H15 -> Đang hoạt động | I77: =D_inventory!T15 -> 2.0664906 | J77: =IF(C77="F01",COUNTIFS($C$67:$C$102,"F01",$E$67:$E$102,">"&E77)+1,"Loại trừ") -> 30
A78: =D_inventory!A16 -> L12 | B78: =D_inventory!C16 -> Thành phẩm chờ xuất – đơn K2 | C78: =D_inventory!E16 -> F01 | D78: =D_inventory!P16 -> 707508192 | E78: =D_inventory!N16 -> 16 | F78: =D_inventory!Q16 -> 30 | G78: =D_inventory!R16 -> 0 | H78: =D_inventory!H16 -> Đang hoạt động | I78: =D_inventory!T16 -> 2.242928 | J78: =IF(C78="F01",COUNTIFS($C$67:$C$102,"F01",$E$67:$E$102,">"&E78)+1,"Loại trừ") -> 28
... A102: =D_inventory!A40 -> L36 | B102: =D_inventory!C40 -> Thân áo cắt sẵn chờ may (K5) | C102: =D_inventory!E40 -> F01 | D102: =D_inventory!P40 -> 711000000 | E102: =D_inventory!N40 -> 1 | F102: =D_inventory!Q40 -> 30 | G102: =D_inventory!R40 -> 0 | H102: =D_inventory!H40 -> Đang hoạt động | I102: =D_inventory!T40 -> 2.2539977 | J102: =IF(C102="F01",COUNTIFS($C$67:$C$102,"F01",$E$67:$E$102,">"&E102)+1,"Loại trừ") -> 36

Sheet F01_UC2
A2: F01 Dự báo tiền từ 01/07 đến 29/09/2026
A4: Chỉ tiêu | B4: Giá trị | C4: Ý nghĩa
A5: Kịch bản | B5: =CHOOSE(D_F01!B19,"Base","Optimistic","Conservative","Stress7","Continuing") -> Base | C5: Một selector tại D_F01!B19
A6: Ngày đầu | B6: =D_F01!B7+1 -> 46204 | C6: AsOf+1
A7: Ngày cuối | B7: =D_F01!B7+7*D_F01!B18 -> 46294 | C7: H13=91 ngày; không phải N181
A8: Tiền đầu dự báo | B8: =D_F01!B11-D_F01!B12 -> 4401925973 | C8: Tiền khả dụng giả lập tại ngày chốt
A9: L – giới hạn dưới | B9: =D_F01!B15 -> 5.5645463e+09 | C9: Tiền < L: thiếu; không xét thiếu chỉ vì thấp hơn Z
A10: Z – mức tiền mục tiêu | B10: =D_F01!B16 -> 6.8559659e+09 | C10: Mức hồi sau điều chỉnh; không tự ghi thêm vào thu dự báo
A11: H – giới hạn trên | B11: =D_F01!B17 -> 9.4388051e+09 | C11: Tiền > H: thừa; tiền trong [L;H] tiếp tục theo dõi
A12: MinCash | B12: =MIN(G70:G160) -> 4140480437 | C12: Số dư cuối ngày thấp nhất
A13: Ngày MinCash | B13: =INDEX(A70:A160,MATCH(B12,G70:G160,0)) -> 46205 | C13: Nếu bằng nhau lấy ngày đầu
A14: PeakBuffer | B14: =MAX(H70:H160) -> 2.7154855e+09 | C14: Không cộng gap lặp qua ngày
A15: PeakZero | B15: =MAX(I70:I160) -> 0 | C15: Không cộng với PeakBuffer
A16: MinCum | B16: =MIN(0,MIN(D70:D160)) -> -261445536 | C16: Lũy kế thu trừ chi, chưa có Cash0
A17: NeedTarget | B17: =IF(COUNTIF(G70:G160,"<"&B9)>0,MAX(0,B10-B16),B8) -> 7.1174114e+09 | C17: Tiền đầu kỳ cần để nâng đáy lên Z khi có ngày dưới L; không thiếu thì giữ Cash0
A18: NeedZero | B18: =MAX(0,-B16) -> 261445536 | C18: Tổng tiền đầu kỳ cần để không âm
A19: Additional | B19: =MAX(0,B17-B8) -> 2.7154855e+09 | C19: NeedTarget trừ tiền đang có, chặn dưới 0
A20: Ngày đầu thiếu | B20: =IF(COUNTIF(G70:G160,"<"&B9)=0,"n.a.",_xlfn.MINIFS(A70:A160,G70:G160,"<"&B9)) -> 46204 | C20: Ngày đầu trong dự báo; xem M43 để biết thiếu đã có tại ngày chốt
A21: Ngày đầu âm | B21: =IF(COUNTIF(G70:G160,"<0")=0,"n.a.",_xlfn.MINIFS(A70:A160,G70:G160,"<0")) -> n.a. | C21: Tách riêng ngày đầu dưới dự trữ
A22: Cảnh báo toàn kỳ | B22: =CHOOSE(MAX(K70:K160)+1,"Không cảnh báo","Vàng","Cam","Đỏ") -> Đỏ | C22: Mức nặng nhất theo ngày của kịch bản đang chọn
A23: TH để định tuyến | B23: =IF(D_F01!B19<>1,"Chọn Base để định tuyến",IF(MIN(G70:G160)<B9,"TH01",IF(MAX(G70:G160)>B11,"TH02","Trong vùng L–H"))) -> TH01 | C23: Base: có ngày dưới L → TH01; nếu không thì có ngày trên H → TH02; còn lại trong vùng
A24: Ô ma trận | B24: =IF(OR(D_F01!B19<>1,B23="Trong vùng L–H"),"—","M"&(VALUE(RIGHT(F01_UC1!B30,1))*2+IF(B23="TH01",1,2))) -> M3 | C24: Ma trận M1–M6, 3 mức W × 2 trạng thái tiền; trong vùng không gán ô
A25: Trạng thái | B25: provisional | C25: Dữ liệu hư cấu, net/noVAT, lịch chi quá hạn là giả định
A26: Chế độ | B26: =D_F01!B20 -> run_off | C26: Run-off không có toàn bộ hoạt động mới; continuing có thêm cả thu và chi
A28: Tuần | B28: Ngày đầu | C28: Ngày cuối | D28: Thu | E28: Chi | F28: Cuối tuần | G28: Thấp nhất tuần | H28: Ngày thấp nhất | I28: Mức cuối tuần | J28: Mức xấu nhất | L28: Khối | M28: Ngày đầu | N28: Ngày cuối | O28: MinDaily | P28: Trạng thái | Q28: Mức xấu nhất | R28: Số ngày | S28: Giới hạn
A29: 1 | B29: =$B$6+0 -> 46204 | C29: =B29+6 -> 46210 | D29: =SUMIFS($B$70:$B$160,$A$70:$A$160,">="&B29,$A$70:$A$160,"<="&C29) -> 3251880497 | E29: =SUMIFS($C$70:$C$160,$A$70:$A$160,">="&B29,$A$70:$A$160,"<="&C29) -> 3138231714 | F29: =INDEX($G$70:$G$160,MATCH(C29,$A$70:$A$160,0)) -> 4515574756 | G29: =_xlfn.MINIFS($G$70:$G$160,$A$70:$A$160,">="&B29,$A$70:$A$160,"<="&C29) -> 4140480437 | H29: =_xlfn.MINIFS($A$70:$A$160,$A$70:$A$160,">="&B29,$A$70:$A$160,"<="&C29,$G$70:$G$160,G29) -> 46205 | I29: =INDEX($K$70:$K$160,MATCH(C29,$A$70:$A$160,0)) -> 3 | J29: =_xlfn.MAXIFS($K$70:$K$160,$A$70:$A$160,">="&B29,$A$70:$A$160,"<="&C29) -> 3 | L29: =1 -> 1 | M29: =$B$6+0 -> 46204 | N29: =MIN($B$7,M29+13) -> 46217 | O29: =_xlfn.MINIFS($G$70:$G$160,$A$70:$A$160,">="&M29,$A$70:$A$160,"<="&N29) -> 4140480437 | P29: =IF(O29<$B$9,"Thiếu",IF(O29>$B$11,"Thừa","Trong vùng L–H")) -> Thiếu | Q29: =_xlfn.MAXIFS($K$70:$K$160,$A$70:$A$160,">="&M29,$A$70:$A$160,"<="&N29) -> 3 | R29: =N29-M29+1 -> 14 | S29: =IF(R29=7,"Khối cuối 7 ngày","Khối 14 ngày") -> Khối 14 ngày
A30: 2 | B30: =$B$6+7 -> 46211 | C30: =B30+6 -> 46217 | D30: =SUMIFS($B$70:$B$160,$A$70:$A$160,">="&B30,$A$70:$A$160,"<="&C30) -> 7371181354 | E30: =SUMIFS($C$70:$C$160,$A$70:$A$160,">="&B30,$A$70:$A$160,"<="&C30) -> 830190311 | F30: =INDEX($G$70:$G$160,MATCH(C30,$A$70:$A$160,0)) -> 11056565799 | G30: =_xlfn.MINIFS($G$70:$G$160,$A$70:$A$160,">="&B30,$A$70:$A$160,"<="&C30) -> 5314587071 | H30: =_xlfn.MINIFS($A$70:$A$160,$A$70:$A$160,">="&B30,$A$70:$A$160,"<="&C30,$G$70:$G$160,G30) -> 46211 | I30: =INDEX($K$70:$K$160,MATCH(C30,$A$70:$A$160,0)) -> 0 | J30: =_xlfn.MAXIFS($K$70:$K$160,$A$70:$A$160,">="&B30,$A$70:$A$160,"<="&C30) -> 3 | L30: =2 -> 2 | M30: =$B$6+14 -> 46218 | N30: =MIN($B$7,M30+13) -> 46231 | O30: =_xlfn.MINIFS($G$70:$G$160,$A$70:$A$160,">="&M30,$A$70:$A$160,"<="&N30) -> 11150672753 | P30: =IF(O30<$B$9,"Thiếu",IF(O30>$B$11,"Thừa","Trong vùng L–H")) -> Thừa | Q30: =_xlfn.MAXIFS($K$70:$K$160,$A$70:$A$160,">="&M30,$A$70:$A$160,"<="&N30) -> 0 | R30: =N30-M30+1 -> 14 | S30: =IF(R30=7,"Khối cuối 7 ngày","Khối 14 ngày") -> Khối 14 ngày
A31: 3 | B31: =$B$6+14 -> 46218 | C31: =B31+6 -> 46224 | D31: =SUMIFS($B$70:$B$160,$A$70:$A$160,">="&B31,$A$70:$A$160,"<="&C31) -> 3653992400 | E31: =SUMIFS($C$70:$C$160,$A$70:$A$160,">="&B31,$A$70:$A$160,"<="&C31) -> 2302640567 | F31: =INDEX($G$70:$G$160,MATCH(C31,$A$70:$A$160,0)) -> 12407917632 | G31: =_xlfn.MINIFS($G$70:$G$160,$A$70:$A$160,">="&B31,$A$70:$A$160,"<="&C31) -> 11150672753 | H31: =_xlfn.MINIFS($A$70:$A$160,$A$70:$A$160,">="&B31,$A$70:$A$160,"<="&C31,$G$70:$G$160,G31) -> 46218 | I31: =INDEX($K$70:$K$160,MATCH(C31,$A$70:$A$160,0)) -> 0 | J31: =_xlfn.MAXIFS($K$70:$K$160,$A$70:$A$160,">="&B31,$A$70:$A$160,"<="&C31) -> 0 | L31: =3 -> 3 | M31: =$B$6+28 -> 46232 | N31: =MIN($B$7,M31+13) -> 46245 | O31: =_xlfn.MINIFS($G$70:$G$160,$A$70:$A$160,">="&M31,$A$70:$A$160,"<="&N31) -> 12461774647 | P31: =IF(O31<$B$9,"Thiếu",IF(O31>$B$11,"Thừa","Trong vùng L–H")) -> Thừa | Q31: =_xlfn.MAXIFS($K$70:$K$160,$A$70:$A$160,">="&M31,$A$70:$A$160,"<="&N31) -> 0 | R31: =N31-M31+1 -> 14 | S31: =IF(R31=7,"Khối cuối 7 ngày","Khối 14 ngày") -> Khối 14 ngày
A32: 4 | B32: =$B$6+21 -> 46225 | C32: =B32+6 -> 46231 | D32: =SUMIFS($B$70:$B$160,$A$70:$A$160,">="&B32,$A$70:$A$160,"<="&C32) -> 3339440235 | E32: =SUMIFS($C$70:$C$160,$A$70:$A$160,">="&B32,$A$70:$A$160,"<="&C32) -> 3225945927 | F32: =INDEX($G$70:$G$160,MATCH(C32,$A$70:$A$160,0)) -> 12521411940 | G32: =_xlfn.MINIFS($G$70:$G$160,$A$70:$A$160,">="&B32,$A$70:$A$160,"<="&C32) -> 11937730444 | H32: =_xlfn.MINIFS($A$70:$A$160,$A$70:$A$160,">="&B32,$A$70:$A$160,"<="&C32,$G$70:$G$160,G32) -> 46226 | I32: =INDEX($K$70:$K$160,MATCH(C32,$A$70:$A$160,0)) -> 0 | J32: =_xlfn.MAXIFS($K$70:$K$160,$A$70:$A$160,">="&B32,$A$70:$A$160,"<="&C32) -> 0 | L32: =4 -> 4 | M32: =$B$6+42 -> 46246 | N32: =MIN($B$7,M32+13) -> 46259 | O32: =_xlfn.MINIFS($G$70:$G$160,$A$70:$A$160,">="&M32,$A$70:$A$160,"<="&N32) -> 15514035449 | P32: =IF(O32<$B$9,"Thiếu",IF(O32>$B$11,"Thừa","Trong vùng L–H")) -> Thừa | Q32: =_xlfn.MAXIFS($K$70:$K$160,$A$70:$A$160,">="&M32,$A$70:$A$160,"<="&N32) -> 0 | R32: =N32-M32+1 -> 14 | S32: =IF(R32=7,"Khối cuối 7 ngày","Khối 14 ngày") -> Khối 14 ngày
A33: 5 | B33: =$B$6+28 -> 46232 | C33: =B33+6 -> 46238 | D33: =SUMIFS($B$70:$B$160,$A$70:$A$160,">="&B33,$A$70:$A$160,"<="&C33) -> 296418085 | E33: =SUMIFS($C$70:$C$160,$A$70:$A$160,">="&B33,$A$70:$A$160,"<="&C33) -> 356055378 | F33: =INDEX($G$70:$G$160,MATCH(C33,$A$70:$A$160,0)) -> 12461774647 | G33: =_xlfn.MINIFS($G$70:$G$160,$A$70:$A$160,">="&B33,$A$70:$A$160,"<="&C33) -> 12461774647 | H33: =_xlfn.MINIFS($A$70:$A$160,$A$70:$A$160,">="&B33,$A$70:$A$160,"<="&C33,$G$70:$G$160,G33) -> 46235 | I33: =INDEX($K$70:$K$160,MATCH(C33,$A$70:$A$160,0)) -> 0 | J33: =_xlfn.MAXIFS($K$70:$K$160,$A$70:$A$160,">="&B33,$A$70:$A$160,"<="&C33) -> 0 | L33: =5 -> 5 | M33: =$B$6+56 -> 46260 | N33: =MIN($B$7,M33+13) -> 46273 | O33: =_xlfn.MINIFS($G$70:$G$160,$A$70:$A$160,">="&M33,$A$70:$A$160,"<="&N33) -> 14828618808 | P33: =IF(O33<$B$9,"Thiếu",IF(O33>$B$11,"Thừa","Trong vùng L–H")) -> Thừa | Q33: =_xlfn.MAXIFS($K$70:$K$160,$A$70:$A$160,">="&M33,$A$70:$A$160,"<="&N33) -> 0 | R33: =N33-M33+1 -> 14 | S33: =IF(R33=7,"Khối cuối 7 ngày","Khối 14 ngày") -> Khối 14 ngày
A34: 6 | B34: =$B$6+35 -> 46239 | C34: =B34+6 -> 46245 | D34: =SUMIFS($B$70:$B$160,$A$70:$A$160,">="&B34,$A$70:$A$160,"<="&C34) -> 3474637645 | E34: =SUMIFS($C$70:$C$160,$A$70:$A$160,">="&B34,$A$70:$A$160,"<="&C34) -> 0 | F34: =INDEX($G$70:$G$160,MATCH(C34,$A$70:$A$160,0)) -> 15936412292 | G34: =_xlfn.MINIFS($G$70:$G$160,$A$70:$A$160,">="&B34,$A$70:$A$160,"<="&C34) -> 12461774647 | H34: =_xlfn.MINIFS($A$70:$A$160,$A$70:$A$160,">="&B34,$A$70:$A$160,"<="&C34,$G$70:$G$160,G34) -> 46239 | I34: =INDEX($K$70:$K$160,MATCH(C34,$A$70:$A$160,0)) -> 0 | J34: =_xlfn.MAXIFS($K$70:$K$160,$A$70:$A$160,">="&B34,$A$70:$A$160,"<="&C34) -> 0 | L34: =6 -> 6 | M34: =$B$6+70 -> 46274 | N34: =MIN($B$7,M34+13) -> 46287 | O34: =_xlfn.MINIFS($G$70:$G$160,$A$70:$A$160,">="&M34,$A$70:$A$160,"<="&N34) -> 15656479147 | P34: =IF(O34<$B$9,"Thiếu",IF(O34>$B$11,"Thừa","Trong vùng L–H")) -> Thừa | Q34: =_xlfn.MAXIFS($K$70:$K$160,$A$70:$A$160,">="&M34,$A$70:$A$160,"<="&N34) -> 0 | R34: =N34-M34+1 -> 14 | S34: =IF(R34=7,"Khối cuối 7 ngày","Khối 14 ngày") -> Khối 14 ngày
A35: 7 | B35: =$B$6+42 -> 46246 | C35: =B35+6 -> 46252 | D35: =SUMIFS($B$70:$B$160,$A$70:$A$160,">="&B35,$A$70:$A$160,"<="&C35) -> 1537862235 | E35: =SUMIFS($C$70:$C$160,$A$70:$A$160,">="&B35,$A$70:$A$160,"<="&C35) -> 1008000000 | F35: =INDEX($G$70:$G$160,MATCH(C35,$A$70:$A$160,0)) -> 16466274527 | G35: =_xlfn.MINIFS($G$70:$G$160,$A$70:$A$160,">="&B35,$A$70:$A$160,"<="&C35) -> 15514035449 | H35: =_xlfn.MINIFS($A$70:$A$160,$A$70:$A$160,">="&B35,$A$70:$A$160,"<="&C35,$G$70:$G$160,G35) -> 46249 | I35: =INDEX($K$70:$K$160,MATCH(C35,$A$70:$A$160,0)) -> 0 | J35: =_xlfn.MAXIFS($K$70:$K$160,$A$70:$A$160,">="&B35,$A$70:$A$160,"<="&C35) -> 0 | L35: =7 -> 7 | M35: =$B$6+84 -> 46288 | N35: =MIN($B$7,M35+13) -> 46294 | O35: =_xlfn.MINIFS($G$70:$G$160,$A$70:$A$160,">="&M35,$A$70:$A$160,"<="&N35) -> 14156479147 | P35: =IF(O35<$B$9,"Thiếu",IF(O35>$B$11,"Thừa","Trong vùng L–H")) -> Thừa | Q35: =_xlfn.MAXIFS($K$70:$K$160,$A$70:$A$160,">="&M35,$A$70:$A$160,"<="&N35) -> 0 | R35: =N35-M35+1 -> 7 | S35: =IF(R35=7,"Khối cuối 7 ngày","Khối 14 ngày") -> Khối cuối 7 ngày
A36: 8 | B36: =$B$6+49 -> 46253 | C36: =B36+6 -> 46259 | D36: =SUMIFS($B$70:$B$160,$A$70:$A$160,">="&B36,$A$70:$A$160,"<="&C36) -> 742318455 | E36: =SUMIFS($C$70:$C$160,$A$70:$A$160,">="&B36,$A$70:$A$160,"<="&C36) -> 528199584 | F36: =INDEX($G$70:$G$160,MATCH(C36,$A$70:$A$160,0)) -> 16680393398 | G36: =_xlfn.MINIFS($G$70:$G$160,$A$70:$A$160,">="&B36,$A$70:$A$160,"<="&C36) -> 15938074943 | H36: =_xlfn.MINIFS($A$70:$A$160,$A$70:$A$160,">="&B36,$A$70:$A$160,"<="&C36,$G$70:$G$160,G36) -> 46254 | I36: =INDEX($K$70:$K$160,MATCH(C36,$A$70:$A$160,0)) -> 0 | J36: =_xlfn.MAXIFS($K$70:$K$160,$A$70:$A$160,">="&B36,$A$70:$A$160,"<="&C36) -> 0
A37: 9 | B37: =$B$6+56 -> 46260 | C37: =B37+6 -> 46266 | D37: =SUMIFS($B$70:$B$160,$A$70:$A$160,">="&B37,$A$70:$A$160,"<="&C37) -> 1247860339 | E37: =SUMIFS($C$70:$C$160,$A$70:$A$160,">="&B37,$A$70:$A$160,"<="&C37) -> 2031774590 | F37: =INDEX($G$70:$G$160,MATCH(C37,$A$70:$A$160,0)) -> 15896479147 | G37: =_xlfn.MINIFS($G$70:$G$160,$A$70:$A$160,">="&B37,$A$70:$A$160,"<="&C37) -> 14828618808 | H37: =_xlfn.MINIFS($A$70:$A$160,$A$70:$A$160,">="&B37,$A$70:$A$160,"<="&C37,$G$70:$G$160,G37) -> 46262 | I37: =INDEX($K$70:$K$160,MATCH(C37,$A$70:$A$160,0)) -> 0 | J37: =_xlfn.MAXIFS($K$70:$K$160,$A$70:$A$160,">="&B37,$A$70:$A$160,"<="&C37) -> 0 | L37: Thiếu kéo dài từ hai khối đủ 28 ngày | M37: =MAX(P70:P160)>=28 -> FALSE
A38: 10 | B38: =$B$6+63 -> 46267 | C38: =B38+6 -> 46273 | D38: =SUMIFS($B$70:$B$160,$A$70:$A$160,">="&B38,$A$70:$A$160,"<="&C38) -> 0 | E38: =SUMIFS($C$70:$C$160,$A$70:$A$160,">="&B38,$A$70:$A$160,"<="&C38) -> 0 | F38: =INDEX($G$70:$G$160,MATCH(C38,$A$70:$A$160,0)) -> 15896479147 | G38: =_xlfn.MINIFS($G$70:$G$160,$A$70:$A$160,">="&B38,$A$70:$A$160,"<="&C38) -> 15896479147 | H38: =_xlfn.MINIFS($A$70:$A$160,$A$70:$A$160,">="&B38,$A$70:$A$160,"<="&C38,$G$70:$G$160,G38) -> 46267 | I38: =INDEX($K$70:$K$160,MATCH(C38,$A$70:$A$160,0)) -> 0 | J38: =_xlfn.MAXIFS($K$70:$K$160,$A$70:$A$160,">="&B38,$A$70:$A$160,"<="&C38) -> 0
A39: 11 | B39: =$B$6+70 -> 46274 | C39: =B39+6 -> 46280 | D39: =SUMIFS($B$70:$B$160,$A$70:$A$160,">="&B39,$A$70:$A$160,"<="&C39) -> 0 | E39: =SUMIFS($C$70:$C$160,$A$70:$A$160,">="&B39,$A$70:$A$160,"<="&C39) -> 0 | F39: =INDEX($G$70:$G$160,MATCH(C39,$A$70:$A$160,0)) -> 15896479147 | G39: =_xlfn.MINIFS($G$70:$G$160,$A$70:$A$160,">="&B39,$A$70:$A$160,"<="&C39) -> 15896479147 | H39: =_xlfn.MINIFS($A$70:$A$160,$A$70:$A$160,">="&B39,$A$70:$A$160,"<="&C39,$G$70:$G$160,G39) -> 46274 | I39: =INDEX($K$70:$K$160,MATCH(C39,$A$70:$A$160,0)) -> 0 | J39: =_xlfn.MAXIFS($K$70:$K$160,$A$70:$A$160,">="&B39,$A$70:$A$160,"<="&C39) -> 0 | L39: Chi thiết yếu bình quân/ngày | M39: =SUMIFS(E220:E341,D220:D341,"OUT",Q220:Q341,1)/91 -> 1.2306159e+08
A40: 12 | B40: =$B$6+77 -> 46281 | C40: =B40+6 -> 46287 | D40: =SUMIFS($B$70:$B$160,$A$70:$A$160,">="&B40,$A$70:$A$160,"<="&C40) -> 0 | E40: =SUMIFS($C$70:$C$160,$A$70:$A$160,">="&B40,$A$70:$A$160,"<="&C40) -> 240000000 | F40: =INDEX($G$70:$G$160,MATCH(C40,$A$70:$A$160,0)) -> 15656479147 | G40: =_xlfn.MINIFS($G$70:$G$160,$A$70:$A$160,">="&B40,$A$70:$A$160,"<="&C40) -> 15656479147 | H40: =_xlfn.MINIFS($A$70:$A$160,$A$70:$A$160,">="&B40,$A$70:$A$160,"<="&C40,$G$70:$G$160,G40) -> 46283 | I40: =INDEX($K$70:$K$160,MATCH(C40,$A$70:$A$160,0)) -> 0 | J40: =_xlfn.MAXIFS($K$70:$K$160,$A$70:$A$160,">="&B40,$A$70:$A$160,"<="&C40) -> 0 | L40: 15 ngày chi thiết yếu | M40: =M39*15 -> 1.8459239e+09
A41: 13 | B41: =$B$6+84 -> 46288 | C41: =B41+6 -> 46294 | D41: =SUMIFS($B$70:$B$160,$A$70:$A$160,">="&B41,$A$70:$A$160,"<="&C41) -> 0 | E41: =SUMIFS($C$70:$C$160,$A$70:$A$160,">="&B41,$A$70:$A$160,"<="&C41) -> 1500000000 | F41: =INDEX($G$70:$G$160,MATCH(C41,$A$70:$A$160,0)) -> 14156479147 | G41: =_xlfn.MINIFS($G$70:$G$160,$A$70:$A$160,">="&B41,$A$70:$A$160,"<="&C41) -> 14156479147 | H41: =_xlfn.MINIFS($A$70:$A$160,$A$70:$A$160,">="&B41,$A$70:$A$160,"<="&C41,$G$70:$G$160,G41) -> 46293 | I41: =INDEX($K$70:$K$160,MATCH(C41,$A$70:$A$160,0)) -> 0 | J41: =_xlfn.MAXIFS($K$70:$K$160,$A$70:$A$160,">="&B41,$A$70:$A$160,"<="&C41) -> 0 | L41: Đối chiếu sàn L với nghĩa vụ thiết yếu | M41: =IF(B9<M40,"L thấp hơn 15 ngày chi thiết yếu: chủ DN xem lại sàn","L không thấp hơn 15 ngày chi thiết yếu") -> L không thấp hơn 15 ngày chi thiết yếu
L42: Tiền thừa lớn nhất về Z | M42: =IF(MAX(G70:G160)>B11,MAX(G70:G160)-B10,0) -> 9.8244275e+09
L43: Thiếu ngay tại ngày chốt | M43: =IF(B8<B9,"Có: thiếu đã có tại AsOf","Không") -> Có: thiếu đã có tại AsOf
L44: Thiếu lớn nhất so với L | M44: =MAX(0,B9-B12) -> 1.4240659e+09
A45: Khách | B45: Số mẫu riêng | C45: Cấp dùng | D45: Số mẫu dùng | E45: Mean gia quyền | F45: P25 mẫu | G45: P75 mẫu | H45: Delay Opt | I45: Delay Cons | J45: Mẫu mở cận dưới
A46: BYR-F01-002 | B46: =COUNTIFS(D_sales!$C$5:$C$121,A46,D_sales!$W$5:$W$121,1) -> 23 | C46: =IF(B46>=D_F01!$B$26,"customer",IF(SUM(D_sales!$W$5:$W$121)>=D_F01!$B$26,"firm","default")) -> customer | D46: =IF(C46="customer",B46,IF(C46="firm",SUM(D_sales!$W$5:$W$121),0)) -> 23 | E46: =IF(C46="default",D_F01!$B$28,IF(C46="customer",SUMIFS(D_sales!$X$5:$X$121,D_sales!$C$5:$C$121,A46)/SUMIFS(D_sales!$V$5:$V$121,D_sales!$C$5:$C$121,A46),SUM(D_sales!$X$5:$X$121)/SUM(D_sales!$V$5:$V$121))) -> 16.211449 | F46: {=IF(C46="default",D_F01!$B$28,IF(C46="customer",PERCENTILE(IF((D_sales!$C$5:$C$121=A46)*(D_sales!$W$5:$W$121=1),D_sales!$U$5:$U$121),0.25),PERCENTILE(IF(D_sales!$W$5:$W$121=1,D_sales!$U$5:$U$121),0.25)))} -> 10.5 | G46: {=IF(C46="default",D_F01!$B$28,IF(C46="customer",PERCENTILE(IF((D_sales!$C$5:$C$121=A46)*(D_sales!$W$5:$W$121=1),D_sales!$U$5:$U$121),0.75),PERCENTILE(IF(D_sales!$W$5:$W$121=1,D_sales!$U$5:$U$121),0.75)))} -> 22.5 | H46: =MIN(E46,F46) -> 10.5 | I46: =MAX(E46,G46) -> 22.5 | J46: =IF(C46="customer",SUMIFS(D_sales!$Y$5:$Y$121,D_sales!$C$5:$C$121,A46),IF(C46="firm",SUM(D_sales!$Y$5:$Y$121),0)) -> 7
A47: BYR-F01-001 | B47: =COUNTIFS(D_sales!$C$5:$C$121,A47,D_sales!$W$5:$W$121,1) -> 26 | C47: =IF(B47>=D_F01!$B$26,"customer",IF(SUM(D_sales!$W$5:$W$121)>=D_F01!$B$26,"firm","default")) -> customer | D47: =IF(C47="customer",B47,IF(C47="firm",SUM(D_sales!$W$5:$W$121),0)) -> 26 | E47: =IF(C47="default",D_F01!$B$28,IF(C47="customer",SUMIFS(D_sales!$X$5:$X$121,D_sales!$C$5:$C$121,A47)/SUMIFS(D_sales!$V$5:$V$121,D_sales!$C$5:$C$121,A47),SUM(D_sales!$X$5:$X$121)/SUM(D_sales!$V$5:$V$121))) -> 1.4317005 | F47: {=IF(C47="default",D_F01!$B$28,IF(C47="customer",PERCENTILE(IF((D_sales!$C$5:$C$121=A47)*(D_sales!$W$5:$W$121=1),D_sales!$U$5:$U$121),0.25),PERCENTILE(IF(D_sales!$W$5:$W$121=1,D_sales!$U$5:$U$121),0.25)))} -> 0 | G47: {=IF(C47="default",D_F01!$B$28,IF(C47="customer",PERCENTILE(IF((D_sales!$C$5:$C$121=A47)*(D_sales!$W$5:$W$121=1),D_sales!$U$5:$U$121),0.75),PERCENTILE(IF(D_sales!$W$5:$W$121=1,D_sales!$U$5:$U$121),0.75)))} -> 3 | H47: =MIN(E47,F47) -> 0 | I47: =MAX(E47,G47) -> 3 | J47: =IF(C47="customer",SUMIFS(D_sales!$Y$5:$Y$121,D_sales!$C$5:$C$121,A47),IF(C47="firm",SUM(D_sales!$Y$5:$Y$121),0)) -> 2
A48: BYR-F01-005 | B48: =COUNTIFS(D_sales!$C$5:$C$121,A48,D_sales!$W$5:$W$121,1) -> 17 | C48: =IF(B48>=D_F01!$B$26,"customer",IF(SUM(D_sales!$W$5:$W$121)>=D_F01!$B$26,"firm","default")) -> customer | D48: =IF(C48="customer",B48,IF(C48="firm",SUM(D_sales!$W$5:$W$121),0)) -> 17 | E48: =IF(C48="default",D_F01!$B$28,IF(C48="customer",SUMIFS(D_sales!$X$5:$X$121,D_sales!$C$5:$C$121,A48)/SUMIFS(D_sales!$V$5:$V$121,D_sales!$C$5:$C$121,A48),SUM(D_sales!$X$5:$X$121)/SUM(D_sales!$V$5:$V$121))) -> 14.556285 | F48: {=IF(C48="default",D_F01!$B$28,IF(C48="customer",PERCENTILE(IF((D_sales!$C$5:$C$121=A48)*(D_sales!$W$5:$W$121=1),D_sales!$U$5:$U$121),0.25),PERCENTILE(IF(D_sales!$W$5:$W$121=1,D_sales!$U$5:$U$121),0.25)))} -> 4 | G48: {=IF(C48="default",D_F01!$B$28,IF(C48="customer",PERCENTILE(IF((D_sales!$C$5:$C$121=A48)*(D_sales!$W$5:$W$121=1),D_sales!$U$5:$U$121),0.75),PERCENTILE(IF(D_sales!$W$5:$W$121=1,D_sales!$U$5:$U$121),0.75)))} -> 10 | H48: =MIN(E48,F48) -> 4 | I48: =MAX(E48,G48) -> 14.556285 | J48: =IF(C48="customer",SUMIFS(D_sales!$Y$5:$Y$121,D_sales!$C$5:$C$121,A48),IF(C48="firm",SUM(D_sales!$Y$5:$Y$121),0)) -> 2
A49: BYR-F01-006 | B49: =COUNTIFS(D_sales!$C$5:$C$121,A49,D_sales!$W$5:$W$121,1) -> 9 | C49: =IF(B49>=D_F01!$B$26,"customer",IF(SUM(D_sales!$W$5:$W$121)>=D_F01!$B$26,"firm","default")) -> customer | D49: =IF(C49="customer",B49,IF(C49="firm",SUM(D_sales!$W$5:$W$121),0)) -> 9 | E49: =IF(C49="default",D_F01!$B$28,IF(C49="customer",SUMIFS(D_sales!$X$5:$X$121,D_sales!$C$5:$C$121,A49)/SUMIFS(D_sales!$V$5:$V$121,D_sales!$C$5:$C$121,A49),SUM(D_sales!$X$5:$X$121)/SUM(D_sales!$V$5:$V$121))) -> 1.7928491 | F49: {=IF(C49="default",D_F01!$B$28,IF(C49="customer",PERCENTILE(IF((D_sales!$C$5:$C$121=A49)*(D_sales!$W$5:$W$121=1),D_sales!$U$5:$U$121),0.25),PERCENTILE(IF(D_sales!$W$5:$W$121=1,D_sales!$U$5:$U$121),0.25)))} -> 0 | G49: {=IF(C49="default",D_F01!$B$28,IF(C49="customer",PERCENTILE(IF((D_sales!$C$5:$C$121=A49)*(D_sales!$W$5:$W$121=1),D_sales!$U$5:$U$121),0.75),PERCENTILE(IF(D_sales!$W$5:$W$121=1,D_sales!$U$5:$U$121),0.75)))} -> 2 | H49: =MIN(E49,F49) -> 0 | I49: =MAX(E49,G49) -> 2 | J49: =IF(C49="customer",SUMIFS(D_sales!$Y$5:$Y$121,D_sales!$C$5:$C$121,A49),IF(C49="firm",SUM(D_sales!$Y$5:$Y$121),0)) -> 1
A50: BYR-F01-003 | B50: =COUNTIFS(D_sales!$C$5:$C$121,A50,D_sales!$W$5:$W$121,1) -> 13 | C50: =IF(B50>=D_F01!$B$26,"customer",IF(SUM(D_sales!$W$5:$W$121)>=D_F01!$B$26,"firm","default")) -> customer | D50: =IF(C50="customer",B50,IF(C50="firm",SUM(D_sales!$W$5:$W$121),0)) -> 13 | E50: =IF(C50="default",D_F01!$B$28,IF(C50="customer",SUMIFS(D_sales!$X$5:$X$121,D_sales!$C$5:$C$121,A50)/SUMIFS(D_sales!$V$5:$V$121,D_sales!$C$5:$C$121,A50),SUM(D_sales!$X$5:$X$121)/SUM(D_sales!$V$5:$V$121))) -> 2.0202039 | F50: {=IF(C50="default",D_F01!$B$28,IF(C50="customer",PERCENTILE(IF((D_sales!$C$5:$C$121=A50)*(D_sales!$W$5:$W$121=1),D_sales!$U$5:$U$121),0.25),PERCENTILE(IF(D_sales!$W$5:$W$121=1,D_sales!$U$5:$U$121),0.25)))} -> 0 | G50: {=IF(C50="default",D_F01!$B$28,IF(C50="customer",PERCENTILE(IF((D_sales!$C$5:$C$121=A50)*(D_sales!$W$5:$W$121=1),D_sales!$U$5:$U$121),0.75),PERCENTILE(IF(D_sales!$W$5:$W$121=1,D_sales!$U$5:$U$121),0.75)))} -> 4 | H50: =MIN(E50,F50) -> 0 | I50: =MAX(E50,G50) -> 4 | J50: =IF(C50="customer",SUMIFS(D_sales!$Y$5:$Y$121,D_sales!$C$5:$C$121,A50),IF(C50="firm",SUM(D_sales!$Y$5:$Y$121),0)) -> 0
A51: BYR-F01-007 | B51: =COUNTIFS(D_sales!$C$5:$C$121,A51,D_sales!$W$5:$W$121,1) -> 3 | C51: =IF(B51>=D_F01!$B$26,"customer",IF(SUM(D_sales!$W$5:$W$121)>=D_F01!$B$26,"firm","default")) -> firm | D51: =IF(C51="customer",B51,IF(C51="firm",SUM(D_sales!$W$5:$W$121),0)) -> 98 | E51: =IF(C51="default",D_F01!$B$28,IF(C51="customer",SUMIFS(D_sales!$X$5:$X$121,D_sales!$C$5:$C$121,A51)/SUMIFS(D_sales!$V$5:$V$121,D_sales!$C$5:$C$121,A51),SUM(D_sales!$X$5:$X$121)/SUM(D_sales!$V$5:$V$121))) -> 7.4681548 | F51: {=IF(C51="default",D_F01!$B$28,IF(C51="customer",PERCENTILE(IF((D_sales!$C$5:$C$121=A51)*(D_sales!$W$5:$W$121=1),D_sales!$U$5:$U$121),0.25),PERCENTILE(IF(D_sales!$W$5:$W$121=1,D_sales!$U$5:$U$121),0.25)))} -> 0 | G51: {=IF(C51="default",D_F01!$B$28,IF(C51="customer",PERCENTILE(IF((D_sales!$C$5:$C$121=A51)*(D_sales!$W$5:$W$121=1),D_sales!$U$5:$U$121),0.75),PERCENTILE(IF(D_sales!$W$5:$W$121=1,D_sales!$U$5:$U$121),0.75)))} -> 9 | H51: =MIN(E51,F51) -> 0 | I51: =MAX(E51,G51) -> 9 | J51: =IF(C51="customer",SUMIFS(D_sales!$Y$5:$Y$121,D_sales!$C$5:$C$121,A51),IF(C51="firm",SUM(D_sales!$Y$5:$Y$121),0)) -> 14
A52: BYR-F01-004 | B52: =COUNTIFS(D_sales!$C$5:$C$121,A52,D_sales!$W$5:$W$121,1) -> 1 | C52: =IF(B52>=D_F01!$B$26,"customer",IF(SUM(D_sales!$W$5:$W$121)>=D_F01!$B$26,"firm","default")) -> firm | D52: =IF(C52="customer",B52,IF(C52="firm",SUM(D_sales!$W$5:$W$121),0)) -> 98 | E52: =IF(C52="default",D_F01!$B$28,IF(C52="customer",SUMIFS(D_sales!$X$5:$X$121,D_sales!$C$5:$C$121,A52)/SUMIFS(D_sales!$V$5:$V$121,D_sales!$C$5:$C$121,A52),SUM(D_sales!$X$5:$X$121)/SUM(D_sales!$V$5:$V$121))) -> 7.4681548 | F52: {=IF(C52="default",D_F01!$B$28,IF(C52="customer",PERCENTILE(IF((D_sales!$C$5:$C$121=A52)*(D_sales!$W$5:$W$121=1),D_sales!$U$5:$U$121),0.25),PERCENTILE(IF(D_sales!$W$5:$W$121=1,D_sales!$U$5:$U$121),0.25)))} -> 0 | G52: {=IF(C52="default",D_F01!$B$28,IF(C52="customer",PERCENTILE(IF((D_sales!$C$5:$C$121=A52)*(D_sales!$W$5:$W$121=1),D_sales!$U$5:$U$121),0.75),PERCENTILE(IF(D_sales!$W$5:$W$121=1,D_sales!$U$5:$U$121),0.75)))} -> 9 | H52: =MIN(E52,F52) -> 0 | I52: =MAX(E52,G52) -> 9 | J52: =IF(C52="customer",SUMIFS(D_sales!$Y$5:$Y$121,D_sales!$C$5:$C$121,A52),IF(C52="firm",SUM(D_sales!$Y$5:$Y$121),0)) -> 14
A53: BYR-F01-008 | B53: =COUNTIFS(D_sales!$C$5:$C$121,A53,D_sales!$W$5:$W$121,1) -> 4 | C53: =IF(B53>=D_F01!$B$26,"customer",IF(SUM(D_sales!$W$5:$W$121)>=D_F01!$B$26,"firm","default")) -> firm | D53: =IF(C53="customer",B53,IF(C53="firm",SUM(D_sales!$W$5:$W$121),0)) -> 98 | E53: =IF(C53="default",D_F01!$B$28,IF(C53="customer",SUMIFS(D_sales!$X$5:$X$121,D_sales!$C$5:$C$121,A53)/SUMIFS(D_sales!$V$5:$V$121,D_sales!$C$5:$C$121,A53),SUM(D_sales!$X$5:$X$121)/SUM(D_sales!$V$5:$V$121))) -> 7.4681548 | F53: {=IF(C53="default",D_F01!$B$28,IF(C53="customer",PERCENTILE(IF((D_sales!$C$5:$C$121=A53)*(D_sales!$W$5:$W$121=1),D_sales!$U$5:$U$121),0.25),PERCENTILE(IF(D_sales!$W$5:$W$121=1,D_sales!$U$5:$U$121),0.25)))} -> 0 | G53: {=IF(C53="default",D_F01!$B$28,IF(C53="customer",PERCENTILE(IF((D_sales!$C$5:$C$121=A53)*(D_sales!$W$5:$W$121=1),D_sales!$U$5:$U$121),0.75),PERCENTILE(IF(D_sales!$W$5:$W$121=1,D_sales!$U$5:$U$121),0.75)))} -> 9 | H53: =MIN(E53,F53) -> 0 | I53: =MAX(E53,G53) -> 9 | J53: =IF(C53="customer",SUMIFS(D_sales!$Y$5:$Y$121,D_sales!$C$5:$C$121,A53),IF(C53="firm",SUM(D_sales!$Y$5:$Y$121),0)) -> 14
A54: BYR-F01-009 | B54: =COUNTIFS(D_sales!$C$5:$C$121,A54,D_sales!$W$5:$W$121,1) -> 2 | C54: =IF(B54>=D_F01!$B$26,"customer",IF(SUM(D_sales!$W$5:$W$121)>=D_F01!$B$26,"firm","default")) -> firm | D54: =IF(C54="customer",B54,IF(C54="firm",SUM(D_sales!$W$5:$W$121),0)) -> 98 | E54: =IF(C54="default",D_F01!$B$28,IF(C54="customer",SUMIFS(D_sales!$X$5:$X$121,D_sales!$C$5:$C$121,A54)/SUMIFS(D_sales!$V$5:$V$121,D_sales!$C$5:$C$121,A54),SUM(D_sales!$X$5:$X$121)/SUM(D_sales!$V$5:$V$121))) -> 7.4681548 | F54: {=IF(C54="default",D_F01!$B$28,IF(C54="customer",PERCENTILE(IF((D_sales!$C$5:$C$121=A54)*(D_sales!$W$5:$W$121=1),D_sales!$U$5:$U$121),0.25),PERCENTILE(IF(D_sales!$W$5:$W$121=1,D_sales!$U$5:$U$121),0.25)))} -> 0 | G54: {=IF(C54="default",D_F01!$B$28,IF(C54="customer",PERCENTILE(IF((D_sales!$C$5:$C$121=A54)*(D_sales!$W$5:$W$121=1),D_sales!$U$5:$U$121),0.75),PERCENTILE(IF(D_sales!$W$5:$W$121=1,D_sales!$U$5:$U$121),0.75)))} -> 9 | H54: =MIN(E54,F54) -> 0 | I54: =MAX(E54,G54) -> 9 | J54: =IF(C54="customer",SUMIFS(D_sales!$Y$5:$Y$121,D_sales!$C$5:$C$121,A54),IF(C54="firm",SUM(D_sales!$Y$5:$Y$121),0)) -> 14
A69: Date | B69: In | C69: Out | D69: CumNet | E69: Opening | F69: Net | G69: Closing | H69: GapTarget | I69: GapZero | J69: GapRatio | K69: Level | L69: EpisodeId | M69: SurplusStreak | N69: StartFlag | O69: EndFlag | P69: EpisodeDays | Q69: ReserveTarget
A70: =$B$6+0 -> 46204 | B70: =SUMIFS($E$220:$E$341,$D$220:$D$341,"IN",$N$220:$N$341,A70) -> 0 | C70: =SUMIFS($E$220:$E$341,$D$220:$D$341,"OUT",$N$220:$N$341,A70) -> 180000000 | D70: =SUM($F$70:F70) -> -180000000 | E70: =$B$8 -> 4401925973 | F70: =B70-C70 -> -180000000 | G70: =E70+F70 -> 4221925973 | H70: =IF(G70<$B$9,$B$10-G70,0) -> 2.6340399e+09 | I70: =MAX(0,-G70) -> 0 | J70: =H70/$B$10 -> 0.38419677 | K70: =IF(G70<$B$9,3,0) -> 3 | L70: =IF(G70<$B$9,SUM($N$70:N70),0) -> 1 | M70: =IF(G70>$B$11,0+1,0) -> 0 | N70: =IF(AND(G70<$B$9,TRUE()),1,0) -> 1 | O70: =IF(AND(G70<$B$9,G71>=$B$9),1,0) -> 0 | P70: =IF(L70>0,COUNTIF($L$70:L70,L70),0) -> 1 | Q70: =$B$10 -> 6.8559659e+09
A71: =$B$6+1 -> 46205 | B71: =SUMIFS($E$220:$E$341,$D$220:$D$341,"IN",$N$220:$N$341,A71) -> 0 | C71: =SUMIFS($E$220:$E$341,$D$220:$D$341,"OUT",$N$220:$N$341,A71) -> 81445536 | D71: =SUM($F$70:F71) -> -261445536 | E71: =G70 -> 4221925973 | F71: =B71-C71 -> -81445536 | G71: =E71+F71 -> 4140480437 | H71: =IF(G71<$B$9,$B$10-G71,0) -> 2.7154855e+09 | I71: =MAX(0,-G71) -> 0 | J71: =H71/$B$10 -> 0.39607628 | K71: =IF(G71<$B$9,3,0) -> 3 | L71: =IF(G71<$B$9,SUM($N$70:N71),0) -> 1 | M71: =IF(G71>$B$11,M70+1,0) -> 0 | N71: =IF(AND(G71<$B$9,G70>=$B$9),1,0) -> 0 | O71: =IF(AND(G71<$B$9,G72>=$B$9),1,0) -> 0 | P71: =IF(L71>0,COUNTIF($L$70:L71,L71),0) -> 2 | Q71: =$B$10 -> 6.8559659e+09
A72: =$B$6+2 -> 46206 | B72: =SUMIFS($E$220:$E$341,$D$220:$D$341,"IN",$N$220:$N$341,A72) -> 1015281069 | C72: =SUMIFS($E$220:$E$341,$D$220:$D$341,"OUT",$N$220:$N$341,A72) -> 371409792 | D72: =SUM($F$70:F72) -> 382425741 | E72: =G71 -> 4140480437 | F72: =B72-C72 -> 643871277 | G72: =E72+F72 -> 4784351714 | H72: =IF(G72<$B$9,$B$10-G72,0) -> 2.0716142e+09 | I72: =MAX(0,-G72) -> 0 | J72: =H72/$B$10 -> 0.30216226 | K72: =IF(G72<$B$9,3,0) -> 3 | L72: =IF(G72<$B$9,SUM($N$70:N72),0) -> 1 | M72: =IF(G72>$B$11,M71+1,0) -> 0 | N72: =IF(AND(G72<$B$9,G71>=$B$9),1,0) -> 0 | O72: =IF(AND(G72<$B$9,G73>=$B$9),1,0) -> 1 | P72: =IF(L72>0,COUNTIF($L$70:L72,L72),0) -> 3 | Q72: =$B$10 -> 6.8559659e+09
A73: =$B$6+3 -> 46207 | B73: =SUMIFS($E$220:$E$341,$D$220:$D$341,"IN",$N$220:$N$341,A73) -> 1915815109 | C73: =SUMIFS($E$220:$E$341,$D$220:$D$341,"OUT",$N$220:$N$341,A73) -> 138127368 | D73: =SUM($F$70:F73) -> 2160113482 | E73: =G72 -> 4784351714 | F73: =B73-C73 -> 1777687741 | G73: =E73+F73 -> 6562039455 | H73: =IF(G73<$B$9,$B$10-G73,0) -> 0 | I73: =MAX(0,-G73) -> 0 | J73: =H73/$B$10 -> 0 | K73: =IF(G73<$B$9,3,0) -> 0 | L73: =IF(G73<$B$9,SUM($N$70:N73),0) -> 0 | M73: =IF(G73>$B$11,M72+1,0) -> 0 | N73: =IF(AND(G73<$B$9,G72>=$B$9),1,0) -> 0 | O73: =IF(AND(G73<$B$9,G74>=$B$9),1,0) -> 0 | P73: =IF(L73>0,COUNTIF($L$70:L73,L73),0) -> 0 | Q73: =$B$10 -> 6.8559659e+09
A74: =$B$6+4 -> 46208 | B74: =SUMIFS($E$220:$E$341,$D$220:$D$341,"IN",$N$220:$N$341,A74) -> 0 | C74: =SUMIFS($E$220:$E$341,$D$220:$D$341,"OUT",$N$220:$N$341,A74) -> 1298279892 | D74: =SUM($F$70:F74) -> 861833590 | E74: =G73 -> 6562039455 | F74: =B74-C74 -> -1298279892 | G74: =E74+F74 -> 5263759563 | H74: =IF(G74<$B$9,$B$10-G74,0) -> 1.5922063e+09 | I74: =MAX(0,-G74) -> 0 | J74: =H74/$B$10 -> 0.23223662 | K74: =IF(G74<$B$9,3,0) -> 3 | L74: =IF(G74<$B$9,SUM($N$70:N74),0) -> 2 | M74: =IF(G74>$B$11,M73+1,0) -> 0 | N74: =IF(AND(G74<$B$9,G73>=$B$9),1,0) -> 1 | O74: =IF(AND(G74<$B$9,G75>=$B$9),1,0) -> 0 | P74: =IF(L74>0,COUNTIF($L$70:L74,L74),0) -> 1 | Q74: =$B$10 -> 6.8559659e+09
A75: =$B$6+5 -> 46209 | B75: =SUMIFS($E$220:$E$341,$D$220:$D$341,"IN",$N$220:$N$341,A75) -> 0 | C75: =SUMIFS($E$220:$E$341,$D$220:$D$341,"OUT",$N$220:$N$341,A75) -> 0 | D75: =SUM($F$70:F75) -> 861833590 | E75: =G74 -> 5263759563 | F75: =B75-C75 -> 0 | G75: =E75+F75 -> 5263759563 | H75: =IF(G75<$B$9,$B$10-G75,0) -> 1.5922063e+09 | I75: =MAX(0,-G75) -> 0 | J75: =H75/$B$10 -> 0.23223662 | K75: =IF(G75<$B$9,3,0) -> 3 | L75: =IF(G75<$B$9,SUM($N$70:N75),0) -> 2 | M75: =IF(G75>$B$11,M74+1,0) -> 0 | N75: =IF(AND(G75<$B$9,G74>=$B$9),1,0) -> 0 | O75: =IF(AND(G75<$B$9,G76>=$B$9),1,0) -> 0 | P75: =IF(L75>0,COUNTIF($L$70:L75,L75),0) -> 2 | Q75: =$B$10 -> 6.8559659e+09
A76: =$B$6+6 -> 46210 | B76: =SUMIFS($E$220:$E$341,$D$220:$D$341,"IN",$N$220:$N$341,A76) -> 320784319 | C76: =SUMIFS($E$220:$E$341,$D$220:$D$341,"OUT",$N$220:$N$341,A76) -> 1068969126 | D76: =SUM($F$70:F76) -> 113648783 | E76: =G75 -> 5263759563 | F76: =B76-C76 -> -748184807 | G76: =E76+F76 -> 4515574756 | H76: =IF(G76<$B$9,$B$10-G76,0) -> 2.3403911e+09 | I76: =MAX(0,-G76) -> 0 | J76: =H76/$B$10 -> 0.34136563 | K76: =IF(G76<$B$9,3,0) -> 3 | L76: =IF(G76<$B$9,SUM($N$70:N76),0) -> 2 | M76: =IF(G76>$B$11,M75+1,0) -> 0 | N76: =IF(AND(G76<$B$9,G75>=$B$9),1,0) -> 0 | O76: =IF(AND(G76<$B$9,G77>=$B$9),1,0) -> 0 | P76: =IF(L76>0,COUNTIF($L$70:L76,L76),0) -> 3 | Q76: =$B$10 -> 6.8559659e+09
A77: =$B$6+7 -> 46211 | B77: =SUMIFS($E$220:$E$341,$D$220:$D$341,"IN",$N$220:$N$341,A77) -> 799012315 | C77: =SUMIFS($E$220:$E$341,$D$220:$D$341,"OUT",$N$220:$N$341,A77) -> 0 | D77: =SUM($F$70:F77) -> 912661098 | E77: =G76 -> 4515574756 | F77: =B77-C77 -> 799012315 | G77: =E77+F77 -> 5314587071 | H77: =IF(G77<$B$9,$B$10-G77,0) -> 1.5413788e+09 | I77: =MAX(0,-G77) -> 0 | J77: =H77/$B$10 -> 0.224823 | K77: =IF(G77<$B$9,3,0) -> 3 | L77: =IF(G77<$B$9,SUM($N$70:N77),0) -> 2 | M77: =IF(G77>$B$11,M76+1,0) -> 0 | N77: =IF(AND(G77<$B$9,G76>=$B$9),1,0) -> 0 | O77: =IF(AND(G77<$B$9,G78>=$B$9),1,0) -> 1 | P77: =IF(L77>0,COUNTIF($L$70:L77,L77),0) -> 4 | Q77: =$B$10 -> 6.8559659e+09
A78: =$B$6+8 -> 46212 | B78: =SUMIFS($E$220:$E$341,$D$220:$D$341,"IN",$N$220:$N$341,A78) -> 574833910 | C78: =SUMIFS($E$220:$E$341,$D$220:$D$341,"OUT",$N$220:$N$341,A78) -> 0 | D78: =SUM($F$70:F78) -> 1487495008 | E78: =G77 -> 5314587071 | F78: =B78-C78 -> 574833910 | G78: =E78+F78 -> 5889420981 | H78: =IF(G78<$B$9,$B$10-G78,0) -> 0 | I78: =MAX(0,-G78) -> 0 | J78: =H78/$B$10 -> 0 | K78: =IF(G78<$B$9,3,0) -> 0 | L78: =IF(G78<$B$9,SUM($N$70:N78),0) -> 0 | M78: =IF(G78>$B$11,M77+1,0) -> 0 | N78: =IF(AND(G78<$B$9,G77>=$B$9),1,0) -> 0 | O78: =IF(AND(G78<$B$9,G79>=$B$9),1,0) -> 0 | P78: =IF(L78>0,COUNTIF($L$70:L78,L78),0) -> 0 | Q78: =$B$10 -> 6.8559659e+09
A79: =$B$6+9 -> 46213 | B79: =SUMIFS($E$220:$E$341,$D$220:$D$341,"IN",$N$220:$N$341,A79) -> 3316615969 | C79: =SUMIFS($E$220:$E$341,$D$220:$D$341,"OUT",$N$220:$N$341,A79) -> 94380226 | D79: =SUM($F$70:F79) -> 4709730751 | E79: =G78 -> 5889420981 | F79: =B79-C79 -> 3222235743 | G79: =E79+F79 -> 9111656724 | H79: =IF(G79<$B$9,$B$10-G79,0) -> 0 | I79: =MAX(0,-G79) -> 0 | J79: =H79/$B$10 -> 0 | K79: =IF(G79<$B$9,3,0) -> 0 | L79: =IF(G79<$B$9,SUM($N$70:N79),0) -> 0 | M79: =IF(G79>$B$11,M78+1,0) -> 0 | N79: =IF(AND(G79<$B$9,G78>=$B$9),1,0) -> 0 | O79: =IF(AND(G79<$B$9,G80>=$B$9),1,0) -> 0 | P79: =IF(L79>0,COUNTIF($L$70:L79,L79),0) -> 0 | Q79: =$B$10 -> 6.8559659e+09
A80: =$B$6+10 -> 46214 | B80: =SUMIFS($E$220:$E$341,$D$220:$D$341,"IN",$N$220:$N$341,A80) -> 967551008 | C80: =SUMIFS($E$220:$E$341,$D$220:$D$341,"OUT",$N$220:$N$341,A80) -> 389201455 | D80: =SUM($F$70:F80) -> 5288080304 | E80: =G79 -> 9111656724 | F80: =B80-C80 -> 578349553 | G80: =E80+F80 -> 9690006277 | H80: =IF(G80<$B$9,$B$10-G80,0) -> 0 | I80: =MAX(0,-G80) -> 0 | J80: =H80/$B$10 -> 0 | K80: =IF(G80<$B$9,3,0) -> 0 | L80: =IF(G80<$B$9,SUM($N$70:N80),0) -> 0 | M80: =IF(G80>$B$11,M79+1,0) -> 1 | N80: =IF(AND(G80<$B$9,G79>=$B$9),1,0) -> 0 | O80: =IF(AND(G80<$B$9,G81>=$B$9),1,0) -> 0 | P80: =IF(L80>0,COUNTIF($L$70:L80,L80),0) -> 0 | Q80: =$B$10 -> 6.8559659e+09
A81: =$B$6+11 -> 46215 | B81: =SUMIFS($E$220:$E$341,$D$220:$D$341,"IN",$N$220:$N$341,A81) -> 461323390 | C81: =SUMIFS($E$220:$E$341,$D$220:$D$341,"OUT",$N$220:$N$341,A81) -> 0 | D81: =SUM($F$70:F81) -> 5749403694 | E81: =G80 -> 9690006277 | F81: =B81-C81 -> 461323390 | G81: =E81+F81 -> 10151329667 | H81: =IF(G81<$B$9,$B$10-G81,0) -> 0 | I81: =MAX(0,-G81) -> 0 | J81: =H81/$B$10 -> 0 | K81: =IF(G81<$B$9,3,0) -> 0 | L81: =IF(G81<$B$9,SUM($N$70:N81),0) -> 0 | M81: =IF(G81>$B$11,M80+1,0) -> 2 | N81: =IF(AND(G81<$B$9,G80>=$B$9),1,0) -> 0 | O81: =IF(AND(G81<$B$9,G82>=$B$9),1,0) -> 0 | P81: =IF(L81>0,COUNTIF($L$70:L81,L81),0) -> 0 | Q81: =$B$10 -> 6.8559659e+09
A82: =$B$6+12 -> 46216 | B82: =SUMIFS($E$220:$E$341,$D$220:$D$341,"IN",$N$220:$N$341,A82) -> 0 | C82: =SUMIFS($E$220:$E$341,$D$220:$D$341,"OUT",$N$220:$N$341,A82) -> 0 | D82: =SUM($F$70:F82) -> 5749403694 | E82: =G81 -> 10151329667 | F82: =B82-C82 -> 0 | G82: =E82+F82 -> 10151329667 | H82: =IF(G82<$B$9,$B$10-G82,0) -> 0 | I82: =MAX(0,-G82) -> 0 | J82: =H82/$B$10 -> 0 | K82: =IF(G82<$B$9,3,0) -> 0 | L82: =IF(G82<$B$9,SUM($N$70:N82),0) -> 0 | M82: =IF(G82>$B$11,M81+1,0) -> 3 | N82: =IF(AND(G82<$B$9,G81>=$B$9),1,0) -> 0 | O82: =IF(AND(G82<$B$9,G83>=$B$9),1,0) -> 0 | P82: =IF(L82>0,COUNTIF($L$70:L82,L82),0) -> 0 | Q82: =$B$10 -> 6.8559659e+09
A83: =$B$6+13 -> 46217 | B83: =SUMIFS($E$220:$E$341,$D$220:$D$341,"IN",$N$220:$N$341,A83) -> 1251844762 | C83: =SUMIFS($E$220:$E$341,$D$220:$D$341,"OUT",$N$220:$N$341,A83) -> 346608630 | D83: =SUM($F$70:F83) -> 6654639826 | E83: =G82 -> 10151329667 | F83: =B83-C83 -> 905236132 | G83: =E83+F83 -> 11056565799 | H83: =IF(G83<$B$9,$B$10-G83,0) -> 0 | I83: =MAX(0,-G83) -> 0 | J83: =H83/$B$10 -> 0 | K83: =IF(G83<$B$9,3,0) -> 0 | L83: =IF(G83<$B$9,SUM($N$70:N83),0) -> 0 | M83: =IF(G83>$B$11,M82+1,0) -> 4 | N83: =IF(AND(G83<$B$9,G82>=$B$9),1,0) -> 0 | O83: =IF(AND(G83<$B$9,G84>=$B$9),1,0) -> 0 | P83: =IF(L83>0,COUNTIF($L$70:L83,L83),0) -> 0 | Q83: =$B$10 -> 6.8559659e+09
A84: =$B$6+14 -> 46218 | B84: =SUMIFS($E$220:$E$341,$D$220:$D$341,"IN",$N$220:$N$341,A84) -> 946197645 | C84: =SUMIFS($E$220:$E$341,$D$220:$D$341,"OUT",$N$220:$N$341,A84) -> 852090691 | D84: =SUM($F$70:F84) -> 6748746780 | E84: =G83 -> 11056565799 | F84: =B84-C84 -> 94106954 | G84: =E84+F84 -> 11150672753 | H84: =IF(G84<$B$9,$B$10-G84,0) -> 0 | I84: =MAX(0,-G84) -> 0 | J84: =H84/$B$10 -> 0 | K84: =IF(G84<$B$9,3,0) -> 0 | L84: =IF(G84<$B$9,SUM($N$70:N84),0) -> 0 | M84: =IF(G84>$B$11,M83+1,0) -> 5 | N84: =IF(AND(G84<$B$9,G83>=$B$9),1,0) -> 0 | O84: =IF(AND(G84<$B$9,G85>=$B$9),1,0) -> 0 | P84: =IF(L84>0,COUNTIF($L$70:L84,L84),0) -> 0 | Q84: =$B$10 -> 6.8559659e+09
A85: =$B$6+15 -> 46219 | B85: =SUMIFS($E$220:$E$341,$D$220:$D$341,"IN",$N$220:$N$341,A85) -> 0 | C85: =SUMIFS($E$220:$E$341,$D$220:$D$341,"OUT",$N$220:$N$341,A85) -> 0 | D85: =SUM($F$70:F85) -> 6748746780 | E85: =G84 -> 11150672753 | F85: =B85-C85 -> 0 | G85: =E85+F85 -> 11150672753 | H85: =IF(G85<$B$9,$B$10-G85,0) -> 0 | I85: =MAX(0,-G85) -> 0 | J85: =H85/$B$10 -> 0 | K85: =IF(G85<$B$9,3,0) -> 0 | L85: =IF(G85<$B$9,SUM($N$70:N85),0) -> 0 | M85: =IF(G85>$B$11,M84+1,0) -> 6 | N85: =IF(AND(G85<$B$9,G84>=$B$9),1,0) -> 0 | O85: =IF(AND(G85<$B$9,G86>=$B$9),1,0) -> 0 | P85: =IF(L85>0,COUNTIF($L$70:L85,L85),0) -> 0 | Q85: =$B$10 -> 6.8559659e+09
A86: =$B$6+16 -> 46220 | B86: =SUMIFS($E$220:$E$341,$D$220:$D$341,"IN",$N$220:$N$341,A86) -> 0 | C86: =SUMIFS($E$220:$E$341,$D$220:$D$341,"OUT",$N$220:$N$341,A86) -> 0 | D86: =SUM($F$70:F86) -> 6748746780 | E86: =G85 -> 11150672753 | F86: =B86-C86 -> 0 | G86: =E86+F86 -> 11150672753 | H86: =IF(G86<$B$9,$B$10-G86,0) -> 0 | I86: =MAX(0,-G86) -> 0 | J86: =H86/$B$10 -> 0 | K86: =IF(G86<$B$9,3,0) -> 0 | L86: =IF(G86<$B$9,SUM($N$70:N86),0) -> 0 | M86: =IF(G86>$B$11,M85+1,0) -> 7 | N86: =IF(AND(G86<$B$9,G85>=$B$9),1,0) -> 0 | O86: =IF(AND(G86<$B$9,G87>=$B$9),1,0) -> 0 | P86: =IF(L86>0,COUNTIF($L$70:L86,L86),0) -> 0 | Q86: =$B$10 -> 6.8559659e+09
A87: =$B$6+17 -> 46221 | B87: =SUMIFS($E$220:$E$341,$D$220:$D$341,"IN",$N$220:$N$341,A87) -> 1219755913 | C87: =SUMIFS($E$220:$E$341,$D$220:$D$341,"OUT",$N$220:$N$341,A87) -> 572395350 | D87: =SUM($F$70:F87) -> 7396107343 | E87: =G86 -> 11150672753 | F87: =B87-C87 -> 647360563 | G87: =E87+F87 -> 11798033316 | H87: =IF(G87<$B$9,$B$10-G87,0) -> 0 | I87: =MAX(0,-G87) -> 0 | J87: =H87/$B$10 -> 0 | K87: =IF(G87<$B$9,3,0) -> 0 | L87: =IF(G87<$B$9,SUM($N$70:N87),0) -> 0 | M87: =IF(G87>$B$11,M86+1,0) -> 8 | N87: =IF(AND(G87<$B$9,G86>=$B$9),1,0) -> 0 | O87: =IF(AND(G87<$B$9,G88>=$B$9),1,0) -> 0 | P87: =IF(L87>0,COUNTIF($L$70:L87,L87),0) -> 0 | Q87: =$B$10 -> 6.8559659e+09
A88: =$B$6+18 -> 46222 | B88: =SUMIFS($E$220:$E$341,$D$220:$D$341,"IN",$N$220:$N$341,A88) -> 560298165 | C88: =SUMIFS($E$220:$E$341,$D$220:$D$341,"OUT",$N$220:$N$341,A88) -> 0 | D88: =SUM($F$70:F88) -> 7956405508 | E88: =G87 -> 11798033316 | F88: =B88-C88 -> 560298165 | G88: =E88+F88 -> 12358331481 | H88: =IF(G88<$B$9,$B$10-G88,0) -> 0 | I88: =MAX(0,-G88) -> 0 | J88: =H88/$B$10 -> 0 | K88: =IF(G88<$B$9,3,0) -> 0 | L88: =IF(G88<$B$9,SUM($N$70:N88),0) -> 0 | M88: =IF(G88>$B$11,M87+1,0) -> 9 | N88: =IF(AND(G88<$B$9,G87>=$B$9),1,0) -> 0 | O88: =IF(AND(G88<$B$9,G89>=$B$9),1,0) -> 0 | P88: =IF(L88>0,COUNTIF($L$70:L88,L88),0) -> 0 | Q88: =$B$10 -> 6.8559659e+09
A89: =$B$6+19 -> 46223 | B89: =SUMIFS($E$220:$E$341,$D$220:$D$341,"IN",$N$220:$N$341,A89) -> 927740677 | C89: =SUMIFS($E$220:$E$341,$D$220:$D$341,"OUT",$N$220:$N$341,A89) -> 409641786 | D89: =SUM($F$70:F89) -> 8474504399 | E89: =G88 -> 12358331481 | F89: =B89-C89 -> 518098891 | G89: =E89+F89 -> 12876430372 | H89: =IF(G89<$B$9,$B$10-G89,0) -> 0 | I89: =MAX(0,-G89) -> 0 | J89: =H89/$B$10 -> 0 | K89: =IF(G89<$B$9,3,0) -> 0 | L89: =IF(G89<$B$9,SUM($N$70:N89),0) -> 0 | M89: =IF(G89>$B$11,M88+1,0) -> 10 | N89: =IF(AND(G89<$B$9,G88>=$B$9),1,0) -> 0 | O89: =IF(AND(G89<$B$9,G90>=$B$9),1,0) -> 0 | P89: =IF(L89>0,COUNTIF($L$70:L89,L89),0) -> 0 | Q89: =$B$10 -> 6.8559659e+09
A90: =$B$6+20 -> 46224 | B90: =SUMIFS($E$220:$E$341,$D$220:$D$341,"IN",$N$220:$N$341,A90) -> 0 | C90: =SUMIFS($E$220:$E$341,$D$220:$D$341,"OUT",$N$220:$N$341,A90) -> 468512740 | D90: =SUM($F$70:F90) -> 8005991659 | E90: =G89 -> 12876430372 | F90: =B90-C90 -> -468512740 | G90: =E90+F90 -> 12407917632 | H90: =IF(G90<$B$9,$B$10-G90,0) -> 0 | I90: =MAX(0,-G90) -> 0 | J90: =H90/$B$10 -> 0 | K90: =IF(G90<$B$9,3,0) -> 0 | L90: =IF(G90<$B$9,SUM($N$70:N90),0) -> 0 | M90: =IF(G90>$B$11,M89+1,0) -> 11 | N90: =IF(AND(G90<$B$9,G89>=$B$9),1,0) -> 0 | O90: =IF(AND(G90<$B$9,G91>=$B$9),1,0) -> 0 | P90: =IF(L90>0,COUNTIF($L$70:L90,L90),0) -> 0 | Q90: =$B$10 -> 6.8559659e+09
A91: =$B$6+21 -> 46225 | B91: =SUMIFS($E$220:$E$341,$D$220:$D$341,"IN",$N$220:$N$341,A91) -> 0 | C91: =SUMIFS($E$220:$E$341,$D$220:$D$341,"OUT",$N$220:$N$341,A91) -> 432157866 | D91: =SUM($F$70:F91) -> 7573833793 | E91: =G90 -> 12407917632 | F91: =B91-C91 -> -432157866 | G91: =E91+F91 -> 11975759766 | H91: =IF(G91<$B$9,$B$10-G91,0) -> 0 | I91: =MAX(0,-G91) -> 0 | J91: =H91/$B$10 -> 0 | K91: =IF(G91<$B$9,3,0) -> 0 | L91: =IF(G91<$B$9,SUM($N$70:N91),0) -> 0 | M91: =IF(G91>$B$11,M90+1,0) -> 12 | N91: =IF(AND(G91<$B$9,G90>=$B$9),1,0) -> 0 | O91: =IF(AND(G91<$B$9,G92>=$B$9),1,0) -> 0 | P91: =IF(L91>0,COUNTIF($L$70:L91,L91),0) -> 0 | Q91: =$B$10 -> 6.8559659e+09
A92: =$B$6+22 -> 46226 | B92: =SUMIFS($E$220:$E$341,$D$220:$D$341,"IN",$N$220:$N$341,A92) -> 274915745 | C92: =SUMIFS($E$220:$E$341,$D$220:$D$341,"OUT",$N$220:$N$341,A92) -> 312945067 | D92: =SUM($F$70:F92) -> 7535804471 | E92: =G91 -> 11975759766 | F92: =B92-C92 -> -38029322 | G92: =E92+F92 -> 11937730444 | H92: =IF(G92<$B$9,$B$10-G92,0) -> 0 | I92: =MAX(0,-G92) -> 0 | J92: =H92/$B$10 -> 0 | K92: =IF(G92<$B$9,3,0) -> 0 | L92: =IF(G92<$B$9,SUM($N$70:N92),0) -> 0 | M92: =IF(G92>$B$11,M91+1,0) -> 13 | N92: =IF(AND(G92<$B$9,G91>=$B$9),1,0) -> 0 | O92: =IF(AND(G92<$B$9,G93>=$B$9),1,0) -> 0 | P92: =IF(L92>0,COUNTIF($L$70:L92,L92),0) -> 0 | Q92: =$B$10 -> 6.8559659e+09
A93: =$B$6+23 -> 46227 | B93: =SUMIFS($E$220:$E$341,$D$220:$D$341,"IN",$N$220:$N$341,A93) -> 0 | C93: =SUMIFS($E$220:$E$341,$D$220:$D$341,"OUT",$N$220:$N$341,A93) -> 0 | D93: =SUM($F$70:F93) -> 7535804471 | E93: =G92 -> 11937730444 | F93: =B93-C93 -> 0 | G93: =E93+F93 -> 11937730444 | H93: =IF(G93<$B$9,$B$10-G93,0) -> 0 | I93: =MAX(0,-G93) -> 0 | J93: =H93/$B$10 -> 0 | K93: =IF(G93<$B$9,3,0) -> 0 | L93: =IF(G93<$B$9,SUM($N$70:N93),0) -> 0 | M93: =IF(G93>$B$11,M92+1,0) -> 14 | N93: =IF(AND(G93<$B$9,G92>=$B$9),1,0) -> 0 | O93: =IF(AND(G93<$B$9,G94>=$B$9),1,0) -> 0 | P93: =IF(L93>0,COUNTIF($L$70:L93,L93),0) -> 0 | Q93: =$B$10 -> 6.8559659e+09
A94: =$B$6+24 -> 46228 | B94: =SUMIFS($E$220:$E$341,$D$220:$D$341,"IN",$N$220:$N$341,A94) -> 1541800145 | C94: =SUMIFS($E$220:$E$341,$D$220:$D$341,"OUT",$N$220:$N$341,A94) -> 0 | D94: =SUM($F$70:F94) -> 9077604616 | E94: =G93 -> 11937730444 | F94: =B94-C94 -> 1541800145 | G94: =E94+F94 -> 13479530589 | H94: =IF(G94<$B$9,$B$10-G94,0) -> 0 | I94: =MAX(0,-G94) -> 0 | J94: =H94/$B$10 -> 0 | K94: =IF(G94<$B$9,3,0) -> 0 | L94: =IF(G94<$B$9,SUM($N$70:N94),0) -> 0 | M94: =IF(G94>$B$11,M93+1,0) -> 15 | N94: =IF(AND(G94<$B$9,G93>=$B$9),1,0) -> 0 | O94: =IF(AND(G94<$B$9,G95>=$B$9),1,0) -> 0 | P94: =IF(L94>0,COUNTIF($L$70:L94,L94),0) -> 0 | Q94: =$B$10 -> 6.8559659e+09
A95: =$B$6+25 -> 46229 | B95: =SUMIFS($E$220:$E$341,$D$220:$D$341,"IN",$N$220:$N$341,A95) -> 0 | C95: =SUMIFS($E$220:$E$341,$D$220:$D$341,"OUT",$N$220:$N$341,A95) -> 376724622 | D95: =SUM($F$70:F95) -> 8700879994 | E95: =G94 -> 13479530589 | F95: =B95-C95 -> -376724622 | G95: =E95+F95 -> 13102805967 | H95: =IF(G95<$B$9,$B$10-G95,0) -> 0 | I95: =MAX(0,-G95) -> 0 | J95: =H95/$B$10 -> 0 | K95: =IF(G95<$B$9,3,0) -> 0 | L95: =IF(G95<$B$9,SUM($N$70:N95),0) -> 0 | M95: =IF(G95>$B$11,M94+1,0) -> 16 | N95: =IF(AND(G95<$B$9,G94>=$B$9),1,0) -> 0 | O95: =IF(AND(G95<$B$9,G96>=$B$9),1,0) -> 0 | P95: =IF(L95>0,COUNTIF($L$70:L95,L95),0) -> 0 | Q95: =$B$10 -> 6.8559659e+09
A96: =$B$6+26 -> 46230 | B96: =SUMIFS($E$220:$E$341,$D$220:$D$341,"IN",$N$220:$N$341,A96) -> 833520428 | C96: =SUMIFS($E$220:$E$341,$D$220:$D$341,"OUT",$N$220:$N$341,A96) -> 604118372 | D96: =SUM($F$70:F96) -> 8930282050 | E96: =G95 -> 13102805967 | F96: =B96-C96 -> 229402056 | G96: =E96+F96 -> 13332208023 | H96: =IF(G96<$B$9,$B$10-G96,0) -> 0 | I96: =MAX(0,-G96) -> 0 | J96: =H96/$B$10 -> 0 | K96: =IF(G96<$B$9,3,0) -> 0 | L96: =IF(G96<$B$9,SUM($N$70:N96),0) -> 0 | M96: =IF(G96>$B$11,M95+1,0) -> 17 | N96: =IF(AND(G96<$B$9,G95>=$B$9),1,0) -> 0 | O96: =IF(AND(G96<$B$9,G97>=$B$9),1,0) -> 0 | P96: =IF(L96>0,COUNTIF($L$70:L96,L96),0) -> 0 | Q96: =$B$10 -> 6.8559659e+09
A97: =$B$6+27 -> 46231 | B97: =SUMIFS($E$220:$E$341,$D$220:$D$341,"IN",$N$220:$N$341,A97) -> 689203917 | C97: =SUMIFS($E$220:$E$341,$D$220:$D$341,"OUT",$N$220:$N$341,A97) -> 1500000000 | D97: =SUM($F$70:F97) -> 8119485967 | E97: =G96 -> 13332208023 | F97: =B97-C97 -> -810796083 | G97: =E97+F97 -> 12521411940 | H97: =IF(G97<$B$9,$B$10-G97,0) -> 0 | I97: =MAX(0,-G97) -> 0 | J97: =H97/$B$10 -> 0 | K97: =IF(G97<$B$9,3,0) -> 0 | L97: =IF(G97<$B$9,SUM($N$70:N97),0) -> 0 | M97: =IF(G97>$B$11,M96+1,0) -> 18 | N97: =IF(AND(G97<$B$9,G96>=$B$9),1,0) -> 0 | O97: =IF(AND(G97<$B$9,G98>=$B$9),1,0) -> 0 | P97: =IF(L97>0,COUNTIF($L$70:L97,L97),0) -> 0 | Q97: =$B$10 -> 6.8559659e+09
A98: =$B$6+28 -> 46232 | B98: =SUMIFS($E$220:$E$341,$D$220:$D$341,"IN",$N$220:$N$341,A98) -> 0 | C98: =SUMIFS($E$220:$E$341,$D$220:$D$341,"OUT",$N$220:$N$341,A98) -> 0 | D98: =SUM($F$70:F98) -> 8119485967 | E98: =G97 -> 12521411940 | F98: =B98-C98 -> 0 | G98: =E98+F98 -> 12521411940 | H98: =IF(G98<$B$9,$B$10-G98,0) -> 0 | I98: =MAX(0,-G98) -> 0 | J98: =H98/$B$10 -> 0 | K98: =IF(G98<$B$9,3,0) -> 0 | L98: =IF(G98<$B$9,SUM($N$70:N98),0) -> 0 | M98: =IF(G98>$B$11,M97+1,0) -> 19 | N98: =IF(AND(G98<$B$9,G97>=$B$9),1,0) -> 0 | O98: =IF(AND(G98<$B$9,G99>=$B$9),1,0) -> 0 | P98: =IF(L98>0,COUNTIF($L$70:L98,L98),0) -> 0 | Q98: =$B$10 -> 6.8559659e+09
A99: =$B$6+29 -> 46233 | B99: =SUMIFS($E$220:$E$341,$D$220:$D$341,"IN",$N$220:$N$341,A99) -> 296418085 | C99: =SUMIFS($E$220:$E$341,$D$220:$D$341,"OUT",$N$220:$N$341,A99) -> 176055378 | D99: =SUM($F$70:F99) -> 8239848674 | E99: =G98 -> 12521411940 | F99: =B99-C99 -> 120362707 | G99: =E99+F99 -> 12641774647 | H99: =IF(G99<$B$9,$B$10-G99,0) -> 0 | I99: =MAX(0,-G99) -> 0 | J99: =H99/$B$10 -> 0 | K99: =IF(G99<$B$9,3,0) -> 0 | L99: =IF(G99<$B$9,SUM($N$70:N99),0) -> 0 | M99: =IF(G99>$B$11,M98+1,0) -> 20 | N99: =IF(AND(G99<$B$9,G98>=$B$9),1,0) -> 0 | O99: =IF(AND(G99<$B$9,G100>=$B$9),1,0) -> 0 | P99: =IF(L99>0,COUNTIF($L$70:L99,L99),0) -> 0 | Q99: =$B$10 -> 6.8559659e+09
A100: =$B$6+30 -> 46234 | B100: =SUMIFS($E$220:$E$341,$D$220:$D$341,"IN",$N$220:$N$341,A100) -> 0 | C100: =SUMIFS($E$220:$E$341,$D$220:$D$341,"OUT",$N$220:$N$341,A100) -> 0 | D100: =SUM($F$70:F100) -> 8239848674 | E100: =G99 -> 12641774647 | F100: =B100-C100 -> 0 | G100: =E100+F100 -> 12641774647 | H100: =IF(G100<$B$9,$B$10-G100,0) -> 0 | I100: =MAX(0,-G100) -> 0 | J100: =H100/$B$10 -> 0 | K100: =IF(G100<$B$9,3,0) -> 0 | L100: =IF(G100<$B$9,SUM($N$70:N100),0) -> 0 | M100: =IF(G100>$B$11,M99+1,0) -> 21 | N100: =IF(AND(G100<$B$9,G99>=$B$9),1,0) -> 0 | O100: =IF(AND(G100<$B$9,G101>=$B$9),1,0) -> 0 | P100: =IF(L100>0,COUNTIF($L$70:L100,L100),0) -> 0 | Q100: =$B$10 -> 6.8559659e+09
A101: =$B$6+31 -> 46235 | B101: =SUMIFS($E$220:$E$341,$D$220:$D$341,"IN",$N$220:$N$341,A101) -> 0 | C101: =SUMIFS($E$220:$E$341,$D$220:$D$341,"OUT",$N$220:$N$341,A101) -> 180000000 | D101: =SUM($F$70:F101) -> 8059848674 | E101: =G100 -> 12641774647 | F101: =B101-C101 -> -180000000 | G101: =E101+F101 -> 12461774647 | H101: =IF(G101<$B$9,$B$10-G101,0) -> 0 | I101: =MAX(0,-G101) -> 0 | J101: =H101/$B$10 -> 0 | K101: =IF(G101<$B$9,3,0) -> 0 | L101: =IF(G101<$B$9,SUM($N$70:N101),0) -> 0 | M101: =IF(G101>$B$11,M100+1,0) -> 22 | N101: =IF(AND(G101<$B$9,G100>=$B$9),1,0) -> 0 | O101: =IF(AND(G101<$B$9,G102>=$B$9),1,0) -> 0 | P101: =IF(L101>0,COUNTIF($L$70:L101,L101),0) -> 0 | Q101: =$B$10 -> 6.8559659e+09
A102: =$B$6+32 -> 46236 | B102: =SUMIFS($E$220:$E$341,$D$220:$D$341,"IN",$N$220:$N$341,A102) -> 0 | C102: =SUMIFS($E$220:$E$341,$D$220:$D$341,"OUT",$N$220:$N$341,A102) -> 0 | D102: =SUM($F$70:F102) -> 8059848674 | E102: =G101 -> 12461774647 | F102: =B102-C102 -> 0 | G102: =E102+F102 -> 12461774647 | H102: =IF(G102<$B$9,$B$10-G102,0) -> 0 | I102: =MAX(0,-G102) -> 0 | J102: =H102/$B$10 -> 0 | K102: =IF(G102<$B$9,3,0) -> 0 | L102: =IF(G102<$B$9,SUM($N$70:N102),0) -> 0 | M102: =IF(G102>$B$11,M101+1,0) -> 23 | N102: =IF(AND(G102<$B$9,G101>=$B$9),1,0) -> 0 | O102: =IF(AND(G102<$B$9,G103>=$B$9),1,0) -> 0 | P102: =IF(L102>0,COUNTIF($L$70:L102,L102),0) -> 0 | Q102: =$B$10 -> 6.8559659e+09
A103: =$B$6+33 -> 46237 | B103: =SUMIFS($E$220:$E$341,$D$220:$D$341,"IN",$N$220:$N$341,A103) -> 0 | C103: =SUMIFS($E$220:$E$341,$D$220:$D$341,"OUT",$N$220:$N$341,A103) -> 0 | D103: =SUM($F$70:F103) -> 8059848674 | E103: =G102 -> 12461774647 | F103: =B103-C103 -> 0 | G103: =E103+F103 -> 12461774647 | H103: =IF(G103<$B$9,$B$10-G103,0) -> 0 | I103: =MAX(0,-G103) -> 0 | J103: =H103/$B$10 -> 0 | K103: =IF(G103<$B$9,3,0) -> 0 | L103: =IF(G103<$B$9,SUM($N$70:N103),0) -> 0 | M103: =IF(G103>$B$11,M102+1,0) -> 24 | N103: =IF(AND(G103<$B$9,G102>=$B$9),1,0) -> 0 | O103: =IF(AND(G103<$B$9,G104>=$B$9),1,0) -> 0 | P103: =IF(L103>0,COUNTIF($L$70:L103,L103),0) -> 0 | Q103: =$B$10 -> 6.8559659e+09
A104: =$B$6+34 -> 46238 | B104: =SUMIFS($E$220:$E$341,$D$220:$D$341,"IN",$N$220:$N$341,A104) -> 0 | C104: =SUMIFS($E$220:$E$341,$D$220:$D$341,"OUT",$N$220:$N$341,A104) -> 0 | D104: =SUM($F$70:F104) -> 8059848674 | E104: =G103 -> 12461774647 | F104: =B104-C104 -> 0 | G104: =E104+F104 -> 12461774647 | H104: =IF(G104<$B$9,$B$10-G104,0) -> 0 | I104: =MAX(0,-G104) -> 0 | J104: =H104/$B$10 -> 0 | K104: =IF(G104<$B$9,3,0) -> 0 | L104: =IF(G104<$B$9,SUM($N$70:N104),0) -> 0 | M104: =IF(G104>$B$11,M103+1,0) -> 25 | N104: =IF(AND(G104<$B$9,G103>=$B$9),1,0) -> 0 | O104: =IF(AND(G104<$B$9,G105>=$B$9),1,0) -> 0 | P104: =IF(L104>0,COUNTIF($L$70:L104,L104),0) -> 0 | Q104: =$B$10 -> 6.8559659e+09
A105: =$B$6+35 -> 46239 | B105: =SUMIFS($E$220:$E$341,$D$220:$D$341,"IN",$N$220:$N$341,A105) -> 0 | C105: =SUMIFS($E$220:$E$341,$D$220:$D$341,"OUT",$N$220:$N$341,A105) -> 0 | D105: =SUM($F$70:F105) -> 8059848674 | E105: =G104 -> 12461774647 | F105: =B105-C105 -> 0 | G105: =E105+F105 -> 12461774647 | H105: =IF(G105<$B$9,$B$10-G105,0) -> 0 | I105: =MAX(0,-G105) -> 0 | J105: =H105/$B$10 -> 0 | K105: =IF(G105<$B$9,3,0) -> 0 | L105: =IF(G105<$B$9,SUM($N$70:N105),0) -> 0 | M105: =IF(G105>$B$11,M104+1,0) -> 26 | N105: =IF(AND(G105<$B$9,G104>=$B$9),1,0) -> 0 | O105: =IF(AND(G105<$B$9,G106>=$B$9),1,0) -> 0 | P105: =IF(L105>0,COUNTIF($L$70:L105,L105),0) -> 0 | Q105: =$B$10 -> 6.8559659e+09
A106: =$B$6+36 -> 46240 | B106: =SUMIFS($E$220:$E$341,$D$220:$D$341,"IN",$N$220:$N$341,A106) -> 0 | C106: =SUMIFS($E$220:$E$341,$D$220:$D$341,"OUT",$N$220:$N$341,A106) -> 0 | D106: =SUM($F$70:F106) -> 8059848674 | E106: =G105 -> 12461774647 | F106: =B106-C106 -> 0 | G106: =E106+F106 -> 12461774647 | H106: =IF(G106<$B$9,$B$10-G106,0) -> 0 | I106: =MAX(0,-G106) -> 0 | J106: =H106/$B$10 -> 0 | K106: =IF(G106<$B$9,3,0) -> 0 | L106: =IF(G106<$B$9,SUM($N$70:N106),0) -> 0 | M106: =IF(G106>$B$11,M105+1,0) -> 27 | N106: =IF(AND(G106<$B$9,G105>=$B$9),1,0) -> 0 | O106: =IF(AND(G106<$B$9,G107>=$B$9),1,0) -> 0 | P106: =IF(L106>0,COUNTIF($L$70:L106,L106),0) -> 0 | Q106: =$B$10 -> 6.8559659e+09
A107: =$B$6+37 -> 46241 | B107: =SUMIFS($E$220:$E$341,$D$220:$D$341,"IN",$N$220:$N$341,A107) -> 0 | C107: =SUMIFS($E$220:$E$341,$D$220:$D$341,"OUT",$N$220:$N$341,A107) -> 0 | D107: =SUM($F$70:F107) -> 8059848674 | E107: =G106 -> 12461774647 | F107: =B107-C107 -> 0 | G107: =E107+F107 -> 12461774647 | H107: =IF(G107<$B$9,$B$10-G107,0) -> 0 | I107: =MAX(0,-G107) -> 0 | J107: =H107/$B$10 -> 0 | K107: =IF(G107<$B$9,3,0) -> 0 | L107: =IF(G107<$B$9,SUM($N$70:N107),0) -> 0 | M107: =IF(G107>$B$11,M106+1,0) -> 28 | N107: =IF(AND(G107<$B$9,G106>=$B$9),1,0) -> 0 | O107: =IF(AND(G107<$B$9,G108>=$B$9),1,0) -> 0 | P107: =IF(L107>0,COUNTIF($L$70:L107,L107),0) -> 0 | Q107: =$B$10 -> 6.8559659e+09
A108: =$B$6+38 -> 46242 | B108: =SUMIFS($E$220:$E$341,$D$220:$D$341,"IN",$N$220:$N$341,A108) -> 508774632 | C108: =SUMIFS($E$220:$E$341,$D$220:$D$341,"OUT",$N$220:$N$341,A108) -> 0 | D108: =SUM($F$70:F108) -> 8568623306 | E108: =G107 -> 12461774647 | F108: =B108-C108 -> 508774632 | G108: =E108+F108 -> 12970549279 | H108: =IF(G108<$B$9,$B$10-G108,0) -> 0 | I108: =MAX(0,-G108) -> 0 | J108: =H108/$B$10 -> 0 | K108: =IF(G108<$B$9,3,0) -> 0 | L108: =IF(G108<$B$9,SUM($N$70:N108),0) -> 0 | M108: =IF(G108>$B$11,M107+1,0) -> 29 | N108: =IF(AND(G108<$B$9,G107>=$B$9),1,0) -> 0 | O108: =IF(AND(G108<$B$9,G109>=$B$9),1,0) -> 0 | P108: =IF(L108>0,COUNTIF($L$70:L108,L108),0) -> 0 | Q108: =$B$10 -> 6.8559659e+09
A109: =$B$6+39 -> 46243 | B109: =SUMIFS($E$220:$E$341,$D$220:$D$341,"IN",$N$220:$N$341,A109) -> 2965863013 | C109: =SUMIFS($E$220:$E$341,$D$220:$D$341,"OUT",$N$220:$N$341,A109) -> 0 | D109: =SUM($F$70:F109) -> 11534486319 | E109: =G108 -> 12970549279 | F109: =B109-C109 -> 2965863013 | G109: =E109+F109 -> 15936412292 | H109: =IF(G109<$B$9,$B$10-G109,0) -> 0 | I109: =MAX(0,-G109) -> 0 | J109: =H109/$B$10 -> 0 | K109: =IF(G109<$B$9,3,0) -> 0 | L109: =IF(G109<$B$9,SUM($N$70:N109),0) -> 0 | M109: =IF(G109>$B$11,M108+1,0) -> 30 | N109: =IF(AND(G109<$B$9,G108>=$B$9),1,0) -> 0 | O109: =IF(AND(G109<$B$9,G110>=$B$9),1,0) -> 0 | P109: =IF(L109>0,COUNTIF($L$70:L109,L109),0) -> 0 | Q109: =$B$10 -> 6.8559659e+09
A110: =$B$6+40 -> 46244 | B110: =SUMIFS($E$220:$E$341,$D$220:$D$341,"IN",$N$220:$N$341,A110) -> 0 | C110: =SUMIFS($E$220:$E$341,$D$220:$D$341,"OUT",$N$220:$N$341,A110) -> 0 | D110: =SUM($F$70:F110) -> 11534486319 | E110: =G109 -> 15936412292 | F110: =B110-C110 -> 0 | G110: =E110+F110 -> 15936412292 | H110: =IF(G110<$B$9,$B$10-G110,0) -> 0 | I110: =MAX(0,-G110) -> 0 | J110: =H110/$B$10 -> 0 | K110: =IF(G110<$B$9,3,0) -> 0 | L110: =IF(G110<$B$9,SUM($N$70:N110),0) -> 0 | M110: =IF(G110>$B$11,M109+1,0) -> 31 | N110: =IF(AND(G110<$B$9,G109>=$B$9),1,0) -> 0 | O110: =IF(AND(G110<$B$9,G111>=$B$9),1,0) -> 0 | P110: =IF(L110>0,COUNTIF($L$70:L110,L110),0) -> 0 | Q110: =$B$10 -> 6.8559659e+09
A111: =$B$6+41 -> 46245 | B111: =SUMIFS($E$220:$E$341,$D$220:$D$341,"IN",$N$220:$N$341,A111) -> 0 | C111: =SUMIFS($E$220:$E$341,$D$220:$D$341,"OUT",$N$220:$N$341,A111) -> 0 | D111: =SUM($F$70:F111) -> 11534486319 | E111: =G110 -> 15936412292 | F111: =B111-C111 -> 0 | G111: =E111+F111 -> 15936412292 | H111: =IF(G111<$B$9,$B$10-G111,0) -> 0 | I111: =MAX(0,-G111) -> 0 | J111: =H111/$B$10 -> 0 | K111: =IF(G111<$B$9,3,0) -> 0 | L111: =IF(G111<$B$9,SUM($N$70:N111),0) -> 0 | M111: =IF(G111>$B$11,M110+1,0) -> 32 | N111: =IF(AND(G111<$B$9,G110>=$B$9),1,0) -> 0 | O111: =IF(AND(G111<$B$9,G112>=$B$9),1,0) -> 0 | P111: =IF(L111>0,COUNTIF($L$70:L111,L111),0) -> 0 | Q111: =$B$10 -> 6.8559659e+09
A112: =$B$6+42 -> 46246 | B112: =SUMIFS($E$220:$E$341,$D$220:$D$341,"IN",$N$220:$N$341,A112) -> 585623157 | C112: =SUMIFS($E$220:$E$341,$D$220:$D$341,"OUT",$N$220:$N$341,A112) -> 0 | D112: =SUM($F$70:F112) -> 12120109476 | E112: =G111 -> 15936412292 | F112: =B112-C112 -> 585623157 | G112: =E112+F112 -> 16522035449 | H112: =IF(G112<$B$9,$B$10-G112,0) -> 0 | I112: =MAX(0,-G112) -> 0 | J112: =H112/$B$10 -> 0 | K112: =IF(G112<$B$9,3,0) -> 0 | L112: =IF(G112<$B$9,SUM($N$70:N112),0) -> 0 | M112: =IF(G112>$B$11,M111+1,0) -> 33 | N112: =IF(AND(G112<$B$9,G111>=$B$9),1,0) -> 0 | O112: =IF(AND(G112<$B$9,G113>=$B$9),1,0) -> 0 | P112: =IF(L112>0,COUNTIF($L$70:L112,L112),0) -> 0 | Q112: =$B$10 -> 6.8559659e+09
A113: =$B$6+43 -> 46247 | B113: =SUMIFS($E$220:$E$341,$D$220:$D$341,"IN",$N$220:$N$341,A113) -> 0 | C113: =SUMIFS($E$220:$E$341,$D$220:$D$341,"OUT",$N$220:$N$341,A113) -> 0 | D113: =SUM($F$70:F113) -> 12120109476 | E113: =G112 -> 16522035449 | F113: =B113-C113 -> 0 | G113: =E113+F113 -> 16522035449 | H113: =IF(G113<$B$9,$B$10-G113,0) -> 0 | I113: =MAX(0,-G113) -> 0 | J113: =H113/$B$10 -> 0 | K113: =IF(G113<$B$9,3,0) -> 0 | L113: =IF(G113<$B$9,SUM($N$70:N113),0) -> 0 | M113: =IF(G113>$B$11,M112+1,0) -> 34 | N113: =IF(AND(G113<$B$9,G112>=$B$9),1,0) -> 0 | O113: =IF(AND(G113<$B$9,G114>=$B$9),1,0) -> 0 | P113: =IF(L113>0,COUNTIF($L$70:L113,L113),0) -> 0 | Q113: =$B$10 -> 6.8559659e+09
A114: =$B$6+44 -> 46248 | B114: =SUMIFS($E$220:$E$341,$D$220:$D$341,"IN",$N$220:$N$341,A114) -> 0 | C114: =SUMIFS($E$220:$E$341,$D$220:$D$341,"OUT",$N$220:$N$341,A114) -> 0 | D114: =SUM($F$70:F114) -> 12120109476 | E114: =G113 -> 16522035449 | F114: =B114-C114 -> 0 | G114: =E114+F114 -> 16522035449 | H114: =IF(G114<$B$9,$B$10-G114,0) -> 0 | I114: =MAX(0,-G114) -> 0 | J114: =H114/$B$10 -> 0 | K114: =IF(G114<$B$9,3,0) -> 0 | L114: =IF(G114<$B$9,SUM($N$70:N114),0) -> 0 | M114: =IF(G114>$B$11,M113+1,0) -> 35 | N114: =IF(AND(G114<$B$9,G113>=$B$9),1,0) -> 0 | O114: =IF(AND(G114<$B$9,G115>=$B$9),1,0) -> 0 | P114: =IF(L114>0,COUNTIF($L$70:L114,L114),0) -> 0 | Q114: =$B$10 -> 6.8559659e+09
A115: =$B$6+45 -> 46249 | B115: =SUMIFS($E$220:$E$341,$D$220:$D$341,"IN",$N$220:$N$341,A115) -> 0 | C115: =SUMIFS($E$220:$E$341,$D$220:$D$341,"OUT",$N$220:$N$341,A115) -> 1008000000 | D115: =SUM($F$70:F115) -> 11112109476 | E115: =G114 -> 16522035449 | F115: =B115-C115 -> -1008000000 | G115: =E115+F115 -> 15514035449 | H115: =IF(G115<$B$9,$B$10-G115,0) -> 0 | I115: =MAX(0,-G115) -> 0 | J115: =H115/$B$10 -> 0 | K115: =IF(G115<$B$9,3,0) -> 0 | L115: =IF(G115<$B$9,SUM($N$70:N115),0) -> 0 | M115: =IF(G115>$B$11,M114+1,0) -> 36 | N115: =IF(AND(G115<$B$9,G114>=$B$9),1,0) -> 0 | O115: =IF(AND(G115<$B$9,G116>=$B$9),1,0) -> 0 | P115: =IF(L115>0,COUNTIF($L$70:L115,L115),0) -> 0 | Q115: =$B$10 -> 6.8559659e+09
A116: =$B$6+46 -> 46250 | B116: =SUMIFS($E$220:$E$341,$D$220:$D$341,"IN",$N$220:$N$341,A116) -> 0 | C116: =SUMIFS($E$220:$E$341,$D$220:$D$341,"OUT",$N$220:$N$341,A116) -> 0 | D116: =SUM($F$70:F116) -> 11112109476 | E116: =G115 -> 15514035449 | F116: =B116-C116 -> 0 | G116: =E116+F116 -> 15514035449 | H116: =IF(G116<$B$9,$B$10-G116,0) -> 0 | I116: =MAX(0,-G116) -> 0 | J116: =H116/$B$10 -> 0 | K116: =IF(G116<$B$9,3,0) -> 0 | L116: =IF(G116<$B$9,SUM($N$70:N116),0) -> 0 | M116: =IF(G116>$B$11,M115+1,0) -> 37 | N116: =IF(AND(G116<$B$9,G115>=$B$9),1,0) -> 0 | O116: =IF(AND(G116<$B$9,G117>=$B$9),1,0) -> 0 | P116: =IF(L116>0,COUNTIF($L$70:L116,L116),0) -> 0 | Q116: =$B$10 -> 6.8559659e+09
A117: =$B$6+47 -> 46251 | B117: =SUMIFS($E$220:$E$341,$D$220:$D$341,"IN",$N$220:$N$341,A117) -> 0 | C117: =SUMIFS($E$220:$E$341,$D$220:$D$341,"OUT",$N$220:$N$341,A117) -> 0 | D117: =SUM($F$70:F117) -> 11112109476 | E117: =G116 -> 15514035449 | F117: =B117-C117 -> 0 | G117: =E117+F117 -> 15514035449 | H117: =IF(G117<$B$9,$B$10-G117,0) -> 0 | I117: =MAX(0,-G117) -> 0 | J117: =H117/$B$10 -> 0 | K117: =IF(G117<$B$9,3,0) -> 0 | L117: =IF(G117<$B$9,SUM($N$70:N117),0) -> 0 | M117: =IF(G117>$B$11,M116+1,0) -> 38 | N117: =IF(AND(G117<$B$9,G116>=$B$9),1,0) -> 0 | O117: =IF(AND(G117<$B$9,G118>=$B$9),1,0) -> 0 | P117: =IF(L117>0,COUNTIF($L$70:L117,L117),0) -> 0 | Q117: =$B$10 -> 6.8559659e+09
...

Sheet F01_UC03
A2: F01 So khớp phương án tài trợ UC03 tại 30/06/2026
A3: Chỉ tính cho kịch bản Base. Đầu vào lấy từ F01_UC1, F01_UC2; sản phẩm và tham số lấy từ D_UC03. UC03 chỉ đề xuất, không thực hiện.
A5: 1. Kết quả UC03 | B5: Giá trị | C5: Ghi chú
A6: Ô ma trận | B6: =$B$35 -> M3 | C6: W × TH cùng snapshot
A7: TH | B7: =$B$33 -> TH01
A8: W | B8: =$B$34 -> W1
A9: Kịch bản | B9: =$B$88 -> A1 | C9: A1–A4, B1, B2
A10: gap_shape | B10: =$B$60 -> giảm một lần
A11: Cờ REVIEW_MANUAL | B11: =$B$61
A12: Số đợt cần tiền | B12: =IF($B$33<>"TH01",0,IF($B$60="tăng một lần",2,1)) -> 1 | C12: Gói chỉ chạy cho đợt 1
A13: need_date đợt 1 | B13: =$B$65 -> 46204
A14: DaysLeft | B14: =$B$73 -> 1
A15: Chế độ | B15: =IF($B$74=1,"KHẨN","THƯỜNG") -> KHẨN
A16: G đợt 1 (VND) | B16: =$B$72 -> 2.7154855e+09
A17: duration (ngày) | B17: =$B$68 -> 14
A18: Xếp hạng 1 – 3 | B18: =C109&IF(C110<>""," > "&C110,"")&IF(C111<>""," > "&C111,"") -> RF-001 > CL-001 > NB-01 | C18: Nguồn đủ điều kiện, kịp hạn đứng trước
A19: Gói đề xuất | B19: =IF($B$33="TH01",$B$132,IF($B$33="TH02",IF($B$34="W0","Đầu tư ngắn hạn trong giới hạn tiền an toàn","Giữ làm dự trữ; xử lý điểm nghẽn"),"Theo dõi; không hành động")) -> RF-001
A20: Tiền thu về (VND) | B20: =$B$125 -> 2.7154855e+09
A21: Chi phí gói (VND) | B21: =$B$126 -> 14061007
A22: CostPerGap | B22: =$B$127 -> 0.0052
A23: Còn thiếu (VND) | B23: =$B$128 -> 0
A24: Số nguồn bị cờ NOT_COVERING_DURATION | B24: =$B$131 -> 0
A25: requires_human_decision | B25: =IF($B$33<>"TH01","false",IF(OR($B$61<>"",$B$128>0,$B$131>0),"true","false")) -> false | C25: REVIEW_MANUAL, còn thiếu hoặc chưa phủ hết thời gian
A30: 2. Đầu vào từ UC01 và UC02 | B30: Giá trị | C30: Cách lấy
A31: Ngày chạy (as_of) | B31: =D_F01!B7 -> 46203 | C31: Ngày chốt
A32: Z – mức tiền mục tiêu | B32: =F01_UC2!B10 -> 6.8559659e+09 | C32: F01_UC2!B10
A33: TH | B33: =F01_UC2!B23 -> TH01 | C33: F01_UC2!B23; chỉ Base
A34: W | B34: =F01_UC1!B30 -> W1 | C34: F01_UC1!B30
A35: Ô ma trận | B35: =F01_UC2!B24 -> M3 | C35: F01_UC2!B24
A36: Thiếu kéo dài (≥ 2 khối, 28 ngày) | B36: =IF(AND($B$33="TH01",F01_UC2!M37=TRUE()),1,0) -> 0 | C36: F01_UC2!M37; điều kiện chuỗi gap T3-11
A37: c_AR | B37: =IF(F01_UC1!B22>=1,1,0) -> 1 | C37: Mức AR ≥ 1
A38: c_INV | B38: =IF(F01_UC1!B23>=1,1,0) -> 0 | C38: Mức INV ≥ 1
A39: c_AP | B39: =IF(F01_UC1!B26>=1,1,0) -> 0 | C39: Tín hiệu AP
A40: n_yếu_tố | B40: =$B$37+$B$38+$B$39 -> 1 | C40: Số yếu tố góp phần
A41: E_AR | B41: =F01_UC1!B27 -> 2.5243312e+09 | C41: Vốn AR vượt ngưỡng (số tham chiếu)
A42: E_INV | B42: =F01_UC1!B28 -> 0 | C42: Vốn tồn vượt ngưỡng (số tham chiếu)
A43: E_AP | B43: =F01_UC1!B18 -> 979364994 | C43: Phải trả quá hạn (số tham chiếu)
A44: model_health | B44: =D_UC03!$C$17 -> ok | C44: D_UC03
A46: 3. Khoảng thiếu và đợt cần tiền | B46: Giá trị | C46: Cách tính
A47: θ = Rtarget × PARAM_THETA_PCT | B47: =$B$32*D_UC03!$C$5 -> 1.7139915e+09 | C47: T3-02
A49: Khối | B49: Ngày đầu | C49: Ngày cuối | D49: Số ngày | E49: MinDaily | F49: Deficit | G49: |Δ| so với khối trước | H49: Đổi mức trọng yếu
A50: =F01_UC2!L29 -> 1 | B50: =F01_UC2!M29 -> 46204 | C50: =F01_UC2!N29 -> 46217 | D50: =F01_UC2!R29 -> 14 | E50: =F01_UC2!O29 -> 4140480437 | F50: =IF(E50<F01_UC2!$B$9,$B$32-E50,0) -> 2.7154855e+09 | H50: 0
A51: =F01_UC2!L30 -> 2 | B51: =F01_UC2!M30 -> 46218 | C51: =F01_UC2!N30 -> 46231 | D51: =F01_UC2!R30 -> 14 | E51: =F01_UC2!O30 -> 11150672753 | F51: =IF(E51<F01_UC2!$B$9,$B$32-E51,0) -> 0 | G51: =ABS(F51-F50) -> 2.7154855e+09 | H51: =IF(AND(G51>=$B$47,D51>=D_UC03!$C$6),1,0) -> 1
A52: =F01_UC2!L31 -> 3 | B52: =F01_UC2!M31 -> 46232 | C52: =F01_UC2!N31 -> 46245 | D52: =F01_UC2!R31 -> 14 | E52: =F01_UC2!O31 -> 12461774647 | F52: =IF(E52<F01_UC2!$B$9,$B$32-E52,0) -> 0 | G52: =ABS(F52-F51) -> 0 | H52: =IF(AND(G52>=$B$47,D52>=D_UC03!$C$6),1,0) -> 0
A53: =F01_UC2!L32 -> 4 | B53: =F01_UC2!M32 -> 46246 | C53: =F01_UC2!N32 -> 46259 | D53: =F01_UC2!R32 -> 14 | E53: =F01_UC2!O32 -> 15514035449 | F53: =IF(E53<F01_UC2!$B$9,$B$32-E53,0) -> 0 | G53: =ABS(F53-F52) -> 0 | H53: =IF(AND(G53>=$B$47,D53>=D_UC03!$C$6),1,0) -> 0
A54: =F01_UC2!L33 -> 5 | B54: =F01_UC2!M33 -> 46260 | C54: =F01_UC2!N33 -> 46273 | D54: =F01_UC2!R33 -> 14 | E54: =F01_UC2!O33 -> 14828618808 | F54: =IF(E54<F01_UC2!$B$9,$B$32-E54,0) -> 0 | G54: =ABS(F54-F53) -> 0 | H54: =IF(AND(G54>=$B$47,D54>=D_UC03!$C$6),1,0) -> 0
A55: =F01_UC2!L34 -> 6 | B55: =F01_UC2!M34 -> 46274 | C55: =F01_UC2!N34 -> 46287 | D55: =F01_UC2!R34 -> 14 | E55: =F01_UC2!O34 -> 15656479147 | F55: =IF(E55<F01_UC2!$B$9,$B$32-E55,0) -> 0 | G55: =ABS(F55-F54) -> 0 | H55: =IF(AND(G55>=$B$47,D55>=D_UC03!$C$6),1,0) -> 0
A56: =F01_UC2!L35 -> 7 | B56: =F01_UC2!M35 -> 46288 | C56: =F01_UC2!N35 -> 46294 | D56: =F01_UC2!R35 -> 7 | E56: =F01_UC2!O35 -> 14156479147 | F56: =IF(E56<F01_UC2!$B$9,$B$32-E56,0) -> 0 | G56: =ABS(F56-F55) -> 0 | H56: =IF(AND(G56>=$B$47,D56>=D_UC03!$C$6),1,0) -> 0
A58: Số lần đổi mức trọng yếu (n) | B58: =SUM(H51:H56) -> 1 | C58: T3-03
A59: Chiều đổi mức (khi n = 1) | B59: =SUMPRODUCT(H51:H56*(F51:F56-F50:F55)) -> -2.7154855e+09 | C59: Dương: tăng; âm: giảm
A60: gap_shape | B60: =IF($B$58=0,"đồng đều",IF($B$58=1,IF($B$59>0,"tăng một lần","giảm một lần"),"không phân loại được")) -> giảm một lần | C60: T3-03
A61: Cờ REVIEW_MANUAL | B61: =IF($B$60="không phân loại được","REVIEW_MANUAL","") | C61: n ≥ 2: dùng mức thiếu lớn nhất, chờ người xem lại
A62: PeakGap (mức thiếu lớn nhất) | B62: =MAX(F50:F56) -> 2.7154855e+09 | C62: Khi MinDaily < L: Z − MinDaily; còn lại 0
A63: Vị trí khối đổi mức | B63: =IFERROR(MATCH(1,H50:H56,0),0) -> 2 | C63: 0 nếu không đổi mức
A64: Mức đợt 1 (G_cum) | B64: =IF($B$60="tăng một lần",INDEX(F50:F56,$B$63-1),$B$62) -> 2.7154855e+09 | C64: Tăng một lần: mức thấp trước ngày chuyển; còn lại: mức lớn nhất
A65: need_date đợt 1 | B65: =F01_UC2!B20 -> 46204 | C65: Ngày đầu dự báo dưới L; UC02!M43 ghi thiếu đã có tại ngày chốt
A66: Ngày chuyển mức | B66: =IF($B$63>0,INDEX(B50:B56,$B$63),"n.a.") -> 46218 | C66: Đầu khối có đổi mức trọng yếu
A67: Ngày cuối số dư dưới L | B67: =IF($B$33="TH01",_xlfn.MAXIFS(F01_UC2!A70:A160,F01_UC2!G70:G160,"<"&F01_UC2!B9),0) -> 46211
A68: duration đợt 1 (ngày) | B68: =IF($B$33<>"TH01",0,IF(AND($B$60="giảm một lần",ISNUMBER($B$66)),$B$66-$B$65,$B$67-$B$65+1)) -> 14 | C68: T3-07: đến ngày cuối còn thiếu; giảm một lần: đến ngày chuyển mức
A69: Đợt 2: G_cum | B69: =IF($B$60="tăng một lần",$B$62,"không có") -> không có | C69: Chỉ khi tăng một lần; F01 chỉ chạy gói đợt 1
A70: Đợt 2: need_date | B70: =IF($B$60="tăng một lần",$B$66,"không có") -> không có
A71: Đợt 2: G_incr | B71: =IF($B$60="tăng một lần",$B$62-$B$64,"không có") -> không có | C71: G_cum đợt 2 − G_cum đợt 1
A72: G đợt 1 (số tiền cần) | B72: =IF($B$33="TH01",$B$64,0) -> 2.7154855e+09 | C72: Chạy gói cho số này
A73: DaysLeft | B73: =IFERROR($B$65-$B$31,0) -> 1 | C73: T3-06
A74: Chế độ Khẩn (1 = có) | B74: =IF($B$73<=D_UC03!$C$12,1,0) -> 1 | C74: DaysLeft ≤ PARAM_URGENT_DAYS
A75: gap_severity | B75: =IF($B$72>=$B$47,"NẶNG","NHẸ") -> NẶNG | C75: T3-05
A76: MinDraw | B76: =$B$72*D_UC03!$C$10 -> 1.3577427e+08 | C76: G × PARAM_MIN_DRAW_PCT
A78: 4. Yếu tố góp phần và kịch bản | B78: Giá trị | C78: Cách tính
A79: Share_AR (tham chiếu) | B79: =IF($B$62>0,MIN(1,$B$41/$B$62),0) -> 0.92960587 | C79: T3-08: chỉ để định tuyến, không cộng được
A80: Share_INV (tham chiếu) | B80: =IF($B$62>0,MIN(1,$B$42/$B$62),0) -> 0 | C80: T3-08: chỉ để định tuyến, không cộng được
A81: Share_AP (tham chiếu) | B81: =IF($B$62>0,MIN(1,$B$43/$B$62),0) -> 0.36065927 | C81: T3-08: chỉ để định tuyến, không cộng được
A82: Vai trò AR | B82: =IF($B$79>=D_UC03!$C$7,"CHÍNH",IF($B$79>=D_UC03!$C$8,"PHỤ","BỎ QUA")) -> CHÍNH | C82: CHÍNH ≥ 50%; PHỤ ≥ 15%
A83: Vai trò INV | B83: =IF($B$80>=D_UC03!$C$7,"CHÍNH",IF($B$80>=D_UC03!$C$8,"PHỤ","BỎ QUA")) -> BỎ QUA | C83: CHÍNH ≥ 50%; PHỤ ≥ 15%
A84: Vai trò AP | B84: =IF($B$81>=D_UC03!$C$7,"CHÍNH",IF($B$81>=D_UC03!$C$8,"PHỤ","BỎ QUA")) -> PHỤ | C84: CHÍNH ≥ 50%; PHỤ ≥ 15%
A85: Yếu tố chính | B85: =IF(AND($B$79>=D_UC03!$C$7,$B$79>=$B$80,$B$79>=$B$81),"AR",IF(AND($B$80>=D_UC03!$C$7,$B$80>=$B$81),"INV",IF($B$81>=D_UC03!$C$7,"AP",""))) -> AR | C85: Rỗng nếu không yếu tố nào ≥ 50%
A86: BestC (nguồn lớn nhất qua lọc, kịp hạn) | B86: =MAX($O$92:$O$105) -> 9.220053e+09 | C86: T3-11
A87: Kịch bản đợt đơn (A1–A4) | B87: =IF($B$85="AR","A1",IF($B$85="INV","A2",IF($B$85="AP","A4","A3"))) -> A1 | C87: T3-10
A88: Kịch bản | B88: =IF($B$33="TH01",IF($B$36=1,"B2",$B$87),IF($B$33="TH02",IF($B$34="W0","D_INVEST","D_RESERVE"),"MONITOR")) -> A1 | C88: Thiếu: gói tài trợ; thừa W0: đầu tư; thừa W1/W2: dự trữ; trong vùng: theo dõi
A90: 5. Lọc cứng, chi phí và xếp hạng sản phẩm
A91: Mã | B91: Nhóm | C91: Phương án | D91: Đối tượng | E91: Cơ sở | F91: Tỷ lệ ròng | G91: C (năng lực) | H91: Hold tính phí | I91: Chi phí | J91: Ngày có tiền | K91: Kịp hạn | L91: Qua lọc cứng | M91: Thuộc kịch bản | N91: Đủ điều kiện | O91: C kịp+qua lọc | P91: CostPerGap | Q91: Ưu tiên ma trận | R91: Dải tốc độ | S91: Độ chắc chắn | T91: Rel | U91: Tier | V91: Thứ tự | W91: Khóa xếp hạng | X91: Hạng | Y91: Mã lý do | Z91: Cờ
A92: =D_UC03!$A$23 -> NB-01 | B92: =D_UC03!$C$23 -> NB | C92: =D_UC03!$D$23 -> O0 | D92: =D_UC03!$E$23 -> OBJ-NB | E92: =D_UC03!$F$23 -> 2000000000 | F92: =IF(B92="INV_SALE",1-D_UC03!$H$23,D_UC03!$G$23) -> 1 | G92: =E92*F92 -> 2000000000 | H92: =IF(D_UC03!$S$23=1,MIN(D_UC03!$L$23,$B$68),D_UC03!$L$23) -> 0 | I92: =IF(B92="INV_SALE",E92*D_UC03!$H$23+D_UC03!$K$23,G92*D_UC03!$I$23*H92/365+G92*D_UC03!$J$23+D_UC03!$K$23) -> 0 | J92: =D_UC03!$M$23 -> 2 | K92: =IF(J92<=$B$73,1,0) -> 0 | L92: =IF(AND(D_UC03!$Q$23<>"Y",D_UC03!$P$23<>"Y",D_UC03!$R$23<>"N",G92>0,NOT(AND($B$68<D_UC03!$C$13,OR(D_UC03!$S$23=0,D_UC03!$K$23>0)))),1,0) -> 1 | M92: =IF($B$33<>"TH01",0,IF($B$35="M1",IF(OR(B92="CL",B92="NB"),1,0),1)) -> 1 | N92: =L92*M92 -> 1 | O92: =IF(AND(L92=1,K92=1),G92,0) -> 0 | P92: =IF(AND(G92>0,$B$72>0),ROUND(I92/MIN(G92,$B$72),4),0) -> 0 | Q92: =IF(B92="NB",0,IF($B$35="M1",IF(B92="CL",1,9),IF($B$35="M3",IF(OR(B92="AR_EARLY",B92="RF",B92="FAC"),1,IF(B92="AP_EXT",2,3)),IF(OR(B92="AR_EARLY",B92="RF",B92="FAC"),1,IF(OR(B92="INV_LOAN",B92="INV_SALE"),2,IF(B92="AP_EXT",3,4)))))) -> 0 | R92: =IF(J92<=3,1,IF(J92<=10,2,3)) -> 1 | S92: =IF($B$44="degraded",3,IF(D_UC03!$N$23="Cao",1,IF(D_UC03!$N$23="Trung bình",2,3))) -> 1 | T92: =D_UC03!$O$23 -> 0 | U92: =IF(K92=1,0,2) -> 2 | V92: 1 | W92: =IF(N92=1,U92*10^13+IF($B$74=1,R92*10^12+Q92*10^11,Q92*10^12+R92*10^11)+S92*10^10+MIN(99999,ROUND(P92*10000,0))*10^5+T92*10^4+MIN(99,J92)*100+V92,9*10^14+V92) -> 21010000000201 | X92: =IF(N92=1,SUMPRODUCT(($W$92:$W$105<W92)*($N$92:$N$105=1))+1,"") -> 3 | Y92: =IF(D_UC03!$Q$23="Y","PLEDGED",IF(D_UC03!$P$23="Y","STRATEGIC_OR_CRITICAL",IF(D_UC03!$R$23="N","NO_PRODUCT_DATA",IF(G92<=0,"NO_NET_CASH",IF(L92=0,"SHORT_DURATION_LOCKED",IF(M92=0,"OUT_OF_SCENARIO",IF(K92=0,"TOO_SLOW",IF(G92<$B$76,"BELOW_MIN_DRAW","")))))))) -> TOO_SLOW | Z92: =IF(AND(D_UC03!$S$23=0,D_UC03!$L$23<$B$68),"NOT_COVERING_DURATION","")
A93: =D_UC03!$A$24 -> EX-01 | B93: =D_UC03!$C$24 -> AP_EXT | C93: =D_UC03!$D$24 -> O1 | D93: =D_UC03!$E$24 -> OBJ-APX | E93: =D_UC03!$F$24 -> 2983068109 | F93: =IF(B93="INV_SALE",1-D_UC03!$H$24,D_UC03!$G$24) -> 1 | G93: =E93*F93 -> 2983068109 | H93: =IF(D_UC03!$S$24=1,MIN(D_UC03!$L$24,$B$68),D_UC03!$L$24) -> 0 | I93: =IF(B93="INV_SALE",E93*D_UC03!$H$24+D_UC03!$K$24,G93*D_UC03!$I$24*H93/365+G93*D_UC03!$J$24+D_UC03!$K$24) -> 0 | J93: =D_UC03!$M$24 -> 2 | K93: =IF(J93<=$B$73,1,0) -> 0 | L93: =IF(AND(D_UC03!$Q$24<>"Y",D_UC03!$P$24<>"Y",D_UC03!$R$24<>"N",G93>0,NOT(AND($B$68<D_UC03!$C$13,OR(D_UC03!$S$24=0,D_UC03!$K$24>0)))),1,0) -> 1 | M93: =IF($B$33<>"TH01",0,IF($B$35="M1",IF(OR(B93="CL",B93="NB"),1,0),1)) -> 1 | N93: =L93*M93 -> 1 | O93: =IF(AND(L93=1,K93=1),G93,0) -> 0 | P93: =IF(AND(G93>0,$B$72>0),ROUND(I93/MIN(G93,$B$72),4),0) -> 0 | Q93: =IF(B93="NB",0,IF($B$35="M1",IF(B93="CL",1,9),IF($B$35="M3",IF(OR(B93="AR_EARLY",B93="RF",B93="FAC"),1,IF(B93="AP_EXT",2,3)),IF(OR(B93="AR_EARLY",B93="RF",B93="FAC"),1,IF(OR(B93="INV_LOAN",B93="INV_SALE"),2,IF(B93="AP_EXT",3,4)))))) -> 2 | R93: =IF(J93<=3,1,IF(J93<=10,2,3)) -> 1 | S93: =IF($B$44="degraded",3,IF(D_UC03!$N$24="Cao",1,IF(D_UC03!$N$24="Trung bình",2,3))) -> 3 | T93: =D_UC03!$O$24 -> 1 | U93: =IF(K93=1,0,2) -> 2 | V93: 2 | W93: =IF(N93=1,U93*10^13+IF($B$74=1,R93*10^12+Q93*10^11,Q93*10^12+R93*10^11)+S93*10^10+MIN(99999,ROUND(P93*10000,0))*10^5+T93*10^4+MIN(99,J93)*100+V93,9*10^14+V93) -> 21230000010202 | X93: =IF(N93=1,SUMPRODUCT(($W$92:$W$105<W93)*($N$92:$N$105=1))+1,"") -> 6 | Y93: =IF(D_UC03!$Q$24="Y","PLEDGED",IF(D_UC03!$P$24="Y","STRATEGIC_OR_CRITICAL",IF(D_UC03!$R$24="N","NO_PRODUCT_DATA",IF(G93<=0,"NO_NET_CASH",IF(L93=0,"SHORT_DURATION_LOCKED",IF(M93=0,"OUT_OF_SCENARIO",IF(K93=0,"TOO_SLOW",IF(G93<$B$76,"BELOW_MIN_DRAW","")))))))) -> TOO_SLOW | Z93: =IF(AND(D_UC03!$S$24=0,D_UC03!$L$24<$B$68),"NOT_COVERING_DURATION","")
A94: =D_UC03!$A$25 -> EX-02 | B94: =D_UC03!$C$25 -> AP_EXT | C94: =D_UC03!$D$25 -> O1 | D94: =D_UC03!$E$25 -> OBJ-APS | E94: =D_UC03!$F$25 -> 4430604968 | F94: =IF(B94="INV_SALE",1-D_UC03!$H$25,D_UC03!$G$25) -> 1 | G94: =E94*F94 -> 4430604968 | H94: =IF(D_UC03!$S$25=1,MIN(D_UC03!$L$25,$B$68),D_UC03!$L$25) -> 0 | I94: =IF(B94="INV_SALE",E94*D_UC03!$H$25+D_UC03!$K$25,G94*D_UC03!$I$25*H94/365+G94*D_UC03!$J$25+D_UC03!$K$25) -> 0 | J94: =D_UC03!$M$25 -> 2 | K94: =IF(J94<=$B$73,1,0) -> 0 | L94: =IF(AND(D_UC03!$Q$25<>"Y",D_UC03!$P$25<>"Y",D_UC03!$R$25<>"N",G94>0,NOT(AND($B$68<D_UC03!$C$13,OR(D_UC03!$S$25=0,D_UC03!$K$25>0)))),1,0) -> 0 | M94: =IF($B$33<>"TH01",0,IF($B$35="M1",IF(OR(B94="CL",B94="NB"),1,0),1)) -> 1 | N94: =L94*M94 -> 0 | O94: =IF(AND(L94=1,K94=1),G94,0) -> 0 | P94: =IF(AND(G94>0,$B$72>0),ROUND(I94/MIN(G94,$B$72),4),0) -> 0 | Q94: =IF(B94="NB",0,IF($B$35="M1",IF(B94="CL",1,9),IF($B$35="M3",IF(OR(B94="AR_EARLY",B94="RF",B94="FAC"),1,IF(B94="AP_EXT",2,3)),IF(OR(B94="AR_EARLY",B94="RF",B94="FAC"),1,IF(OR(B94="INV_LOAN",B94="INV_SALE"),2,IF(B94="AP_EXT",3,4)))))) -> 2 | R94: =IF(J94<=3,1,IF(J94<=10,2,3)) -> 1 | S94: =IF($B$44="degraded",3,IF(D_UC03!$N$25="Cao",1,IF(D_UC03!$N$25="Trung bình",2,3))) -> 3 | T94: =D_UC03!$O$25 -> 2 | U94: =IF(K94=1,0,2) -> 2 | V94: 3 | W94: =IF(N94=1,U94*10^13+IF($B$74=1,R94*10^12+Q94*10^11,Q94*10^12+R94*10^11)+S94*10^10+MIN(99999,ROUND(P94*10000,0))*10^5+T94*10^4+MIN(99,J94)*100+V94,9*10^14+V94) -> 900000000000003 | X94: =IF(N94=1,SUMPRODUCT(($W$92:$W$105<W94)*($N$92:$N$105=1))+1,"") | Y94: =IF(D_UC03!$Q$25="Y","PLEDGED",IF(D_UC03!$P$25="Y","STRATEGIC_OR_CRITICAL",IF(D_UC03!$R$25="N","NO_PRODUCT_DATA",IF(G94<=0,"NO_NET_CASH",IF(L94=0,"SHORT_DURATION_LOCKED",IF(M94=0,"OUT_OF_SCENARIO",IF(K94=0,"TOO_SLOW",IF(G94<$B$76,"BELOW_MIN_DRAW","")))))))) -> STRATEGIC_OR_CRITICAL | Z94: =IF(AND(D_UC03!$S$25=0,D_UC03!$L$25<$B$68),"NOT_COVERING_DURATION","")
A95: =D_UC03!$A$26 -> AR-01 | B95: =D_UC03!$C$26 -> AR_EARLY | C95: =D_UC03!$D$26 -> O4 | D95: =D_UC03!$E$26 -> OBJ-AR-K1 | E95: =D_UC03!$F$26 -> 9705318986 | F95: =IF(B95="INV_SALE",1-D_UC03!$H$26,D_UC03!$G$26) -> 1 | G95: =E95*F95 -> 9705318986 | H95: =IF(D_UC03!$S$26=1,MIN(D_UC03!$L$26,$B$68),D_UC03!$L$26) -> 0 | I95: =IF(B95="INV_SALE",E95*D_UC03!$H$26+D_UC03!$K$26,G95*D_UC03!$I$26*H95/365+G95*D_UC03!$J$26+D_UC03!$K$26) -> 97053190 | J95: =D_UC03!$M$26 -> 5 | K95: =IF(J95<=$B$73,1,0) -> 0 | L95: =IF(AND(D_UC03!$Q$26<>"Y",D_UC03!$P$26<>"Y",D_UC03!$R$26<>"N",G95>0,NOT(AND($B$68<D_UC03!$C$13,OR(D_UC03!$S$26=0,D_UC03!$K$26>0)))),1,0) -> 1 | M95: =IF($B$33<>"TH01",0,IF($B$35="M1",IF(OR(B95="CL",B95="NB"),1,0),1)) -> 1 | N95: =L95*M95 -> 1 | O95: =IF(AND(L95=1,K95=1),G95,0) -> 0 | P95: =IF(AND(G95>0,$B$72>0),ROUND(I95/MIN(G95,$B$72),4),0) -> 0.0357 | Q95: =IF(B95="NB",0,IF($B$35="M1",IF(B95="CL",1,9),IF($B$35="M3",IF(OR(B95="AR_EARLY",B95="RF",B95="FAC"),1,IF(B95="AP_EXT",2,3)),IF(OR(B95="AR_EARLY",B95="RF",B95="FAC"),1,IF(OR(B95="INV_LOAN",B95="INV_SALE"),2,IF(B95="AP_EXT",3,4)))))) -> 1 | R95: =IF(J95<=3,1,IF(J95<=10,2,3)) -> 2 | S95: =IF($B$44="degraded",3,IF(D_UC03!$N$26="Cao",1,IF(D_UC03!$N$26="Trung bình",2,3))) -> 2 | T95: =D_UC03!$O$26 -> 1 | U95: =IF(K95=1,0,2) -> 2 | V95: 4 | W95: =IF(N95=1,U95*10^13+IF($B$74=1,R95*10^12+Q95*10^11,Q95*10^12+R95*10^11)+S95*10^10+MIN(99999,ROUND(P95*10000,0))*10^5+T95*10^4+MIN(99,J95)*100+V95,9*10^14+V95) -> 22120035710504 | X95: =IF(N95=1,SUMPRODUCT(($W$92:$W$105<W95)*($N$92:$N$105=1))+1,"") -> 8 | Y95: =IF(D_UC03!$Q$26="Y","PLEDGED",IF(D_UC03!$P$26="Y","STRATEGIC_OR_CRITICAL",IF(D_UC03!$R$26="N","NO_PRODUCT_DATA",IF(G95<=0,"NO_NET_CASH",IF(L95=0,"SHORT_DURATION_LOCKED",IF(M95=0,"OUT_OF_SCENARIO",IF(K95=0,"TOO_SLOW",IF(G95<$B$76,"BELOW_MIN_DRAW","")))))))) -> TOO_SLOW | Z95: =IF(AND(D_UC03!$S$26=0,D_UC03!$L$26<$B$68),"NOT_COVERING_DURATION","")
A96: =D_UC03!$A$27 -> AR-02 | B96: =D_UC03!$C$27 -> AR_EARLY | C96: =D_UC03!$D$27 -> O4 | D96: =D_UC03!$E$27 -> OBJ-AR-K2 | E96: =D_UC03!$F$27 -> 2871750170 | F96: =IF(B96="INV_SALE",1-D_UC03!$H$27,D_UC03!$G$27) -> 1 | G96: =E96*F96 -> 2871750170 | H96: =IF(D_UC03!$S$27=1,MIN(D_UC03!$L$27,$B$68),D_UC03!$L$27) -> 0 | I96: =IF(B96="INV_SALE",E96*D_UC03!$H$27+D_UC03!$K$27,G96*D_UC03!$I$27*H96/365+G96*D_UC03!$J$27+D_UC03!$K$27) -> 28717502 | J96: =D_UC03!$M$27 -> 5 | K96: =IF(J96<=$B$73,1,0) -> 0 | L96: =IF(AND(D_UC03!$Q$27<>"Y",D_UC03!$P$27<>"Y",D_UC03!$R$27<>"N",G96>0,NOT(AND($B$68<D_UC03!$C$13,OR(D_UC03!$S$27=0,D_UC03!$K$27>0)))),1,0) -> 0 | M96: =IF($B$33<>"TH01",0,IF($B$35="M1",IF(OR(B96="CL",B96="NB"),1,0),1)) -> 1 | N96: =L96*M96 -> 0 | O96: =IF(AND(L96=1,K96=1),G96,0) -> 0 | P96: =IF(AND(G96>0,$B$72>0),ROUND(I96/MIN(G96,$B$72),4),0) -> 0.0106 | Q96: =IF(B96="NB",0,IF($B$35="M1",IF(B96="CL",1,9),IF($B$35="M3",IF(OR(B96="AR_EARLY",B96="RF",B96="FAC"),1,IF(B96="AP_EXT",2,3)),IF(OR(B96="AR_EARLY",B96="RF",B96="FAC"),1,IF(OR(B96="INV_LOAN",B96="INV_SALE"),2,IF(B96="AP_EXT",3,4)))))) -> 1 | R96: =IF(J96<=3,1,IF(J96<=10,2,3)) -> 2 | S96: =IF($B$44="degraded",3,IF(D_UC03!$N$27="Cao",1,IF(D_UC03!$N$27="Trung bình",2,3))) -> 2 | T96: =D_UC03!$O$27 -> 2 | U96: =IF(K96=1,0,2) -> 2 | V96: 5 | W96: =IF(N96=1,U96*10^13+IF($B$74=1,R96*10^12+Q96*10^11,Q96*10^12+R96*10^11)+S96*10^10+MIN(99999,ROUND(P96*10000,0))*10^5+T96*10^4+MIN(99,J96)*100+V96,9*10^14+V96) -> 900000000000005 | X96: =IF(N96=1,SUMPRODUCT(($W$92:$W$105<W96)*($N$92:$N$105=1))+1,"") | Y96: =IF(D_UC03!$Q$27="Y","PLEDGED",IF(D_UC03!$P$27="Y","STRATEGIC_OR_CRITICAL",IF(D_UC03!$R$27="N","NO_PRODUCT_DATA",IF(G96<=0,"NO_NET_CASH",IF(L96=0,"SHORT_DURATION_LOCKED",IF(M96=0,"OUT_OF_SCENARIO",IF(K96=0,"TOO_SLOW",IF(G96<$B$76,"BELOW_MIN_DRAW","")))))))) -> STRATEGIC_OR_CRITICAL | Z96: =IF(AND(D_UC03!$S$27=0,D_UC03!$L$27<$B$68),"NOT_COVERING_DURATION","")
A97: =D_UC03!$A$28 -> RF-001 | B97: =D_UC03!$C$28 -> RF | C97: =D_UC03!$D$28 -> O2 | D97: =D_UC03!$E$28 -> OBJ-AR-K1 | E97: =D_UC03!$F$28 -> 9705318986 | F97: =IF(B97="INV_SALE",1-D_UC03!$H$28,D_UC03!$G$28) -> 0.95 | G97: =E97*F97 -> 9.220053e+09 | H97: =IF(D_UC03!$S$28=1,MIN(D_UC03!$L$28,$B$68),D_UC03!$L$28) -> 21 | I97: =IF(B97="INV_SALE",E97*D_UC03!$H$28+D_UC03!$K$28,G97*D_UC03!$I$28*H97/365+G97*D_UC03!$J$28+D_UC03!$K$28) -> 47742192 | J97: =D_UC03!$M$28 -> 1 | K97: =IF(J97<=$B$73,1,0) -> 1 | L97: =IF(AND(D_UC03!$Q$28<>"Y",D_UC03!$P$28<>"Y",D_UC03!$R$28<>"N",G97>0,NOT(AND($B$68<D_UC03!$C$13,OR(D_UC03!$S$28=0,D_UC03!$K$28>0)))),1,0) -> 1 | M97: =IF($B$33<>"TH01",0,IF($B$35="M1",IF(OR(B97="CL",B97="NB"),1,0),1)) -> 1 | N97: =L97*M97 -> 1 | O97: =IF(AND(L97=1,K97=1),G97,0) -> 9.220053e+09 | P97: =IF(AND(G97>0,$B$72>0),ROUND(I97/MIN(G97,$B$72),4),0) -> 0.0176 | Q97: =IF(B97="NB",0,IF($B$35="M1",IF(B97="CL",1,9),IF($B$35="M3",IF(OR(B97="AR_EARLY",B97="RF",B97="FAC"),1,IF(B97="AP_EXT",2,3)),IF(OR(B97="AR_EARLY",B97="RF",B97="FAC"),1,IF(OR(B97="INV_LOAN",B97="INV_SALE"),2,IF(B97="AP_EXT",3,4)))))) -> 1 | R97: =IF(J97<=3,1,IF(J97<=10,2,3)) -> 1 | S97: =IF($B$44="degraded",3,IF(D_UC03!$N$28="Cao",1,IF(D_UC03!$N$28="Trung bình",2,3))) -> 2 | T97: =D_UC03!$O$28 -> 0 | U97: =IF(K97=1,0,2) -> 0 | V97: 6 | W97: =IF(N97=1,U97*10^13+IF($B$74=1,R97*10^12+Q97*10^11,Q97*10^12+R97*10^11)+S97*10^10+MIN(99999,ROUND(P97*10000,0))*10^5+T97*10^4+MIN(99,J97)*100+V97,9*10^14+V97) -> 1120017600106 | X97: =IF(N97=1,SUMPRODUCT(($W$92:$W$105<W97)*($N$92:$N$105=1))+1,"") -> 1 | Y97: =IF(D_UC03!$Q$28="Y","PLEDGED",IF(D_UC03!$P$28="Y","STRATEGIC_OR_CRITICAL",IF(D_UC03!$R$28="N","NO_PRODUCT_DATA",IF(G97<=0,"NO_NET_CASH",IF(L97=0,"SHORT_DURATION_LOCKED",IF(M97=0,"OUT_OF_SCENARIO",IF(K97=0,"TOO_SLOW",IF(G97<$B$76,"BELOW_MIN_DRAW","")))))))) | Z97: =IF(AND(D_UC03!$S$28=0,D_UC03!$L$28<$B$68),"NOT_COVERING_DURATION","")
A98: =D_UC03!$A$29 -> FAC-001 | B98: =D_UC03!$C$29 -> FAC | C98: =D_UC03!$D$29 -> O2 | D98: =D_UC03!$E$29 -> OBJ-AR-K1 | E98: =D_UC03!$F$29 -> 9705318986 | F98: =IF(B98="INV_SALE",1-D_UC03!$H$29,D_UC03!$G$29) -> 0.85 | G98: =E98*F98 -> 8.2495211e+09 | H98: =IF(D_UC03!$S$29=1,MIN(D_UC03!$L$29,$B$68),D_UC03!$L$29) -> 21 | I98: =IF(B98="INV_SALE",E98*D_UC03!$H$29+D_UC03!$K$29,G98*D_UC03!$I$29*H98/365+G98*D_UC03!$J$29+D_UC03!$K$29) -> 98203204 | J98: =D_UC03!$M$29 -> 3 | K98: =IF(J98<=$B$73,1,0) -> 0 | L98: =IF(AND(D_UC03!$Q$29<>"Y",D_UC03!$P$29<>"Y",D_UC03!$R$29<>"N",G98>0,NOT(AND($B$68<D_UC03!$C$13,OR(D_UC03!$S$29=0,D_UC03!$K$29>0)))),1,0) -> 1 | M98: =IF($B$33<>"TH01",0,IF($B$35="M1",IF(OR(B98="CL",B98="NB"),1,0),1)) -> 1 | N98: =L98*M98 -> 1 | O98: =IF(AND(L98=1,K98=1),G98,0) -> 0 | P98: =IF(AND(G98>0,$B$72>0),ROUND(I98/MIN(G98,$B$72),4),0) -> 0.0362 | Q98: =IF(B98="NB",0,IF($B$35="M1",IF(B98="CL",1,9),IF($B$35="M3",IF(OR(B98="AR_EARLY",B98="RF",B98="FAC"),1,IF(B98="AP_EXT",2,3)),IF(OR(B98="AR_EARLY",B98="RF",B98="FAC"),1,IF(OR(B98="INV_LOAN",B98="INV_SALE"),2,IF(B98="AP_EXT",3,4)))))) -> 1 | R98: =IF(J98<=3,1,IF(J98<=10,2,3)) -> 1 | S98: =IF($B$44="degraded",3,IF(D_UC03!$N$29="Cao",1,IF(D_UC03!$N$29="Trung bình",2,3))) -> 2 | T98: =D_UC03!$O$29 -> 1 | U98: =IF(K98=1,0,2) -> 2 | V98: 7 | W98: =IF(N98=1,U98*10^13+IF($B$74=1,R98*10^12+Q98*10^11,Q98*10^12+R98*10^11)+S98*10^10+MIN(99999,ROUND(P98*10000,0))*10^5+T98*10^4+MIN(99,J98)*100+V98,9*10^14+V98) -> 21120036210307 | X98: =IF(N98=1,SUMPRODUCT(($W$92:$W$105<W98)*($N$92:$N$105=1))+1,"") -> 5 | Y98: =IF(D_UC03!$Q$29="Y","PLEDGED",IF(D_UC03!$P$29="Y","STRATEGIC_OR_CRITICAL",IF(D_UC03!$R$29="N","NO_PRODUCT_DATA",IF(G98<=0,"NO_NET_CASH",IF(L98=0,"SHORT_DURATION_LOCKED",IF(M98=0,"OUT_OF_SCENARIO",IF(K98=0,"TOO_SLOW",IF(G98<$B$76,"BELOW_MIN_DRAW","")))))))) -> TOO_SLOW | Z98: =IF(AND(D_UC03!$S$29=0,D_UC03!$L$29<$B$68),"NOT_COVERING_DURATION","")
A99: =D_UC03!$A$30 -> FAC-002 | B99: =D_UC03!$C$30 -> FAC | C99: =D_UC03!$D$30 -> O2 | D99: =D_UC03!$E$30 -> OBJ-AR-K6 | E99: =D_UC03!$F$30 -> 689203917 | F99: =IF(B99="INV_SALE",1-D_UC03!$H$30,D_UC03!$G$30) -> 0.8 | G99: =E99*F99 -> 5.5136313e+08 | H99: =IF(D_UC03!$S$30=1,MIN(D_UC03!$L$30,$B$68),D_UC03!$L$30) -> 30 | I99: =IF(B99="INV_SALE",E99*D_UC03!$H$30+D_UC03!$K$30,G99*D_UC03!$I$30*H99/365+G99*D_UC03!$J$30+D_UC03!$K$30) -> 8648093 | J99: =D_UC03!$M$30 -> 3 | K99: =IF(J99<=$B$73,1,0) -> 0 | L99: =IF(AND(D_UC03!$Q$30<>"Y",D_UC03!$P$30<>"Y",D_UC03!$R$30<>"N",G99>0,NOT(AND($B$68<D_UC03!$C$13,OR(D_UC03!$S$30=0,D_UC03!$K$30>0)))),1,0) -> 1 | M99: =IF($B$33<>"TH01",0,IF($B$35="M1",IF(OR(B99="CL",B99="NB"),1,0),1)) -> 1 | N99: =L99*M99 -> 1 | O99: =IF(AND(L99=1,K99=1),G99,0) -> 0 | P99: =IF(AND(G99>0,$B$72>0),ROUND(I99/MIN(G99,$B$72),4),0) -> 0.0157 | Q99: =IF(B99="NB",0,IF($B$35="M1",IF(B99="CL",1,9),IF($B$35="M3",IF(OR(B99="AR_EARLY",B99="RF",B99="FAC"),1,IF(B99="AP_EXT",2,3)),IF(OR(B99="AR_EARLY",B99="RF",B99="FAC"),1,IF(OR(B99="INV_LOAN",B99="INV_SALE"),2,IF(B99="AP_EXT",3,4)))))) -> 1 | R99: =IF(J99<=3,1,IF(J99<=10,2,3)) -> 1 | S99: =IF($B$44="degraded",3,IF(D_UC03!$N$30="Cao",1,IF(D_UC03!$N$30="Trung bình",2,3))) -> 2 | T99: =D_UC03!$O$30 -> 0 | U99: =IF(K99=1,0,2) -> 2 | V99: 8 | W99: =IF(N99=1,U99*10^13+IF($B$74=1,R99*10^12+Q99*10^11,Q99*10^12+R99*10^11)+S99*10^10+MIN(99999,ROUND(P99*10000,0))*10^5+T99*10^4+MIN(99,J99)*100+V99,9*10^14+V99) -> 21120015700308 | X99: =IF(N99=1,SUMPRODUCT(($W$92:$W$105<W99)*($N$92:$N$105=1))+1,"") -> 4 | Y99: =IF(D_UC03!$Q$30="Y","PLEDGED",IF(D_UC03!$P$30="Y","STRATEGIC_OR_CRITICAL",IF(D_UC03!$R$30="N","NO_PRODUCT_DATA",IF(G99<=0,"NO_NET_CASH",IF(L99=0,"SHORT_DURATION_LOCKED",IF(M99=0,"OUT_OF_SCENARIO",IF(K99=0,"TOO_SLOW",IF(G99<$B$76,"BELOW_MIN_DRAW","")))))))) -> TOO_SLOW | Z99: =IF(AND(D_UC03!$S$30=0,D_UC03!$L$30<$B$68),"NOT_COVERING_DURATION","")
A100: =D_UC03!$A$31 -> INV-001 | B100: =D_UC03!$C$31 -> INV_LOAN | C100: =D_UC03!$D$31 -> O2 | D100: =D_UC03!$E$31 -> OBJ-INV-NOR | E100: =D_UC03!$F$31 -> 18884515458 | F100: =IF(B100="INV_SALE",1-D_UC03!$H$31,D_UC03!$G$31) -> 0.6 | G100: =E100*F100 -> 1.1330709e+10 | H100: =IF(D_UC03!$S$31=1,MIN(D_UC03!$L$31,$B$68),D_UC03!$L$31) -> 14 | I100: =IF(B100="INV_SALE",E100*D_UC03!$H$31+D_UC03!$K$31,G100*D_UC03!$I$31*H100/365+G100*D_UC03!$J$31+D_UC03!$K$31) -> 47806280 | J100: =D_UC03!$M$31 -> 5 | K100: =IF(J100<=$B$73,1,0) -> 0 | L100: =IF(AND(D_UC03!$Q$31<>"Y",D_UC03!$P$31<>"Y",D_UC03!$R$31<>"N",G100>0,NOT(AND($B$68<D_UC03!$C$13,OR(D_UC03!$S$31=0,D_UC03!$K$31>0)))),1,0) -> 1 | M100: =IF($B$33<>"TH01",0,IF($B$35="M1",IF(OR(B100="CL",B100="NB"),1,0),1)) -> 1 | N100: =L100*M100 -> 1 | O100: =IF(AND(L100=1,K100=1),G100,0) -> 0 | P100: =IF(AND(G100>0,$B$72>0),ROUND(I100/MIN(G100,$B$72),4),0) -> 0.0176 | Q100: =IF(B100="NB",0,IF($B$35="M1",IF(B100="CL",1,9),IF($B$35="M3",IF(OR(B100="AR_EARLY",B100="RF",B100="FAC"),1,IF(B100="AP_EXT",2,3)),IF(OR(B100="AR_EARLY",B100="RF",B100="FAC"),1,IF(OR(B100="INV_LOAN",B100="INV_SALE"),2,IF(B100="AP_EXT",3,4)))))) -> 3 | R100: =IF(J100<=3,1,IF(J100<=10,2,3)) -> 2 | S100: =IF($B$44="degraded",3,IF(D_UC03!$N$31="Cao",1,IF(D_UC03!$N$31="Trung bình",2,3))) -> 2 | T100: =D_UC03!$O$31 -> 0 | U100: =IF(K100=1,0,2) -> 2 | V100: 9 | W100: =IF(N100=1,U100*10^13+IF($B$74=1,R100*10^12+Q100*10^11,Q100*10^12+R100*10^11)+S100*10^10+MIN(99999,ROUND(P100*10000,0))*10^5+T100*10^4+MIN(99,J100)*100+V100,9*10^14+V100) -> 22320017600509 | X100: =IF(N100=1,SUMPRODUCT(($W$92:$W$105<W100)*($N$92:$N$105=1))+1,"") -> 9 | Y100: =IF(D_UC03!$Q$31="Y","PLEDGED",IF(D_UC03!$P$31="Y","STRATEGIC_OR_CRITICAL",IF(D_UC03!$R$31="N","NO_PRODUCT_DATA",IF(G100<=0,"NO_NET_CASH",IF(L100=0,"SHORT_DURATION_LOCKED",IF(M100=0,"OUT_OF_SCENARIO",IF(K100=0,"TOO_SLOW",IF(G100<$B$76,"BELOW_MIN_DRAW","")))))))) -> TOO_SLOW | Z100: =IF(AND(D_UC03!$S$31=0,D_UC03!$L$31<$B$68),"NOT_COVERING_DURATION","")
A101: =D_UC03!$A$32 -> INV-002 | B101: =D_UC03!$C$32 -> INV_SALE | C101: =D_UC03!$D$32 -> O3 | D101: =D_UC03!$E$32 -> OBJ-INV-SLOW | E101: =D_UC03!$F$32 -> 2610842457 | F101: =IF(B101="INV_SALE",1-D_UC03!$H$32,D_UC03!$G$32) -> 0.875 | G101: =E101*F101 -> 2.2844871e+09 | H101: =IF(D_UC03!$S$32=1,MIN(D_UC03!$L$32,$B$68),D_UC03!$L$32) -> 0 | I101: =IF(B101="INV_SALE",E101*D_UC03!$H$32+D_UC03!$K$32,G101*D_UC03!$I$32*H101/365+G101*D_UC03!$J$32+D_UC03!$K$32) -> 3.2635531e+08 | J101: =D_UC03!$M$32 -> 30 | K101: =IF(J101<=$B$73,1,0) -> 0 | L101: =IF(AND(D_UC03!$Q$32<>"Y",D_UC03!$P$32<>"Y",D_UC03!$R$32<>"N",G101>0,NOT(AND($B$68<D_UC03!$C$13,OR(D_UC03!$S$32=0,D_UC03!$K$32>0)))),1,0) -> 1 | M101: =IF($B$33<>"TH01",0,IF($B$35="M1",IF(OR(B101="CL",B101="NB"),1,0),1)) -> 1 | N101: =L101*M101 -> 1 | O101: =IF(AND(L101=1,K101=1),G101,0) -> 0 | P101: =IF(AND(G101>0,$B$72>0),ROUND(I101/MIN(G101,$B$72),4),0) -> 0.1429 | Q101: =IF(B101="NB",0,IF($B$35="M1",IF(B101="CL",1,9),IF($B$35="M3",IF(OR(B101="AR_EARLY",B101="RF",B101="FAC"),1,IF(B101="AP_EXT",2,3)),IF(OR(B101="AR_EARLY",B101="RF",B101="FAC"),1,IF(OR(B101="INV_LOAN",B101="INV_SALE"),2,IF(B101="AP_EXT",3,4)))))) -> 3 | R101: =IF(J101<=3,1,IF(J101<=10,2,3)) -> 3 | S101: =IF($B$44="degraded",3,IF(D_UC03!$N$32="Cao",1,IF(D_UC03!$N$32="Trung bình",2,3))) -> 3 | T101: =D_UC03!$O$32 -> 1 | U101: =IF(K101=1,0,2) -> 2 | V101: 10 | W101: =IF(N101=1,U101*10^13+IF($B$74=1,R101*10^12+Q101*10^11,Q101*10^12+R101*10^11)+S101*10^10+MIN(99999,ROUND(P101*10000,0))*10^5+T101*10^4+MIN(99,J101)*100+V101,9*10^14+V101) -> 23330142913010 | X101: =IF(N101=1,SUMPRODUCT(($W$92:$W$105<W101)*($N$92:$N$105=1))+1,"") -> 10 | Y101: =IF(D_UC03!$Q$32="Y","PLEDGED",IF(D_UC03!$P$32="Y","STRATEGIC_OR_CRITICAL",IF(D_UC03!$R$32="N","NO_PRODUCT_DATA",IF(G101<=0,"NO_NET_CASH",IF(L101=0,"SHORT_DURATION_LOCKED",IF(M101=0,"OUT_OF_SCENARIO",IF(K101=0,"TOO_SLOW",IF(G101<$B$76,"BELOW_MIN_DRAW","")))))))) -> TOO_SLOW | Z101: =IF(AND(D_UC03!$S$32=0,D_UC03!$L$32<$B$68),"NOT_COVERING_DURATION","")
A102: =D_UC03!$A$33 -> INV-003 | B102: =D_UC03!$C$33 -> INV_LOAN | C102: =D_UC03!$D$33 -> O2 | D102: =D_UC03!$E$33 -> OBJ-INV-PLG | E102: =D_UC03!$F$33 -> 738578100 | F102: =IF(B102="INV_SALE",1-D_UC03!$H$33,D_UC03!$G$33) -> 0.6 | G102: =E102*F102 -> 443146860 | H102: =IF(D_UC03!$S$33=1,MIN(D_UC03!$L$33,$B$68),D_UC03!$L$33) -> 14 | I102: =IF(B102="INV_SALE",E102*D_UC03!$H$33+D_UC03!$K$33,G102*D_UC03!$I$33*H102/365+G102*D_UC03!$J$33+D_UC03!$K$33) -> 1869715.5 | J102: =D_UC03!$M$33 -> 5 | K102: =IF(J102<=$B$73,1,0) -> 0 | L102: =IF(AND(D_UC03!$Q$33<>"Y",D_UC03!$P$33<>"Y",D_UC03!$R$33<>"N",G102>0,NOT(AND($B$68<D_UC03!$C$13,OR(D_UC03!$S$33=0,D_UC03!$K$33>0)))),1,0) -> 0 | M102: =IF($B$33<>"TH01",0,IF($B$35="M1",IF(OR(B102="CL",B102="NB"),1,0),1)) -> 1 | N102: =L102*M102 -> 0 | O102: =IF(AND(L102=1,K102=1),G102,0) -> 0 | P102: =IF(AND(G102>0,$B$72>0),ROUND(I102/MIN(G102,$B$72),4),0) -> 0.0042 | Q102: =IF(B102="NB",0,IF($B$35="M1",IF(B102="CL",1,9),IF($B$35="M3",IF(OR(B102="AR_EARLY",B102="RF",B102="FAC"),1,IF(B102="AP_EXT",2,3)),IF(OR(B102="AR_EARLY",B102="RF",B102="FAC"),1,IF(OR(B102="INV_LOAN",B102="INV_SALE"),2,IF(B102="AP_EXT",3,4)))))) -> 3 | R102: =IF(J102<=3,1,IF(J102<=10,2,3)) -> 2 | S102: =IF($B$44="degraded",3,IF(D_UC03!$N$33="Cao",1,IF(D_UC03!$N$33="Trung bình",2,3))) -> 2 | T102: =D_UC03!$O$33 -> 0 | U102: =IF(K102=1,0,2) -> 2 | V102: 11 | W102: =IF(N102=1,U102*10^13+IF($B$74=1,R102*10^12+Q102*10^11,Q102*10^12+R102*10^11)+S102*10^10+MIN(99999,ROUND(P102*10000,0))*10^5+T102*10^4+MIN(99,J102)*100+V102,9*10^14+V102) -> 900000000000011 | X102: =IF(N102=1,SUMPRODUCT(($W$92:$W$105<W102)*($N$92:$N$105=1))+1,"") | Y102: =IF(D_UC03!$Q$33="Y","PLEDGED",IF(D_UC03!$P$33="Y","STRATEGIC_OR_CRITICAL",IF(D_UC03!$R$33="N","NO_PRODUCT_DATA",IF(G102<=0,"NO_NET_CASH",IF(L102=0,"SHORT_DURATION_LOCKED",IF(M102=0,"OUT_OF_SCENARIO",IF(K102=0,"TOO_SLOW",IF(G102<$B$76,"BELOW_MIN_DRAW","")))))))) -> PLEDGED | Z102: =IF(AND(D_UC03!$S$33=0,D_UC03!$L$33<$B$68),"NOT_COVERING_DURATION","")
A103: =D_UC03!$A$34 -> CL-001 | B103: =D_UC03!$C$34 -> CL | C103: =D_UC03!$D$34 -> O2 | D103: =D_UC03!$E$34 -> LIM-CL-001 | E103: =D_UC03!$F$34 -> 3000000000 | F103: =IF(B103="INV_SALE",1-D_UC03!$H$34,D_UC03!$G$34) -> 1 | G103: =E103*F103 -> 3000000000 | H103: =IF(D_UC03!$S$34=1,MIN(D_UC03!$L$34,$B$68),D_UC03!$L$34) -> 14 | I103: =IF(B103="INV_SALE",E103*D_UC03!$H$34+D_UC03!$K$34,G103*D_UC03!$I$34*H103/365+G103*D_UC03!$J$34+D_UC03!$K$34) -> 11506849 | J103: =D_UC03!$M$34 -> 1 | K103: =IF(J103<=$B$73,1,0) -> 1 | L103: =IF(AND(D_UC03!$Q$34<>"Y",D_UC03!$P$34<>"Y",D_UC03!$R$34<>"N",G103>0,NOT(AND($B$68<D_UC03!$C$13,OR(D_UC03!$S$34=0,D_UC03!$K$34>0)))),1,0) -> 1 | M103: =IF($B$33<>"TH01",0,IF($B$35="M1",IF(OR(B103="CL",B103="NB"),1,0),1)) -> 1 | N103: =L103*M103 -> 1 | O103: =IF(AND(L103=1,K103=1),G103,0) -> 3000000000 | P103: =IF(AND(G103>0,$B$72>0),ROUND(I103/MIN(G103,$B$72),4),0) -> 0.0042 | Q103: =IF(B103="NB",0,IF($B$35="M1",IF(B103="CL",1,9),IF($B$35="M3",IF(OR(B103="AR_EARLY",B103="RF",B103="FAC"),1,IF(B103="AP_EXT",2,3)),IF(OR(B103="AR_EARLY",B103="RF",B103="FAC"),1,IF(OR(B103="INV_LOAN",B103="INV_SALE"),2,IF(B103="AP_EXT",3,4)))))) -> 3 | R103: =IF(J103<=3,1,IF(J103<=10,2,3)) -> 1 | S103: =IF($B$44="degraded",3,IF(D_UC03!$N$34="Cao",1,IF(D_UC03!$N$34="Trung bình",2,3))) -> 1 | T103: =D_UC03!$O$34 -> 0 | U103: =IF(K103=1,0,2) -> 0 | V103: 12 | W103: =IF(N103=1,U103*10^13+IF($B$74=1,R103*10^12+Q103*10^11,Q103*10^12+R103*10^11)+S103*10^10+MIN(99999,ROUND(P103*10000,0))*10^5+T103*10^4+MIN(99,J103)*100+V103,9*10^14+V103) -> 1310004200112 | X103: =IF(N103=1,SUMPRODUCT(($W$92:$W$105<W103)*($N$92:$N$105=1))+1,"") -> 2 | Y103: =IF(D_UC03!$Q$34="Y","PLEDGED",IF(D_UC03!$P$34="Y","STRATEGIC_OR_CRITICAL",IF(D_UC03!$R$34="N","NO_PRODUCT_DATA",IF(G103<=0,"NO_NET_CASH",IF(L103=0,"SHORT_DURATION_LOCKED",IF(M103=0,"OUT_OF_SCENARIO",IF(K103=0,"TOO_SLOW",IF(G103<$B$76,"BELOW_MIN_DRAW","")))))))) | Z103: =IF(AND(D_UC03!$S$34=0,D_UC03!$L$34<$B$68),"NOT_COVERING_DURATION","")
A104: =D_UC03!$A$35 -> CL-002 | B104: =D_UC03!$C$35 -> CL | C104: =D_UC03!$D$35 -> O2 | D104: =D_UC03!$E$35 -> LIM-CL-002 | E104: =D_UC03!$F$35 -> 1500000000 | F104: =IF(B104="INV_SALE",1-D_UC03!$H$35,D_UC03!$G$35) -> 1 | G104: =E104*F104 -> 1500000000 | H104: =IF(D_UC03!$S$35=1,MIN(D_UC03!$L$35,$B$68),D_UC03!$L$35) -> 14 | I104: =IF(B104="INV_SALE",E104*D_UC03!$H$35+D_UC03!$K$35,G104*D_UC03!$I$35*H104/365+G104*D_UC03!$J$35+D_UC03!$K$35) -> 6904109.6 | J104: =D_UC03!$M$35 -> 2 | K104: =IF(J104<=$B$73,1,0) -> 0 | L104: =IF(AND(D_UC03!$Q$35<>"Y",D_UC03!$P$35<>"Y",D_UC03!$R$35<>"N",G104>0,NOT(AND($B$68<D_UC03!$C$13,OR(D_UC03!$S$35=0,D_UC03!$K$35>0)))),1,0) -> 1 | M104: =IF($B$33<>"TH01",0,IF($B$35="M1",IF(OR(B104="CL",B104="NB"),1,0),1)) -> 1 | N104: =L104*M104 -> 1 | O104: =IF(AND(L104=1,K104=1),G104,0) -> 0 | P104: =IF(AND(G104>0,$B$72>0),ROUND(I104/MIN(G104,$B$72),4),0) -> 0.0046 | Q104: =IF(B104="NB",0,IF($B$35="M1",IF(B104="CL",1,9),IF($B$35="M3",IF(OR(B104="AR_EARLY",B104="RF",B104="FAC"),1,IF(B104="AP_EXT",2,3)),IF(OR(B104="AR_EARLY",B104="RF",B104="FAC"),1,IF(OR(B104="INV_LOAN",B104="INV_SALE"),2,IF(B104="AP_EXT",3,4)))))) -> 3 | R104: =IF(J104<=3,1,IF(J104<=10,2,3)) -> 1 | S104: =IF($B$44="degraded",3,IF(D_UC03!$N$35="Cao",1,IF(D_UC03!$N$35="Trung bình",2,3))) -> 1 | T104: =D_UC03!$O$35 -> 0 | U104: =IF(K104=1,0,2) -> 2 | V104: 13 | W104: =IF(N104=1,U104*10^13+IF($B$74=1,R104*10^12+Q104*10^11,Q104*10^12+R104*10^11)+S104*10^10+MIN(99999,ROUND(P104*10000,0))*10^5+T104*10^4+MIN(99,J104)*100+V104,9*10^14+V104) -> 21310004600213 | X104: =IF(N104=1,SUMPRODUCT(($W$92:$W$105<W104)*($N$92:$N$105=1))+1,"") -> 7 | Y104: =IF(D_UC03!$Q$35="Y","PLEDGED",IF(D_UC03!$P$35="Y","STRATEGIC_OR_CRITICAL",IF(D_UC03!$R$35="N","NO_PRODUCT_DATA",IF(G104<=0,"NO_NET_CASH",IF(L104=0,"SHORT_DURATION_LOCKED",IF(M104=0,"OUT_OF_SCENARIO",IF(K104=0,"TOO_SLOW",IF(G104<$B$76,"BELOW_MIN_DRAW","")))))))) -> TOO_SLOW | Z104: =IF(AND(D_UC03!$S$35=0,D_UC03!$L$35<$B$68),"NOT_COVERING_DURATION","")
A105: =D_UC03!$A$36 -> TT-001 | B105: =D_UC03!$C$36 -> CL | C105: =D_UC03!$D$36 -> O2 | D105: =D_UC03!$E$36 -> LIM-TT-001 | E105: =D_UC03!$F$36 -> 0 | F105: =IF(B105="INV_SALE",1-D_UC03!$H$36,D_UC03!$G$36) -> 1 | G105: =E105*F105 -> 0 | H105: =IF(D_UC03!$S$36=1,MIN(D_UC03!$L$36,$B$68),D_UC03!$L$36) -> 0 | I105: =IF(B105="INV_SALE",E105*D_UC03!$H$36+D_UC03!$K$36,G105*D_UC03!$I$36*H105/365+G105*D_UC03!$J$36+D_UC03!$K$36) -> 0 | J105: =D_UC03!$M$36 -> 0 | K105: =IF(J105<=$B$73,1,0) -> 1 | L105: =IF(AND(D_UC03!$Q$36<>"Y",D_UC03!$P$36<>"Y",D_UC03!$R$36<>"N",G105>0,NOT(AND($B$68<D_UC03!$C$13,OR(D_UC03!$S$36=0,D_UC03!$K$36>0)))),1,0) -> 0 | M105: =IF($B$33<>"TH01",0,IF($B$35="M1",IF(OR(B105="CL",B105="NB"),1,0),1)) -> 1 | N105: =L105*M105 -> 0 | O105: =IF(AND(L105=1,K105=1),G105,0) -> 0 | P105: =IF(AND(G105>0,$B$72>0),ROUND(I105/MIN(G105,$B$72),4),0) -> 0 | Q105: =IF(B105="NB",0,IF($B$35="M1",IF(B105="CL",1,9),IF($B$35="M3",IF(OR(B105="AR_EARLY",B105="RF",B105="FAC"),1,IF(B105="AP_EXT",2,3)),IF(OR(B105="AR_EARLY",B105="RF",B105="FAC"),1,IF(OR(B105="INV_LOAN",B105="INV_SALE"),2,IF(B105="AP_EXT",3,4)))))) -> 3 | R105: =IF(J105<=3,1,IF(J105<=10,2,3)) -> 1 | S105: =IF($B$44="degraded",3,IF(D_UC03!$N$36="Cao",1,IF(D_UC03!$N$36="Trung bình",2,3))) -> 1 | T105: =D_UC03!$O$36 -> 0 | U105: =IF(K105=1,0,2) -> 0 | V105: 14 | W105: =IF(N105=1,U105*10^13+IF($B$74=1,R105*10^12+Q105*10^11,Q105*10^12+R105*10^11)+S105*10^10+MIN(99999,ROUND(P105*10000,0))*10^5+T105*10^4+MIN(99,J105)*100+V105,9*10^14+V105) -> 900000000000014 | X105: =IF(N105=1,SUMPRODUCT(($W$92:$W$105<W105)*($N$92:$N$105=1))+1,"") | Y105: =IF(D_UC03!$Q$36="Y","PLEDGED",IF(D_UC03!$P$36="Y","STRATEGIC_OR_CRITICAL",IF(D_UC03!$R$36="N","NO_PRODUCT_DATA",IF(G105<=0,"NO_NET_CASH",IF(L105=0,"SHORT_DURATION_LOCKED",IF(M105=0,"OUT_OF_SCENARIO",IF(K105=0,"TOO_SLOW",IF(G105<$B$76,"BELOW_MIN_DRAW","")))))))) -> NO_PRODUCT_DATA | Z105: =IF(AND(D_UC03!$S$36=0,D_UC03!$L$36<$B$68),"NOT_COVERING_DURATION","")
A107: 6. Gói theo thứ hạng
A108: Hạng | B108: Dòng SP | C108: Mã | D108: Phương án | E108: Đối tượng | F108: C | G108: Chi phí đủ C | H108: Tier | I108: Lý do bỏ qua | J108: Dùng | K108: Đã rút trước | L108: Rút | M108: Chi phí phần rút | N108: Số nguồn cùng phương án | O108: Cờ | P108: Gói (lũy kế) | Q108: Ngày có tiền | R108: Độ chắc chắn
A109: 1 | B109: =IFERROR(MATCH(A109,$X$92:$X$105,0),0) -> 6 | C109: =IF(B109=0,"",INDEX($A$92:$A$105,B109)) -> RF-001 | D109: =IF(B109=0,"",INDEX($C$92:$C$105,B109)) -> O2 | E109: =IF(B109=0,"",INDEX($D$92:$D$105,B109)) -> OBJ-AR-K1 | F109: =IF(B109=0,0,INDEX($G$92:$G$105,B109)) -> 9.220053e+09 | G109: =IF(B109=0,0,INDEX($I$92:$I$105,B109)) -> 47742192 | H109: =IF(B109=0,"",INDEX($U$92:$U$105,B109)) -> 0 | I109: =IF(C109="","",IF(H109=2,"TOO_SLOW",IF(F109<$B$76,"BELOW_MIN_DRAW",IF(COUNTIFS(E$108:E108,E109,J$108:J108,1)>0,"OBJECT_USED",IF(N109>=D_UC03!$C$15,"MAX_PER_OPTION",IF(K109>=$B$72,"GAP_COVERED",IF(COUNTIFS(J$108:J108,1)>=D_UC03!$C$11,"MAX_SOURCES",""))))))) | J109: =IF(AND(C109<>"",I109=""),1,0) -> 1 | K109: =SUM(L$108:L108) -> 0 | L109: =IF(J109=1,MIN(F109,$B$72-K109),0) -> 2.7154855e+09 | M109: =IF(J109=1,G109*L109/F109,0) -> 14061007 | N109: =COUNTIFS(D$108:D108,D109,J$108:J108,1) -> 0 | O109: =IF(B109=0,"",INDEX($Z$92:$Z$105,B109)) | P109: =IF(J109=1,C109,"") -> RF-001 | Q109: =IF(B109=0,"",INDEX($J$92:$J$105,B109)) -> 1 | R109: =IF(B109=0,"",INDEX(D_UC03!$N$23:$N$36,B109)) -> Trung bình
A110: 2 | B110: =IFERROR(MATCH(A110,$X$92:$X$105,0),0) -> 12 | C110: =IF(B110=0,"",INDEX($A$92:$A$105,B110)) -> CL-001 | D110: =IF(B110=0,"",INDEX($C$92:$C$105,B110)) -> O2 | E110: =IF(B110=0,"",INDEX($D$92:$D$105,B110)) -> LIM-CL-001 | F110: =IF(B110=0,0,INDEX($G$92:$G$105,B110)) -> 3000000000 | G110: =IF(B110=0,0,INDEX($I$92:$I$105,B110)) -> 11506849 | H110: =IF(B110=0,"",INDEX($U$92:$U$105,B110)) -> 0 | I110: =IF(C110="","",IF(H110=2,"TOO_SLOW",IF(F110<$B$76,"BELOW_MIN_DRAW",IF(COUNTIFS(E$108:E109,E110,J$108:J109,1)>0,"OBJECT_USED",IF(N110>=D_UC03!$C$15,"MAX_PER_OPTION",IF(K110>=$B$72,"GAP_COVERED",IF(COUNTIFS(J$108:J109,1)>=D_UC03!$C$11,"MAX_SOURCES",""))))))) -> GAP_COVERED | J110: =IF(AND(C110<>"",I110=""),1,0) -> 0 | K110: =SUM(L$108:L109) -> 2.7154855e+09 | L110: =IF(J110=1,MIN(F110,$B$72-K110),0) -> 0 | M110: =IF(J110=1,G110*L110/F110,0) -> 0 | N110: =COUNTIFS(D$108:D109,D110,J$108:J109,1) -> 1 | O110: =IF(B110=0,"",INDEX($Z$92:$Z$105,B110)) | P110: =IF(J110=1,IF(P109="",C110,P109&" + "&C110),P109) -> RF-001 | Q110: =IF(B110=0,"",INDEX($J$92:$J$105,B110)) -> 1 | R110: =IF(B110=0,"",INDEX(D_UC03!$N$23:$N$36,B110)) -> Cao
A111: 3 | B111: =IFERROR(MATCH(A111,$X$92:$X$105,0),0) -> 1 | C111: =IF(B111=0,"",INDEX($A$92:$A$105,B111)) -> NB-01 | D111: =IF(B111=0,"",INDEX($C$92:$C$105,B111)) -> O0 | E111: =IF(B111=0,"",INDEX($D$92:$D$105,B111)) -> OBJ-NB | F111: =IF(B111=0,0,INDEX($G$92:$G$105,B111)) -> 2000000000 | G111: =IF(B111=0,0,INDEX($I$92:$I$105,B111)) -> 0 | H111: =IF(B111=0,"",INDEX($U$92:$U$105,B111)) -> 2 | I111: =IF(C111="","",IF(H111=2,"TOO_SLOW",IF(F111<$B$76,"BELOW_MIN_DRAW",IF(COUNTIFS(E$108:E110,E111,J$108:J110,1)>0,"OBJECT_USED",IF(N111>=D_UC03!$C$15,"MAX_PER_OPTION",IF(K111>=$B$72,"GAP_COVERED",IF(COUNTIFS(J$108:J110,1)>=D_UC03!$C$11,"MAX_SOURCES",""))))))) -> TOO_SLOW | J111: =IF(AND(C111<>"",I111=""),1,0) -> 0 | K111: =SUM(L$108:L110) -> 2.7154855e+09 | L111: =IF(J111=1,MIN(F111,$B$72-K111),0) -> 0 | M111: =IF(J111=1,G111*L111/F111,0) -> 0 | N111: =COUNTIFS(D$108:D110,D111,J$108:J110,1) -> 0 | O111: =IF(B111=0,"",INDEX($Z$92:$Z$105,B111)) | P111: =IF(J111=1,IF(P110="",C111,P110&" + "&C111),P110) -> RF-001 | Q111: =IF(B111=0,"",INDEX($J$92:$J$105,B111)) -> 2 | R111: =IF(B111=0,"",INDEX(D_UC03!$N$23:$N$36,B111)) -> Cao
A112: 4 | B112: =IFERROR(MATCH(A112,$X$92:$X$105,0),0) -> 8 | C112: =IF(B112=0,"",INDEX($A$92:$A$105,B112)) -> FAC-002 | D112: =IF(B112=0,"",INDEX($C$92:$C$105,B112)) -> O2 | E112: =IF(B112=0,"",INDEX($D$92:$D$105,B112)) -> OBJ-AR-K6 | F112: =IF(B112=0,0,INDEX($G$92:$G$105,B112)) -> 5.5136313e+08 | G112: =IF(B112=0,0,INDEX($I$92:$I$105,B112)) -> 8648093 | H112: =IF(B112=0,"",INDEX($U$92:$U$105,B112)) -> 2 | I112: =IF(C112="","",IF(H112=2,"TOO_SLOW",IF(F112<$B$76,"BELOW_MIN_DRAW",IF(COUNTIFS(E$108:E111,E112,J$108:J111,1)>0,"OBJECT_USED",IF(N112>=D_UC03!$C$15,"MAX_PER_OPTION",IF(K112>=$B$72,"GAP_COVERED",IF(COUNTIFS(J$108:J111,1)>=D_UC03!$C$11,"MAX_SOURCES",""))))))) -> TOO_SLOW | J112: =IF(AND(C112<>"",I112=""),1,0) -> 0 | K112: =SUM(L$108:L111) -> 2.7154855e+09 | L112: =IF(J112=1,MIN(F112,$B$72-K112),0) -> 0 | M112: =IF(J112=1,G112*L112/F112,0) -> 0 | N112: =COUNTIFS(D$108:D111,D112,J$108:J111,1) -> 1 | O112: =IF(B112=0,"",INDEX($Z$92:$Z$105,B112)) | P112: =IF(J112=1,IF(P111="",C112,P111&" + "&C112),P111) -> RF-001 | Q112: =IF(B112=0,"",INDEX($J$92:$J$105,B112)) -> 3 | R112: =IF(B112=0,"",INDEX(D_UC03!$N$23:$N$36,B112)) -> Trung bình
...

Sheet F01_UC4
A2: F01 UC04 Mô phỏng trên cùng dữ liệu UC01 và UC02
A4: Thiết lập | B4: Giá trị | C4: Giải thích | E4: So sánh kết quả | F4: Nền UC02 | G4: Sau mô phỏng | H4: Cách đọc
A5: Mã kịch bản UC04 | B5: 1 | C5: 0 Giữ nguyên; 1 thực hiện giả định; 2 thu sớm 50%; 3 NCC từ chối; 4 tồn bán chậm; 5 kết hợp bất lợi; 6 khách trả chậm | E5: Kịch bản | F5: =F01_UC2!B5 -> Base | G5: =IF($B$34="Hợp lệ",B6,"Chưa tính") -> Thực hiện giả định | H5: So cùng đường tiền gốc
A6: Kịch bản đang chọn | B6: =CHOOSE(B5+1,"Giữ nguyên","Thực hiện giả định","Thu sớm chỉ đạt một phần","NCC từ chối giãn","Bán tồn chậm","Bất lợi kết hợp","Khách trả chậm") -> Thực hiện giả định | C6: Một selector B5; không thay D_F01!B19 khi đổi UC04 | E6: Tiền thấp nhất | F6: =F01_UC2!B12 -> 4140480437 | G6: =IF($B$34="Hợp lệ",MIN(H51:H141),"Chưa tính") -> 4.6833681e+09 | H6: Không coi tăng tiền tạm thời là giải quyết cả kỳ
A7: Khách được chọn | B7: BYR-F01-002 | C7: =IFERROR(INDEX(D_F01!B38:B46,MATCH(B7,D_F01!A38:A46,0))&"; chọn bằng ID","Không tìm thấy khách") -> Khách mua FOB Lớn K1; chọn bằng ID | E7: Ngày tiền thấp nhất | F7: =F01_UC2!B13 -> 46205 | G7: =IF($B$34="Hợp lệ",INDEX(A51:A141,MATCH(G6,H51:H141,0)),"Chưa tính") -> 46204 | H7: Cùng đáy chọn ngày đầu
A8: Phần khoản thu chuyển lịch | B8: 0.5 | C8: 50% mỗi khoản thu hợp lệ của khách; còn lại giữ ngày cũ | E8: Thiếu lớn nhất so Rtarget | F8: =F01_UC2!B14 -> 2.7154855e+09 | G8: =IF($B$34="Hợp lệ",MAX(J51:J141),"Chưa tính") -> 2.1725978e+09 | H8: Không cộng thiếu qua các ngày
A9: Số ngày thu sớm | B9: 7 | C9: Ngày lịch; cận dưới là ngày đầu dự báo | E9: Thiếu lớn nhất để không âm | F9: =F01_UC2!B15 -> 0 | G9: =IF($B$34="Hợp lệ",MAX(0,-G6),"Chưa tính") -> 0 | H9: Không cộng với dòng trên
A10: Chiết khấu thu sớm | B10: 0.01 | C10: Giả định 1% trên phần thực sự thu sớm | E10: Số ngày dưới L | F10: =COUNTIF(I51:I141,">0") -> 7 | G10: =IF($B$34="Hợp lệ",COUNTIF(J51:J141,">0"),"Chưa tính") -> 2 | H10: Ngày trong 91 ngày
A11: Stress số ngày khách trả chậm | B11: 14 | C11: Case6: thay thu sớm bằng thu chậm | E11: Số ngày tiền âm | F11: =COUNTIF(B51:B141,"<0") -> 0 | G11: =IF($B$34="Hợp lệ",COUNTIF(H51:H141,"<0"),"Chưa tính") -> 0 | H11: Không phản ánh thiếu tiền trong từng giờ
A12: Cho thử thay lịch đã xác nhận | B12: 0 | C12: 0 giữ lịch confirmed; 1 cho phép giả định thay lịch; không sửa cam kết thật | E12: Cảnh báo nặng nhất | F12: =F01_UC2!B22 -> Đỏ | G12: =IF($B$34="Hợp lệ",CHOOSE(MAX(K51:K141)+1,"Không cảnh báo","Vàng","Cam","Đỏ"),"Chưa tính") -> Đỏ | H12: Ngưỡng UC02 giữ nguyên
A13: NCC được chọn | B13: SUP-F01-001 | C13: =IFERROR(INDEX(D_F01!B51:B59,MATCH(B13,D_F01!A51:A59,0))&"; chỉ khoản Trả NCC","Không tìm thấy NCC") -> Nhà phân phối vải Beta; chỉ khoản Trả NCC | E13: Tiền cuối horizon | F13: =F01_UC2!G160 -> 14156479147 | G13: =IF($B$34="Hợp lệ",H141,"Chưa tính") -> 1.4319228e+10 | H13: Mốc 29/09/2026
A14: Phần phải trả được giãn | B14: 0.5 | C14: 0–100%; không xóa nợ | E14: Tiền ngày trọng yếu | F14: =INDEX(B51:B141,MATCH($B$26,A51:A141,0)) -> 4140480437 | G14: =IF($B$34="Hợp lệ",INDEX(H51:H141,MATCH($B$26,A51:A141,0)),"Chưa tính") -> 4.8864653e+09 | H14: Cùng ngày B26
A15: Số ngày giãn trả | B15: 14 | C15: Ngày lịch, tính từ lịch UC02 | E15: Mức giảm thiếu lớn nhất | G15: =IF($B$34="Hợp lệ",F8-G8,"Chưa tính") -> 5.4288762e+08 | H15: Âm là xấu hơn
A16: Phí giãn trả một lần | B16: 0.005 | C16: Giả định 0,5% trên phần thật sự dịch | E16: Số ngày thiếu mới | G16: =IF($B$34="Hợp lệ",SUM(L51:L141),"Chưa tính") -> 0 | H16: Nền đủ nhưng sau thiếu
A17: Cho phép thử với NCC thiết yếu | B17: 1 | C17: 1 xác nhận giả định để thử, không phải đồng ý từ NCC | E17: Số ngày gap xấu đi | G17: =IF($B$34="Hợp lệ",SUM(M51:M141),"Chưa tính") -> 0 | H17: Bắt cả ngày nền đã thiếu
A18: Lô thử bán | B18: L27 | C18: =IFERROR(INDEX(D_inventory!C5:C40,MATCH(B18,D_inventory!A5:A40,0))&"; kiểm quyền sở hữu/cầm cố","Không tìm thấy lô") -> Thành phẩm bộ sưu tập mùa trước; kiểm quyền sở hữu/cầm cố | E18: CK thu sớm giảm thu | G18: =IF($B$34="Hợp lệ",SUM(M151:M272),"Chưa tính") -> 69465391 | H18: Không ghi chi thêm lần nữa
A19: Tỷ lệ lô bán | B19: 0.5 | C19: 50% giá ghi sổ/khối lượng cùng đơn giá của lô | E19: Phí giãn trả NCC | G19: =IF($B$34="Hợp lệ",SUM(Q151:Q272),"Chưa tính") -> 6875165.5 | H19: Chi ở lịch trả mới
A20: Tỷ lệ giá thu hồi | B20: 0.8 | C20: 80% giá ghi sổ là giả định, không là giá thị trường | E20: Chi phí tiền bán tồn | G20: =IF($B$34="Hợp lệ",B47,"Chưa tính") -> 4879366.8 | H20: Tỷ lệ trên tiền bán gộp
A21: Số ngày từ Start đến bán/thu | B21: 14 | C21: Demo giao và thu cùng ngày; backend tách ngày bán/ngày thu | E21: Giảm giá trị so sổ | G21: =IF($B$34="Hợp lệ",MAX(0,B45-B46),"Chưa tính") -> 60992085 | H21: Không phải dòng chi tiền riêng
A22: Chi phí tiền khi bán | B22: 0.02 | C22: 2% tiền bán gộp; trừ đúng một lần | E22: Tổng chi phí tiền | G22: =IF($B$34="Hợp lệ",SUM(G18:G20),"Chưa tính") -> 81219924 | H22: Chi phí đủ trong và ngoài kỳ
A23: Stress bán tồn trễ thêm | B23: 21 | C23: Case4/5; không tự thay tỷ lệ giá thu hồi | E23: Chi phí kinh tế mô phỏng | G23: =IF($B$34="Hợp lệ",G22+G21,"Chưa tính") -> 1.4221201e+08 | H23: Không trừ lại khỏi dòng tiền
A24: Xác nhận giả định có thể bán lô | B24: 1 | C24: 0 chặn khi có tỷ lệ bán>0; không chứng minh có người mua | E24: Nợ giãn dời sau horizon | G24: =IF($B$34="Hợp lệ",SUMIFS(P151:P272,O151:O272,">"&F01_UC2!B7),"Chưa tính") -> 0 | H24: Chưa trả không đồng nghĩa tiết kiệm
A25: Tỷ lệ thu sớm thực hiện khi stress | B25: 0.5 | C25: Case2/5 chỉ thu sớm được 50% phần đã định chuyển; phần khác về ngày cũ | E25: Thu dịch dời sau horizon | G25: =IF($B$34="Hợp lệ",SUMIFS(L151:L272,K151:K272,">"&F01_UC2!B7)+IF(B33>F01_UC2!B7,B48,0),"Chưa tính") -> 0 | H25: Tiền chưa về trong horizon
A26: Ngày đối chiếu trọng yếu | B26: =F01_UC2!B13 -> 46205 | C26: Mặc định ngày đáy UC02; có thể nhập ngày trong horizon | E26: W tại ngày chốt | F26: =F01_UC1!B30 -> W1 | G26: =IF($B$34="Hợp lệ",F01_UC1!B30,"Chưa tính") -> W1 | H26: Không sửa chẩn đoán lịch sử
A27: Sai số tiền kiểm tra (VND) | B27: 1 | C27: Không phải ngưỡng cảnh báo | E27: TH trong kịch bản | F27: =F01_UC2!B23 -> TH01 | G27: =IF($B$34="Hợp lệ",IF(MIN(H51:H141)<F01_UC2!B9,"TH01",IF(MAX(H51:H141)>F01_UC2!B11,"TH02","Trong vùng L–H")),"Chưa tính") -> TH01 | H27: Nếu nền không Base: chỉ tham khảo
A28: AR share hiệu lực | B28: =IF(B5=0,0,IF(OR(B5=2,B5=5),B8*B25,B8)) -> 0.5 | C28: Thay đổi theo case; không sửa nguồn | E28: Ô ma trận tham khảo | F28: =F01_UC2!B24 -> M3 | G28: =IF($B$34="Hợp lệ",IF(G27="Trong vùng L–H","—","M"&(VALUE(RIGHT(F01_UC1!B30,1))*2+IF(G27="TH01",1,2))),"Chưa tính") -> M3 | H28: Không đồng nhất màu cảnh báo với ô M
A29: Ngày dịch thu có dấu | B29: =IF(B5=6,B11,-B9) -> -7 | C29: Âm = sớm; dương = chậm | E29: Phần thu KH được chuyển | G29: =IF($B$34="Hợp lệ",SUM(J151:J272),"Chưa tính") -> 6.9465391e+09 | H29: Số tiền gộp, khác lợi ích tại một ngày
A30: Chiết khấu hiệu lực | B30: =IF(B5=6,0,B10) -> 0.01 | C30: Case6 không chiết khấu | E30: Phần trả NCC được chuyển | G30: =IF($B$34="Hợp lệ",SUM(N151:N272),"Chưa tính") -> 1375033107 | H30: Giữ nghĩa vụ hoàn trả
A31: AP share hiệu lực | B31: =IF(OR(B5=0,B5=3,B5=5,B5=6),0,B14) -> 0.5 | C31: NCC từ chối → 0 | E31: Tiền ròng bán tồn | G31: =IF($B$34="Hợp lệ",B48,"Chưa tính") -> 2.3908897e+08 | H31: Có thể đến sau horizon
A32: Tỷ lệ bán hiệu lực | B32: =IF(OR(B5=0,B5=6),0,B19) -> 0.5 | C32: Case0 không bán | E32: Ngày đầu dưới dự trữ | F32: =F01_UC2!B20 -> 46204 | G32: =IF($B$34="Hợp lệ",IF(COUNTIF(J51:J141,">0")=0,"Không có",_xlfn.MINIFS(A51:A141,J51:J141,">0")),"Chưa tính") -> 46204 | H32: Chưa thay thế mốc vấn đề có từ ngày chốt
A33: Ngày bán/thu hiệu lực | B33: =F01_UC2!B6+B21+IF(OR(B5=4,B5=5),B23,0) -> 46218 | C33: Có thể nằm sau horizon; không xóa khoản đó | E33: AR ngày vốn tương đương | G33: =IF($B$34="Hợp lệ",IF(F01_UC1!B5<=0,"n.a.",SUMPRODUCT(J151:J272,F151:F272-K151:K272)/F01_UC1!B5),"Chưa tính") -> 0.6715932 | H33: Không là số ngày CCC giảm
A34: Kiểm tra thiết lập | B34: =IF(OR(B5<0,B5>6,MOD(B5,1)<>0,COUNT(B5,B8:B12,B14:B17,B19:B27)<>19,B8<0,B8>1,B14<0,B14>1,B19<0,B19>1,B20<0,B20>1,B10<0,B10>1,B16<0,B16>1,B22<0,B22>1,B25<0,B25>1,B9<0,MOD(B9,1)<>0,B11<0,MOD(B11,1)<>0,B15<0,MOD(B15,1)<>0,B21<0,MOD(B21,1)<>0,B23<0,MOD(B23,1)<>0,B12<0,B12>1,MOD(B12,1)<>0,B17<0,B17>1,MOD(B17,1)<>0,B24<0,B24>1,MOD(B24,1)<>0,B27<=0,B26<F01_UC2!B6,B26>F01_UC2!B7,D_F01!B15<0,D_F01!B16<=0,D_F01!B15>D_F01!B16,D_F01!B16>D_F01!B17),"LỖI tham số",IF(OR(COUNTIF(D_sales!C5:C121,B7)=0,COUNTIF(D_purchases!C5:C139,B13)=0),"LỖI ID đối tác",IF(AND(B32>0,OR(B38<>D_F01!B5,B39<>"không",B24<>1)),"CHẶN lô hàng",IF(AND(B31>0,B15>0,B17<>1,COUNTIFS(F01_UC2!C220:C341,B13,F01_UC2!P220:P341,"Trả NCC",F01_UC2!Q220:Q341,1)>0),"CHẶN NCC thiết yếu","Hợp lệ")))) -> Hợp lệ | C34: Lỗi chặn kết quả sau; phải sửa đầu vào | E34: AP ngày vốn tương đương | G34: =IF($B$34="Hợp lệ",IF(F01_UC1!B6<=0,"n.a.",SUMPRODUCT(N151:N272,O151:O272-F151:F272)/F01_UC1!B6),"Chưa tính") -> 0.3371681 | H34: Không đổi DPO tại 30/06
A35: Kịch bản nền UC02 | B35: =F01_UC2!B5 -> Base | C35: Base mặc định. Chọn nền khác ở D_F01: mọi đối chiếu dùng đúng nền đó | E35: CCC tại ngày chốt | F35: =F01_UC1!B15 -> 117.62031 | G35: =IF($B$34="Hợp lệ",F01_UC1!B15,"Chưa tính") -> 117.62031 | H35: Ngày, giữ nguyên
A36: Snapshot | B36: =D_F01!B22 -> F01-FOB-20260630-v11 | C36: Giữ cùng snapshot UC01/UC02 | E36: Kết luận | G36: =IF($B$34="Hợp lệ",IF(G24>0,"Chưa đủ đánh giá: có nợ sau kỳ",IF(G8<=B27,"Không thiếu trong phạm vi mô phỏng",IF(G17>0,"Có ngày thiếu xấu đi",IF(OR(G15>B27,G10<F10,MAX(O51:O141)>B27),"Cải thiện một phần","Không cải thiện")))),"Chưa tính") -> Cải thiện một phần | H36: Không phải quyết định hoặc cam kết
A37: Giá ghi sổ lô | B37: =IFERROR(INDEX(D_inventory!O5:O40,MATCH(B18,D_inventory!A5:A40,0)),0) -> 609920850 | C37: Tra D_inventory trực tiếp | E37: Trạng thái | G37: =IF($B$34="Hợp lệ","provisional","Chưa tính") -> provisional | H37: Giả định; dữ liệu hư cấu; chưa mô hình VAT
A38: Chủ sở hữu lô | B38: =IFERROR(INDEX(D_inventory!E5:E40,MATCH(B18,D_inventory!A5:A40,0)),"Không tìm thấy") -> F01 | C38: Chỉ bán lô thuộc F01; mô hình FOB tự sở hữu nguyên liệu và thành phẩm | E38: Lịch confirmed bị thử thay | G38: =IF($B$34="Hợp lệ",COUNTIFS(J151:J272,">0",G151:G272,">0"),"Chưa tính") -> 0 | H38: Nếu >0 phải nêu trong diễn giải
A39: Cầm cố lô | B39: =IFERROR(INDEX(D_inventory!M5:M40,MATCH(B18,D_inventory!A5:A40,0)),"Không tìm thấy") -> không | C39: Chưa rõ cũng bị chặn | E39: Dự trữ mục tiêu | F39: =F01_UC2!B10 -> 6.8559659e+09 | G39: =IF($B$34="Hợp lệ",F01_UC2!B10,"Chưa tính") -> 6.8559659e+09 | H39: Không thay để tạo kết quả đẹp
A40: Nguồn các tham số UC04 | B40: demo_assumption | C40: Dữ liệu giả lập; không xác nhận phương án khả thi; net_noVAT | E40: Giới hạn | F40: Chỉ 13 tuần | G40: Không thực thi | H40: Không suy tiết kiệm lãi; không gọi bền vững từ một lần chạy
A44: Tồn kho | B44: Giá trị | C44: Giải thích
A45: Giá ghi sổ phần bán | B45: =IF(B34="Hợp lệ",B37*B32,0) -> 304960425 | C45: Không là tiền thu
A46: Tiền bán gộp | B46: =B45*B20 -> 243968340 | C46: Theo tỷ lệ thu hồi giả định
A47: Chi phí bán bằng tiền | B47: =B46*B22 -> 4879366.8 | C47: Giảm thu ròng, không chi thêm lần hai
A48: Tiền bán ròng | B48: =B46-B47 -> 2.3908897e+08 | C48: Giao và thu ngay trong demo
A50: Ngày | B50: Tiền nền | C50: Δ thu KH | D50: Δ trả NCC | E50: Δ bán tồn | F50: Δ ròng | G50: Δ lũy kế | H50: Tiền sau | I50: Thiếu nền | J50: Thiếu sau | K50: Mức màu sau | L50: Ngày thiếu mới | M50: Ngày gap xấu đi | N50: Chuỗi dư sau | O50: Giảm gap
A51: =F01_UC2!A70 -> 46204 | B51: =F01_UC2!G70 -> 4221925973 | C51: =SUMIFS($L$151:$L$272,$K$151:$K$272,A51)-SUMIFS($J$151:$J$272,$F$151:$F$272,A51) -> 4.6144209e+08 | D51: =SUMIFS($N$151:$N$272,$F$151:$F$272,A51)-SUMIFS($P$151:$P$272,$O$151:$O$272,A51) -> 0 | E51: =IF(A51=$B$33,$B$48,0) -> 0 | F51: =SUM(C51:E51) -> 4.6144209e+08 | G51: =SUM($F$51:F51) -> 4.6144209e+08 | H51: =IF($B$34="Hợp lệ",B51+G51,"Chưa tính") -> 4.6833681e+09 | I51: =F01_UC2!H70 -> 2.6340399e+09 | J51: =IF($B$34="Hợp lệ",IF(H51<F01_UC2!$B$9,F01_UC2!$B$10-H51,0),"Chưa tính") -> 2.1725978e+09 | K51: =IF($B$34<>"Hợp lệ","Chưa tính",IF(H51<F01_UC2!$B$9,3,0)) -> 3 | L51: =IF($B$34="Hợp lệ",IF(AND(I51=0,J51>$B$27),1,0),"Chưa tính") -> 0 | M51: =IF($B$34="Hợp lệ",IF(J51>I51+$B$27,1,0),"Chưa tính") -> 0 | N51: =IF($B$34<>"Hợp lệ","Chưa tính",IF(H51>F01_UC2!$B$11,1,0)) -> 0 | O51: =IF($B$34="Hợp lệ",I51-J51,"Chưa tính") -> 4.6144209e+08
A52: =F01_UC2!A71 -> 46205 | B52: =F01_UC2!G71 -> 4140480437 | C52: =SUMIFS($L$151:$L$272,$K$151:$K$272,A52)-SUMIFS($J$151:$J$272,$F$151:$F$272,A52) -> 2.8454279e+08 | D52: =SUMIFS($N$151:$N$272,$F$151:$F$272,A52)-SUMIFS($P$151:$P$272,$O$151:$O$272,A52) -> 0 | E52: =IF(A52=$B$33,$B$48,0) -> 0 | F52: =SUM(C52:E52) -> 2.8454279e+08 | G52: =SUM($F$51:F52) -> 7.4598487e+08 | H52: =IF($B$34="Hợp lệ",B52+G52,"Chưa tính") -> 4.8864653e+09 | I52: =F01_UC2!H71 -> 2.7154855e+09 | J52: =IF($B$34="Hợp lệ",IF(H52<F01_UC2!$B$9,F01_UC2!$B$10-H52,0),"Chưa tính") -> 1.9695006e+09 | K52: =IF($B$34<>"Hợp lệ","Chưa tính",IF(H52<F01_UC2!$B$9,3,0)) -> 3 | L52: =IF($B$34="Hợp lệ",IF(AND(I52=0,J52>$B$27),1,0),"Chưa tính") -> 0 | M52: =IF($B$34="Hợp lệ",IF(J52>I52+$B$27,1,0),"Chưa tính") -> 0 | N52: =IF($B$34<>"Hợp lệ","Chưa tính",IF(H52>F01_UC2!$B$11,N51+1,0)) -> 0 | O52: =IF($B$34="Hợp lệ",I52-J52,"Chưa tính") -> 7.4598487e+08
A53: =F01_UC2!A72 -> 46206 | B53: =F01_UC2!G72 -> 4784351714 | C53: =SUMIFS($L$151:$L$272,$K$151:$K$272,A53)-SUMIFS($J$151:$J$272,$F$151:$F$272,A53) -> 0 | D53: =SUMIFS($N$151:$N$272,$F$151:$F$272,A53)-SUMIFS($P$151:$P$272,$O$151:$O$272,A53) -> 185704896 | E53: =IF(A53=$B$33,$B$48,0) -> 0 | F53: =SUM(C53:E53) -> 185704896 | G53: =SUM($F$51:F53) -> 9.3168977e+08 | H53: =IF($B$34="Hợp lệ",B53+G53,"Chưa tính") -> 5.7160415e+09 | I53: =F01_UC2!H72 -> 2.0716142e+09 | J53: =IF($B$34="Hợp lệ",IF(H53<F01_UC2!$B$9,F01_UC2!$B$10-H53,0),"Chưa tính") -> 0 | K53: =IF($B$34<>"Hợp lệ","Chưa tính",IF(H53<F01_UC2!$B$9,3,0)) -> 0 | L53: =IF($B$34="Hợp lệ",IF(AND(I53=0,J53>$B$27),1,0),"Chưa tính") -> 0 | M53: =IF($B$34="Hợp lệ",IF(J53>I53+$B$27,1,0),"Chưa tính") -> 0 | N53: =IF($B$34<>"Hợp lệ","Chưa tính",IF(H53>F01_UC2!$B$11,N52+1,0)) -> 0 | O53: =IF($B$34="Hợp lệ",I53-J53,"Chưa tính") -> 2.0716142e+09
A54: =F01_UC2!A73 -> 46207 | B54: =F01_UC2!G73 -> 6562039455 | C54: =SUMIFS($L$151:$L$272,$K$151:$K$272,A54)-SUMIFS($J$151:$J$272,$F$151:$F$272,A54) -> 12834630 | D54: =SUMIFS($N$151:$N$272,$F$151:$F$272,A54)-SUMIFS($P$151:$P$272,$O$151:$O$272,A54) -> 0 | E54: =IF(A54=$B$33,$B$48,0) -> 0 | F54: =SUM(C54:E54) -> 12834630 | G54: =SUM($F$51:F54) -> 9.445244e+08 | H54: =IF($B$34="Hợp lệ",B54+G54,"Chưa tính") -> 7.5065639e+09 | I54: =F01_UC2!H73 -> 0 | J54: =IF($B$34="Hợp lệ",IF(H54<F01_UC2!$B$9,F01_UC2!$B$10-H54,0),"Chưa tính") -> 0 | K54: =IF($B$34<>"Hợp lệ","Chưa tính",IF(H54<F01_UC2!$B$9,3,0)) -> 0 | L54: =IF($B$34="Hợp lệ",IF(AND(I54=0,J54>$B$27),1,0),"Chưa tính") -> 0 | M54: =IF($B$34="Hợp lệ",IF(J54>I54+$B$27,1,0),"Chưa tính") -> 0 | N54: =IF($B$34<>"Hợp lệ","Chưa tính",IF(H54>F01_UC2!$B$11,N53+1,0)) -> 0 | O54: =IF($B$34="Hợp lệ",I54-J54,"Chưa tính") -> 0
A55: =F01_UC2!A74 -> 46208 | B55: =F01_UC2!G74 -> 5263759563 | C55: =SUMIFS($L$151:$L$272,$K$151:$K$272,A55)-SUMIFS($J$151:$J$272,$F$151:$F$272,A55) -> 2.2835508e+08 | D55: =SUMIFS($N$151:$N$272,$F$151:$F$272,A55)-SUMIFS($P$151:$P$272,$O$151:$O$272,A55) -> 0 | E55: =IF(A55=$B$33,$B$48,0) -> 0 | F55: =SUM(C55:E55) -> 2.2835508e+08 | G55: =SUM($F$51:F55) -> 1.1728795e+09 | H55: =IF($B$34="Hợp lệ",B55+G55,"Chưa tính") -> 6.436639e+09 | I55: =F01_UC2!H74 -> 1.5922063e+09 | J55: =IF($B$34="Hợp lệ",IF(H55<F01_UC2!$B$9,F01_UC2!$B$10-H55,0),"Chưa tính") -> 0 | K55: =IF($B$34<>"Hợp lệ","Chưa tính",IF(H55<F01_UC2!$B$9,3,0)) -> 0 | L55: =IF($B$34="Hợp lệ",IF(AND(I55=0,J55>$B$27),1,0),"Chưa tính") -> 0 | M55: =IF($B$34="Hợp lệ",IF(J55>I55+$B$27,1,0),"Chưa tính") -> 0 | N55: =IF($B$34<>"Hợp lệ","Chưa tính",IF(H55>F01_UC2!$B$11,N54+1,0)) -> 0 | O55: =IF($B$34="Hợp lệ",I55-J55,"Chưa tính") -> 1.5922063e+09
A56: =F01_UC2!A75 -> 46209 | B56: =F01_UC2!G75 -> 5263759563 | C56: =SUMIFS($L$151:$L$272,$K$151:$K$272,A56)-SUMIFS($J$151:$J$272,$F$151:$F$272,A56) -> 0 | D56: =SUMIFS($N$151:$N$272,$F$151:$F$272,A56)-SUMIFS($P$151:$P$272,$O$151:$O$272,A56) -> 0 | E56: =IF(A56=$B$33,$B$48,0) -> 0 | F56: =SUM(C56:E56) -> 0 | G56: =SUM($F$51:F56) -> 1.1728795e+09 | H56: =IF($B$34="Hợp lệ",B56+G56,"Chưa tính") -> 6.436639e+09 | I56: =F01_UC2!H75 -> 1.5922063e+09 | J56: =IF($B$34="Hợp lệ",IF(H56<F01_UC2!$B$9,F01_UC2!$B$10-H56,0),"Chưa tính") -> 0 | K56: =IF($B$34<>"Hợp lệ","Chưa tính",IF(H56<F01_UC2!$B$9,3,0)) -> 0 | L56: =IF($B$34="Hợp lệ",IF(AND(I56=0,J56>$B$27),1,0),"Chưa tính") -> 0 | M56: =IF($B$34="Hợp lệ",IF(J56>I56+$B$27,1,0),"Chưa tính") -> 0 | N56: =IF($B$34<>"Hợp lệ","Chưa tính",IF(H56>F01_UC2!$B$11,N55+1,0)) -> 0 | O56: =IF($B$34="Hợp lệ",I56-J56,"Chưa tính") -> 1.5922063e+09
A57: =F01_UC2!A76 -> 46210 | B57: =F01_UC2!G76 -> 4515574756 | C57: =SUMIFS($L$151:$L$272,$K$151:$K$272,A57)-SUMIFS($J$151:$J$272,$F$151:$F$272,A57) -> 6.1966316e+08 | D57: =SUMIFS($N$151:$N$272,$F$151:$F$272,A57)-SUMIFS($P$151:$P$272,$O$151:$O$272,A57) -> 0 | E57: =IF(A57=$B$33,$B$48,0) -> 0 | F57: =SUM(C57:E57) -> 6.1966316e+08 | G57: =SUM($F$51:F57) -> 1.7925426e+09 | H57: =IF($B$34="Hợp lệ",B57+G57,"Chưa tính") -> 6.3081174e+09 | I57: =F01_UC2!H76 -> 2.3403911e+09 | J57: =IF($B$34="Hợp lệ",IF(H57<F01_UC2!$B$9,F01_UC2!$B$10-H57,0),"Chưa tính") -> 0 | K57: =IF($B$34<>"Hợp lệ","Chưa tính",IF(H57<F01_UC2!$B$9,3,0)) -> 0 | L57: =IF($B$34="Hợp lệ",IF(AND(I57=0,J57>$B$27),1,0),"Chưa tính") -> 0 | M57: =IF($B$34="Hợp lệ",IF(J57>I57+$B$27,1,0),"Chưa tính") -> 0 | N57: =IF($B$34<>"Hợp lệ","Chưa tính",IF(H57>F01_UC2!$B$11,N56+1,0)) -> 0 | O57: =IF($B$34="Hợp lệ",I57-J57,"Chưa tính") -> 2.3403911e+09
A58: =F01_UC2!A77 -> 46211 | B58: =F01_UC2!G77 -> 5314587071 | C58: =SUMIFS($L$151:$L$272,$K$151:$K$272,A58)-SUMIFS($J$151:$J$272,$F$151:$F$272,A58) -> 0 | D58: =SUMIFS($N$151:$N$272,$F$151:$F$272,A58)-SUMIFS($P$151:$P$272,$O$151:$O$272,A58) -> 0 | E58: =IF(A58=$B$33,$B$48,0) -> 0 | F58: =SUM(C58:E58) -> 0 | G58: =SUM($F$51:F58) -> 1.7925426e+09 | H58: =IF($B$34="Hợp lệ",B58+G58,"Chưa tính") -> 7.1071297e+09 | I58: =F01_UC2!H77 -> 1.5413788e+09 | J58: =IF($B$34="Hợp lệ",IF(H58<F01_UC2!$B$9,F01_UC2!$B$10-H58,0),"Chưa tính") -> 0 | K58: =IF($B$34<>"Hợp lệ","Chưa tính",IF(H58<F01_UC2!$B$9,3,0)) -> 0 | L58: =IF($B$34="Hợp lệ",IF(AND(I58=0,J58>$B$27),1,0),"Chưa tính") -> 0 | M58: =IF($B$34="Hợp lệ",IF(J58>I58+$B$27,1,0),"Chưa tính") -> 0 | N58: =IF($B$34<>"Hợp lệ","Chưa tính",IF(H58>F01_UC2!$B$11,N57+1,0)) -> 0 | O58: =IF($B$34="Hợp lệ",I58-J58,"Chưa tính") -> 1.5413788e+09
A59: =F01_UC2!A78 -> 46212 | B59: =F01_UC2!G78 -> 5889420981 | C59: =SUMIFS($L$151:$L$272,$K$151:$K$272,A59)-SUMIFS($J$151:$J$272,$F$151:$F$272,A59) -> -287416955 | D59: =SUMIFS($N$151:$N$272,$F$151:$F$272,A59)-SUMIFS($P$151:$P$272,$O$151:$O$272,A59) -> 0 | E59: =IF(A59=$B$33,$B$48,0) -> 0 | F59: =SUM(C59:E59) -> -287416955 | G59: =SUM($F$51:F59) -> 1.5051257e+09 | H59: =IF($B$34="Hợp lệ",B59+G59,"Chưa tính") -> 7.3945467e+09 | I59: =F01_UC2!H78 -> 0 | J59: =IF($B$34="Hợp lệ",IF(H59<F01_UC2!$B$9,F01_UC2!$B$10-H59,0),"Chưa tính") -> 0 | K59: =IF($B$34<>"Hợp lệ","Chưa tính",IF(H59<F01_UC2!$B$9,3,0)) -> 0 | L59: =IF($B$34="Hợp lệ",IF(AND(I59=0,J59>$B$27),1,0),"Chưa tính") -> 0 | M59: =IF($B$34="Hợp lệ",IF(J59>I59+$B$27,1,0),"Chưa tính") -> 0 | N59: =IF($B$34<>"Hợp lệ","Chưa tính",IF(H59>F01_UC2!$B$11,N58+1,0)) -> 0 | O59: =IF($B$34="Hợp lệ",I59-J59,"Chưa tính") -> 0
A60: =F01_UC2!A79 -> 46213 | B60: =F01_UC2!G79 -> 9111656724 | C60: =SUMIFS($L$151:$L$272,$K$151:$K$272,A60)-SUMIFS($J$151:$J$272,$F$151:$F$272,A60) -> 0 | D60: =SUMIFS($N$151:$N$272,$F$151:$F$272,A60)-SUMIFS($P$151:$P$272,$O$151:$O$272,A60) -> 0 | E60: =IF(A60=$B$33,$B$48,0) -> 0 | F60: =SUM(C60:E60) -> 0 | G60: =SUM($F$51:F60) -> 1.5051257e+09 | H60: =IF($B$34="Hợp lệ",B60+G60,"Chưa tính") -> 1.0616782e+10 | I60: =F01_UC2!H79 -> 0 | J60: =IF($B$34="Hợp lệ",IF(H60<F01_UC2!$B$9,F01_UC2!$B$10-H60,0),"Chưa tính") -> 0 | K60: =IF($B$34<>"Hợp lệ","Chưa tính",IF(H60<F01_UC2!$B$9,3,0)) -> 0 | L60: =IF($B$34="Hợp lệ",IF(AND(I60=0,J60>$B$27),1,0),"Chưa tính") -> 0 | M60: =IF($B$34="Hợp lệ",IF(J60>I60+$B$27,1,0),"Chưa tính") -> 0 | N60: =IF($B$34<>"Hợp lệ","Chưa tính",IF(H60>F01_UC2!$B$11,N59+1,0)) -> 1 | O60: =IF($B$34="Hợp lệ",I60-J60,"Chưa tính") -> 0
A61: =F01_UC2!A80 -> 46214 | B61: =F01_UC2!G80 -> 9690006277 | C61: =SUMIFS($L$151:$L$272,$K$151:$K$272,A61)-SUMIFS($J$151:$J$272,$F$151:$F$272,A61) -> -43296945 | D61: =SUMIFS($N$151:$N$272,$F$151:$F$272,A61)-SUMIFS($P$151:$P$272,$O$151:$O$272,A61) -> 0 | E61: =IF(A61=$B$33,$B$48,0) -> 0 | F61: =SUM(C61:E61) -> -43296945 | G61: =SUM($F$51:F61) -> 1.4618287e+09 | H61: =IF($B$34="Hợp lệ",B61+G61,"Chưa tính") -> 1.1151835e+10 | I61: =F01_UC2!H80 -> 0 | J61: =IF($B$34="Hợp lệ",IF(H61<F01_UC2!$B$9,F01_UC2!$B$10-H61,0),"Chưa tính") -> 0 | K61: =IF($B$34<>"Hợp lệ","Chưa tính",IF(H61<F01_UC2!$B$9,3,0)) -> 0 | L61: =IF($B$34="Hợp lệ",IF(AND(I61=0,J61>$B$27),1,0),"Chưa tính") -> 0 | M61: =IF($B$34="Hợp lệ",IF(J61>I61+$B$27,1,0),"Chưa tính") -> 0 | N61: =IF($B$34<>"Hợp lệ","Chưa tính",IF(H61>F01_UC2!$B$11,N60+1,0)) -> 2 | O61: =IF($B$34="Hợp lệ",I61-J61,"Chưa tính") -> 0
A62: =F01_UC2!A81 -> 46215 | B62: =F01_UC2!G81 -> 10151329667 | C62: =SUMIFS($L$151:$L$272,$K$151:$K$272,A62)-SUMIFS($J$151:$J$272,$F$151:$F$272,A62) -> 46685897 | D62: =SUMIFS($N$151:$N$272,$F$151:$F$272,A62)-SUMIFS($P$151:$P$272,$O$151:$O$272,A62) -> 0 | E62: =IF(A62=$B$33,$B$48,0) -> 0 | F62: =SUM(C62:E62) -> 46685897 | G62: =SUM($F$51:F62) -> 1.5085146e+09 | H62: =IF($B$34="Hợp lệ",B62+G62,"Chưa tính") -> 1.1659844e+10 | I62: =F01_UC2!H81 -> 0 | J62: =IF($B$34="Hợp lệ",IF(H62<F01_UC2!$B$9,F01_UC2!$B$10-H62,0),"Chưa tính") -> 0 | K62: =IF($B$34<>"Hợp lệ","Chưa tính",IF(H62<F01_UC2!$B$9,3,0)) -> 0 | L62: =IF($B$34="Hợp lệ",IF(AND(I62=0,J62>$B$27),1,0),"Chưa tính") -> 0 | M62: =IF($B$34="Hợp lệ",IF(J62>I62+$B$27,1,0),"Chưa tính") -> 0 | N62: =IF($B$34<>"Hợp lệ","Chưa tính",IF(H62>F01_UC2!$B$11,N61+1,0)) -> 3 | O62: =IF($B$34="Hợp lệ",I62-J62,"Chưa tính") -> 0
A63: =F01_UC2!A82 -> 46216 | B63: =F01_UC2!G82 -> 10151329667 | C63: =SUMIFS($L$151:$L$272,$K$151:$K$272,A63)-SUMIFS($J$151:$J$272,$F$151:$F$272,A63) -> 4.5923164e+08 | D63: =SUMIFS($N$151:$N$272,$F$151:$F$272,A63)-SUMIFS($P$151:$P$272,$O$151:$O$272,A63) -> 0 | E63: =IF(A63=$B$33,$B$48,0) -> 0 | F63: =SUM(C63:E63) -> 4.5923164e+08 | G63: =SUM($F$51:F63) -> 1.9677463e+09 | H63: =IF($B$34="Hợp lệ",B63+G63,"Chưa tính") -> 1.2119076e+10 | I63: =F01_UC2!H82 -> 0 | J63: =IF($B$34="Hợp lệ",IF(H63<F01_UC2!$B$9,F01_UC2!$B$10-H63,0),"Chưa tính") -> 0 | K63: =IF($B$34<>"Hợp lệ","Chưa tính",IF(H63<F01_UC2!$B$9,3,0)) -> 0 | L63: =IF($B$34="Hợp lệ",IF(AND(I63=0,J63>$B$27),1,0),"Chưa tính") -> 0 | M63: =IF($B$34="Hợp lệ",IF(J63>I63+$B$27,1,0),"Chưa tính") -> 0 | N63: =IF($B$34<>"Hợp lệ","Chưa tính",IF(H63>F01_UC2!$B$11,N62+1,0)) -> 4 | O63: =IF($B$34="Hợp lệ",I63-J63,"Chưa tính") -> 0
... A141: =F01_UC2!A160 -> 46294 | B141: =F01_UC2!G160 -> 14156479147 | C141: =SUMIFS($L$151:$L$272,$K$151:$K$272,A141)-SUMIFS($J$151:$J$272,$F$151:$F$272,A141) -> 0 | D141: =SUMIFS($N$151:$N$272,$F$151:$F$272,A141)-SUMIFS($P$151:$P$272,$O$151:$O$272,A141) -> 0 | E141: =IF(A141=$B$33,$B$48,0) -> 0 | F141: =SUM(C141:E141) -> 0 | G141: =SUM($F$51:F141) -> 1.6274842e+08 | H141: =IF($B$34="Hợp lệ",B141+G141,"Chưa tính") -> 1.4319228e+10 | I141: =F01_UC2!H160 -> 0 | J141: =IF($B$34="Hợp lệ",IF(H141<F01_UC2!$B$9,F01_UC2!$B$10-H141,0),"Chưa tính") -> 0 | K141: =IF($B$34<>"Hợp lệ","Chưa tính",IF(H141<F01_UC2!$B$9,3,0)) -> 0 | L141: =IF($B$34="Hợp lệ",IF(AND(I141=0,J141>$B$27),1,0),"Chưa tính") -> 0 | M141: =IF($B$34="Hợp lệ",IF(J141>I141+$B$27,1,0),"Chưa tính") -> 0 | N141: =IF($B$34<>"Hợp lệ","Chưa tính",IF(H141>F01_UC2!$B$11,N140+1,0)) -> 82 | O141: =IF($B$34="Hợp lệ",I141-J141,"Chưa tính") -> 0
A150: event_id | B150: source_id | C150: entity_id | D150: Hướng | E150: Tiền nền | F150: Ngày nền | G150: Ngày xác nhận | H150: Loại | I150: Thiết yếu | J150: Phần AR chuyển | K150: Ngày AR mới | L150: AR thu ròng | M150: CK giảm thu | N150: Phần AP chuyển | O150: Ngày AP mới | P150: AP trả gồm phí | Q150: Phí AP | R150: Phần giữ lịch | S150: Hợp lệ sự kiện
A151: =F01_UC2!A220 -> RCV-INV-F01-0038 | B151: =F01_UC2!B220 -> INV-F01-0038 | C151: =F01_UC2!C220 -> BYR-F01-008 | D151: =F01_UC2!D220 -> IN | E151: =F01_UC2!E220 -> 82708587 | F151: =F01_UC2!N220 -> 46213 | G151: =F01_UC2!M220 -> 0 | H151: =F01_UC2!P220 -> Thu công nợ | I151: =F01_UC2!Q220 -> 0 | J151: =IF(AND($B$34="Hợp lệ",D151="IN",H151="Thu công nợ",C151=$B$7,OR(G151=0,$B$12=1),K151<>F151),E151*$B$28,0) -> 0 | K151: =MAX(F01_UC2!$B$6,F151+$B$29) -> 46206 | L151: =J151-M151 -> 0 | M151: =IF(K151<F151,J151*$B$30,0) -> 0 | N151: =IF(AND($B$34="Hợp lệ",D151="OUT",H151="Trả NCC",C151=$B$13,OR(I151=0,$B$17=1),O151<>F151),E151*$B$31,0) -> 0 | O151: =F151+$B$15 -> 46227 | P151: =N151+Q151 -> 0 | Q151: =N151*$B$16 -> 0 | R151: =E151-J151-N151 -> 82708587 | S151: =IF(AND(J151>=0,N151>=0,R151>=0,ABS(R151+J151+N151-E151)<=$B$27),"Khớp","LỆCH") -> Khớp
A152: =F01_UC2!A221 -> RCV-INV-F01-0051 | B152: =F01_UC2!B221 -> INV-F01-0051 | C152: =F01_UC2!C221 -> BYR-F01-005 | D152: =F01_UC2!D221 -> IN | E152: =F01_UC2!E221 -> 730432904 | F152: =F01_UC2!N221 -> 46213 | G152: =F01_UC2!M221 -> 0 | H152: =F01_UC2!P221 -> Thu công nợ | I152: =F01_UC2!Q221 -> 0 | J152: =IF(AND($B$34="Hợp lệ",D152="IN",H152="Thu công nợ",C152=$B$7,OR(G152=0,$B$12=1),K152<>F152),E152*$B$28,0) -> 0 | K152: =MAX(F01_UC2!$B$6,F152+$B$29) -> 46206 | L152: =J152-M152 -> 0 | M152: =IF(K152<F152,J152*$B$30,0) -> 0 | N152: =IF(AND($B$34="Hợp lệ",D152="OUT",H152="Trả NCC",C152=$B$13,OR(I152=0,$B$17=1),O152<>F152),E152*$B$31,0) -> 0 | O152: =F152+$B$15 -> 46227 | P152: =N152+Q152 -> 0 | Q152: =N152*$B$16 -> 0 | R152: =E152-J152-N152 -> 730432904 | S152: =IF(AND(J152>=0,N152>=0,R152>=0,ABS(R152+J152+N152-E152)<=$B$27),"Khớp","LỆCH") -> Khớp
